Workbook
Name AccountTypeList: Lists!$T$2:$T$3
Name CallStatusList: Lists!$B$2:$B$8
Name CallTypeList: Lists!$C$2:$C$4
Name CheckNo: Lists!$J$3
Name CheckYes: Lists!$J$2
Name CompletionList: Lists!$S$2:$S$3
Name EquipStatusList: Lists!$E$2:$E$4
Name InstWeek2End: Installs!$P$5
Name InstWeekEnd: Installs!$P$4
Name InstWeekStart: Installs!$P$3
Name InternalTechList: Lists!$O$2:$O$8
Name ModulePlatformList: Lists!$L$2:$L$4
Name ModuleStatusList: Lists!$N$2:$N$9
Name ModuleTypeList: Lists!$M$2:$M$11
Name PartsStatusList: Lists!$G$2:$G$6
Name PaymentStatusList: Lists!$P$2:$P$6
Name PaymentTermsList: Lists!$R$2:$R$5
Name PMStatusList: Lists!$H$2:$H$8
Name PMStyleList: Lists!$F$2:$F$5
Name ProducerList: OFFSET(Lists!$Q$2,0,0,MAX(1,COUNTA(Lists!$Q$2:$Q$30)),1)
Name RepList: Lists!$I$2:$I$10
Name RequirementsList: Lists!$W$2:$W$3
Name TechList: Lists!$A$2:$A$9
Name YesNoList: Lists!$D$2:$D$3

Sheet SOP
B1: STANDARD OPERATING PROCEDURE — Equipment Forecasting & Install Tracker
B2: Last updated: July 30, 2026 · Questions: contact the service manager
B4: Jump to a tab:
B5: → Dashboard
B6: → Projected Sales or Lease
B7: → Installs
B8: → Lists
B9: → Install Clock
B10: WHAT EACH TAB DOES
B11: SOP — this page. How to use the file.
B12: Dashboard — live sales performance summary. All numbers update automatically; never type on this tab.
B13: Projected Sales or Lease — the SALES TEAM works here. One row per high-value equipment deal.
... B98: If you ever want a completed deal to stop showing in the AUTO section, add it to the tracker above under the same name (or set its Equipment Status to Installed).

Sheet Dashboard
A1: SALES & LEASE DASHBOARD
A2: Auto-updates from the Projected Sales or Lease tab. Deals marked X (fell through) are excluded from all figures except the "Fell Through" count.
A3: Go to: | B3: SOP | C3: Projected Sales or Lease | D3: Installs | E3: Lists
A5: Active Deals | B5: Active Pipeline $ | C5: Completed Deals | D5: Completed $ | E5: Total Booked $ (Active + Completed) | F5: Fell Through
A6: =COUNTIFS('Projected Sales or Lease'!$A$3:$A$200,"<>",'Projected Sales or Lease'!$L$3:$L$200,"=") -> 14 | B6: =SUMIFS('Projected Sales or Lease'!$F$3:$F$200,'Projected Sales or Lease'!$A$3:$A$200,"<>",'Projected Sales or Lease'!$L$3:$L$200,"=") -> 286643.36 | C6: =COUNTIFS('Projected Sales or Lease'!$L$3:$L$200,"✔") -> 15 | D6: =SUMIFS('Projected Sales or Lease'!$F$3:$F$200,'Projected Sales or Lease'!$L$3:$L$200,"✔") -> 453859.92 | E6: =SUMIFS('Projected Sales or Lease'!$F$3:$F$200,'Projected Sales or Lease'!$A$3:$A$200,"<>",'Projected Sales or Lease'!$L$3:$L$200,"<>X") -> 740503.28 | F6: =COUNTIFS('Projected Sales or Lease'!$L$3:$L$200,"X") -> 0
A9: BY PRODUCER — projected sales & leases
A10: Producer | B10: # Deals | C10: Sales $ | D10: Lease $ | E10: Total $ | F10: Completed # | G10: Completed $ | H10: Open $
A11: =IF(Lists!$Q$2="","",Lists!$Q$2) -> Bill | B11: =IF($A11="","",COUNTIFS('Projected Sales or Lease'!$B$3:$B$200,$A11,'Projected Sales or Lease'!$L$3:$L$200,"<>X")) -> 0 | C11: =IF($A11="","",SUMIFS('Projected Sales or Lease'!$F$3:$F$200,'Projected Sales or Lease'!$B$3:$B$200,$A11,'Projected Sales or Lease'!$L$3:$L$200,"<>X",'Projected Sales or Lease'!$J$3:$J$200,"<>Lease")) -> 0 | D11: =IF($A11="","",SUMIFS('Projected Sales or Lease'!$F$3:$F$200,'Projected Sales or Lease'!$B$3:$B$200,$A11,'Projected Sales or Lease'!$L$3:$L$200,"<>X",'Projected Sales or Lease'!$J$3:$J$200,"Lease")) -> 0 | E11: =IF($A11="","",SUMIFS('Projected Sales or Lease'!$F$3:$F$200,'Projected Sales or Lease'!$B$3:$B$200,$A11,'Projected Sales or Lease'!$L$3:$L$200,"<>X")) -> 0 | F11: =IF($A11="","",COUNTIFS('Projected Sales or Lease'!$B$3:$B$200,$A11,'Projected Sales or Lease'!$L$3:$L$200,"✔")) -> 0 | G11: =IF($A11="","",SUMIFS('Projected Sales or Lease'!$F$3:$F$200,'Projected Sales or Lease'!$B$3:$B$200,$A11,'Projected Sales or Lease'!$L$3:$L$200,"✔")) -> 0 | H11: =IF($A11="","",$E11-$G11) -> 0
A12: =IF(Lists!$Q$3="","",Lists!$Q$3) -> Lance | B12: =IF($A12="","",COUNTIFS('Projected Sales or Lease'!$B$3:$B$200,$A12,'Projected Sales or Lease'!$L$3:$L$200,"<>X")) -> 1 | C12: =IF($A12="","",SUMIFS('Projected Sales or Lease'!$F$3:$F$200,'Projected Sales or Lease'!$B$3:$B$200,$A12,'Projected Sales or Lease'!$L$3:$L$200,"<>X",'Projected Sales or Lease'!$J$3:$J$200,"<>Lease")) -> 23953.08 | D12: =IF($A12="","",SUMIFS('Projected Sales or Lease'!$F$3:$F$200,'Projected Sales or Lease'!$B$3:$B$200,$A12,'Projected Sales or Lease'!$L$3:$L$200,"<>X",'Projected Sales or Lease'!$J$3:$J$200,"Lease")) -> 0 | E12: =IF($A12="","",SUMIFS('Projected Sales or Lease'!$F$3:$F$200,'Projected Sales or Lease'!$B$3:$B$200,$A12,'Projected Sales or Lease'!$L$3:$L$200,"<>X")) -> 23953.08 | F12: =IF($A12="","",COUNTIFS('Projected Sales or Lease'!$B$3:$B$200,$A12,'Projected Sales or Lease'!$L$3:$L$200,"✔")) -> 1 | G12: =IF($A12="","",SUMIFS('Projected Sales or Lease'!$F$3:$F$200,'Projected Sales or Lease'!$B$3:$B$200,$A12,'Projected Sales or Lease'!$L$3:$L$200,"✔")) -> 23953.08 | H12: =IF($A12="","",$E12-$G12) -> 0
A13: =IF(Lists!$Q$4="","",Lists!$Q$4) -> Sean | B13: =IF($A13="","",COUNTIFS('Projected Sales or Lease'!$B$3:$B$200,$A13,'Projected Sales or Lease'!$L$3:$L$200,"<>X")) -> 3 | C13: =IF($A13="","",SUMIFS('Projected Sales or Lease'!$F$3:$F$200,'Projected Sales or Lease'!$B$3:$B$200,$A13,'Projected Sales or Lease'!$L$3:$L$200,"<>X",'Projected Sales or Lease'!$J$3:$J$200,"<>Lease")) -> 0 | D13: =IF($A13="","",SUMIFS('Projected Sales or Lease'!$F$3:$F$200,'Projected Sales or Lease'!$B$3:$B$200,$A13,'Projected Sales or Lease'!$L$3:$L$200,"<>X",'Projected Sales or Lease'!$J$3:$J$200,"Lease")) -> 59728.4 | E13: =IF($A13="","",SUMIFS('Projected Sales or Lease'!$F$3:$F$200,'Projected Sales or Lease'!$B$3:$B$200,$A13,'Projected Sales or Lease'!$L$3:$L$200,"<>X")) -> 59728.4 | F13: =IF($A13="","",COUNTIFS('Projected Sales or Lease'!$B$3:$B$200,$A13,'Projected Sales or Lease'!$L$3:$L$200,"✔")) -> 1 | G13: =IF($A13="","",SUMIFS('Projected Sales or Lease'!$F$3:$F$200,'Projected Sales or Lease'!$B$3:$B$200,$A13,'Projected Sales or Lease'!$L$3:$L$200,"✔")) -> 19800 | H13: =IF($A13="","",$E13-$G13) -> 39928.4
A14: =IF(Lists!$Q$5="","",Lists!$Q$5) -> Shannon | B14: =IF($A14="","",COUNTIFS('Projected Sales or Lease'!$B$3:$B$200,$A14,'Projected Sales or Lease'!$L$3:$L$200,"<>X")) -> 1 | C14: =IF($A14="","",SUMIFS('Projected Sales or Lease'!$F$3:$F$200,'Projected Sales or Lease'!$B$3:$B$200,$A14,'Projected Sales or Lease'!$L$3:$L$200,"<>X",'Projected Sales or Lease'!$J$3:$J$200,"<>Lease")) -> 16051 | D14: =IF($A14="","",SUMIFS('Projected Sales or Lease'!$F$3:$F$200,'Projected Sales or Lease'!$B$3:$B$200,$A14,'Projected Sales or Lease'!$L$3:$L$200,"<>X",'Projected Sales or Lease'!$J$3:$J$200,"Lease")) -> 0 | E14: =IF($A14="","",SUMIFS('Projected Sales or Lease'!$F$3:$F$200,'Projected Sales or Lease'!$B$3:$B$200,$A14,'Projected Sales or Lease'!$L$3:$L$200,"<>X")) -> 16051 | F14: =IF($A14="","",COUNTIFS('Projected Sales or Lease'!$B$3:$B$200,$A14,'Projected Sales or Lease'!$L$3:$L$200,"✔")) -> 0 | G14: =IF($A14="","",SUMIFS('Projected Sales or Lease'!$F$3:$F$200,'Projected Sales or Lease'!$B$3:$B$200,$A14,'Projected Sales or Lease'!$L$3:$L$200,"✔")) -> 0 | H14: =IF($A14="","",$E14-$G14) -> 16051
A15: =IF(Lists!$Q$6="","",Lists!$Q$6) -> Lizbeth | B15: =IF($A15="","",COUNTIFS('Projected Sales or Lease'!$B$3:$B$200,$A15,'Projected Sales or Lease'!$L$3:$L$200,"<>X")) -> 10 | C15: =IF($A15="","",SUMIFS('Projected Sales or Lease'!$F$3:$F$200,'Projected Sales or Lease'!$B$3:$B$200,$A15,'Projected Sales or Lease'!$L$3:$L$200,"<>X",'Projected Sales or Lease'!$J$3:$J$200,"<>Lease")) -> 238090.64 | D15: =IF($A15="","",SUMIFS('Projected Sales or Lease'!$F$3:$F$200,'Projected Sales or Lease'!$B$3:$B$200,$A15,'Projected Sales or Lease'!$L$3:$L$200,"<>X",'Projected Sales or Lease'!$J$3:$J$200,"Lease")) -> 39600 | E15: =IF($A15="","",SUMIFS('Projected Sales or Lease'!$F$3:$F$200,'Projected Sales or Lease'!$B$3:$B$200,$A15,'Projected Sales or Lease'!$L$3:$L$200,"<>X")) -> 277690.64 | F15: =IF($A15="","",COUNTIFS('Projected Sales or Lease'!$B$3:$B$200,$A15,'Projected Sales or Lease'!$L$3:$L$200,"✔")) -> 4 | G15: =IF($A15="","",SUMIFS('Projected Sales or Lease'!$F$3:$F$200,'Projected Sales or Lease'!$B$3:$B$200,$A15,'Projected Sales or Lease'!$L$3:$L$200,"✔")) -> 133008.38 | H15: =IF($A15="","",$E15-$G15) -> 144682.26
A16: =IF(Lists!$Q$7="","",Lists!$Q$7) -> Amanda | B16: =IF($A16="","",COUNTIFS('Projected Sales or Lease'!$B$3:$B$200,$A16,'Projected Sales or Lease'!$L$3:$L$200,"<>X")) -> 12 | C16: =IF($A16="","",SUMIFS('Projected Sales or Lease'!$F$3:$F$200,'Projected Sales or Lease'!$B$3:$B$200,$A16,'Projected Sales or Lease'!$L$3:$L$200,"<>X",'Projected Sales or Lease'!$J$3:$J$200,"<>Lease")) -> 348080.16 | D16: =IF($A16="","",SUMIFS('Projected Sales or Lease'!$F$3:$F$200,'Projected Sales or Lease'!$B$3:$B$200,$A16,'Projected Sales or Lease'!$L$3:$L$200,"<>X",'Projected Sales or Lease'!$J$3:$J$200,"Lease")) -> 15000 | E16: =IF($A16="","",SUMIFS('Projected Sales or Lease'!$F$3:$F$200,'Projected Sales or Lease'!$B$3:$B$200,$A16,'Projected Sales or Lease'!$L$3:$L$200,"<>X")) -> 363080.16 | F16: =IF($A16="","",COUNTIFS('Projected Sales or Lease'!$B$3:$B$200,$A16,'Projected Sales or Lease'!$L$3:$L$200,"✔")) -> 9 | G16: =IF($A16="","",SUMIFS('Projected Sales or Lease'!$F$3:$F$200,'Projected Sales or Lease'!$B$3:$B$200,$A16,'Projected Sales or Lease'!$L$3:$L$200,"✔")) -> 277098.46 | H16: =IF($A16="","",$E16-$G16) -> 85981.7
A17: =IF(Lists!$Q$8="","",Lists!$Q$8) -> Jesus | B17: =IF($A17="","",COUNTIFS('Projected Sales or Lease'!$B$3:$B$200,$A17,'Projected Sales or Lease'!$L$3:$L$200,"<>X")) -> 0 | C17: =IF($A17="","",SUMIFS('Projected Sales or Lease'!$F$3:$F$200,'Projected Sales or Lease'!$B$3:$B$200,$A17,'Projected Sales or Lease'!$L$3:$L$200,"<>X",'Projected Sales or Lease'!$J$3:$J$200,"<>Lease")) -> 0 | D17: =IF($A17="","",SUMIFS('Projected Sales or Lease'!$F$3:$F$200,'Projected Sales or Lease'!$B$3:$B$200,$A17,'Projected Sales or Lease'!$L$3:$L$200,"<>X",'Projected Sales or Lease'!$J$3:$J$200,"Lease")) -> 0 | E17: =IF($A17="","",SUMIFS('Projected Sales or Lease'!$F$3:$F$200,'Projected Sales or Lease'!$B$3:$B$200,$A17,'Projected Sales or Lease'!$L$3:$L$200,"<>X")) -> 0 | F17: =IF($A17="","",COUNTIFS('Projected Sales or Lease'!$B$3:$B$200,$A17,'Projected Sales or Lease'!$L$3:$L$200,"✔")) -> 0 | G17: =IF($A17="","",SUMIFS('Projected Sales or Lease'!$F$3:$F$200,'Projected Sales or Lease'!$B$3:$B$200,$A17,'Projected Sales or Lease'!$L$3:$L$200,"✔")) -> 0 | H17: =IF($A17="","",$E17-$G17) -> 0
A18: =IF(Lists!$Q$9="","",Lists!$Q$9) | B18: =IF($A18="","",COUNTIFS('Projected Sales or Lease'!$B$3:$B$200,$A18,'Projected Sales or Lease'!$L$3:$L$200,"<>X")) | C18: =IF($A18="","",SUMIFS('Projected Sales or Lease'!$F$3:$F$200,'Projected Sales or Lease'!$B$3:$B$200,$A18,'Projected Sales or Lease'!$L$3:$L$200,"<>X",'Projected Sales or Lease'!$J$3:$J$200,"<>Lease")) | D18: =IF($A18="","",SUMIFS('Projected Sales or Lease'!$F$3:$F$200,'Projected Sales or Lease'!$B$3:$B$200,$A18,'Projected Sales or Lease'!$L$3:$L$200,"<>X",'Projected Sales or Lease'!$J$3:$J$200,"Lease")) | E18: =IF($A18="","",SUMIFS('Projected Sales or Lease'!$F$3:$F$200,'Projected Sales or Lease'!$B$3:$B$200,$A18,'Projected Sales or Lease'!$L$3:$L$200,"<>X")) | F18: =IF($A18="","",COUNTIFS('Projected Sales or Lease'!$B$3:$B$200,$A18,'Projected Sales or Lease'!$L$3:$L$200,"✔")) | G18: =IF($A18="","",SUMIFS('Projected Sales or Lease'!$F$3:$F$200,'Projected Sales or Lease'!$B$3:$B$200,$A18,'Projected Sales or Lease'!$L$3:$L$200,"✔")) | H18: =IF($A18="","",$E18-$G18)
A19: =IF(Lists!$Q$10="","",Lists!$Q$10) | B19: =IF($A19="","",COUNTIFS('Projected Sales or Lease'!$B$3:$B$200,$A19,'Projected Sales or Lease'!$L$3:$L$200,"<>X")) | C19: =IF($A19="","",SUMIFS('Projected Sales or Lease'!$F$3:$F$200,'Projected Sales or Lease'!$B$3:$B$200,$A19,'Projected Sales or Lease'!$L$3:$L$200,"<>X",'Projected Sales or Lease'!$J$3:$J$200,"<>Lease")) | D19: =IF($A19="","",SUMIFS('Projected Sales or Lease'!$F$3:$F$200,'Projected Sales or Lease'!$B$3:$B$200,$A19,'Projected Sales or Lease'!$L$3:$L$200,"<>X",'Projected Sales or Lease'!$J$3:$J$200,"Lease")) | E19: =IF($A19="","",SUMIFS('Projected Sales or Lease'!$F$3:$F$200,'Projected Sales or Lease'!$B$3:$B$200,$A19,'Projected Sales or Lease'!$L$3:$L$200,"<>X")) | F19: =IF($A19="","",COUNTIFS('Projected Sales or Lease'!$B$3:$B$200,$A19,'Projected Sales or Lease'!$L$3:$L$200,"✔")) | G19: =IF($A19="","",SUMIFS('Projected Sales or Lease'!$F$3:$F$200,'Projected Sales or Lease'!$B$3:$B$200,$A19,'Projected Sales or Lease'!$L$3:$L$200,"✔")) | H19: =IF($A19="","",$E19-$G19)
A20: =IF(Lists!$Q$11="","",Lists!$Q$11) | B20: =IF($A20="","",COUNTIFS('Projected Sales or Lease'!$B$3:$B$200,$A20,'Projected Sales or Lease'!$L$3:$L$200,"<>X")) | C20: =IF($A20="","",SUMIFS('Projected Sales or Lease'!$F$3:$F$200,'Projected Sales or Lease'!$B$3:$B$200,$A20,'Projected Sales or Lease'!$L$3:$L$200,"<>X",'Projected Sales or Lease'!$J$3:$J$200,"<>Lease")) | D20: =IF($A20="","",SUMIFS('Projected Sales or Lease'!$F$3:$F$200,'Projected Sales or Lease'!$B$3:$B$200,$A20,'Projected Sales or Lease'!$L$3:$L$200,"<>X",'Projected Sales or Lease'!$J$3:$J$200,"Lease")) | E20: =IF($A20="","",SUMIFS('Projected Sales or Lease'!$F$3:$F$200,'Projected Sales or Lease'!$B$3:$B$200,$A20,'Projected Sales or Lease'!$L$3:$L$200,"<>X")) | F20: =IF($A20="","",COUNTIFS('Projected Sales or Lease'!$B$3:$B$200,$A20,'Projected Sales or Lease'!$L$3:$L$200,"✔")) | G20: =IF($A20="","",SUMIFS('Projected Sales or Lease'!$F$3:$F$200,'Projected Sales or Lease'!$B$3:$B$200,$A20,'Projected Sales or Lease'!$L$3:$L$200,"✔")) | H20: =IF($A20="","",$E20-$G20)
A21: =IF(Lists!$Q$12="","",Lists!$Q$12) | B21: =IF($A21="","",COUNTIFS('Projected Sales or Lease'!$B$3:$B$200,$A21,'Projected Sales or Lease'!$L$3:$L$200,"<>X")) | C21: =IF($A21="","",SUMIFS('Projected Sales or Lease'!$F$3:$F$200,'Projected Sales or Lease'!$B$3:$B$200,$A21,'Projected Sales or Lease'!$L$3:$L$200,"<>X",'Projected Sales or Lease'!$J$3:$J$200,"<>Lease")) | D21: =IF($A21="","",SUMIFS('Projected Sales or Lease'!$F$3:$F$200,'Projected Sales or Lease'!$B$3:$B$200,$A21,'Projected Sales or Lease'!$L$3:$L$200,"<>X",'Projected Sales or Lease'!$J$3:$J$200,"Lease")) | E21: =IF($A21="","",SUMIFS('Projected Sales or Lease'!$F$3:$F$200,'Projected Sales or Lease'!$B$3:$B$200,$A21,'Projected Sales or Lease'!$L$3:$L$200,"<>X")) | F21: =IF($A21="","",COUNTIFS('Projected Sales or Lease'!$B$3:$B$200,$A21,'Projected Sales or Lease'!$L$3:$L$200,"✔")) | G21: =IF($A21="","",SUMIFS('Projected Sales or Lease'!$F$3:$F$200,'Projected Sales or Lease'!$B$3:$B$200,$A21,'Projected Sales or Lease'!$L$3:$L$200,"✔")) | H21: =IF($A21="","",$E21-$G21)
A22: =IF(Lists!$Q$13="","",Lists!$Q$13) | B22: =IF($A22="","",COUNTIFS('Projected Sales or Lease'!$B$3:$B$200,$A22,'Projected Sales or Lease'!$L$3:$L$200,"<>X")) | C22: =IF($A22="","",SUMIFS('Projected Sales or Lease'!$F$3:$F$200,'Projected Sales or Lease'!$B$3:$B$200,$A22,'Projected Sales or Lease'!$L$3:$L$200,"<>X",'Projected Sales or Lease'!$J$3:$J$200,"<>Lease")) | D22: =IF($A22="","",SUMIFS('Projected Sales or Lease'!$F$3:$F$200,'Projected Sales or Lease'!$B$3:$B$200,$A22,'Projected Sales or Lease'!$L$3:$L$200,"<>X",'Projected Sales or Lease'!$J$3:$J$200,"Lease")) | E22: =IF($A22="","",SUMIFS('Projected Sales or Lease'!$F$3:$F$200,'Projected Sales or Lease'!$B$3:$B$200,$A22,'Projected Sales or Lease'!$L$3:$L$200,"<>X")) | F22: =IF($A22="","",COUNTIFS('Projected Sales or Lease'!$B$3:$B$200,$A22,'Projected Sales or Lease'!$L$3:$L$200,"✔")) | G22: =IF($A22="","",SUMIFS('Projected Sales or Lease'!$F$3:$F$200,'Projected Sales or Lease'!$B$3:$B$200,$A22,'Projected Sales or Lease'!$L$3:$L$200,"✔")) | H22: =IF($A22="","",$E22-$G22)
A23: =IF(Lists!$Q$14="","",Lists!$Q$14) | B23: =IF($A23="","",COUNTIFS('Projected Sales or Lease'!$B$3:$B$200,$A23,'Projected Sales or Lease'!$L$3:$L$200,"<>X")) | C23: =IF($A23="","",SUMIFS('Projected Sales or Lease'!$F$3:$F$200,'Projected Sales or Lease'!$B$3:$B$200,$A23,'Projected Sales or Lease'!$L$3:$L$200,"<>X",'Projected Sales or Lease'!$J$3:$J$200,"<>Lease")) | D23: =IF($A23="","",SUMIFS('Projected Sales or Lease'!$F$3:$F$200,'Projected Sales or Lease'!$B$3:$B$200,$A23,'Projected Sales or Lease'!$L$3:$L$200,"<>X",'Projected Sales or Lease'!$J$3:$J$200,"Lease")) | E23: =IF($A23="","",SUMIFS('Projected Sales or Lease'!$F$3:$F$200,'Projected Sales or Lease'!$B$3:$B$200,$A23,'Projected Sales or Lease'!$L$3:$L$200,"<>X")) | F23: =IF($A23="","",COUNTIFS('Projected Sales or Lease'!$B$3:$B$200,$A23,'Projected Sales or Lease'!$L$3:$L$200,"✔")) | G23: =IF($A23="","",SUMIFS('Projected Sales or Lease'!$F$3:$F$200,'Projected Sales or Lease'!$B$3:$B$200,$A23,'Projected Sales or Lease'!$L$3:$L$200,"✔")) | H23: =IF($A23="","",$E23-$G23)
A24: =IF(Lists!$Q$15="","",Lists!$Q$15) | B24: =IF($A24="","",COUNTIFS('Projected Sales or Lease'!$B$3:$B$200,$A24,'Projected Sales or Lease'!$L$3:$L$200,"<>X")) | C24: =IF($A24="","",SUMIFS('Projected Sales or Lease'!$F$3:$F$200,'Projected Sales or Lease'!$B$3:$B$200,$A24,'Projected Sales or Lease'!$L$3:$L$200,"<>X",'Projected Sales or Lease'!$J$3:$J$200,"<>Lease")) | D24: =IF($A24="","",SUMIFS('Projected Sales or Lease'!$F$3:$F$200,'Projected Sales or Lease'!$B$3:$B$200,$A24,'Projected Sales or Lease'!$L$3:$L$200,"<>X",'Projected Sales or Lease'!$J$3:$J$200,"Lease")) | E24: =IF($A24="","",SUMIFS('Projected Sales or Lease'!$F$3:$F$200,'Projected Sales or Lease'!$B$3:$B$200,$A24,'Projected Sales or Lease'!$L$3:$L$200,"<>X")) | F24: =IF($A24="","",COUNTIFS('Projected Sales or Lease'!$B$3:$B$200,$A24,'Projected Sales or Lease'!$L$3:$L$200,"✔")) | G24: =IF($A24="","",SUMIFS('Projected Sales or Lease'!$F$3:$F$200,'Projected Sales or Lease'!$B$3:$B$200,$A24,'Projected Sales or Lease'!$L$3:$L$200,"✔")) | H24: =IF($A24="","",$E24-$G24)
A25: =IF(Lists!$Q$16="","",Lists!$Q$16) | B25: =IF($A25="","",COUNTIFS('Projected Sales or Lease'!$B$3:$B$200,$A25,'Projected Sales or Lease'!$L$3:$L$200,"<>X")) | C25: =IF($A25="","",SUMIFS('Projected Sales or Lease'!$F$3:$F$200,'Projected Sales or Lease'!$B$3:$B$200,$A25,'Projected Sales or Lease'!$L$3:$L$200,"<>X",'Projected Sales or Lease'!$J$3:$J$200,"<>Lease")) | D25: =IF($A25="","",SUMIFS('Projected Sales or Lease'!$F$3:$F$200,'Projected Sales or Lease'!$B$3:$B$200,$A25,'Projected Sales or Lease'!$L$3:$L$200,"<>X",'Projected Sales or Lease'!$J$3:$J$200,"Lease")) | E25: =IF($A25="","",SUMIFS('Projected Sales or Lease'!$F$3:$F$200,'Projected Sales or Lease'!$B$3:$B$200,$A25,'Projected Sales or Lease'!$L$3:$L$200,"<>X")) | F25: =IF($A25="","",COUNTIFS('Projected Sales or Lease'!$B$3:$B$200,$A25,'Projected Sales or Lease'!$L$3:$L$200,"✔")) | G25: =IF($A25="","",SUMIFS('Projected Sales or Lease'!$F$3:$F$200,'Projected Sales or Lease'!$B$3:$B$200,$A25,'Projected Sales or Lease'!$L$3:$L$200,"✔")) | H25: =IF($A25="","",$E25-$G25)
A26: (No producer / not on list) | B26: =COUNTIFS('Projected Sales or Lease'!$A$3:$A$200,"<>",'Projected Sales or Lease'!$L$3:$L$200,"<>X")-SUM(B11:B25) -> 2 | C26: =SUMIFS('Projected Sales or Lease'!$F$3:$F$200,'Projected Sales or Lease'!$A$3:$A$200,"<>",'Projected Sales or Lease'!$L$3:$L$200,"<>X",'Projected Sales or Lease'!$J$3:$J$200,"<>Lease")-SUM(C11:C25) -> 0 | D26: =SUMIFS('Projected Sales or Lease'!$F$3:$F$200,'Projected Sales or Lease'!$A$3:$A$200,"<>",'Projected Sales or Lease'!$L$3:$L$200,"<>X",'Projected Sales or Lease'!$J$3:$J$200,"Lease")-SUM(D11:D25) -> 0 | E26: =SUMIFS('Projected Sales or Lease'!$F$3:$F$200,'Projected Sales or Lease'!$A$3:$A$200,"<>",'Projected Sales or Lease'!$L$3:$L$200,"<>X")-SUM(E11:E25) -> 0 | F26: =COUNTIFS('Projected Sales or Lease'!$L$3:$L$200,"✔")-SUM(F11:F25) -> 0 | G26: =SUMIFS('Projected Sales or Lease'!$F$3:$F$200,'Projected Sales or Lease'!$L$3:$L$200,"✔")-SUM(G11:G25) -> 0 | H26: =$E26-$G26 -> 0
A27: TOTAL | B27: =SUM(B11:B26) -> 29 | C27: =SUM(C11:C26) -> 626174.88 | D27: =SUM(D11:D26) -> 114328.4 | E27: =SUM(E11:E26) -> 740503.28 | F27: =SUM(F11:F26) -> 15 | G27: =SUM(G11:G26) -> 453859.92 | H27: =SUM(H11:H26) -> 286643.36
A30: BY PAYMENT TERMS | E30: DEAL PROGRESS (active + completed)
A31: Payment Terms | B31: # Deals | C31: Amount $ | E31: Stage | F31: # Deals | G31: Amount $
A32: =Lists!$R$2 -> Payment Plan | B32: =COUNTIFS('Projected Sales or Lease'!$J$3:$J$200,$A32,'Projected Sales or Lease'!$L$3:$L$200,"<>X") -> 2 | C32: =SUMIFS('Projected Sales or Lease'!$F$3:$F$200,'Projected Sales or Lease'!$J$3:$J$200,$A32,'Projected Sales or Lease'!$L$3:$L$200,"<>X") -> 118616.06 | E32: Good to Order ✔ | F32: =COUNTIFS('Projected Sales or Lease'!$G$3:$G$200,"✔",'Projected Sales or Lease'!$L$3:$L$200,"<>X") -> 22 | G32: =SUMIFS('Projected Sales or Lease'!$F$3:$F$200,'Projected Sales or Lease'!$G$3:$G$200,"✔",'Projected Sales or Lease'!$L$3:$L$200,"<>X") -> 614521.86
A33: =Lists!$R$3 -> 50% Down + 50% upon install/30 days after | B33: =COUNTIFS('Projected Sales or Lease'!$J$3:$J$200,$A33,'Projected Sales or Lease'!$L$3:$L$200,"<>X") -> 4 | C33: =SUMIFS('Projected Sales or Lease'!$F$3:$F$200,'Projected Sales or Lease'!$J$3:$J$200,$A33,'Projected Sales or Lease'!$L$3:$L$200,"<>X") -> 73322.28 | E33: Equipment Ordered ✔ | F33: =COUNTIFS('Projected Sales or Lease'!$H$3:$H$200,"✔",'Projected Sales or Lease'!$L$3:$L$200,"<>X") -> 21 | G33: =SUMIFS('Projected Sales or Lease'!$F$3:$F$200,'Projected Sales or Lease'!$H$3:$H$200,"✔",'Projected Sales or Lease'!$L$3:$L$200,"<>X") -> 594721.86
A34: =Lists!$R$4 -> Lease | B34: =COUNTIFS('Projected Sales or Lease'!$J$3:$J$200,$A34,'Projected Sales or Lease'!$L$3:$L$200,"<>X") -> 6 | C34: =SUMIFS('Projected Sales or Lease'!$F$3:$F$200,'Projected Sales or Lease'!$J$3:$J$200,$A34,'Projected Sales or Lease'!$L$3:$L$200,"<>X") -> 114328.4 | E34: Deal Complete ✔ | F34: =COUNTIFS('Projected Sales or Lease'!$L$3:$L$200,"✔") -> 15 | G34: =SUMIFS('Projected Sales or Lease'!$F$3:$F$200,'Projected Sales or Lease'!$L$3:$L$200,"✔") -> 453859.92
A35: =Lists!$R$5 -> Paid in Full | B35: =COUNTIFS('Projected Sales or Lease'!$J$3:$J$200,$A35,'Projected Sales or Lease'!$L$3:$L$200,"<>X") -> 11 | C35: =SUMIFS('Projected Sales or Lease'!$F$3:$F$200,'Projected Sales or Lease'!$J$3:$J$200,$A35,'Projected Sales or Lease'!$L$3:$L$200,"<>X") -> 318255.12
A36: (Not set) | B36: =COUNTIFS('Projected Sales or Lease'!$A$3:$A$200,"<>",'Projected Sales or Lease'!$J$3:$J$200,"=",'Projected Sales or Lease'!$L$3:$L$200,"<>X") -> 6 | C36: =SUMIFS('Projected Sales or Lease'!$F$3:$F$200,'Projected Sales or Lease'!$A$3:$A$200,"<>",'Projected Sales or Lease'!$J$3:$J$200,"=",'Projected Sales or Lease'!$L$3:$L$200,"<>X") -> 115981.42

Sheet Projected Sales or Lease
A1: PROJECTED SALES OR LEASE | E1: Sales team: one row per deal — see the SOP tab for full instructions. Account Type flags Avi/Richard accounts. Deal Completion: ✔ = finalized (row turns green + deal auto-copies to the Installs tab) · X = fell through (row turns red, excluded from Dashboard).
A2: Customer Name | B2: Producer | C2: Account Type | D2: Date of Deal | E2: Equipment | F2: Equipment Deal Amount ($) | G2: Good to Order ✔ | H2: Equipment Ordered ✔ | I2: Equipment ETA | J2: Payment Terms | K2: Invoice # | L2: Deal Completion | M2: Notes | N2: new? | O2: rank
A3: Truffle & Rye | B3: Amanda | E3: La Marz GS3, jay grinder | F3: 11118.85 | G3: ✔ | H3: ✔ | I3: Here | J3: Paid in Full | K3: 740831 | L3: ✔ | M3: Waiting on broker to ship to Turks for final amount | N3: =IF(AND($L3="✔",$A3<>"",COUNTIF(Installs!$B$5:$B$159,$A3)=0),1,0) -> 1 | O3: =IF($N3=1,SUM($N$3:$N3),"") -> 1
A4: Jonathan's The Rub - Bridgeland | B4: Amanda | C4: Avi Account | E4: Cameo c'2s | F4: 22151.26 | G4: ✔ | H4: ✔ | I4: Installed | J4: Payment Plan | K4: 734302 | L4: ✔ | N4: =IF(AND($L4="✔",$A4<>"",COUNTIF(Installs!$B$5:$B$159,$A4)=0),1,0) -> 1 | O4: =IF($N4=1,SUM($N$3:$N4),"") -> 2
A5: Coco Crepe Elyson Town Center | B5: Lizbeth | E5: Eversys Enigma e'4s Classic | F5: 37611.26 | G5: ✔ | H5: ✔ | J5: Paid in Full | K5: 745528 | M5: Still under remodel | N5: =IF(AND($L5="✔",$A5<>"",COUNTIF(Installs!$B$5:$B$159,$A5)=0),1,0) -> 0 | O5: =IF($N5=1,SUM($N$3:$N5),"")
A6: Valentinas Coffee | B6: Lizbeth | E6: La Marzocco Strada XT 2 Group, Mazzer ZM Filter Grinder - Black, Mazzer Robur S Electronic, Puqpress Q2 Automatic Tamper BLACK, Everpure EZ-RO 200/10 Gallon Hydropneumatic Tank, Blendtec Stealth 885, Blendtec Rapid Rinse Station | F6: 49601.19 | G6: ✔ | H6: ✔ | J6: Paid in Full | K6: 754770 754497 749838 | L6: ✔ | M6: Special order. Waiting on ETA from LM. | N6: =IF(AND($L6="✔",$A6<>"",COUNTIF(Installs!$B$5:$B$159,$A6)=0),1,0) -> 1 | O6: =IF($N6=1,SUM($N$3:$N6),"") -> 3
A7: El toro tex mex | B7: Lizbeth | C7: Avi Account | E7: Eversys e'4 | F7: 35000 | M7: Working on getting out of Coca Cola Lease | N7: =IF(AND($L7="✔",$A7<>"",COUNTIF(Installs!$B$5:$B$159,$A7)=0),1,0) -> 0 | O7: =IF($N7=1,SUM($N$3:$N7),"")
A8: Ciao Bella Bakery | N8: =IF(AND($L8="✔",$A8<>"",COUNTIF(Installs!$B$5:$B$159,$A8)=0),1,0) -> 0 | O8: =IF($N8=1,SUM($N$3:$N8),"")
A9: Work Around Café | B9: Amanda | E9: strada s 2 gr, jay, mahl ek43, mahl e65, fetco 1251, itbdd, puq | F9: 49930.42 | N9: =IF(AND($L9="✔",$A9<>"",COUNTIF(Installs!$B$5:$B$159,$A9)=0),1,0) -> 0 | O9: =IF($N9=1,SUM($N$3:$N9),"")
A10: Coco Crepe Bellaire | B10: Lizbeth | E10: La Marzocco Linea Classic S 2 Group AV & La Marzocco Swift Dual-Hopper Espresso Grinder | F10: 27271 | G10: ✔ | H10: ✔ | I10: Here | J10: 50% Down + 50% upon install/30 days after | K10: 746261 | N10: =IF(AND($L10="✔",$A10<>"",COUNTIF(Installs!$B$5:$B$159,$A10)=0),1,0) -> 0 | O10: =IF($N10=1,SUM($N$3:$N10),"")
A11: Local Foods - ATX #2 | B11: Amanda | E11: La Marzocco Linea Classic S 2 Group AV & La Marzocco Swift Dual-Hopper Espresso Grinder, Fetco 1251, ITB-DD EZRO200 | F11: 31902 | G11: ✔ | H11: ✔ | I11: Here | J11: Paid in Full | K11: 746493 | L11: ✔ | N11: =IF(AND($L11="✔",$A11<>"",COUNTIF(Installs!$B$5:$B$159,$A11)=0),1,0) -> 0 | O11: =IF($N11=1,SUM($N$3:$N11),"")
A12: Bella Flori | N12: =IF(AND($L12="✔",$A12<>"",COUNTIF(Installs!$B$5:$B$159,$A12)=0),1,0) -> 0 | O12: =IF($N12=1,SUM($N$3:$N12),"")
A13: Luzia Coffee Shop | B13: Lizbeth | E13: Invicta 3GR, Robur S E, Puqpress | F13: 26089.52 | G13: ✔ | H13: ✔ | I13: Installed | J13: Paid in Full | K13: 748258 | L13: ✔ | M13: Pending Down Payment | N13: =IF(AND($L13="✔",$A13<>"",COUNTIF(Installs!$B$5:$B$159,$A13)=0),1,0) -> 0 | O13: =IF($N13=1,SUM($N$3:$N13),"")
A14: The Audrey Restaurant & Bar Post Oak | B14: Lizbeth | E14: Eversys Cameo c'2s | F14: 19800 | G14: ✔ | H14: ✔ | I14: Installed | J14: Lease | L14: ✔ | N14: =IF(AND($L14="✔",$A14<>"",COUNTIF(Installs!$B$5:$B$159,$A14)=0),1,0) -> 1 | O14: =IF($N14=1,SUM($N$3:$N14),"") -> 4
A15: Lakewood Yacht Club | B15: Lizbeth | C15: Avi Account | E15: Eversys Cameo c'2s | F15: 19800 | G15: ✔ | J15: Lease | N15: =IF(AND($L15="✔",$A15<>"",COUNTIF(Installs!$B$5:$B$159,$A15)=0),1,0) -> 0 | O15: =IF($N15=1,SUM($N$3:$N15),"")
A16: Common Bond Spring | B16: Amanda | C16: Avi Account | E16: 2 x e4s with 1.5 wands SN: 0110710025266E0006 Fetco 1252 Plus SN: 1252UB23015260303 Bunn ITB-DD SN: ITB0065171 Fetco GRS1202 SN:12021A00020259710 | F16: 96464.8 | G16: ✔ | H16: ✔ | I16: Installed | J16: Payment Plan | K16: 749148 | L16: ✔ | N16: =IF(AND($L16="✔",$A16<>"",COUNTIF(Installs!$B$5:$B$159,$A16)=0),1,0) -> 0 | O16: =IF($N16=1,SUM($N$3:$N16),"")
A17: CoPlay Cove | B17: Lizbeth | E17: e4s SN: 0110700025150E0012 | F17: 37517.67 | G17: ✔ | H17: ✔ | I17: Installed | J17: Paid in Full | K17: 735103 | L17: ✔ | N17: =IF(AND($L17="✔",$A17<>"",COUNTIF(Installs!$B$5:$B$159,$A17)=0),1,0) -> 0 | O17: =IF($N17=1,SUM($N$3:$N17),"")
A18: Sunrise Coffee | B18: Amanda | E18: Linea S 2 Group SN:LS029320 Mazzer Super Jolly SN:2540764 | F18: 21043.39 | G18: ✔ | H18: ✔ | I18: Installed | J18: Paid in Full | K18: 751629 | L18: ✔ | N18: =IF(AND($L18="✔",$A18<>"",COUNTIF(Installs!$B$5:$B$159,$A18)=0),1,0) -> 0 | O18: =IF($N18=1,SUM($N$3:$N18),"")
A19: Latte Cafe - La Grange | B19: Amanda | E19: Rancilio Classe 9 | F19: 14018.16 | G19: ✔ | H19: ✔ | I19: Installed | J19: Paid in Full | K19: 752128 | L19: ✔ | N19: =IF(AND($L19="✔",$A19<>"",COUNTIF(Installs!$B$5:$B$159,$A19)=0),1,0) -> 0 | O19: =IF($N19=1,SUM($N$3:$N19),"")
A20: Taha Market Mediterranean Foods | B20: Sean | E20: Eversys Cameo c'2s | F20: 19800 | G20: ✔ | H20: ✔ | I20: Installed | J20: Lease | K20: X | L20: ✔ | N20: =IF(AND($L20="✔",$A20<>"",COUNTIF(Installs!$B$5:$B$159,$A20)=0),1,0) -> 0 | O20: =IF($N20=1,SUM($N$3:$N20),"")
A21: Clover | B21: Amanda | E21: Eversys e'4s | F21: 35400 | G21: ✔ | H21: ✔ | I21: Installed | J21: Paid in Full | K21: 754732 | L21: ✔ | N21: =IF(AND($L21="✔",$A21<>"",COUNTIF(Installs!$B$5:$B$159,$A21)=0),1,0) -> 0 | O21: =IF($N21=1,SUM($N$3:$N21),"")
A22: Parkwood American Grille | B22: Amanda | C22: Avi Account | E22: Eversys Legacy | F22: 16051.28 | G22: ✔ | H22: ✔ | I22: Mid-August | J22: 50% Down + 50% upon install/30 days after | K22: 756106 | M22: Will need Cameo until Legacycomes in. | N22: =IF(AND($L22="✔",$A22<>"",COUNTIF(Installs!$B$5:$B$159,$A22)=0),1,0) -> 0 | O22: =IF($N22=1,SUM($N$3:$N22),"")
A23: Uchi - Houston | B23: Shannon | E23: Eversys Legacy | F23: 16051 | M23: Will use loaner Legacy unit trial is over | N23: =IF(AND($L23="✔",$A23<>"",COUNTIF(Installs!$B$5:$B$159,$A23)=0),1,0) -> 0 | O23: =IF($N23=1,SUM($N$3:$N23),"")
A24: Brews & Books | B24: Lance | E24: Eversys Cameo c'2s | F24: 23953.08 | G24: ✔ | H24: ✔ | I24: 45121 | J24: Paid in Full | K24: 755161 | L24: ✔ | N24: =IF(AND($L24="✔",$A24<>"",COUNTIF(Installs!$B$5:$B$159,$A24)=0),1,0) -> 1 | O24: =IF($N24=1,SUM($N$3:$N24),"") -> 5
A25: Riot Comedy Club | B25: Sean | E25: Rancilio Classe 5 Compact, Mazzer SJ E, Mazzer Mini E | F25: 11128.4 | G25: ✔ | H25: ✔ | I25: Here | J25: Lease | M25: Tentative install date 7/28 earliest. | N25: =IF(AND($L25="✔",$A25<>"",COUNTIF(Installs!$B$5:$B$159,$A25)=0),1,0) -> 0 | O25: =IF($N25=1,SUM($N$3:$N25),"")
A26: Osso & Kristalla | B26: Sean | C26: Avi Account | E26: Everysys E'4 | F26: 28800 | G26: ✔ | H26: ✔ | J26: Lease | M26: Will be month to month, $800/mo | N26: =IF(AND($L26="✔",$A26<>"",COUNTIF(Installs!$B$5:$B$159,$A26)=0),1,0) -> 0 | O26: =IF($N26=1,SUM($N$3:$N26),"")
A27: bloom chica brew | B27: Amanda | E27: linea classic, jay grinder | F27: 30000 | G27: ✔ | H27: ✔ | J27: Paid in Full | K27: 743957 | L27: ✔ | M27: 3rd party installation | N27: =IF(AND($L27="✔",$A27<>"",COUNTIF(Installs!$B$5:$B$159,$A27)=0),1,0) -> 0 | O27: =IF($N27=1,SUM($N$3:$N27),"")
A28: kol fac 118 | B28: Amanda | E28: cameo c'2s | F28: 20000 | G28: ✔ | H28: ✔ | J28: 50% Down + 50% upon install/30 days after | K28: 756855 | N28: =IF(AND($L28="✔",$A28<>"",COUNTIF(Installs!$B$5:$B$159,$A28)=0),1,0) -> 0 | O28: =IF($N28=1,SUM($N$3:$N28),"")
A29: petroleum club | B29: Amanda | C29: Avi Account | E29: cameo c'2s | F29: 15000 | G29: ✔ | H29: ✔ | I29: ready | J29: Lease | L29: ✔ | N29: =IF(AND($L29="✔",$A29<>"",COUNTIF(Installs!$B$5:$B$159,$A29)=0),1,0) -> 0 | O29: =IF($N29=1,SUM($N$3:$N29),"")
A30: Vam Foods #2 | B30: Lizbeth | E30: Bravilor Sego 12 120V | F30: 10000 | J30: 50% Down + 50% upon install/30 days after | M30: Waiting for approval on purchase | N30: =IF(AND($L30="✔",$A30<>"",COUNTIF(Installs!$B$5:$B$159,$A30)=0),1,0) -> 0 | O30: =IF($N30=1,SUM($N$3:$N30),"")
A31: Mexico Lindo Bakery | B31: Lizbeth | E31: Rancilio Classe 5 USB 2 Group Auto-Volumetric | F31: 15000 | N31: =IF(AND($L31="✔",$A31<>"",COUNTIF(Installs!$B$5:$B$159,$A31)=0),1,0) -> 0 | O31: =IF($N31=1,SUM($N$3:$N31),"")
N32: =IF(AND($L32="✔",$A32<>"",COUNTIF(Installs!$B$5:$B$159,$A32)=0),1,0) -> 0 | O32: =IF($N32=1,SUM($N$3:$N32),"")
N33: =IF(AND($L33="✔",$A33<>"",COUNTIF(Installs!$B$5:$B$159,$A33)=0),1,0) -> 0 | O33: =IF($N33=1,SUM($N$3:$N33),"")
N34: =IF(AND($L34="✔",$A34<>"",COUNTIF(Installs!$B$5:$B$159,$A34)=0),1,0) -> 0 | O34: =IF($N34=1,SUM($N$3:$N34),"")
N35: =IF(AND($L35="✔",$A35<>"",COUNTIF(Installs!$B$5:$B$159,$A35)=0),1,0) -> 0 | O35: =IF($N35=1,SUM($N$3:$N35),"")
N36: =IF(AND($L36="✔",$A36<>"",COUNTIF(Installs!$B$5:$B$159,$A36)=0),1,0) -> 0 | O36: =IF($N36=1,SUM($N$3:$N36),"")
N37: =IF(AND($L37="✔",$A37<>"",COUNTIF(Installs!$B$5:$B$159,$A37)=0),1,0) -> 0 | O37: =IF($N37=1,SUM($N$3:$N37),"")
N38: =IF(AND($L38="✔",$A38<>"",COUNTIF(Installs!$B$5:$B$159,$A38)=0),1,0) -> 0 | O38: =IF($N38=1,SUM($N$3:$N38),"")
N39: =IF(AND($L39="✔",$A39<>"",COUNTIF(Installs!$B$5:$B$159,$A39)=0),1,0) -> 0 | O39: =IF($N39=1,SUM($N$3:$N39),"")
N40: =IF(AND($L40="✔",$A40<>"",COUNTIF(Installs!$B$5:$B$159,$A40)=0),1,0) -> 0 | O40: =IF($N40=1,SUM($N$3:$N40),"")
N41: =IF(AND($L41="✔",$A41<>"",COUNTIF(Installs!$B$5:$B$159,$A41)=0),1,0) -> 0 | O41: =IF($N41=1,SUM($N$3:$N41),"")
N42: =IF(AND($L42="✔",$A42<>"",COUNTIF(Installs!$B$5:$B$159,$A42)=0),1,0) -> 0 | O42: =IF($N42=1,SUM($N$3:$N42),"")
N43: =IF(AND($L43="✔",$A43<>"",COUNTIF(Installs!$B$5:$B$159,$A43)=0),1,0) -> 0 | O43: =IF($N43=1,SUM($N$3:$N43),"")
... N200: =IF(AND($L200="✔",$A200<>"",COUNTIF(Installs!$B$5:$B$159,$A200)=0),1,0) -> 0 | O200: =IF($N200=1,SUM($N$3:$N200),"")

Sheet Install Clock
A1: ⏱ INSTALL CLOCK
A2: ← Back to the Installation Tracker | C2: Everything here is read-only and recalculates on open. Fix things on the Installs tab.
A4: Today | B4: This week (Mon–Sun) | C4: Next week | D4: ⚠ Equipment NOT ready | E4: ⚠ Past due & not ready | F4: ⚠ Customer not ready | G4: Completed installs | H4: In queue (not yet installed)
A5: =TODAY() -> 46254 | B5: =TEXT(Installs!$P$3,"m/d")&" – "&TEXT(Installs!$P$4,"m/d") -> 8/17 – 8/23 | C5: =TEXT(Installs!$P$3+7,"m/d")&" – "&TEXT(Installs!$P$5,"m/d") -> 8/24 – 8/30 | D5: =COUNTIF(Installs!$M$5:$M$200,"⚠ EQUIP NOT READY") -> 0 | E5: =COUNTIF(Installs!$M$5:$M$200,"⚠ PAST DUE - NOT READY") -> 0 | F5: =COUNTIF(Installs!$M$5:$M$200,"⚠ CUSTOMER NOT READY") -> 0 | G5: =COUNTIF(Installs!$D$5:$D$200,"Installed") -> 41 | H5: =COUNTIF(Installs!$O$5:$O$200,"<999999999") -> 13
A7: ⚠ AT RISK NOW — scheduled this week or next (or already past due) and not ready
A8: # | B8: Account | C8: Why it's flagged | D8: Equip Status | E8: Install Date | F8: Assigned Tech | G8: Work Order | H8: Requirements
A9: =IF($P9="","",1) | B9: =IF($P9="","",IFERROR(IF(INDEX(Installs!$B$1:$B$200,$P9)="","",INDEX(Installs!$B$1:$B$200,$P9)),"")) | C9: =IF($P9="","",IFERROR(IF(INDEX(Installs!$M$1:$M$200,$P9)="","",INDEX(Installs!$M$1:$M$200,$P9)),"")) | D9: =IF($P9="","",IFERROR(IF(INDEX(Installs!$D$1:$D$200,$P9)="","",INDEX(Installs!$D$1:$D$200,$P9)),"")) | E9: =IF($P9="","",IFERROR(IF(INDEX(Installs!$E$1:$E$200,$P9)="","",INDEX(Installs!$E$1:$E$200,$P9)),"")) | F9: =IF($P9="","",IFERROR(IF(INDEX(Installs!$F$1:$F$200,$P9)="","",INDEX(Installs!$F$1:$F$200,$P9)),"")) | G9: =IF($P9="","",IFERROR(IF(INDEX(Installs!$G$1:$G$200,$P9)="","",INDEX(Installs!$G$1:$G$200,$P9)),"")) | H9: =IF($P9="","",IFERROR(IF(INDEX(Installs!$H$1:$H$200,$P9)="","",INDEX(Installs!$H$1:$H$200,$P9)),"")) | P9: =IFERROR(MATCH(1,Installs!$R$5:$R$200,0)+4,"")
A10: =IF($P10="","",2) | B10: =IF($P10="","",IFERROR(IF(INDEX(Installs!$B$1:$B$200,$P10)="","",INDEX(Installs!$B$1:$B$200,$P10)),"")) | C10: =IF($P10="","",IFERROR(IF(INDEX(Installs!$M$1:$M$200,$P10)="","",INDEX(Installs!$M$1:$M$200,$P10)),"")) | D10: =IF($P10="","",IFERROR(IF(INDEX(Installs!$D$1:$D$200,$P10)="","",INDEX(Installs!$D$1:$D$200,$P10)),"")) | E10: =IF($P10="","",IFERROR(IF(INDEX(Installs!$E$1:$E$200,$P10)="","",INDEX(Installs!$E$1:$E$200,$P10)),"")) | F10: =IF($P10="","",IFERROR(IF(INDEX(Installs!$F$1:$F$200,$P10)="","",INDEX(Installs!$F$1:$F$200,$P10)),"")) | G10: =IF($P10="","",IFERROR(IF(INDEX(Installs!$G$1:$G$200,$P10)="","",INDEX(Installs!$G$1:$G$200,$P10)),"")) | H10: =IF($P10="","",IFERROR(IF(INDEX(Installs!$H$1:$H$200,$P10)="","",INDEX(Installs!$H$1:$H$200,$P10)),"")) | P10: =IFERROR(MATCH(2,Installs!$R$5:$R$200,0)+4,"")
A11: =IF($P11="","",3) | B11: =IF($P11="","",IFERROR(IF(INDEX(Installs!$B$1:$B$200,$P11)="","",INDEX(Installs!$B$1:$B$200,$P11)),"")) | C11: =IF($P11="","",IFERROR(IF(INDEX(Installs!$M$1:$M$200,$P11)="","",INDEX(Installs!$M$1:$M$200,$P11)),"")) | D11: =IF($P11="","",IFERROR(IF(INDEX(Installs!$D$1:$D$200,$P11)="","",INDEX(Installs!$D$1:$D$200,$P11)),"")) | E11: =IF($P11="","",IFERROR(IF(INDEX(Installs!$E$1:$E$200,$P11)="","",INDEX(Installs!$E$1:$E$200,$P11)),"")) | F11: =IF($P11="","",IFERROR(IF(INDEX(Installs!$F$1:$F$200,$P11)="","",INDEX(Installs!$F$1:$F$200,$P11)),"")) | G11: =IF($P11="","",IFERROR(IF(INDEX(Installs!$G$1:$G$200,$P11)="","",INDEX(Installs!$G$1:$G$200,$P11)),"")) | H11: =IF($P11="","",IFERROR(IF(INDEX(Installs!$H$1:$H$200,$P11)="","",INDEX(Installs!$H$1:$H$200,$P11)),"")) | P11: =IFERROR(MATCH(3,Installs!$R$5:$R$200,0)+4,"")
A12: =IF($P12="","",4) | B12: =IF($P12="","",IFERROR(IF(INDEX(Installs!$B$1:$B$200,$P12)="","",INDEX(Installs!$B$1:$B$200,$P12)),"")) | C12: =IF($P12="","",IFERROR(IF(INDEX(Installs!$M$1:$M$200,$P12)="","",INDEX(Installs!$M$1:$M$200,$P12)),"")) | D12: =IF($P12="","",IFERROR(IF(INDEX(Installs!$D$1:$D$200,$P12)="","",INDEX(Installs!$D$1:$D$200,$P12)),"")) | E12: =IF($P12="","",IFERROR(IF(INDEX(Installs!$E$1:$E$200,$P12)="","",INDEX(Installs!$E$1:$E$200,$P12)),"")) | F12: =IF($P12="","",IFERROR(IF(INDEX(Installs!$F$1:$F$200,$P12)="","",INDEX(Installs!$F$1:$F$200,$P12)),"")) | G12: =IF($P12="","",IFERROR(IF(INDEX(Installs!$G$1:$G$200,$P12)="","",INDEX(Installs!$G$1:$G$200,$P12)),"")) | H12: =IF($P12="","",IFERROR(IF(INDEX(Installs!$H$1:$H$200,$P12)="","",INDEX(Installs!$H$1:$H$200,$P12)),"")) | P12: =IFERROR(MATCH(4,Installs!$R$5:$R$200,0)+4,"")
A13: =IF($P13="","",5) | B13: =IF($P13="","",IFERROR(IF(INDEX(Installs!$B$1:$B$200,$P13)="","",INDEX(Installs!$B$1:$B$200,$P13)),"")) | C13: =IF($P13="","",IFERROR(IF(INDEX(Installs!$M$1:$M$200,$P13)="","",INDEX(Installs!$M$1:$M$200,$P13)),"")) | D13: =IF($P13="","",IFERROR(IF(INDEX(Installs!$D$1:$D$200,$P13)="","",INDEX(Installs!$D$1:$D$200,$P13)),"")) | E13: =IF($P13="","",IFERROR(IF(INDEX(Installs!$E$1:$E$200,$P13)="","",INDEX(Installs!$E$1:$E$200,$P13)),"")) | F13: =IF($P13="","",IFERROR(IF(INDEX(Installs!$F$1:$F$200,$P13)="","",INDEX(Installs!$F$1:$F$200,$P13)),"")) | G13: =IF($P13="","",IFERROR(IF(INDEX(Installs!$G$1:$G$200,$P13)="","",INDEX(Installs!$G$1:$G$200,$P13)),"")) | H13: =IF($P13="","",IFERROR(IF(INDEX(Installs!$H$1:$H$200,$P13)="","",INDEX(Installs!$H$1:$H$200,$P13)),"")) | P13: =IFERROR(MATCH(5,Installs!$R$5:$R$200,0)+4,"")
A14: =IF($P14="","",6) | B14: =IF($P14="","",IFERROR(IF(INDEX(Installs!$B$1:$B$200,$P14)="","",INDEX(Installs!$B$1:$B$200,$P14)),"")) | C14: =IF($P14="","",IFERROR(IF(INDEX(Installs!$M$1:$M$200,$P14)="","",INDEX(Installs!$M$1:$M$200,$P14)),"")) | D14: =IF($P14="","",IFERROR(IF(INDEX(Installs!$D$1:$D$200,$P14)="","",INDEX(Installs!$D$1:$D$200,$P14)),"")) | E14: =IF($P14="","",IFERROR(IF(INDEX(Installs!$E$1:$E$200,$P14)="","",INDEX(Installs!$E$1:$E$200,$P14)),"")) | F14: =IF($P14="","",IFERROR(IF(INDEX(Installs!$F$1:$F$200,$P14)="","",INDEX(Installs!$F$1:$F$200,$P14)),"")) | G14: =IF($P14="","",IFERROR(IF(INDEX(Installs!$G$1:$G$200,$P14)="","",INDEX(Installs!$G$1:$G$200,$P14)),"")) | H14: =IF($P14="","",IFERROR(IF(INDEX(Installs!$H$1:$H$200,$P14)="","",INDEX(Installs!$H$1:$H$200,$P14)),"")) | P14: =IFERROR(MATCH(6,Installs!$R$5:$R$200,0)+4,"")
A15: =IF($P15="","",7) | B15: =IF($P15="","",IFERROR(IF(INDEX(Installs!$B$1:$B$200,$P15)="","",INDEX(Installs!$B$1:$B$200,$P15)),"")) | C15: =IF($P15="","",IFERROR(IF(INDEX(Installs!$M$1:$M$200,$P15)="","",INDEX(Installs!$M$1:$M$200,$P15)),"")) | D15: =IF($P15="","",IFERROR(IF(INDEX(Installs!$D$1:$D$200,$P15)="","",INDEX(Installs!$D$1:$D$200,$P15)),"")) | E15: =IF($P15="","",IFERROR(IF(INDEX(Installs!$E$1:$E$200,$P15)="","",INDEX(Installs!$E$1:$E$200,$P15)),"")) | F15: =IF($P15="","",IFERROR(IF(INDEX(Installs!$F$1:$F$200,$P15)="","",INDEX(Installs!$F$1:$F$200,$P15)),"")) | G15: =IF($P15="","",IFERROR(IF(INDEX(Installs!$G$1:$G$200,$P15)="","",INDEX(Installs!$G$1:$G$200,$P15)),"")) | H15: =IF($P15="","",IFERROR(IF(INDEX(Installs!$H$1:$H$200,$P15)="","",INDEX(Installs!$H$1:$H$200,$P15)),"")) | P15: =IFERROR(MATCH(7,Installs!$R$5:$R$200,0)+4,"")
A16: =IF($P16="","",8) | B16: =IF($P16="","",IFERROR(IF(INDEX(Installs!$B$1:$B$200,$P16)="","",INDEX(Installs!$B$1:$B$200,$P16)),"")) | C16: =IF($P16="","",IFERROR(IF(INDEX(Installs!$M$1:$M$200,$P16)="","",INDEX(Installs!$M$1:$M$200,$P16)),"")) | D16: =IF($P16="","",IFERROR(IF(INDEX(Installs!$D$1:$D$200,$P16)="","",INDEX(Installs!$D$1:$D$200,$P16)),"")) | E16: =IF($P16="","",IFERROR(IF(INDEX(Installs!$E$1:$E$200,$P16)="","",INDEX(Installs!$E$1:$E$200,$P16)),"")) | F16: =IF($P16="","",IFERROR(IF(INDEX(Installs!$F$1:$F$200,$P16)="","",INDEX(Installs!$F$1:$F$200,$P16)),"")) | G16: =IF($P16="","",IFERROR(IF(INDEX(Installs!$G$1:$G$200,$P16)="","",INDEX(Installs!$G$1:$G$200,$P16)),"")) | H16: =IF($P16="","",IFERROR(IF(INDEX(Installs!$H$1:$H$200,$P16)="","",INDEX(Installs!$H$1:$H$200,$P16)),"")) | P16: =IFERROR(MATCH(8,Installs!$R$5:$R$200,0)+4,"")
A17: =IF($P17="","",9) | B17: =IF($P17="","",IFERROR(IF(INDEX(Installs!$B$1:$B$200,$P17)="","",INDEX(Installs!$B$1:$B$200,$P17)),"")) | C17: =IF($P17="","",IFERROR(IF(INDEX(Installs!$M$1:$M$200,$P17)="","",INDEX(Installs!$M$1:$M$200,$P17)),"")) | D17: =IF($P17="","",IFERROR(IF(INDEX(Installs!$D$1:$D$200,$P17)="","",INDEX(Installs!$D$1:$D$200,$P17)),"")) | E17: =IF($P17="","",IFERROR(IF(INDEX(Installs!$E$1:$E$200,$P17)="","",INDEX(Installs!$E$1:$E$200,$P17)),"")) | F17: =IF($P17="","",IFERROR(IF(INDEX(Installs!$F$1:$F$200,$P17)="","",INDEX(Installs!$F$1:$F$200,$P17)),"")) | G17: =IF($P17="","",IFERROR(IF(INDEX(Installs!$G$1:$G$200,$P17)="","",INDEX(Installs!$G$1:$G$200,$P17)),"")) | H17: =IF($P17="","",IFERROR(IF(INDEX(Installs!$H$1:$H$200,$P17)="","",INDEX(Installs!$H$1:$H$200,$P17)),"")) | P17: =IFERROR(MATCH(9,Installs!$R$5:$R$200,0)+4,"")
A18: =IF($P18="","",10) | B18: =IF($P18="","",IFERROR(IF(INDEX(Installs!$B$1:$B$200,$P18)="","",INDEX(Installs!$B$1:$B$200,$P18)),"")) | C18: =IF($P18="","",IFERROR(IF(INDEX(Installs!$M$1:$M$200,$P18)="","",INDEX(Installs!$M$1:$M$200,$P18)),"")) | D18: =IF($P18="","",IFERROR(IF(INDEX(Installs!$D$1:$D$200,$P18)="","",INDEX(Installs!$D$1:$D$200,$P18)),"")) | E18: =IF($P18="","",IFERROR(IF(INDEX(Installs!$E$1:$E$200,$P18)="","",INDEX(Installs!$E$1:$E$200,$P18)),"")) | F18: =IF($P18="","",IFERROR(IF(INDEX(Installs!$F$1:$F$200,$P18)="","",INDEX(Installs!$F$1:$F$200,$P18)),"")) | G18: =IF($P18="","",IFERROR(IF(INDEX(Installs!$G$1:$G$200,$P18)="","",INDEX(Installs!$G$1:$G$200,$P18)),"")) | H18: =IF($P18="","",IFERROR(IF(INDEX(Installs!$H$1:$H$200,$P18)="","",INDEX(Installs!$H$1:$H$200,$P18)),"")) | P18: =IFERROR(MATCH(10,Installs!$R$5:$R$200,0)+4,"")
A19: =IF(SUM(Installs!$Q$5:$Q$200)=0,"✓ Nothing flagged — no scheduled account is at risk right now.",IF(SUM(Installs!$Q$5:$Q$200)>10,"Showing the first 10 of "&SUM(Installs!$Q$5:$Q$200)&" flagged accounts — the rest are the red rows on the Installs tab.","All "&SUM(Installs!$Q$5:$Q$200)&" flagged account(s) are listed above.")) -> ✓ Nothing flagged — no scheduled account is at risk right now.
A21: 🔧 PREP QUEUE — every account not yet installed, in install-date order. Work top to bottom.
A22: Days out | B22: Account | C22: Equipment to prep | D22: Equip Status | E22: Install Date | F22: Assigned Tech | G22: Work Order | H22: Requirements
A23: =IF($P23="","",IFERROR(IF(ISNUMBER(INDEX(Installs!$E$1:$E$200,$P23)),INDEX(Installs!$E$1:$E$200,$P23)-TODAY(),"needs date"),"")) -> -7 | B23: =IF($P23="","",IFERROR(IF(INDEX(Installs!$B$1:$B$200,$P23)="","",INDEX(Installs!$B$1:$B$200,$P23)),"")) -> Ninfa's - Navigation | C23: =IF($P23="","",IFERROR(IF(INDEX(Installs!$C$1:$C$200,$P23)="","",INDEX(Installs!$C$1:$C$200,$P23)),"")) -> TB3 | D23: =IF($P23="","",IFERROR(IF(INDEX(Installs!$D$1:$D$200,$P23)="","",INDEX(Installs!$D$1:$D$200,$P23)),"")) -> Ready | E23: =IF($P23="","",IFERROR(IF(INDEX(Installs!$E$1:$E$200,$P23)="","",INDEX(Installs!$E$1:$E$200,$P23)),"")) -> 46247 | F23: =IF($P23="","",IFERROR(IF(INDEX(Installs!$F$1:$F$200,$P23)="","",INDEX(Installs!$F$1:$F$200,$P23)),"")) | G23: =IF($P23="","",IFERROR(IF(INDEX(Installs!$G$1:$G$200,$P23)="","",INDEX(Installs!$G$1:$G$200,$P23)),"")) | H23: =IF($P23="","",IFERROR(IF(INDEX(Installs!$H$1:$H$200,$P23)="","",INDEX(Installs!$H$1:$H$200,$P23)),"")) | P23: =IF(COUNTIF(Installs!$O$5:$O$200,"<999999999")<1,"",IFERROR(MOD(SMALL(Installs!$O$5:$O$200,1),10000)+4,"")) -> 33
A24: =IF($P24="","",IFERROR(IF(ISNUMBER(INDEX(Installs!$E$1:$E$200,$P24)),INDEX(Installs!$E$1:$E$200,$P24)-TODAY(),"needs date"),"")) -> 0 | B24: =IF($P24="","",IFERROR(IF(INDEX(Installs!$B$1:$B$200,$P24)="","",INDEX(Installs!$B$1:$B$200,$P24)),"")) -> Southern Ice CO | C24: =IF($P24="","",IFERROR(IF(INDEX(Installs!$C$1:$C$200,$P24)="","",INDEX(Installs!$C$1:$C$200,$P24)),"")) -> bunn itcb | D24: =IF($P24="","",IFERROR(IF(INDEX(Installs!$D$1:$D$200,$P24)="","",INDEX(Installs!$D$1:$D$200,$P24)),"")) -> Ready | E24: =IF($P24="","",IFERROR(IF(INDEX(Installs!$E$1:$E$200,$P24)="","",INDEX(Installs!$E$1:$E$200,$P24)),"")) -> 46254 | F24: =IF($P24="","",IFERROR(IF(INDEX(Installs!$F$1:$F$200,$P24)="","",INDEX(Installs!$F$1:$F$200,$P24)),"")) | G24: =IF($P24="","",IFERROR(IF(INDEX(Installs!$G$1:$G$200,$P24)="","",INDEX(Installs!$G$1:$G$200,$P24)),"")) -> WO-0406 | H24: =IF($P24="","",IFERROR(IF(INDEX(Installs!$H$1:$H$200,$P24)="","",INDEX(Installs!$H$1:$H$200,$P24)),"")) -> Ready | P24: =IF(COUNTIF(Installs!$O$5:$O$200,"<999999999")<2,"",IFERROR(MOD(SMALL(Installs!$O$5:$O$200,2),10000)+4,"")) -> 52
A25: =IF($P25="","",IFERROR(IF(ISNUMBER(INDEX(Installs!$E$1:$E$200,$P25)),INDEX(Installs!$E$1:$E$200,$P25)-TODAY(),"needs date"),"")) -> needs date | B25: =IF($P25="","",IFERROR(IF(INDEX(Installs!$B$1:$B$200,$P25)="","",INDEX(Installs!$B$1:$B$200,$P25)),"")) -> kol fac 118 | C25: =IF($P25="","",IFERROR(IF(INDEX(Installs!$C$1:$C$200,$P25)="","",INDEX(Installs!$C$1:$C$200,$P25)),"")) -> cameo, itcb | D25: =IF($P25="","",IFERROR(IF(INDEX(Installs!$D$1:$D$200,$P25)="","",INDEX(Installs!$D$1:$D$200,$P25)),"")) -> Not Ready | E25: =IF($P25="","",IFERROR(IF(INDEX(Installs!$E$1:$E$200,$P25)="","",INDEX(Installs!$E$1:$E$200,$P25)),"")) | F25: =IF($P25="","",IFERROR(IF(INDEX(Installs!$F$1:$F$200,$P25)="","",INDEX(Installs!$F$1:$F$200,$P25)),"")) | G25: =IF($P25="","",IFERROR(IF(INDEX(Installs!$G$1:$G$200,$P25)="","",INDEX(Installs!$G$1:$G$200,$P25)),"")) | H25: =IF($P25="","",IFERROR(IF(INDEX(Installs!$H$1:$H$200,$P25)="","",INDEX(Installs!$H$1:$H$200,$P25)),"")) | P25: =IF(COUNTIF(Installs!$O$5:$O$200,"<999999999")<3,"",IFERROR(MOD(SMALL(Installs!$O$5:$O$200,3),10000)+4,"")) -> 42
A26: =IF($P26="","",IFERROR(IF(ISNUMBER(INDEX(Installs!$E$1:$E$200,$P26)),INDEX(Installs!$E$1:$E$200,$P26)-TODAY(),"needs date"),"")) -> needs date | B26: =IF($P26="","",IFERROR(IF(INDEX(Installs!$B$1:$B$200,$P26)="","",INDEX(Installs!$B$1:$B$200,$P26)),"")) -> Coco Crepes Bellaire | C26: =IF($P26="","",IFERROR(IF(INDEX(Installs!$C$1:$C$200,$P26)="","",INDEX(Installs!$C$1:$C$200,$P26)),"")) -> La Marzocco Linea Classic S 2 Group AV/ La Marzocco Swift Dual-Hopper Espresso Grinder/ Bunn Axiom-APS | D26: =IF($P26="","",IFERROR(IF(INDEX(Installs!$D$1:$D$200,$P26)="","",INDEX(Installs!$D$1:$D$200,$P26)),"")) -> Not Ready | E26: =IF($P26="","",IFERROR(IF(INDEX(Installs!$E$1:$E$200,$P26)="","",INDEX(Installs!$E$1:$E$200,$P26)),"")) | F26: =IF($P26="","",IFERROR(IF(INDEX(Installs!$F$1:$F$200,$P26)="","",INDEX(Installs!$F$1:$F$200,$P26)),"")) | G26: =IF($P26="","",IFERROR(IF(INDEX(Installs!$G$1:$G$200,$P26)="","",INDEX(Installs!$G$1:$G$200,$P26)),"")) | H26: =IF($P26="","",IFERROR(IF(INDEX(Installs!$H$1:$H$200,$P26)="","",INDEX(Installs!$H$1:$H$200,$P26)),"")) | P26: =IF(COUNTIF(Installs!$O$5:$O$200,"<999999999")<4,"",IFERROR(MOD(SMALL(Installs!$O$5:$O$200,4),10000)+4,"")) -> 45
A27: =IF($P27="","",IFERROR(IF(ISNUMBER(INDEX(Installs!$E$1:$E$200,$P27)),INDEX(Installs!$E$1:$E$200,$P27)-TODAY(),"needs date"),"")) -> needs date | B27: =IF($P27="","",IFERROR(IF(INDEX(Installs!$B$1:$B$200,$P27)="","",INDEX(Installs!$B$1:$B$200,$P27)),"")) -> waller county court house | C27: =IF($P27="","",IFERROR(IF(INDEX(Installs!$C$1:$C$200,$P27)="","",INDEX(Installs!$C$1:$C$200,$P27)),"")) -> axiom aps | D27: =IF($P27="","",IFERROR(IF(INDEX(Installs!$D$1:$D$200,$P27)="","",INDEX(Installs!$D$1:$D$200,$P27)),"")) -> Ready | E27: =IF($P27="","",IFERROR(IF(INDEX(Installs!$E$1:$E$200,$P27)="","",INDEX(Installs!$E$1:$E$200,$P27)),"")) | F27: =IF($P27="","",IFERROR(IF(INDEX(Installs!$F$1:$F$200,$P27)="","",INDEX(Installs!$F$1:$F$200,$P27)),"")) | G27: =IF($P27="","",IFERROR(IF(INDEX(Installs!$G$1:$G$200,$P27)="","",INDEX(Installs!$G$1:$G$200,$P27)),"")) | H27: =IF($P27="","",IFERROR(IF(INDEX(Installs!$H$1:$H$200,$P27)="","",INDEX(Installs!$H$1:$H$200,$P27)),"")) -> Not Ready | P27: =IF(COUNTIF(Installs!$O$5:$O$200,"<999999999")<5,"",IFERROR(MOD(SMALL(Installs!$O$5:$O$200,5),10000)+4,"")) -> 48
A28: =IF($P28="","",IFERROR(IF(ISNUMBER(INDEX(Installs!$E$1:$E$200,$P28)),INDEX(Installs!$E$1:$E$200,$P28)-TODAY(),"needs date"),"")) -> needs date | B28: =IF($P28="","",IFERROR(IF(INDEX(Installs!$B$1:$B$200,$P28)="","",INDEX(Installs!$B$1:$B$200,$P28)),"")) -> Doug's Diner | C28: =IF($P28="","",IFERROR(IF(INDEX(Installs!$C$1:$C$200,$P28)="","",INDEX(Installs!$C$1:$C$200,$P28)),"")) -> Fetco MBS x 2 / Powder Machine | D28: =IF($P28="","",IFERROR(IF(INDEX(Installs!$D$1:$D$200,$P28)="","",INDEX(Installs!$D$1:$D$200,$P28)),"")) -> Not Ready | E28: =IF($P28="","",IFERROR(IF(INDEX(Installs!$E$1:$E$200,$P28)="","",INDEX(Installs!$E$1:$E$200,$P28)),"")) | F28: =IF($P28="","",IFERROR(IF(INDEX(Installs!$F$1:$F$200,$P28)="","",INDEX(Installs!$F$1:$F$200,$P28)),"")) -> 3rd Party | G28: =IF($P28="","",IFERROR(IF(INDEX(Installs!$G$1:$G$200,$P28)="","",INDEX(Installs!$G$1:$G$200,$P28)),"")) | H28: =IF($P28="","",IFERROR(IF(INDEX(Installs!$H$1:$H$200,$P28)="","",INDEX(Installs!$H$1:$H$200,$P28)),"")) -> Ready | P28: =IF(COUNTIF(Installs!$O$5:$O$200,"<999999999")<6,"",IFERROR(MOD(SMALL(Installs!$O$5:$O$200,6),10000)+4,"")) -> 50
A29: =IF($P29="","",IFERROR(IF(ISNUMBER(INDEX(Installs!$E$1:$E$200,$P29)),INDEX(Installs!$E$1:$E$200,$P29)-TODAY(),"needs date"),"")) -> needs date | B29: =IF($P29="","",IFERROR(IF(INDEX(Installs!$B$1:$B$200,$P29)="","",INDEX(Installs!$B$1:$B$200,$P29)),"")) -> Two Step Taqueria - South | C29: =IF($P29="","",IFERROR(IF(INDEX(Installs!$C$1:$C$200,$P29)="","",INDEX(Installs!$C$1:$C$200,$P29)),"")) | D29: =IF($P29="","",IFERROR(IF(INDEX(Installs!$D$1:$D$200,$P29)="","",INDEX(Installs!$D$1:$D$200,$P29)),"")) -> Not Ready | E29: =IF($P29="","",IFERROR(IF(INDEX(Installs!$E$1:$E$200,$P29)="","",INDEX(Installs!$E$1:$E$200,$P29)),"")) | F29: =IF($P29="","",IFERROR(IF(INDEX(Installs!$F$1:$F$200,$P29)="","",INDEX(Installs!$F$1:$F$200,$P29)),"")) -> Lance | G29: =IF($P29="","",IFERROR(IF(INDEX(Installs!$G$1:$G$200,$P29)="","",INDEX(Installs!$G$1:$G$200,$P29)),"")) | H29: =IF($P29="","",IFERROR(IF(INDEX(Installs!$H$1:$H$200,$P29)="","",INDEX(Installs!$H$1:$H$200,$P29)),"")) | P29: =IF(COUNTIF(Installs!$O$5:$O$200,"<999999999")<7,"",IFERROR(MOD(SMALL(Installs!$O$5:$O$200,7),10000)+4,"")) -> 51
A30: =IF($P30="","",IFERROR(IF(ISNUMBER(INDEX(Installs!$E$1:$E$200,$P30)),INDEX(Installs!$E$1:$E$200,$P30)-TODAY(),"needs date"),"")) -> needs date | B30: =IF($P30="","",IFERROR(IF(INDEX(Installs!$B$1:$B$200,$P30)="","",INDEX(Installs!$B$1:$B$200,$P30)),"")) -> Scrambles Breakfast & Lunch | C30: =IF($P30="","",IFERROR(IF(INDEX(Installs!$C$1:$C$200,$P30)="","",INDEX(Installs!$C$1:$C$200,$P30)),"")) -> BUNN ITCB & BUNN G9 GRINDER | D30: =IF($P30="","",IFERROR(IF(INDEX(Installs!$D$1:$D$200,$P30)="","",INDEX(Installs!$D$1:$D$200,$P30)),"")) | E30: =IF($P30="","",IFERROR(IF(INDEX(Installs!$E$1:$E$200,$P30)="","",INDEX(Installs!$E$1:$E$200,$P30)),"")) | F30: =IF($P30="","",IFERROR(IF(INDEX(Installs!$F$1:$F$200,$P30)="","",INDEX(Installs!$F$1:$F$200,$P30)),"")) | G30: =IF($P30="","",IFERROR(IF(INDEX(Installs!$G$1:$G$200,$P30)="","",INDEX(Installs!$G$1:$G$200,$P30)),"")) | H30: =IF($P30="","",IFERROR(IF(INDEX(Installs!$H$1:$H$200,$P30)="","",INDEX(Installs!$H$1:$H$200,$P30)),"")) | P30: =IF(COUNTIF(Installs!$O$5:$O$200,"<999999999")<8,"",IFERROR(MOD(SMALL(Installs!$O$5:$O$200,8),10000)+4,"")) -> 53
A31: =IF($P31="","",IFERROR(IF(ISNUMBER(INDEX(Installs!$E$1:$E$200,$P31)),INDEX(Installs!$E$1:$E$200,$P31)-TODAY(),"needs date"),"")) -> needs date | B31: =IF($P31="","",IFERROR(IF(INDEX(Installs!$B$1:$B$200,$P31)="","",INDEX(Installs!$B$1:$B$200,$P31)),"")) -> Truffle & Rye | C31: =IF($P31="","",IFERROR(IF(INDEX(Installs!$C$1:$C$200,$P31)="","",INDEX(Installs!$C$1:$C$200,$P31)),"")) -> La Marz GS3, jay grinder | D31: =IF($P31="","",IFERROR(IF(INDEX(Installs!$D$1:$D$200,$P31)="","",INDEX(Installs!$D$1:$D$200,$P31)),"")) | E31: =IF($P31="","",IFERROR(IF(INDEX(Installs!$E$1:$E$200,$P31)="","",INDEX(Installs!$E$1:$E$200,$P31)),"")) | F31: =IF($P31="","",IFERROR(IF(INDEX(Installs!$F$1:$F$200,$P31)="","",INDEX(Installs!$F$1:$F$200,$P31)),"")) | G31: =IF($P31="","",IFERROR(IF(INDEX(Installs!$G$1:$G$200,$P31)="","",INDEX(Installs!$G$1:$G$200,$P31)),"")) | H31: =IF($P31="","",IFERROR(IF(INDEX(Installs!$H$1:$H$200,$P31)="","",INDEX(Installs!$H$1:$H$200,$P31)),"")) | P31: =IF(COUNTIF(Installs!$O$5:$O$200,"<999999999")<9,"",IFERROR(MOD(SMALL(Installs!$O$5:$O$200,9),10000)+4,"")) -> 161
A32: =IF($P32="","",IFERROR(IF(ISNUMBER(INDEX(Installs!$E$1:$E$200,$P32)),INDEX(Installs!$E$1:$E$200,$P32)-TODAY(),"needs date"),"")) -> needs date | B32: =IF($P32="","",IFERROR(IF(INDEX(Installs!$B$1:$B$200,$P32)="","",INDEX(Installs!$B$1:$B$200,$P32)),"")) -> Jonathan's The Rub - Bridgeland | C32: =IF($P32="","",IFERROR(IF(INDEX(Installs!$C$1:$C$200,$P32)="","",INDEX(Installs!$C$1:$C$200,$P32)),"")) -> Cameo c'2s | D32: =IF($P32="","",IFERROR(IF(INDEX(Installs!$D$1:$D$200,$P32)="","",INDEX(Installs!$D$1:$D$200,$P32)),"")) | E32: =IF($P32="","",IFERROR(IF(INDEX(Installs!$E$1:$E$200,$P32)="","",INDEX(Installs!$E$1:$E$200,$P32)),"")) | F32: =IF($P32="","",IFERROR(IF(INDEX(Installs!$F$1:$F$200,$P32)="","",INDEX(Installs!$F$1:$F$200,$P32)),"")) | G32: =IF($P32="","",IFERROR(IF(INDEX(Installs!$G$1:$G$200,$P32)="","",INDEX(Installs!$G$1:$G$200,$P32)),"")) | H32: =IF($P32="","",IFERROR(IF(INDEX(Installs!$H$1:$H$200,$P32)="","",INDEX(Installs!$H$1:$H$200,$P32)),"")) | P32: =IF(COUNTIF(Installs!$O$5:$O$200,"<999999999")<10,"",IFERROR(MOD(SMALL(Installs!$O$5:$O$200,10),10000)+4,"")) -> 162
A33: =IF($P33="","",IFERROR(IF(ISNUMBER(INDEX(Installs!$E$1:$E$200,$P33)),INDEX(Installs!$E$1:$E$200,$P33)-TODAY(),"needs date"),"")) -> needs date | B33: =IF($P33="","",IFERROR(IF(INDEX(Installs!$B$1:$B$200,$P33)="","",INDEX(Installs!$B$1:$B$200,$P33)),"")) -> Valentinas Coffee | C33: =IF($P33="","",IFERROR(IF(INDEX(Installs!$C$1:$C$200,$P33)="","",INDEX(Installs!$C$1:$C$200,$P33)),"")) -> La Marzocco Strada XT 2 Group, Mazzer ZM Filter Grinder - Black, Mazzer Robur S Electronic, Puqpress Q2 Automatic Tamper BLACK, Everpure EZ-RO 200/10 Gallon Hydropneumatic Tank, Blendtec Stealth 885, Blendtec Rapid Rinse Station | D33: =IF($P33="","",IFERROR(IF(INDEX(Installs!$D$1:$D$200,$P33)="","",INDEX(Installs!$D$1:$D$200,$P33)),"")) | E33: =IF($P33="","",IFERROR(IF(INDEX(Installs!$E$1:$E$200,$P33)="","",INDEX(Installs!$E$1:$E$200,$P33)),"")) | F33: =IF($P33="","",IFERROR(IF(INDEX(Installs!$F$1:$F$200,$P33)="","",INDEX(Installs!$F$1:$F$200,$P33)),"")) | G33: =IF($P33="","",IFERROR(IF(INDEX(Installs!$G$1:$G$200,$P33)="","",INDEX(Installs!$G$1:$G$200,$P33)),"")) | H33: =IF($P33="","",IFERROR(IF(INDEX(Installs!$H$1:$H$200,$P33)="","",INDEX(Installs!$H$1:$H$200,$P33)),"")) | P33: =IF(COUNTIF(Installs!$O$5:$O$200,"<999999999")<11,"",IFERROR(MOD(SMALL(Installs!$O$5:$O$200,11),10000)+4,"")) -> 163
A34: =IF($P34="","",IFERROR(IF(ISNUMBER(INDEX(Installs!$E$1:$E$200,$P34)),INDEX(Installs!$E$1:$E$200,$P34)-TODAY(),"needs date"),"")) -> needs date | B34: =IF($P34="","",IFERROR(IF(INDEX(Installs!$B$1:$B$200,$P34)="","",INDEX(Installs!$B$1:$B$200,$P34)),"")) -> The Audrey Restaurant & Bar Post Oak | C34: =IF($P34="","",IFERROR(IF(INDEX(Installs!$C$1:$C$200,$P34)="","",INDEX(Installs!$C$1:$C$200,$P34)),"")) -> Eversys Cameo c'2s | D34: =IF($P34="","",IFERROR(IF(INDEX(Installs!$D$1:$D$200,$P34)="","",INDEX(Installs!$D$1:$D$200,$P34)),"")) | E34: =IF($P34="","",IFERROR(IF(INDEX(Installs!$E$1:$E$200,$P34)="","",INDEX(Installs!$E$1:$E$200,$P34)),"")) | F34: =IF($P34="","",IFERROR(IF(INDEX(Installs!$F$1:$F$200,$P34)="","",INDEX(Installs!$F$1:$F$200,$P34)),"")) | G34: =IF($P34="","",IFERROR(IF(INDEX(Installs!$G$1:$G$200,$P34)="","",INDEX(Installs!$G$1:$G$200,$P34)),"")) | H34: =IF($P34="","",IFERROR(IF(INDEX(Installs!$H$1:$H$200,$P34)="","",INDEX(Installs!$H$1:$H$200,$P34)),"")) | P34: =IF(COUNTIF(Installs!$O$5:$O$200,"<999999999")<12,"",IFERROR(MOD(SMALL(Installs!$O$5:$O$200,12),10000)+4,"")) -> 164
A35: =IF($P35="","",IFERROR(IF(ISNUMBER(INDEX(Installs!$E$1:$E$200,$P35)),INDEX(Installs!$E$1:$E$200,$P35)-TODAY(),"needs date"),"")) -> needs date | B35: =IF($P35="","",IFERROR(IF(INDEX(Installs!$B$1:$B$200,$P35)="","",INDEX(Installs!$B$1:$B$200,$P35)),"")) -> Brews & Books | C35: =IF($P35="","",IFERROR(IF(INDEX(Installs!$C$1:$C$200,$P35)="","",INDEX(Installs!$C$1:$C$200,$P35)),"")) -> Eversys Cameo c'2s | D35: =IF($P35="","",IFERROR(IF(INDEX(Installs!$D$1:$D$200,$P35)="","",INDEX(Installs!$D$1:$D$200,$P35)),"")) | E35: =IF($P35="","",IFERROR(IF(INDEX(Installs!$E$1:$E$200,$P35)="","",INDEX(Installs!$E$1:$E$200,$P35)),"")) | F35: =IF($P35="","",IFERROR(IF(INDEX(Installs!$F$1:$F$200,$P35)="","",INDEX(Installs!$F$1:$F$200,$P35)),"")) | G35: =IF($P35="","",IFERROR(IF(INDEX(Installs!$G$1:$G$200,$P35)="","",INDEX(Installs!$G$1:$G$200,$P35)),"")) | H35: =IF($P35="","",IFERROR(IF(INDEX(Installs!$H$1:$H$200,$P35)="","",INDEX(Installs!$H$1:$H$200,$P35)),"")) | P35: =IF(COUNTIF(Installs!$O$5:$O$200,"<999999999")<13,"",IFERROR(MOD(SMALL(Installs!$O$5:$O$200,13),10000)+4,"")) -> 165
A36: =IF($P36="","",IFERROR(IF(ISNUMBER(INDEX(Installs!$E$1:$E$200,$P36)),INDEX(Installs!$E$1:$E$200,$P36)-TODAY(),"needs date"),"")) | B36: =IF($P36="","",IFERROR(IF(INDEX(Installs!$B$1:$B$200,$P36)="","",INDEX(Installs!$B$1:$B$200,$P36)),"")) | C36: =IF($P36="","",IFERROR(IF(INDEX(Installs!$C$1:$C$200,$P36)="","",INDEX(Installs!$C$1:$C$200,$P36)),"")) | D36: =IF($P36="","",IFERROR(IF(INDEX(Installs!$D$1:$D$200,$P36)="","",INDEX(Installs!$D$1:$D$200,$P36)),"")) | E36: =IF($P36="","",IFERROR(IF(INDEX(Installs!$E$1:$E$200,$P36)="","",INDEX(Installs!$E$1:$E$200,$P36)),"")) | F36: =IF($P36="","",IFERROR(IF(INDEX(Installs!$F$1:$F$200,$P36)="","",INDEX(Installs!$F$1:$F$200,$P36)),"")) | G36: =IF($P36="","",IFERROR(IF(INDEX(Installs!$G$1:$G$200,$P36)="","",INDEX(Installs!$G$1:$G$200,$P36)),"")) | H36: =IF($P36="","",IFERROR(IF(INDEX(Installs!$H$1:$H$200,$P36)="","",INDEX(Installs!$H$1:$H$200,$P36)),"")) | P36: =IF(COUNTIF(Installs!$O$5:$O$200,"<999999999")<14,"",IFERROR(MOD(SMALL(Installs!$O$5:$O$200,14),10000)+4,""))
A37: =IF($P37="","",IFERROR(IF(ISNUMBER(INDEX(Installs!$E$1:$E$200,$P37)),INDEX(Installs!$E$1:$E$200,$P37)-TODAY(),"needs date"),"")) | B37: =IF($P37="","",IFERROR(IF(INDEX(Installs!$B$1:$B$200,$P37)="","",INDEX(Installs!$B$1:$B$200,$P37)),"")) | C37: =IF($P37="","",IFERROR(IF(INDEX(Installs!$C$1:$C$200,$P37)="","",INDEX(Installs!$C$1:$C$200,$P37)),"")) | D37: =IF($P37="","",IFERROR(IF(INDEX(Installs!$D$1:$D$200,$P37)="","",INDEX(Installs!$D$1:$D$200,$P37)),"")) | E37: =IF($P37="","",IFERROR(IF(INDEX(Installs!$E$1:$E$200,$P37)="","",INDEX(Installs!$E$1:$E$200,$P37)),"")) | F37: =IF($P37="","",IFERROR(IF(INDEX(Installs!$F$1:$F$200,$P37)="","",INDEX(Installs!$F$1:$F$200,$P37)),"")) | G37: =IF($P37="","",IFERROR(IF(INDEX(Installs!$G$1:$G$200,$P37)="","",INDEX(Installs!$G$1:$G$200,$P37)),"")) | H37: =IF($P37="","",IFERROR(IF(INDEX(Installs!$H$1:$H$200,$P37)="","",INDEX(Installs!$H$1:$H$200,$P37)),"")) | P37: =IF(COUNTIF(Installs!$O$5:$O$200,"<999999999")<15,"",IFERROR(MOD(SMALL(Installs!$O$5:$O$200,15),10000)+4,""))
A38: =IF($P38="","",IFERROR(IF(ISNUMBER(INDEX(Installs!$E$1:$E$200,$P38)),INDEX(Installs!$E$1:$E$200,$P38)-TODAY(),"needs date"),"")) | B38: =IF($P38="","",IFERROR(IF(INDEX(Installs!$B$1:$B$200,$P38)="","",INDEX(Installs!$B$1:$B$200,$P38)),"")) | C38: =IF($P38="","",IFERROR(IF(INDEX(Installs!$C$1:$C$200,$P38)="","",INDEX(Installs!$C$1:$C$200,$P38)),"")) | D38: =IF($P38="","",IFERROR(IF(INDEX(Installs!$D$1:$D$200,$P38)="","",INDEX(Installs!$D$1:$D$200,$P38)),"")) | E38: =IF($P38="","",IFERROR(IF(INDEX(Installs!$E$1:$E$200,$P38)="","",INDEX(Installs!$E$1:$E$200,$P38)),"")) | F38: =IF($P38="","",IFERROR(IF(INDEX(Installs!$F$1:$F$200,$P38)="","",INDEX(Installs!$F$1:$F$200,$P38)),"")) | G38: =IF($P38="","",IFERROR(IF(INDEX(Installs!$G$1:$G$200,$P38)="","",INDEX(Installs!$G$1:$G$200,$P38)),"")) | H38: =IF($P38="","",IFERROR(IF(INDEX(Installs!$H$1:$H$200,$P38)="","",INDEX(Installs!$H$1:$H$200,$P38)),"")) | P38: =IF(COUNTIF(Installs!$O$5:$O$200,"<999999999")<16,"",IFERROR(MOD(SMALL(Installs!$O$5:$O$200,16),10000)+4,""))
A39: =IF($P39="","",IFERROR(IF(ISNUMBER(INDEX(Installs!$E$1:$E$200,$P39)),INDEX(Installs!$E$1:$E$200,$P39)-TODAY(),"needs date"),"")) | B39: =IF($P39="","",IFERROR(IF(INDEX(Installs!$B$1:$B$200,$P39)="","",INDEX(Installs!$B$1:$B$200,$P39)),"")) | C39: =IF($P39="","",IFERROR(IF(INDEX(Installs!$C$1:$C$200,$P39)="","",INDEX(Installs!$C$1:$C$200,$P39)),"")) | D39: =IF($P39="","",IFERROR(IF(INDEX(Installs!$D$1:$D$200,$P39)="","",INDEX(Installs!$D$1:$D$200,$P39)),"")) | E39: =IF($P39="","",IFERROR(IF(INDEX(Installs!$E$1:$E$200,$P39)="","",INDEX(Installs!$E$1:$E$200,$P39)),"")) | F39: =IF($P39="","",IFERROR(IF(INDEX(Installs!$F$1:$F$200,$P39)="","",INDEX(Installs!$F$1:$F$200,$P39)),"")) | G39: =IF($P39="","",IFERROR(IF(INDEX(Installs!$G$1:$G$200,$P39)="","",INDEX(Installs!$G$1:$G$200,$P39)),"")) | H39: =IF($P39="","",IFERROR(IF(INDEX(Installs!$H$1:$H$200,$P39)="","",INDEX(Installs!$H$1:$H$200,$P39)),"")) | P39: =IF(COUNTIF(Installs!$O$5:$O$200,"<999999999")<17,"",IFERROR(MOD(SMALL(Installs!$O$5:$O$200,17),10000)+4,""))
A40: =IF($P40="","",IFERROR(IF(ISNUMBER(INDEX(Installs!$E$1:$E$200,$P40)),INDEX(Installs!$E$1:$E$200,$P40)-TODAY(),"needs date"),"")) | B40: =IF($P40="","",IFERROR(IF(INDEX(Installs!$B$1:$B$200,$P40)="","",INDEX(Installs!$B$1:$B$200,$P40)),"")) | C40: =IF($P40="","",IFERROR(IF(INDEX(Installs!$C$1:$C$200,$P40)="","",INDEX(Installs!$C$1:$C$200,$P40)),"")) | D40: =IF($P40="","",IFERROR(IF(INDEX(Installs!$D$1:$D$200,$P40)="","",INDEX(Installs!$D$1:$D$200,$P40)),"")) | E40: =IF($P40="","",IFERROR(IF(INDEX(Installs!$E$1:$E$200,$P40)="","",INDEX(Installs!$E$1:$E$200,$P40)),"")) | F40: =IF($P40="","",IFERROR(IF(INDEX(Installs!$F$1:$F$200,$P40)="","",INDEX(Installs!$F$1:$F$200,$P40)),"")) | G40: =IF($P40="","",IFERROR(IF(INDEX(Installs!$G$1:$G$200,$P40)="","",INDEX(Installs!$G$1:$G$200,$P40)),"")) | H40: =IF($P40="","",IFERROR(IF(INDEX(Installs!$H$1:$H$200,$P40)="","",INDEX(Installs!$H$1:$H$200,$P40)),"")) | P40: =IF(COUNTIF(Installs!$O$5:$O$200,"<999999999")<18,"",IFERROR(MOD(SMALL(Installs!$O$5:$O$200,18),10000)+4,""))
A41: =IF($P41="","",IFERROR(IF(ISNUMBER(INDEX(Installs!$E$1:$E$200,$P41)),INDEX(Installs!$E$1:$E$200,$P41)-TODAY(),"needs date"),"")) | B41: =IF($P41="","",IFERROR(IF(INDEX(Installs!$B$1:$B$200,$P41)="","",INDEX(Installs!$B$1:$B$200,$P41)),"")) | C41: =IF($P41="","",IFERROR(IF(INDEX(Installs!$C$1:$C$200,$P41)="","",INDEX(Installs!$C$1:$C$200,$P41)),"")) | D41: =IF($P41="","",IFERROR(IF(INDEX(Installs!$D$1:$D$200,$P41)="","",INDEX(Installs!$D$1:$D$200,$P41)),"")) | E41: =IF($P41="","",IFERROR(IF(INDEX(Installs!$E$1:$E$200,$P41)="","",INDEX(Installs!$E$1:$E$200,$P41)),"")) | F41: =IF($P41="","",IFERROR(IF(INDEX(Installs!$F$1:$F$200,$P41)="","",INDEX(Installs!$F$1:$F$200,$P41)),"")) | G41: =IF($P41="","",IFERROR(IF(INDEX(Installs!$G$1:$G$200,$P41)="","",INDEX(Installs!$G$1:$G$200,$P41)),"")) | H41: =IF($P41="","",IFERROR(IF(INDEX(Installs!$H$1:$H$200,$P41)="","",INDEX(Installs!$H$1:$H$200,$P41)),"")) | P41: =IF(COUNTIF(Installs!$O$5:$O$200,"<999999999")<19,"",IFERROR(MOD(SMALL(Installs!$O$5:$O$200,19),10000)+4,""))
A42: =IF($P42="","",IFERROR(IF(ISNUMBER(INDEX(Installs!$E$1:$E$200,$P42)),INDEX(Installs!$E$1:$E$200,$P42)-TODAY(),"needs date"),"")) | B42: =IF($P42="","",IFERROR(IF(INDEX(Installs!$B$1:$B$200,$P42)="","",INDEX(Installs!$B$1:$B$200,$P42)),"")) | C42: =IF($P42="","",IFERROR(IF(INDEX(Installs!$C$1:$C$200,$P42)="","",INDEX(Installs!$C$1:$C$200,$P42)),"")) | D42: =IF($P42="","",IFERROR(IF(INDEX(Installs!$D$1:$D$200,$P42)="","",INDEX(Installs!$D$1:$D$200,$P42)),"")) | E42: =IF($P42="","",IFERROR(IF(INDEX(Installs!$E$1:$E$200,$P42)="","",INDEX(Installs!$E$1:$E$200,$P42)),"")) | F42: =IF($P42="","",IFERROR(IF(INDEX(Installs!$F$1:$F$200,$P42)="","",INDEX(Installs!$F$1:$F$200,$P42)),"")) | G42: =IF($P42="","",IFERROR(IF(INDEX(Installs!$G$1:$G$200,$P42)="","",INDEX(Installs!$G$1:$G$200,$P42)),"")) | H42: =IF($P42="","",IFERROR(IF(INDEX(Installs!$H$1:$H$200,$P42)="","",INDEX(Installs!$H$1:$H$200,$P42)),"")) | P42: =IF(COUNTIF(Installs!$O$5:$O$200,"<999999999")<20,"",IFERROR(MOD(SMALL(Installs!$O$5:$O$200,20),10000)+4,""))
A43: =IF(COUNTIF(Installs!$O$5:$O$200,"<999999999")=0,"Nothing in the queue — every account with an install date is installed.",IF(COUNTIF(Installs!$O$5:$O$200,"<999999999")>20,"Showing the next 20 of "&COUNTIF(Installs!$O$5:$O$200,"<999999999")&" accounts waiting to be installed.","All "&COUNTIF(Installs!$O$5:$O$200,"<999999999")&" account(s) waiting to be installed are listed above.")) -> All 13 account(s) waiting to be installed are listed above.
A45: ="Sales hand-off: "&COUNTIF('Projected Sales or Lease'!$L$3:$L$200,"✔")&" completed deal(s) on the Projected tab · "&SUM('Projected Sales or Lease'!$N$3:$N$200)&" not yet in this tracker (shown in the AUTO section) · "&(COUNTIF('Projected Sales or Lease'!$L$3:$L$200,"✔")-SUM('Projected Sales or Lease'!$N$3:$N$200))&" already tracked, so not duplicated." -> Sales hand-off: 15 completed deal(s) on the Projected tab · 5 not yet in this tracker (shown in the AUTO section) · 10 already tracked, so not duplicated.

Sheet Installs
A1: INSTALLATION TRACKER | C1: ⏱ Open the Install Clock →
A2: Today | B2: This week (Mon–Sun) | C2: Next week | D2: ⚠ Equipment NOT ready | E2: ⚠ Past due & not ready | F2: ⚠ Customer not ready | G2: Completed installs | H2: In queue (not yet installed) | I2: Full detail — who is at risk and what to prep next — is on the Install Clock tab.
A3: =TODAY() -> 46254 | B3: =TEXT($P$3,"m/d")&" – "&TEXT($P$4,"m/d") -> 8/17 – 8/23 | C3: =TEXT($P$3+7,"m/d")&" – "&TEXT($P$5,"m/d") -> 8/24 – 8/30 | D3: =COUNTIF($M$5:$M$200,"⚠ EQUIP NOT READY") -> 0 | E3: =COUNTIF($M$5:$M$200,"⚠ PAST DUE - NOT READY") -> 0 | F3: =COUNTIF($M$5:$M$200,"⚠ CUSTOMER NOT READY") -> 0 | G3: =COUNTIF($D$5:$D$200,"Installed") -> 41 | H3: =COUNTIF($O$5:$O$200,"<999999999") -> 13 | P3: =TODAY()-WEEKDAY(TODAY(),2)+1 -> 46251
A4: Date Received | B4: Customer Name | C4: Equipment / Serial Numbers | D4: Equipment Status | E4: Install Date | F4: Assigned Tech | G4: Work Order | H4: Requirements Ready? | I4: Notes | J4: Account Rep | K4: Payment Status | L4: Install Complete ✔ | M4: ⚠ Install Alert | P4: =P3+6 -> 46257
A5: 46155 | B5: Wildwood | C5: Fetco 52H SN:231515042 | D5: Installed | E5: 46169 | F5: Josh | G5: WO-9537 | H5: Ready | I5: Elia Bench 5/20/2026 | J5: AL | K5: No Purchased Equipment | L5: =IF($D5="Installed","✔","") -> ✔ | M5: =IF($B5="","",IF($D5="Installed","",IF(AND($D5="Not Ready",$E5<>"",NOT(ISNUMBER($E5))),"⚠ CHECK DATE",IF(AND($D5="Not Ready",ISNUMBER($E5),$E5<$P$3),"⚠ PAST DUE - NOT READY",IF(AND($D5="Not Ready",ISNUMBER($E5),$E5>=$P$3,$E5<=$P$5),"⚠ EQUIP NOT READY",IF(AND($H5="Not Ready",ISNUMBER($E5),$E5>=$P$3,$E5<=$P$5),"⚠ CUSTOMER NOT READY","")))))) | O5: =IF($B5="",999999999,IF($D5="Installed",999999999,IF(NOT(ISNUMBER($E5)),999900000+1,$E5*10000+1))) -> 999999999 | P5: =P3+13 -> 46264 | Q5: =IF(LEFT($M5,1)="⚠",1,0) -> 0 | R5: =IF($Q5=1,SUM($Q$5:$Q5),"")
A6: 46141 | B6: Gennaro's - Wimberly | C6: Bunn ITCB | D6: Installed | E6: 46162 | F6: Lance | G6: WO-9469 | H6: Ready | J6: LO | K6: No Purchased Equipment | L6: =IF($D6="Installed","✔","") -> ✔ | M6: =IF($B6="","",IF($D6="Installed","",IF(AND($D6="Not Ready",$E6<>"",NOT(ISNUMBER($E6))),"⚠ CHECK DATE",IF(AND($D6="Not Ready",ISNUMBER($E6),$E6<$P$3),"⚠ PAST DUE - NOT READY",IF(AND($D6="Not Ready",ISNUMBER($E6),$E6>=$P$3,$E6<=$P$5),"⚠ EQUIP NOT READY",IF(AND($H6="Not Ready",ISNUMBER($E6),$E6>=$P$3,$E6<=$P$5),"⚠ CUSTOMER NOT READY","")))))) | O6: =IF($B6="",999999999,IF($D6="Installed",999999999,IF(NOT(ISNUMBER($E6)),999900000+2,$E6*10000+2))) -> 999999999 | Q6: =IF(LEFT($M6,1)="⚠",1,0) -> 0 | R6: =IF($Q6=1,SUM($Q$5:$Q6),"")
A7: 46141 | B7: Common Bond Spring | C7: 2 x e4s with 1.5 wands SN: 0110710025266E0006 Fetco 1252 Plus SN: 1252UB23015260303 Bunn ITB-DD SN: ITB0065171 Fetco GRS1202 SN:12021A00020259710 | D7: Installed | E7: 46170 | F7: Josh | G7: WO-9589 | H7: Ready | I7: All equipment needs to be benched Ryan Bench GR 1202 Elia Bench ITB-DD Josh Bench/setup 1x e4'ms 1.5 arm installed 05/28/2026 | J7: AL | K7: Payment Plan | L7: =IF($D7="Installed","✔","") -> ✔ | M7: =IF($B7="","",IF($D7="Installed","",IF(AND($D7="Not Ready",$E7<>"",NOT(ISNUMBER($E7))),"⚠ CHECK DATE",IF(AND($D7="Not Ready",ISNUMBER($E7),$E7<$P$3),"⚠ PAST DUE - NOT READY",IF(AND($D7="Not Ready",ISNUMBER($E7),$E7>=$P$3,$E7<=$P$5),"⚠ EQUIP NOT READY",IF(AND($H7="Not Ready",ISNUMBER($E7),$E7>=$P$3,$E7<=$P$5),"⚠ CUSTOMER NOT READY","")))))) | O7: =IF($B7="",999999999,IF($D7="Installed",999999999,IF(NOT(ISNUMBER($E7)),999900000+3,$E7*10000+3))) -> 999999999 | Q7: =IF(LEFT($M7,1)="⚠",1,0) -> 0 | R7: =IF($Q7=1,SUM($Q$5:$Q7),"")
A8: 46143 | B8: Local Foods - ATX #2 | C8: LM Linea S 2AV SN:LS028751 Swift Grinder SN:9386 Fetco 1251 SN:12511B23045259780 Bunn ITB-DD SN:ITB0065194 EZRO200-10 | D8: Installed | E8: 46224 | F8: Oliver | G8: WO-0134 | H8: Ready | I8: Linea, Swift, and fetco Benched by Oliver ITB-DD benched by Elias SWIFT is at Local Foods #1 Austin | J8: AL/LO | K8: Paid in Full | L8: =IF($D8="Installed","✔","") -> ✔ | M8: =IF($B8="","",IF($D8="Installed","",IF(AND($D8="Not Ready",$E8<>"",NOT(ISNUMBER($E8))),"⚠ CHECK DATE",IF(AND($D8="Not Ready",ISNUMBER($E8),$E8<$P$3),"⚠ PAST DUE - NOT READY",IF(AND($D8="Not Ready",ISNUMBER($E8),$E8>=$P$3,$E8<=$P$5),"⚠ EQUIP NOT READY",IF(AND($H8="Not Ready",ISNUMBER($E8),$E8>=$P$3,$E8<=$P$5),"⚠ CUSTOMER NOT READY","")))))) | O8: =IF($B8="",999999999,IF($D8="Installed",999999999,IF(NOT(ISNUMBER($E8)),999900000+4,$E8*10000+4))) -> 999999999 | Q8: =IF(LEFT($M8,1)="⚠",1,0) -> 0 | R8: =IF($Q8=1,SUM($Q$5:$Q8),"")
A9: 46143 | B9: CoPlay Cove | C9: e4s SN: 0110700025150E0012 Bunn Axiom-APS 120V SN: AXAP048647 | D9: Installed | E9: 46181 | F9: Lance | G9: WO-9698 | H9: Ready | I9: velvet / Decaf 8oz/12oz need kids temp steam (orig. install date entered as "Week of 6/8") | J9: LR | K9: Paid in Full | L9: =IF($D9="Installed","✔","") -> ✔ | M9: =IF($B9="","",IF($D9="Installed","",IF(AND($D9="Not Ready",$E9<>"",NOT(ISNUMBER($E9))),"⚠ CHECK DATE",IF(AND($D9="Not Ready",ISNUMBER($E9),$E9<$P$3),"⚠ PAST DUE - NOT READY",IF(AND($D9="Not Ready",ISNUMBER($E9),$E9>=$P$3,$E9<=$P$5),"⚠ EQUIP NOT READY",IF(AND($H9="Not Ready",ISNUMBER($E9),$E9>=$P$3,$E9<=$P$5),"⚠ CUSTOMER NOT READY","")))))) | O9: =IF($B9="",999999999,IF($D9="Installed",999999999,IF(NOT(ISNUMBER($E9)),999900000+5,$E9*10000+5))) -> 999999999 | Q9: =IF(LEFT($M9,1)="⚠",1,0) -> 0 | R9: =IF($Q9=1,SUM($Q$5:$Q9),"")
A10: 46143 | B10: La Michoacana #52 - Dallas | C10: Bunn ITCB 220V | D10: Installed | E10: 46175 | F10: Bill | G10: WO-9646 | H10: Ready | J10: LR | K10: No Purchased Equipment | L10: =IF($D10="Installed","✔","") -> ✔ | M10: =IF($B10="","",IF($D10="Installed","",IF(AND($D10="Not Ready",$E10<>"",NOT(ISNUMBER($E10))),"⚠ CHECK DATE",IF(AND($D10="Not Ready",ISNUMBER($E10),$E10<$P$3),"⚠ PAST DUE - NOT READY",IF(AND($D10="Not Ready",ISNUMBER($E10),$E10>=$P$3,$E10<=$P$5),"⚠ EQUIP NOT READY",IF(AND($H10="Not Ready",ISNUMBER($E10),$E10>=$P$3,$E10<=$P$5),"⚠ CUSTOMER NOT READY","")))))) | O10: =IF($B10="",999999999,IF($D10="Installed",999999999,IF(NOT(ISNUMBER($E10)),999900000+6,$E10*10000+6))) -> 999999999 | Q10: =IF(LEFT($M10,1)="⚠",1,0) -> 0 | R10: =IF($Q10=1,SUM($Q$5:$Q10),"")
A11: 46148 | B11: Hunter Road Country Club | C11: Bunn ITCB 120V SN:ITCB189507 | D11: Installed | E11: 46164 | F11: Lance | G11: WO-9470 | H11: Ready | I11: 85oz Airpots Ship on Wednesday truck. 5/20 Oliver Benched and Boxed for shipment 05/18 | J11: AL/LO | K11: No Purchased Equipment | L11: =IF($D11="Installed","✔","") -> ✔ | M11: =IF($B11="","",IF($D11="Installed","",IF(AND($D11="Not Ready",$E11<>"",NOT(ISNUMBER($E11))),"⚠ CHECK DATE",IF(AND($D11="Not Ready",ISNUMBER($E11),$E11<$P$3),"⚠ PAST DUE - NOT READY",IF(AND($D11="Not Ready",ISNUMBER($E11),$E11>=$P$3,$E11<=$P$5),"⚠ EQUIP NOT READY",IF(AND($H11="Not Ready",ISNUMBER($E11),$E11>=$P$3,$E11<=$P$5),"⚠ CUSTOMER NOT READY","")))))) | O11: =IF($B11="",999999999,IF($D11="Installed",999999999,IF(NOT(ISNUMBER($E11)),999900000+7,$E11*10000+7))) -> 999999999 | Q11: =IF(LEFT($M11,1)="⚠",1,0) -> 0 | R11: =IF($Q11=1,SUM($Q$5:$Q11),"")
A12: 46160 | B12: Cowgirl Coffee | C12: Bunn Axiom-APS 120V SN:AXAP028340 | D12: Installed | E12: 46175 | F12: Elias | G12: WO-9477 | H12: Ready | I12: Elias benched 05/19 | J12: AL/LO | K12: No Purchased Equipment | L12: =IF($D12="Installed","✔","") -> ✔ | M12: =IF($B12="","",IF($D12="Installed","",IF(AND($D12="Not Ready",$E12<>"",NOT(ISNUMBER($E12))),"⚠ CHECK DATE",IF(AND($D12="Not Ready",ISNUMBER($E12),$E12<$P$3),"⚠ PAST DUE - NOT READY",IF(AND($D12="Not Ready",ISNUMBER($E12),$E12>=$P$3,$E12<=$P$5),"⚠ EQUIP NOT READY",IF(AND($H12="Not Ready",ISNUMBER($E12),$E12>=$P$3,$E12<=$P$5),"⚠ CUSTOMER NOT READY","")))))) | O12: =IF($B12="",999999999,IF($D12="Installed",999999999,IF(NOT(ISNUMBER($E12)),999900000+8,$E12*10000+8))) -> 999999999 | Q12: =IF(LEFT($M12,1)="⚠",1,0) -> 0 | R12: =IF($Q12=1,SUM($Q$5:$Q12),"")
A13: 46164 | B13: Sunrise Coffee | C13: Linea S 2 Group SN:LS029320 Mazzer Super Jolly SN:2540764 | D13: Installed | E13: 46231 | F13: Josh | G13: WO-0143 | H13: Ready | I13: Need to pre-insepct first Velvet Esp 2oz | J13: AL/LO | K13: 50% Down / 50% at Install or Net 30 | L13: =IF($D13="Installed","✔","") -> ✔ | M13: =IF($B13="","",IF($D13="Installed","",IF(AND($D13="Not Ready",$E13<>"",NOT(ISNUMBER($E13))),"⚠ CHECK DATE",IF(AND($D13="Not Ready",ISNUMBER($E13),$E13<$P$3),"⚠ PAST DUE - NOT READY",IF(AND($D13="Not Ready",ISNUMBER($E13),$E13>=$P$3,$E13<=$P$5),"⚠ EQUIP NOT READY",IF(AND($H13="Not Ready",ISNUMBER($E13),$E13>=$P$3,$E13<=$P$5),"⚠ CUSTOMER NOT READY","")))))) | O13: =IF($B13="",999999999,IF($D13="Installed",999999999,IF(NOT(ISNUMBER($E13)),999900000+9,$E13*10000+9))) -> 999999999 | Q13: =IF(LEFT($M13,1)="⚠",1,0) -> 0 | R13: =IF($Q13=1,SUM($Q$5:$Q13),"")
A14: 46163 | B14: Cherry Block | C14: CWTF-APS Pour over | D14: Installed | E14: 46169 | F14: Ryan | G14: WO-9582 | H14: Ready | J14: LR | K14: No Purchased Equipment | L14: =IF($D14="Installed","✔","") -> ✔ | M14: =IF($B14="","",IF($D14="Installed","",IF(AND($D14="Not Ready",$E14<>"",NOT(ISNUMBER($E14))),"⚠ CHECK DATE",IF(AND($D14="Not Ready",ISNUMBER($E14),$E14<$P$3),"⚠ PAST DUE - NOT READY",IF(AND($D14="Not Ready",ISNUMBER($E14),$E14>=$P$3,$E14<=$P$5),"⚠ EQUIP NOT READY",IF(AND($H14="Not Ready",ISNUMBER($E14),$E14>=$P$3,$E14<=$P$5),"⚠ CUSTOMER NOT READY","")))))) | O14: =IF($B14="",999999999,IF($D14="Installed",999999999,IF(NOT(ISNUMBER($E14)),999900000+10,$E14*10000+10))) -> 999999999 | Q14: =IF(LEFT($M14,1)="⚠",1,0) -> 0 | R14: =IF($Q14=1,SUM($Q$5:$Q14),"")
A15: 46168 | B15: Osso | C15: Mazzer Mini Doser SN: 2318377 | D15: Installed | E15: 46175 | F15: Ryan | G15: WO-9600 | H15: Ready | I15: Adding Whole Bean espresso Elias Benching 6/1/2026 | J15: SC | K15: No Purchased Equipment | L15: =IF($D15="Installed","✔","") -> ✔ | M15: =IF($B15="","",IF($D15="Installed","",IF(AND($D15="Not Ready",$E15<>"",NOT(ISNUMBER($E15))),"⚠ CHECK DATE",IF(AND($D15="Not Ready",ISNUMBER($E15),$E15<$P$3),"⚠ PAST DUE - NOT READY",IF(AND($D15="Not Ready",ISNUMBER($E15),$E15>=$P$3,$E15<=$P$5),"⚠ EQUIP NOT READY",IF(AND($H15="Not Ready",ISNUMBER($E15),$E15>=$P$3,$E15<=$P$5),"⚠ CUSTOMER NOT READY","")))))) | O15: =IF($B15="",999999999,IF($D15="Installed",999999999,IF(NOT(ISNUMBER($E15)),999900000+11,$E15*10000+11))) -> 999999999 | Q15: =IF(LEFT($M15,1)="⚠",1,0) -> 0 | R15: =IF($Q15=1,SUM($Q$5:$Q15),"")
A16: 46170 | B16: Latte Cafe - La Grange | C16: Classe 9 | D16: Installed | E16: 46177 | F16: Oliver | G16: WO-9598 | H16: Ready | I16: Ollie Calibrating josh verified working | J16: JG | K16: Paid in Full | L16: =IF($D16="Installed","✔","") -> ✔ | M16: =IF($B16="","",IF($D16="Installed","",IF(AND($D16="Not Ready",$E16<>"",NOT(ISNUMBER($E16))),"⚠ CHECK DATE",IF(AND($D16="Not Ready",ISNUMBER($E16),$E16<$P$3),"⚠ PAST DUE - NOT READY",IF(AND($D16="Not Ready",ISNUMBER($E16),$E16>=$P$3,$E16<=$P$5),"⚠ EQUIP NOT READY",IF(AND($H16="Not Ready",ISNUMBER($E16),$E16>=$P$3,$E16<=$P$5),"⚠ CUSTOMER NOT READY","")))))) | O16: =IF($B16="",999999999,IF($D16="Installed",999999999,IF(NOT(ISNUMBER($E16)),999900000+12,$E16*10000+12))) -> 999999999 | Q16: =IF(LEFT($M16,1)="⚠",1,0) -> 0 | R16: =IF($Q16=1,SUM($Q$5:$Q16),"")
A17: 46170 | B17: Shirley's Donut | C17: Bunn Axiom-APS 120V SN:AXAP049095 Bunn G9-2 Short SN: G900075916 | D17: Installed | E17: 46177 | F17: Ryan | G17: WO-9638 | H17: Ready | J17: LR | K17: No Purchased Equipment | L17: =IF($D17="Installed","✔","") -> ✔ | M17: =IF($B17="","",IF($D17="Installed","",IF(AND($D17="Not Ready",$E17<>"",NOT(ISNUMBER($E17))),"⚠ CHECK DATE",IF(AND($D17="Not Ready",ISNUMBER($E17),$E17<$P$3),"⚠ PAST DUE - NOT READY",IF(AND($D17="Not Ready",ISNUMBER($E17),$E17>=$P$3,$E17<=$P$5),"⚠ EQUIP NOT READY",IF(AND($H17="Not Ready",ISNUMBER($E17),$E17>=$P$3,$E17<=$P$5),"⚠ CUSTOMER NOT READY","")))))) | O17: =IF($B17="",999999999,IF($D17="Installed",999999999,IF(NOT(ISNUMBER($E17)),999900000+13,$E17*10000+13))) -> 999999999 | Q17: =IF(LEFT($M17,1)="⚠",1,0) -> 0 | R17: =IF($Q17=1,SUM($Q$5:$Q17),"")
A18: 46170 | B18: Velocity Sim Lounge | C18: Bunn Axiom SN:AXAP028345 | D18: Installed | E18: 46183 | F18: Oliver | G18: WO-9665 | H18: Ready | J18: AL | K18: No Purchased Equipment | L18: =IF($D18="Installed","✔","") -> ✔ | M18: =IF($B18="","",IF($D18="Installed","",IF(AND($D18="Not Ready",$E18<>"",NOT(ISNUMBER($E18))),"⚠ CHECK DATE",IF(AND($D18="Not Ready",ISNUMBER($E18),$E18<$P$3),"⚠ PAST DUE - NOT READY",IF(AND($D18="Not Ready",ISNUMBER($E18),$E18>=$P$3,$E18<=$P$5),"⚠ EQUIP NOT READY",IF(AND($H18="Not Ready",ISNUMBER($E18),$E18>=$P$3,$E18<=$P$5),"⚠ CUSTOMER NOT READY","")))))) | O18: =IF($B18="",999999999,IF($D18="Installed",999999999,IF(NOT(ISNUMBER($E18)),999900000+14,$E18*10000+14))) -> 999999999 | Q18: =IF(LEFT($M18,1)="⚠",1,0) -> 0 | R18: =IF($Q18=1,SUM($Q$5:$Q18),"")
A19: 46170 | B19: Cheeks Coffee | C19: ITCB SN: ITCB075996 | D19: Installed | E19: 46182 | F19: Elias | G19: WO-9672 | H19: Ready | J19: AL | K19: Paid in Full | L19: =IF($D19="Installed","✔","") -> ✔ | M19: =IF($B19="","",IF($D19="Installed","",IF(AND($D19="Not Ready",$E19<>"",NOT(ISNUMBER($E19))),"⚠ CHECK DATE",IF(AND($D19="Not Ready",ISNUMBER($E19),$E19<$P$3),"⚠ PAST DUE - NOT READY",IF(AND($D19="Not Ready",ISNUMBER($E19),$E19>=$P$3,$E19<=$P$5),"⚠ EQUIP NOT READY",IF(AND($H19="Not Ready",ISNUMBER($E19),$E19>=$P$3,$E19<=$P$5),"⚠ CUSTOMER NOT READY","")))))) | O19: =IF($B19="",999999999,IF($D19="Installed",999999999,IF(NOT(ISNUMBER($E19)),999900000+15,$E19*10000+15))) -> 999999999 | Q19: =IF(LEFT($M19,1)="⚠",1,0) -> 0 | R19: =IF($Q19=1,SUM($Q$5:$Q19),"")
A20: 46177 | B20: Kol Fac #113 | C20: Bunn ITCB SN: ITCB082942 | D20: Installed | E20: 46183 | F20: Oliver | G20: WO-9697 | H20: Ready | J20: AL | K20: No Purchased Equipment | L20: =IF($D20="Installed","✔","") -> ✔ | M20: =IF($B20="","",IF($D20="Installed","",IF(AND($D20="Not Ready",$E20<>"",NOT(ISNUMBER($E20))),"⚠ CHECK DATE",IF(AND($D20="Not Ready",ISNUMBER($E20),$E20<$P$3),"⚠ PAST DUE - NOT READY",IF(AND($D20="Not Ready",ISNUMBER($E20),$E20>=$P$3,$E20<=$P$5),"⚠ EQUIP NOT READY",IF(AND($H20="Not Ready",ISNUMBER($E20),$E20>=$P$3,$E20<=$P$5),"⚠ CUSTOMER NOT READY","")))))) | O20: =IF($B20="",999999999,IF($D20="Installed",999999999,IF(NOT(ISNUMBER($E20)),999900000+16,$E20*10000+16))) -> 999999999 | Q20: =IF(LEFT($M20,1)="⚠",1,0) -> 0 | R20: =IF($Q20=1,SUM($Q$5:$Q20),"")
A21: 46182 | B21: Audrey Post Oak | C21: ITCB 220v SN:143215 Cameo - Not here yet. Need a loaner for Cameo | D21: Installed | E21: 46191 | F21: Ryan | G21: WO-9875 | H21: Ready | J21: LR | K21: Lease | L21: =IF($D21="Installed","✔","") -> ✔ | M21: =IF($B21="","",IF($D21="Installed","",IF(AND($D21="Not Ready",$E21<>"",NOT(ISNUMBER($E21))),"⚠ CHECK DATE",IF(AND($D21="Not Ready",ISNUMBER($E21),$E21<$P$3),"⚠ PAST DUE - NOT READY",IF(AND($D21="Not Ready",ISNUMBER($E21),$E21>=$P$3,$E21<=$P$5),"⚠ EQUIP NOT READY",IF(AND($H21="Not Ready",ISNUMBER($E21),$E21>=$P$3,$E21<=$P$5),"⚠ CUSTOMER NOT READY","")))))) | O21: =IF($B21="",999999999,IF($D21="Installed",999999999,IF(NOT(ISNUMBER($E21)),999900000+17,$E21*10000+17))) -> 999999999 | Q21: =IF(LEFT($M21,1)="⚠",1,0) -> 0 | R21: =IF($Q21=1,SUM($Q$5:$Q21),"")
A22: 46184 | B22: Sweet | C22: Bunn Axiom-APS SN :AXAP049095 | D22: Installed | E22: 46188 | F22: Oliver | G22: WO-9642 | H22: Ready | I22: (orig. install date entered as "week of 6/15/2026") | J22: AL/JG | K22: No Purchased Equipment | L22: =IF($D22="Installed","✔","") -> ✔ | M22: =IF($B22="","",IF($D22="Installed","",IF(AND($D22="Not Ready",$E22<>"",NOT(ISNUMBER($E22))),"⚠ CHECK DATE",IF(AND($D22="Not Ready",ISNUMBER($E22),$E22<$P$3),"⚠ PAST DUE - NOT READY",IF(AND($D22="Not Ready",ISNUMBER($E22),$E22>=$P$3,$E22<=$P$5),"⚠ EQUIP NOT READY",IF(AND($H22="Not Ready",ISNUMBER($E22),$E22>=$P$3,$E22<=$P$5),"⚠ CUSTOMER NOT READY","")))))) | O22: =IF($B22="",999999999,IF($D22="Installed",999999999,IF(NOT(ISNUMBER($E22)),999900000+18,$E22*10000+18))) -> 999999999 | Q22: =IF(LEFT($M22,1)="⚠",1,0) -> 0 | R22: =IF($Q22=1,SUM($Q$5:$Q22),"")
A23: 46184 | B23: Taha Market Mediterranean Foods | C23: Cameo - New in barn SN: 0099820025259C0040 | D23: Installed | E23: 46188 | F23: Oliver | G23: WO-9874 | H23: Ready | I23: (orig. install date entered as "week of 6/15/2026") | J23: SM/RK | K23: Lease | L23: =IF($D23="Installed","✔","") -> ✔ | M23: =IF($B23="","",IF($D23="Installed","",IF(AND($D23="Not Ready",$E23<>"",NOT(ISNUMBER($E23))),"⚠ CHECK DATE",IF(AND($D23="Not Ready",ISNUMBER($E23),$E23<$P$3),"⚠ PAST DUE - NOT READY",IF(AND($D23="Not Ready",ISNUMBER($E23),$E23>=$P$3,$E23<=$P$5),"⚠ EQUIP NOT READY",IF(AND($H23="Not Ready",ISNUMBER($E23),$E23>=$P$3,$E23<=$P$5),"⚠ CUSTOMER NOT READY","")))))) | O23: =IF($B23="",999999999,IF($D23="Installed",999999999,IF(NOT(ISNUMBER($E23)),999900000+19,$E23*10000+19))) -> 999999999 | Q23: =IF(LEFT($M23,1)="⚠",1,0) -> 0 | R23: =IF($Q23=1,SUM($Q$5:$Q23),"")
A24: 46189 | B24: Tepatitlan Mexican Grill | C24: Bunn ITCB 120v SN:ITCB064919 Bunn G9-2T SN:G900073972 | D24: Installed | E24: 46195 | F24: Ryan | G24: WO-9897 | H24: Ready | I24: Account is read. replacing same equipment. | J24: LR | K24: No Purchased Equipment | L24: =IF($D24="Installed","✔","") -> ✔ | M24: =IF($B24="","",IF($D24="Installed","",IF(AND($D24="Not Ready",$E24<>"",NOT(ISNUMBER($E24))),"⚠ CHECK DATE",IF(AND($D24="Not Ready",ISNUMBER($E24),$E24<$P$3),"⚠ PAST DUE - NOT READY",IF(AND($D24="Not Ready",ISNUMBER($E24),$E24>=$P$3,$E24<=$P$5),"⚠ EQUIP NOT READY",IF(AND($H24="Not Ready",ISNUMBER($E24),$E24>=$P$3,$E24<=$P$5),"⚠ CUSTOMER NOT READY","")))))) | O24: =IF($B24="",999999999,IF($D24="Installed",999999999,IF(NOT(ISNUMBER($E24)),999900000+20,$E24*10000+20))) -> 999999999 | Q24: =IF(LEFT($M24,1)="⚠",1,0) -> 0 | R24: =IF($Q24=1,SUM($Q$5:$Q24),"")
A25: 46191 | B25: Clutch Auto - Pearland | C25: Bunn CWTF-APS (PO) SN:CWTF547359 | D25: Installed | E25: 46197 | F25: Elias | G25: WO-9941 | H25: Ready | I25: Pedro is gettting a unit ready | J25: AL | K25: No Purchased Equipment | L25: =IF($D25="Installed","✔","") -> ✔ | M25: =IF($B25="","",IF($D25="Installed","",IF(AND($D25="Not Ready",$E25<>"",NOT(ISNUMBER($E25))),"⚠ CHECK DATE",IF(AND($D25="Not Ready",ISNUMBER($E25),$E25<$P$3),"⚠ PAST DUE - NOT READY",IF(AND($D25="Not Ready",ISNUMBER($E25),$E25>=$P$3,$E25<=$P$5),"⚠ EQUIP NOT READY",IF(AND($H25="Not Ready",ISNUMBER($E25),$E25>=$P$3,$E25<=$P$5),"⚠ CUSTOMER NOT READY","")))))) | O25: =IF($B25="",999999999,IF($D25="Installed",999999999,IF(NOT(ISNUMBER($E25)),999900000+21,$E25*10000+21))) -> 999999999 | Q25: =IF(LEFT($M25,1)="⚠",1,0) -> 0 | R25: =IF($Q25=1,SUM($Q$5:$Q25),"")
A26: 46191 | B26: Clover | C26: E4s | D26: Installed | E26: 46195 | F26: Oliver | G26: WO-9891 | H26: Ready | I26: getting e4s from lobby (orig. install date entered as "week of 6/22") | J26: AL/JG | K26: Paid in Full | L26: =IF($D26="Installed","✔","") -> ✔ | M26: =IF($B26="","",IF($D26="Installed","",IF(AND($D26="Not Ready",$E26<>"",NOT(ISNUMBER($E26))),"⚠ CHECK DATE",IF(AND($D26="Not Ready",ISNUMBER($E26),$E26<$P$3),"⚠ PAST DUE - NOT READY",IF(AND($D26="Not Ready",ISNUMBER($E26),$E26>=$P$3,$E26<=$P$5),"⚠ EQUIP NOT READY",IF(AND($H26="Not Ready",ISNUMBER($E26),$E26>=$P$3,$E26<=$P$5),"⚠ CUSTOMER NOT READY","")))))) | O26: =IF($B26="",999999999,IF($D26="Installed",999999999,IF(NOT(ISNUMBER($E26)),999900000+22,$E26*10000+22))) -> 999999999 | Q26: =IF(LEFT($M26,1)="⚠",1,0) -> 0 | R26: =IF($Q26=1,SUM($Q$5:$Q26),"")
A27: 46192 | B27: Triple Steel - Galvestion | C27: Bunn Axiom-APS | D27: Installed | E27: 46203 | F27: Ryan | G27: WO-9934 | H27: Ready | I27: (orig. install date entered as "week of 6/30") | K27: No Purchased Equipment | L27: =IF($D27="Installed","✔","") -> ✔ | M27: =IF($B27="","",IF($D27="Installed","",IF(AND($D27="Not Ready",$E27<>"",NOT(ISNUMBER($E27))),"⚠ CHECK DATE",IF(AND($D27="Not Ready",ISNUMBER($E27),$E27<$P$3),"⚠ PAST DUE - NOT READY",IF(AND($D27="Not Ready",ISNUMBER($E27),$E27>=$P$3,$E27<=$P$5),"⚠ EQUIP NOT READY",IF(AND($H27="Not Ready",ISNUMBER($E27),$E27>=$P$3,$E27<=$P$5),"⚠ CUSTOMER NOT READY","")))))) | O27: =IF($B27="",999999999,IF($D27="Installed",999999999,IF(NOT(ISNUMBER($E27)),999900000+23,$E27*10000+23))) -> 999999999 | Q27: =IF(LEFT($M27,1)="⚠",1,0) -> 0 | R27: =IF($Q27=1,SUM($Q$5:$Q27),"")
A28: 46202 | B28: Helfman RiverOaks | C28: Sego 12 SN:10140095 | D28: Installed | E28: 46217 | F28: Elias | G28: WO-0091 | H28: Ready | I28: Velvet Hot Choco Epouria milk | J28: AL | K28: No Purchased Equipment | L28: =IF($D28="Installed","✔","") -> ✔ | M28: =IF($B28="","",IF($D28="Installed","",IF(AND($D28="Not Ready",$E28<>"",NOT(ISNUMBER($E28))),"⚠ CHECK DATE",IF(AND($D28="Not Ready",ISNUMBER($E28),$E28<$P$3),"⚠ PAST DUE - NOT READY",IF(AND($D28="Not Ready",ISNUMBER($E28),$E28>=$P$3,$E28<=$P$5),"⚠ EQUIP NOT READY",IF(AND($H28="Not Ready",ISNUMBER($E28),$E28>=$P$3,$E28<=$P$5),"⚠ CUSTOMER NOT READY","")))))) | O28: =IF($B28="",999999999,IF($D28="Installed",999999999,IF(NOT(ISNUMBER($E28)),999900000+24,$E28*10000+24))) -> 999999999 | Q28: =IF(LEFT($M28,1)="⚠",1,0) -> 0 | R28: =IF($Q28=1,SUM($Q$5:$Q28),"")
A29: 46203 | B29: Uchi | C29: Legacy | D29: Installed | E29: 46224 | F29: Oliver | G29: WO-0138 | H29: Ready | I29: Waiting on product and setting | J29: SC | L29: =IF($D29="Installed","✔","") -> ✔ | M29: =IF($B29="","",IF($D29="Installed","",IF(AND($D29="Not Ready",$E29<>"",NOT(ISNUMBER($E29))),"⚠ CHECK DATE",IF(AND($D29="Not Ready",ISNUMBER($E29),$E29<$P$3),"⚠ PAST DUE - NOT READY",IF(AND($D29="Not Ready",ISNUMBER($E29),$E29>=$P$3,$E29<=$P$5),"⚠ EQUIP NOT READY",IF(AND($H29="Not Ready",ISNUMBER($E29),$E29>=$P$3,$E29<=$P$5),"⚠ CUSTOMER NOT READY","")))))) | O29: =IF($B29="",999999999,IF($D29="Installed",999999999,IF(NOT(ISNUMBER($E29)),999900000+25,$E29*10000+25))) -> 999999999 | Q29: =IF(LEFT($M29,1)="⚠",1,0) -> 0 | R29: =IF($Q29=1,SUM($Q$5:$Q29),"")
A30: 46203 | B30: Parkwood American Grille | C30: Legacy (Cameo loaner for the time being), ITCB | D30: Installed | E30: 46233 | F30: Ryan | G30: WO-0250 | H30: Ready | J30: AL | K30: 50% Down / 50% at Install or Net 30 | L30: =IF($D30="Installed","✔","") -> ✔ | M30: =IF($B30="","",IF($D30="Installed","",IF(AND($D30="Not Ready",$E30<>"",NOT(ISNUMBER($E30))),"⚠ CHECK DATE",IF(AND($D30="Not Ready",ISNUMBER($E30),$E30<$P$3),"⚠ PAST DUE - NOT READY",IF(AND($D30="Not Ready",ISNUMBER($E30),$E30>=$P$3,$E30<=$P$5),"⚠ EQUIP NOT READY",IF(AND($H30="Not Ready",ISNUMBER($E30),$E30>=$P$3,$E30<=$P$5),"⚠ CUSTOMER NOT READY","")))))) | O30: =IF($B30="",999999999,IF($D30="Installed",999999999,IF(NOT(ISNUMBER($E30)),999900000+26,$E30*10000+26))) -> 999999999 | Q30: =IF(LEFT($M30,1)="⚠",1,0) -> 0 | R30: =IF($Q30=1,SUM($Q$5:$Q30),"")
A31: 46204 | B31: Lakewoodd Yacht Club | C31: 52H TB3 x 2 ITCB 220V L14-20 | D31: Installed | E31: 46225 | F31: Ryan | G31: WO-0151 | H31: Ready | J31: LR | K31: No Purchased Equipment | L31: =IF($D31="Installed","✔","") -> ✔ | M31: =IF($B31="","",IF($D31="Installed","",IF(AND($D31="Not Ready",$E31<>"",NOT(ISNUMBER($E31))),"⚠ CHECK DATE",IF(AND($D31="Not Ready",ISNUMBER($E31),$E31<$P$3),"⚠ PAST DUE - NOT READY",IF(AND($D31="Not Ready",ISNUMBER($E31),$E31>=$P$3,$E31<=$P$5),"⚠ EQUIP NOT READY",IF(AND($H31="Not Ready",ISNUMBER($E31),$E31>=$P$3,$E31<=$P$5),"⚠ CUSTOMER NOT READY","")))))) | O31: =IF($B31="",999999999,IF($D31="Installed",999999999,IF(NOT(ISNUMBER($E31)),999900000+27,$E31*10000+27))) -> 999999999 | Q31: =IF(LEFT($M31,1)="⚠",1,0) -> 0 | R31: =IF($Q31=1,SUM($Q$5:$Q31),"")
A32: 46209 | B32: Rice University - South Main | C32: ITCB 120V | D32: Installed | E32: 46212 | F32: Elias | G32: WO-0044 | H32: Ready | I32: Rice Settings | J32: AL | K32: No Purchased Equipment | L32: =IF($D32="Installed","✔","") -> ✔ | M32: =IF($B32="","",IF($D32="Installed","",IF(AND($D32="Not Ready",$E32<>"",NOT(ISNUMBER($E32))),"⚠ CHECK DATE",IF(AND($D32="Not Ready",ISNUMBER($E32),$E32<$P$3),"⚠ PAST DUE - NOT READY",IF(AND($D32="Not Ready",ISNUMBER($E32),$E32>=$P$3,$E32<=$P$5),"⚠ EQUIP NOT READY",IF(AND($H32="Not Ready",ISNUMBER($E32),$E32>=$P$3,$E32<=$P$5),"⚠ CUSTOMER NOT READY","")))))) | O32: =IF($B32="",999999999,IF($D32="Installed",999999999,IF(NOT(ISNUMBER($E32)),999900000+28,$E32*10000+28))) -> 999999999 | Q32: =IF(LEFT($M32,1)="⚠",1,0) -> 0 | R32: =IF($Q32=1,SUM($Q$5:$Q32),"")
A33: 46210 | B33: Ninfa's - Navigation | C33: TB3 | D33: Ready | E33: 46247 | I33: Additional Brewer | J33: JG | K33: No Purchased Equipment | L33: =IF($D33="Installed","✔","") | M33: =IF($B33="","",IF($D33="Installed","",IF(AND($D33="Not Ready",$E33<>"",NOT(ISNUMBER($E33))),"⚠ CHECK DATE",IF(AND($D33="Not Ready",ISNUMBER($E33),$E33<$P$3),"⚠ PAST DUE - NOT READY",IF(AND($D33="Not Ready",ISNUMBER($E33),$E33>=$P$3,$E33<=$P$5),"⚠ EQUIP NOT READY",IF(AND($H33="Not Ready",ISNUMBER($E33),$E33>=$P$3,$E33<=$P$5),"⚠ CUSTOMER NOT READY","")))))) | O33: =IF($B33="",999999999,IF($D33="Installed",999999999,IF(NOT(ISNUMBER($E33)),999900000+29,$E33*10000+29))) -> 462470029 | Q33: =IF(LEFT($M33,1)="⚠",1,0) -> 0 | R33: =IF($Q33=1,SUM($Q$5:$Q33),"")
A34: 46213 | B34: Luzia Coffee Shop | C34: Invicta 3GR, Robur S E, Puqpress, Fetco51H, GR2.2, TB3 | D34: Installed | E34: 46230 | F34: Josh | G34: WO-0156 | H34: Ready | I34: 7/13 - preinspection | J34: LR | K34: 50% Down / 50% at Install or Net 30 | L34: =IF($D34="Installed","✔","") -> ✔ | M34: =IF($B34="","",IF($D34="Installed","",IF(AND($D34="Not Ready",$E34<>"",NOT(ISNUMBER($E34))),"⚠ CHECK DATE",IF(AND($D34="Not Ready",ISNUMBER($E34),$E34<$P$3),"⚠ PAST DUE - NOT READY",IF(AND($D34="Not Ready",ISNUMBER($E34),$E34>=$P$3,$E34<=$P$5),"⚠ EQUIP NOT READY",IF(AND($H34="Not Ready",ISNUMBER($E34),$E34>=$P$3,$E34<=$P$5),"⚠ CUSTOMER NOT READY","")))))) | O34: =IF($B34="",999999999,IF($D34="Installed",999999999,IF(NOT(ISNUMBER($E34)),999900000+30,$E34*10000+30))) -> 999999999 | Q34: =IF(LEFT($M34,1)="⚠",1,0) -> 0 | R34: =IF($Q34=1,SUM($Q$5:$Q34),"")
A35: 46213 | B35: Coco Shrimp - Dallas | C35: TB3 | D35: Installed | E35: 46216 | F35: Bill | G35: WO-0119 | H35: Ready | I35: Ship next week to Bill (orig. install date entered as "Week of 7/13/2026") | J35: BM | K35: No Purchased Equipment | L35: =IF($D35="Installed","✔","") -> ✔ | M35: =IF($B35="","",IF($D35="Installed","",IF(AND($D35="Not Ready",$E35<>"",NOT(ISNUMBER($E35))),"⚠ CHECK DATE",IF(AND($D35="Not Ready",ISNUMBER($E35),$E35<$P$3),"⚠ PAST DUE - NOT READY",IF(AND($D35="Not Ready",ISNUMBER($E35),$E35>=$P$3,$E35<=$P$5),"⚠ EQUIP NOT READY",IF(AND($H35="Not Ready",ISNUMBER($E35),$E35>=$P$3,$E35<=$P$5),"⚠ CUSTOMER NOT READY","")))))) | O35: =IF($B35="",999999999,IF($D35="Installed",999999999,IF(NOT(ISNUMBER($E35)),999900000+31,$E35*10000+31))) -> 999999999 | Q35: =IF(LEFT($M35,1)="⚠",1,0) -> 0 | R35: =IF($Q35=1,SUM($Q$5:$Q35),"")
A36: 46217 | B36: Brew & Books | C36: Cameo c'2s | D36: Installed | F36: Lance | G36: WO-0112 | H36: Ready | I36: Lance needs asap. JM & Decaf Esp | J36: LO | K36: 50% Down / 50% at Install or Net 30 | L36: =IF($D36="Installed","✔","") -> ✔ | M36: =IF($B36="","",IF($D36="Installed","",IF(AND($D36="Not Ready",$E36<>"",NOT(ISNUMBER($E36))),"⚠ CHECK DATE",IF(AND($D36="Not Ready",ISNUMBER($E36),$E36<$P$3),"⚠ PAST DUE - NOT READY",IF(AND($D36="Not Ready",ISNUMBER($E36),$E36>=$P$3,$E36<=$P$5),"⚠ EQUIP NOT READY",IF(AND($H36="Not Ready",ISNUMBER($E36),$E36>=$P$3,$E36<=$P$5),"⚠ CUSTOMER NOT READY","")))))) | O36: =IF($B36="",999999999,IF($D36="Installed",999999999,IF(NOT(ISNUMBER($E36)),999900000+32,$E36*10000+32))) -> 999999999 | Q36: =IF(LEFT($M36,1)="⚠",1,0) -> 0 | R36: =IF($Q36=1,SUM($Q$5:$Q36),"")
A37: 46218 | B37: Rice University - Moody Center | C37: Fetco 52H SN: F52H03082026 | D37: Installed | E37: 46238 | F37: Elias | G37: WO-0283 | H37: Ready | I37: New catering area | J37: AL | K37: No Purchased Equipment | L37: =IF($D37="Installed","✔","") -> ✔ | M37: =IF($B37="","",IF($D37="Installed","",IF(AND($D37="Not Ready",$E37<>"",NOT(ISNUMBER($E37))),"⚠ CHECK DATE",IF(AND($D37="Not Ready",ISNUMBER($E37),$E37<$P$3),"⚠ PAST DUE - NOT READY",IF(AND($D37="Not Ready",ISNUMBER($E37),$E37>=$P$3,$E37<=$P$5),"⚠ EQUIP NOT READY",IF(AND($H37="Not Ready",ISNUMBER($E37),$E37>=$P$3,$E37<=$P$5),"⚠ CUSTOMER NOT READY","")))))) | O37: =IF($B37="",999999999,IF($D37="Installed",999999999,IF(NOT(ISNUMBER($E37)),999900000+33,$E37*10000+33))) -> 999999999 | Q37: =IF(LEFT($M37,1)="⚠",1,0) -> 0 | R37: =IF($Q37=1,SUM($Q$5:$Q37),"")
A38: 46218 | B38: The Riot Comedy Club | C38: Rancilio Classe 5 Compact SN:10467673, Mazzer SJ E SN:2601514, Mazzer Mini E SN:2608789 | D38: Installed | E38: 46247 | F38: Charles | G38: WO-0351 | H38: Ready | I38: (orig. install date entered as "Week of 7/27") | J38: SM | K38: Lease | L38: =IF($D38="Installed","✔","") -> ✔ | M38: =IF($B38="","",IF($D38="Installed","",IF(AND($D38="Not Ready",$E38<>"",NOT(ISNUMBER($E38))),"⚠ CHECK DATE",IF(AND($D38="Not Ready",ISNUMBER($E38),$E38<$P$3),"⚠ PAST DUE - NOT READY",IF(AND($D38="Not Ready",ISNUMBER($E38),$E38>=$P$3,$E38<=$P$5),"⚠ EQUIP NOT READY",IF(AND($H38="Not Ready",ISNUMBER($E38),$E38>=$P$3,$E38<=$P$5),"⚠ CUSTOMER NOT READY","")))))) | O38: =IF($B38="",999999999,IF($D38="Installed",999999999,IF(NOT(ISNUMBER($E38)),999900000+34,$E38*10000+34))) -> 999999999 | Q38: =IF(LEFT($M38,1)="⚠",1,0) -> 0 | R38: =IF($Q38=1,SUM($Q$5:$Q38),"")
A39: 46218 | B39: La Lucha / Star Rover | C39: Bunn ICB Tall | D39: Installed | E39: 46224 | F39: Ryan | G39: WO-9221 | H39: Ready | J39: SM | K39: No Purchased Equipment | L39: =IF($D39="Installed","✔","") -> ✔ | M39: =IF($B39="","",IF($D39="Installed","",IF(AND($D39="Not Ready",$E39<>"",NOT(ISNUMBER($E39))),"⚠ CHECK DATE",IF(AND($D39="Not Ready",ISNUMBER($E39),$E39<$P$3),"⚠ PAST DUE - NOT READY",IF(AND($D39="Not Ready",ISNUMBER($E39),$E39>=$P$3,$E39<=$P$5),"⚠ EQUIP NOT READY",IF(AND($H39="Not Ready",ISNUMBER($E39),$E39>=$P$3,$E39<=$P$5),"⚠ CUSTOMER NOT READY","")))))) | O39: =IF($B39="",999999999,IF($D39="Installed",999999999,IF(NOT(ISNUMBER($E39)),999900000+35,$E39*10000+35))) -> 999999999 | Q39: =IF(LEFT($M39,1)="⚠",1,0) -> 0 | R39: =IF($Q39=1,SUM($Q$5:$Q39),"")
A40: 46218 | B40: Southerleigh SA Airport | C40: Bunn ITCB | D40: Installed | E40: 46220 | F40: Lance | G40: WO-0125 | H40: Ready | J40: LO | K40: No Purchased Equipment | L40: =IF($D40="Installed","✔","") -> ✔ | M40: =IF($B40="","",IF($D40="Installed","",IF(AND($D40="Not Ready",$E40<>"",NOT(ISNUMBER($E40))),"⚠ CHECK DATE",IF(AND($D40="Not Ready",ISNUMBER($E40),$E40<$P$3),"⚠ PAST DUE - NOT READY",IF(AND($D40="Not Ready",ISNUMBER($E40),$E40>=$P$3,$E40<=$P$5),"⚠ EQUIP NOT READY",IF(AND($H40="Not Ready",ISNUMBER($E40),$E40>=$P$3,$E40<=$P$5),"⚠ CUSTOMER NOT READY","")))))) | O40: =IF($B40="",999999999,IF($D40="Installed",999999999,IF(NOT(ISNUMBER($E40)),999900000+36,$E40*10000+36))) -> 999999999 | Q40: =IF(LEFT($M40,1)="⚠",1,0) -> 0 | R40: =IF($Q40=1,SUM($Q$5:$Q40),"")
A41: 46226 | B41: petroleum club | C41: used cameo 2 step, itcb, g9-2t, fetco, gr2.2, TB3 | D41: Installed | E41: 46233 | F41: Josh | G41: WO-0251 | H41: Ready | I41: Fetcos Banquet: 1.5 gal and carafe Bunn Kitchen: 1 gallon and carafe. Coffee: Bayou and MB decaf | J41: al | K41: lease | L41: =IF($D41="Installed","✔","") -> ✔ | M41: =IF($B41="","",IF($D41="Installed","",IF(AND($D41="Not Ready",$E41<>"",NOT(ISNUMBER($E41))),"⚠ CHECK DATE",IF(AND($D41="Not Ready",ISNUMBER($E41),$E41<$P$3),"⚠ PAST DUE - NOT READY",IF(AND($D41="Not Ready",ISNUMBER($E41),$E41>=$P$3,$E41<=$P$5),"⚠ EQUIP NOT READY",IF(AND($H41="Not Ready",ISNUMBER($E41),$E41>=$P$3,$E41<=$P$5),"⚠ CUSTOMER NOT READY","")))))) | O41: =IF($B41="",999999999,IF($D41="Installed",999999999,IF(NOT(ISNUMBER($E41)),999900000+37,$E41*10000+37))) -> 999999999 | Q41: =IF(LEFT($M41,1)="⚠",1,0) -> 0 | R41: =IF($Q41=1,SUM($Q$5:$Q41),"")
A42: 46225 | B42: kol fac 118 | C42: cameo, itcb | D42: Not Ready | J42: al | K42: 50% Down / 50% at Install or Net 30 | L42: =IF($D42="Installed","✔","") | M42: =IF($B42="","",IF($D42="Installed","",IF(AND($D42="Not Ready",$E42<>"",NOT(ISNUMBER($E42))),"⚠ CHECK DATE",IF(AND($D42="Not Ready",ISNUMBER($E42),$E42<$P$3),"⚠ PAST DUE - NOT READY",IF(AND($D42="Not Ready",ISNUMBER($E42),$E42>=$P$3,$E42<=$P$5),"⚠ EQUIP NOT READY",IF(AND($H42="Not Ready",ISNUMBER($E42),$E42>=$P$3,$E42<=$P$5),"⚠ CUSTOMER NOT READY","")))))) | O42: =IF($B42="",999999999,IF($D42="Installed",999999999,IF(NOT(ISNUMBER($E42)),999900000+38,$E42*10000+38))) -> 999900038 | Q42: =IF(LEFT($M42,1)="⚠",1,0) -> 0 | R42: =IF($Q42=1,SUM($Q$5:$Q42),"")
A43: 46225 | B43: bloom chica brew | C43: la marz linea, jay grinder | D43: Installed | E43: 46240 | F43: 3rd Party | G43: WO-0267 | H43: Ready | I43: Reached out Coffee Maverick | J43: AL | K43: Paid in Full | L43: =IF($D43="Installed","✔","") -> ✔ | M43: =IF($B43="","",IF($D43="Installed","",IF(AND($D43="Not Ready",$E43<>"",NOT(ISNUMBER($E43))),"⚠ CHECK DATE",IF(AND($D43="Not Ready",ISNUMBER($E43),$E43<$P$3),"⚠ PAST DUE - NOT READY",IF(AND($D43="Not Ready",ISNUMBER($E43),$E43>=$P$3,$E43<=$P$5),"⚠ EQUIP NOT READY",IF(AND($H43="Not Ready",ISNUMBER($E43),$E43>=$P$3,$E43<=$P$5),"⚠ CUSTOMER NOT READY","")))))) | O43: =IF($B43="",999999999,IF($D43="Installed",999999999,IF(NOT(ISNUMBER($E43)),999900000+39,$E43*10000+39))) -> 999999999 | Q43: =IF(LEFT($M43,1)="⚠",1,0) -> 0 | R43: =IF($Q43=1,SUM($Q$5:$Q43),"")
A44: 46224 | B44: HEB Division Office | C44: Bunn Axiom-TC Bunn LPG | D44: Installed | E44: 46233 | F44: Bill | G44: WO-0262 | H44: Ready | J44: BM | K44: No Purchased Equipment | L44: =IF($D44="Installed","✔","") -> ✔ | M44: =IF($B44="","",IF($D44="Installed","",IF(AND($D44="Not Ready",$E44<>"",NOT(ISNUMBER($E44))),"⚠ CHECK DATE",IF(AND($D44="Not Ready",ISNUMBER($E44),$E44<$P$3),"⚠ PAST DUE - NOT READY",IF(AND($D44="Not Ready",ISNUMBER($E44),$E44>=$P$3,$E44<=$P$5),"⚠ EQUIP NOT READY",IF(AND($H44="Not Ready",ISNUMBER($E44),$E44>=$P$3,$E44<=$P$5),"⚠ CUSTOMER NOT READY","")))))) | O44: =IF($B44="",999999999,IF($D44="Installed",999999999,IF(NOT(ISNUMBER($E44)),999900000+40,$E44*10000+40))) -> 999999999 | Q44: =IF(LEFT($M44,1)="⚠",1,0) -> 0 | R44: =IF($Q44=1,SUM($Q$5:$Q44),"")
A45: 46226 | B45: Coco Crepes Bellaire | C45: La Marzocco Linea Classic S 2 Group AV/ La Marzocco Swift Dual-Hopper Espresso Grinder/ Bunn Axiom-APS | D45: Not Ready | J45: LR | K45: Paid in Full | L45: =IF($D45="Installed","✔","") | M45: =IF($B45="","",IF($D45="Installed","",IF(AND($D45="Not Ready",$E45<>"",NOT(ISNUMBER($E45))),"⚠ CHECK DATE",IF(AND($D45="Not Ready",ISNUMBER($E45),$E45<$P$3),"⚠ PAST DUE - NOT READY",IF(AND($D45="Not Ready",ISNUMBER($E45),$E45>=$P$3,$E45<=$P$5),"⚠ EQUIP NOT READY",IF(AND($H45="Not Ready",ISNUMBER($E45),$E45>=$P$3,$E45<=$P$5),"⚠ CUSTOMER NOT READY","")))))) | O45: =IF($B45="",999999999,IF($D45="Installed",999999999,IF(NOT(ISNUMBER($E45)),999900000+41,$E45*10000+41))) -> 999900041 | Q45: =IF(LEFT($M45,1)="⚠",1,0) -> 0 | R45: =IF($Q45=1,SUM($Q$5:$Q45),"")
A46: 46226 | B46: Vam Foods | C46: Bravilor Sego 12 120V & QTY 2 Airpot Brewers | D46: Installed | E46: 46240 | F46: Ryan | G46: WO-0312 | H46: Ready | J46: LR | K46: No Purchased Equipment | L46: =IF($D46="Installed","✔","") -> ✔ | M46: =IF($B46="","",IF($D46="Installed","",IF(AND($D46="Not Ready",$E46<>"",NOT(ISNUMBER($E46))),"⚠ CHECK DATE",IF(AND($D46="Not Ready",ISNUMBER($E46),$E46<$P$3),"⚠ PAST DUE - NOT READY",IF(AND($D46="Not Ready",ISNUMBER($E46),$E46>=$P$3,$E46<=$P$5),"⚠ EQUIP NOT READY",IF(AND($H46="Not Ready",ISNUMBER($E46),$E46>=$P$3,$E46<=$P$5),"⚠ CUSTOMER NOT READY","")))))) | O46: =IF($B46="",999999999,IF($D46="Installed",999999999,IF(NOT(ISNUMBER($E46)),999900000+42,$E46*10000+42))) -> 999999999 | Q46: =IF(LEFT($M46,1)="⚠",1,0) -> 0 | R46: =IF($Q46=1,SUM($Q$5:$Q46),"")
A47: 46234 | B47: Sage The Vilage School | C47: e4 & itcb from cafeteria to new coffee shop | D47: Installed | E47: 46240 | F47: Oliver | G47: WO-0181 | H47: Ready | I47: they own the e4 and loan the ictb | J47: al | K47: No Purchased Equipment | L47: =IF($D47="Installed","✔","") -> ✔ | M47: =IF($B47="","",IF($D47="Installed","",IF(AND($D47="Not Ready",$E47<>"",NOT(ISNUMBER($E47))),"⚠ CHECK DATE",IF(AND($D47="Not Ready",ISNUMBER($E47),$E47<$P$3),"⚠ PAST DUE - NOT READY",IF(AND($D47="Not Ready",ISNUMBER($E47),$E47>=$P$3,$E47<=$P$5),"⚠ EQUIP NOT READY",IF(AND($H47="Not Ready",ISNUMBER($E47),$E47>=$P$3,$E47<=$P$5),"⚠ CUSTOMER NOT READY","")))))) | O47: =IF($B47="",999999999,IF($D47="Installed",999999999,IF(NOT(ISNUMBER($E47)),999900000+43,$E47*10000+43))) -> 999999999 | Q47: =IF(LEFT($M47,1)="⚠",1,0) -> 0 | R47: =IF($Q47=1,SUM($Q$5:$Q47),"")
A48: 46237 | B48: waller county court house | C48: axiom aps | D48: Ready | H48: Not Ready | J48: al | K48: No Purchased Equipment | L48: =IF($D48="Installed","✔","") | M48: =IF($B48="","",IF($D48="Installed","",IF(AND($D48="Not Ready",$E48<>"",NOT(ISNUMBER($E48))),"⚠ CHECK DATE",IF(AND($D48="Not Ready",ISNUMBER($E48),$E48<$P$3),"⚠ PAST DUE - NOT READY",IF(AND($D48="Not Ready",ISNUMBER($E48),$E48>=$P$3,$E48<=$P$5),"⚠ EQUIP NOT READY",IF(AND($H48="Not Ready",ISNUMBER($E48),$E48>=$P$3,$E48<=$P$5),"⚠ CUSTOMER NOT READY","")))))) | O48: =IF($B48="",999999999,IF($D48="Installed",999999999,IF(NOT(ISNUMBER($E48)),999900000+44,$E48*10000+44))) -> 999900044 | Q48: =IF(LEFT($M48,1)="⚠",1,0) -> 0 | R48: =IF($Q48=1,SUM($Q$5:$Q48),"")
A49: 46238 | B49: Hawker's Franklin | C49: Bunn ITCB | D49: Installed | E49: 46257 | F49: 3rd Party | G49: WO-0314 | H49: Ready | J49: SC | K49: No Purchased Equipment | L49: =IF($D49="Installed","✔","") -> ✔ | M49: =IF($B49="","",IF($D49="Installed","",IF(AND($D49="Not Ready",$E49<>"",NOT(ISNUMBER($E49))),"⚠ CHECK DATE",IF(AND($D49="Not Ready",ISNUMBER($E49),$E49<$P$3),"⚠ PAST DUE - NOT READY",IF(AND($D49="Not Ready",ISNUMBER($E49),$E49>=$P$3,$E49<=$P$5),"⚠ EQUIP NOT READY",IF(AND($H49="Not Ready",ISNUMBER($E49),$E49>=$P$3,$E49<=$P$5),"⚠ CUSTOMER NOT READY","")))))) | O49: =IF($B49="",999999999,IF($D49="Installed",999999999,IF(NOT(ISNUMBER($E49)),999900000+45,$E49*10000+45))) -> 999999999 | Q49: =IF(LEFT($M49,1)="⚠",1,0) -> 0 | R49: =IF($Q49=1,SUM($Q$5:$Q49),"")
A50: 46238 | B50: Doug's Diner | C50: Fetco MBS x 2 / Powder Machine | D50: Not Ready | F50: 3rd Party | H50: Ready | J50: SC | K50: No Purchased Equipment | L50: =IF($D50="Installed","✔","") | M50: =IF($B50="","",IF($D50="Installed","",IF(AND($D50="Not Ready",$E50<>"",NOT(ISNUMBER($E50))),"⚠ CHECK DATE",IF(AND($D50="Not Ready",ISNUMBER($E50),$E50<$P$3),"⚠ PAST DUE - NOT READY",IF(AND($D50="Not Ready",ISNUMBER($E50),$E50>=$P$3,$E50<=$P$5),"⚠ EQUIP NOT READY",IF(AND($H50="Not Ready",ISNUMBER($E50),$E50>=$P$3,$E50<=$P$5),"⚠ CUSTOMER NOT READY","")))))) | O50: =IF($B50="",999999999,IF($D50="Installed",999999999,IF(NOT(ISNUMBER($E50)),999900000+46,$E50*10000+46))) -> 999900046 | Q50: =IF(LEFT($M50,1)="⚠",1,0) -> 0 | R50: =IF($Q50=1,SUM($Q$5:$Q50),"")
A51: 46246 | B51: Two Step Taqueria - South | D51: Not Ready | F51: Lance | I51: They need a 51h to replace an ITCB | K51: No Purchased Equipment | L51: =IF($D51="Installed","✔","") | M51: =IF($B51="","",IF($D51="Installed","",IF(AND($D51="Not Ready",$E51<>"",NOT(ISNUMBER($E51))),"⚠ CHECK DATE",IF(AND($D51="Not Ready",ISNUMBER($E51),$E51<$P$3),"⚠ PAST DUE - NOT READY",IF(AND($D51="Not Ready",ISNUMBER($E51),$E51>=$P$3,$E51<=$P$5),"⚠ EQUIP NOT READY",IF(AND($H51="Not Ready",ISNUMBER($E51),$E51>=$P$3,$E51<=$P$5),"⚠ CUSTOMER NOT READY","")))))) | O51: =IF($B51="",999999999,IF($D51="Installed",999999999,IF(NOT(ISNUMBER($E51)),999900000+47,$E51*10000+47))) -> 999900047 | Q51: =IF(LEFT($M51,1)="⚠",1,0) -> 0 | R51: =IF($Q51=1,SUM($Q$5:$Q51),"")
A52: 46247 | B52: Southern Ice CO | C52: bunn itcb | D52: Ready | E52: 46254 | G52: WO-0406 | H52: Ready | I52: waiting on paperwork, need to send a loaner | J52: al | K52: No Purchased Equipment | L52: =IF($D52="Installed","✔","") | M52: =IF($B52="","",IF($D52="Installed","",IF(AND($D52="Not Ready",$E52<>"",NOT(ISNUMBER($E52))),"⚠ CHECK DATE",IF(AND($D52="Not Ready",ISNUMBER($E52),$E52<$P$3),"⚠ PAST DUE - NOT READY",IF(AND($D52="Not Ready",ISNUMBER($E52),$E52>=$P$3,$E52<=$P$5),"⚠ EQUIP NOT READY",IF(AND($H52="Not Ready",ISNUMBER($E52),$E52>=$P$3,$E52<=$P$5),"⚠ CUSTOMER NOT READY","")))))) | O52: =IF($B52="",999999999,IF($D52="Installed",999999999,IF(NOT(ISNUMBER($E52)),999900000+48,$E52*10000+48))) -> 462540048 | Q52: =IF(LEFT($M52,1)="⚠",1,0) -> 0 | R52: =IF($Q52=1,SUM($Q$5:$Q52),"")
A53: 46251 | B53: Scrambles Breakfast & Lunch | C53: BUNN ITCB & BUNN G9 GRINDER | L53: =IF($D53="Installed","✔","") | M53: =IF($B53="","",IF($D53="Installed","",IF(AND($D53="Not Ready",$E53<>"",NOT(ISNUMBER($E53))),"⚠ CHECK DATE",IF(AND($D53="Not Ready",ISNUMBER($E53),$E53<$P$3),"⚠ PAST DUE - NOT READY",IF(AND($D53="Not Ready",ISNUMBER($E53),$E53>=$P$3,$E53<=$P$5),"⚠ EQUIP NOT READY",IF(AND($H53="Not Ready",ISNUMBER($E53),$E53>=$P$3,$E53<=$P$5),"⚠ CUSTOMER NOT READY","")))))) | O53: =IF($B53="",999999999,IF($D53="Installed",999999999,IF(NOT(ISNUMBER($E53)),999900000+49,$E53*10000+49))) -> 999900049 | Q53: =IF(LEFT($M53,1)="⚠",1,0) -> 0 | R53: =IF($Q53=1,SUM($Q$5:$Q53),"")
L54: =IF($D54="Installed","✔","") | M54: =IF($B54="","",IF($D54="Installed","",IF(AND($D54="Not Ready",$E54<>"",NOT(ISNUMBER($E54))),"⚠ CHECK DATE",IF(AND($D54="Not Ready",ISNUMBER($E54),$E54<$P$3),"⚠ PAST DUE - NOT READY",IF(AND($D54="Not Ready",ISNUMBER($E54),$E54>=$P$3,$E54<=$P$5),"⚠ EQUIP NOT READY",IF(AND($H54="Not Ready",ISNUMBER($E54),$E54>=$P$3,$E54<=$P$5),"⚠ CUSTOMER NOT READY","")))))) | O54: =IF($B54="",999999999,IF($D54="Installed",999999999,IF(NOT(ISNUMBER($E54)),999900000+50,$E54*10000+50))) -> 999999999 | Q54: =IF(LEFT($M54,1)="⚠",1,0) -> 0 | R54: =IF($Q54=1,SUM($Q$5:$Q54),"")
L55: =IF($D55="Installed","✔","") | M55: =IF($B55="","",IF($D55="Installed","",IF(AND($D55="Not Ready",$E55<>"",NOT(ISNUMBER($E55))),"⚠ CHECK DATE",IF(AND($D55="Not Ready",ISNUMBER($E55),$E55<$P$3),"⚠ PAST DUE - NOT READY",IF(AND($D55="Not Ready",ISNUMBER($E55),$E55>=$P$3,$E55<=$P$5),"⚠ EQUIP NOT READY",IF(AND($H55="Not Ready",ISNUMBER($E55),$E55>=$P$3,$E55<=$P$5),"⚠ CUSTOMER NOT READY","")))))) | O55: =IF($B55="",999999999,IF($D55="Installed",999999999,IF(NOT(ISNUMBER($E55)),999900000+51,$E55*10000+51))) -> 999999999 | Q55: =IF(LEFT($M55,1)="⚠",1,0) -> 0 | R55: =IF($Q55=1,SUM($Q$5:$Q55),"")
L56: =IF($D56="Installed","✔","") | M56: =IF($B56="","",IF($D56="Installed","",IF(AND($D56="Not Ready",$E56<>"",NOT(ISNUMBER($E56))),"⚠ CHECK DATE",IF(AND($D56="Not Ready",ISNUMBER($E56),$E56<$P$3),"⚠ PAST DUE - NOT READY",IF(AND($D56="Not Ready",ISNUMBER($E56),$E56>=$P$3,$E56<=$P$5),"⚠ EQUIP NOT READY",IF(AND($H56="Not Ready",ISNUMBER($E56),$E56>=$P$3,$E56<=$P$5),"⚠ CUSTOMER NOT READY","")))))) | O56: =IF($B56="",999999999,IF($D56="Installed",999999999,IF(NOT(ISNUMBER($E56)),999900000+52,$E56*10000+52))) -> 999999999 | Q56: =IF(LEFT($M56,1)="⚠",1,0) -> 0 | R56: =IF($Q56=1,SUM($Q$5:$Q56),"")
L57: =IF($D57="Installed","✔","") | M57: =IF($B57="","",IF($D57="Installed","",IF(AND($D57="Not Ready",$E57<>"",NOT(ISNUMBER($E57))),"⚠ CHECK DATE",IF(AND($D57="Not Ready",ISNUMBER($E57),$E57<$P$3),"⚠ PAST DUE - NOT READY",IF(AND($D57="Not Ready",ISNUMBER($E57),$E57>=$P$3,$E57<=$P$5),"⚠ EQUIP NOT READY",IF(AND($H57="Not Ready",ISNUMBER($E57),$E57>=$P$3,$E57<=$P$5),"⚠ CUSTOMER NOT READY","")))))) | O57: =IF($B57="",999999999,IF($D57="Installed",999999999,IF(NOT(ISNUMBER($E57)),999900000+53,$E57*10000+53))) -> 999999999 | Q57: =IF(LEFT($M57,1)="⚠",1,0) -> 0 | R57: =IF($Q57=1,SUM($Q$5:$Q57),"")
L58: =IF($D58="Installed","✔","") | M58: =IF($B58="","",IF($D58="Installed","",IF(AND($D58="Not Ready",$E58<>"",NOT(ISNUMBER($E58))),"⚠ CHECK DATE",IF(AND($D58="Not Ready",ISNUMBER($E58),$E58<$P$3),"⚠ PAST DUE - NOT READY",IF(AND($D58="Not Ready",ISNUMBER($E58),$E58>=$P$3,$E58<=$P$5),"⚠ EQUIP NOT READY",IF(AND($H58="Not Ready",ISNUMBER($E58),$E58>=$P$3,$E58<=$P$5),"⚠ CUSTOMER NOT READY","")))))) | O58: =IF($B58="",999999999,IF($D58="Installed",999999999,IF(NOT(ISNUMBER($E58)),999900000+54,$E58*10000+54))) -> 999999999 | Q58: =IF(LEFT($M58,1)="⚠",1,0) -> 0 | R58: =IF($Q58=1,SUM($Q$5:$Q58),"")
L59: =IF($D59="Installed","✔","") | M59: =IF($B59="","",IF($D59="Installed","",IF(AND($D59="Not Ready",$E59<>"",NOT(ISNUMBER($E59))),"⚠ CHECK DATE",IF(AND($D59="Not Ready",ISNUMBER($E59),$E59<$P$3),"⚠ PAST DUE - NOT READY",IF(AND($D59="Not Ready",ISNUMBER($E59),$E59>=$P$3,$E59<=$P$5),"⚠ EQUIP NOT READY",IF(AND($H59="Not Ready",ISNUMBER($E59),$E59>=$P$3,$E59<=$P$5),"⚠ CUSTOMER NOT READY","")))))) | O59: =IF($B59="",999999999,IF($D59="Installed",999999999,IF(NOT(ISNUMBER($E59)),999900000+55,$E59*10000+55))) -> 999999999 | Q59: =IF(LEFT($M59,1)="⚠",1,0) -> 0 | R59: =IF($Q59=1,SUM($Q$5:$Q59),"")
L60: =IF($D60="Installed","✔","") | M60: =IF($B60="","",IF($D60="Installed","",IF(AND($D60="Not Ready",$E60<>"",NOT(ISNUMBER($E60))),"⚠ CHECK DATE",IF(AND($D60="Not Ready",ISNUMBER($E60),$E60<$P$3),"⚠ PAST DUE - NOT READY",IF(AND($D60="Not Ready",ISNUMBER($E60),$E60>=$P$3,$E60<=$P$5),"⚠ EQUIP NOT READY",IF(AND($H60="Not Ready",ISNUMBER($E60),$E60>=$P$3,$E60<=$P$5),"⚠ CUSTOMER NOT READY","")))))) | O60: =IF($B60="",999999999,IF($D60="Installed",999999999,IF(NOT(ISNUMBER($E60)),999900000+56,$E60*10000+56))) -> 999999999 | Q60: =IF(LEFT($M60,1)="⚠",1,0) -> 0 | R60: =IF($Q60=1,SUM($Q$5:$Q60),"")
L61: =IF($D61="Installed","✔","") | M61: =IF($B61="","",IF($D61="Installed","",IF(AND($D61="Not Ready",$E61<>"",NOT(ISNUMBER($E61))),"⚠ CHECK DATE",IF(AND($D61="Not Ready",ISNUMBER($E61),$E61<$P$3),"⚠ PAST DUE - NOT READY",IF(AND($D61="Not Ready",ISNUMBER($E61),$E61>=$P$3,$E61<=$P$5),"⚠ EQUIP NOT READY",IF(AND($H61="Not Ready",ISNUMBER($E61),$E61>=$P$3,$E61<=$P$5),"⚠ CUSTOMER NOT READY","")))))) | O61: =IF($B61="",999999999,IF($D61="Installed",999999999,IF(NOT(ISNUMBER($E61)),999900000+57,$E61*10000+57))) -> 999999999 | Q61: =IF(LEFT($M61,1)="⚠",1,0) -> 0 | R61: =IF($Q61=1,SUM($Q$5:$Q61),"")
L62: =IF($D62="Installed","✔","") | M62: =IF($B62="","",IF($D62="Installed","",IF(AND($D62="Not Ready",$E62<>"",NOT(ISNUMBER($E62))),"⚠ CHECK DATE",IF(AND($D62="Not Ready",ISNUMBER($E62),$E62<$P$3),"⚠ PAST DUE - NOT READY",IF(AND($D62="Not Ready",ISNUMBER($E62),$E62>=$P$3,$E62<=$P$5),"⚠ EQUIP NOT READY",IF(AND($H62="Not Ready",ISNUMBER($E62),$E62>=$P$3,$E62<=$P$5),"⚠ CUSTOMER NOT READY","")))))) | O62: =IF($B62="",999999999,IF($D62="Installed",999999999,IF(NOT(ISNUMBER($E62)),999900000+58,$E62*10000+58))) -> 999999999 | Q62: =IF(LEFT($M62,1)="⚠",1,0) -> 0 | R62: =IF($Q62=1,SUM($Q$5:$Q62),"")
L63: =IF($D63="Installed","✔","") | M63: =IF($B63="","",IF($D63="Installed","",IF(AND($D63="Not Ready",$E63<>"",NOT(ISNUMBER($E63))),"⚠ CHECK DATE",IF(AND($D63="Not Ready",ISNUMBER($E63),$E63<$P$3),"⚠ PAST DUE - NOT READY",IF(AND($D63="Not Ready",ISNUMBER($E63),$E63>=$P$3,$E63<=$P$5),"⚠ EQUIP NOT READY",IF(AND($H63="Not Ready",ISNUMBER($E63),$E63>=$P$3,$E63<=$P$5),"⚠ CUSTOMER NOT READY","")))))) | O63: =IF($B63="",999999999,IF($D63="Installed",999999999,IF(NOT(ISNUMBER($E63)),999900000+59,$E63*10000+59))) -> 999999999 | Q63: =IF(LEFT($M63,1)="⚠",1,0) -> 0 | R63: =IF($Q63=1,SUM($Q$5:$Q63),"")
L64: =IF($D64="Installed","✔","") | M64: =IF($B64="","",IF($D64="Installed","",IF(AND($D64="Not Ready",$E64<>"",NOT(ISNUMBER($E64))),"⚠ CHECK DATE",IF(AND($D64="Not Ready",ISNUMBER($E64),$E64<$P$3),"⚠ PAST DUE - NOT READY",IF(AND($D64="Not Ready",ISNUMBER($E64),$E64>=$P$3,$E64<=$P$5),"⚠ EQUIP NOT READY",IF(AND($H64="Not Ready",ISNUMBER($E64),$E64>=$P$3,$E64<=$P$5),"⚠ CUSTOMER NOT READY","")))))) | O64: =IF($B64="",999999999,IF($D64="Installed",999999999,IF(NOT(ISNUMBER($E64)),999900000+60,$E64*10000+60))) -> 999999999 | Q64: =IF(LEFT($M64,1)="⚠",1,0) -> 0 | R64: =IF($Q64=1,SUM($Q$5:$Q64),"")
L65: =IF($D65="Installed","✔","") | M65: =IF($B65="","",IF($D65="Installed","",IF(AND($D65="Not Ready",$E65<>"",NOT(ISNUMBER($E65))),"⚠ CHECK DATE",IF(AND($D65="Not Ready",ISNUMBER($E65),$E65<$P$3),"⚠ PAST DUE - NOT READY",IF(AND($D65="Not Ready",ISNUMBER($E65),$E65>=$P$3,$E65<=$P$5),"⚠ EQUIP NOT READY",IF(AND($H65="Not Ready",ISNUMBER($E65),$E65>=$P$3,$E65<=$P$5),"⚠ CUSTOMER NOT READY","")))))) | O65: =IF($B65="",999999999,IF($D65="Installed",999999999,IF(NOT(ISNUMBER($E65)),999900000+61,$E65*10000+61))) -> 999999999 | Q65: =IF(LEFT($M65,1)="⚠",1,0) -> 0 | R65: =IF($Q65=1,SUM($Q$5:$Q65),"")
L66: =IF($D66="Installed","✔","") | M66: =IF($B66="","",IF($D66="Installed","",IF(AND($D66="Not Ready",$E66<>"",NOT(ISNUMBER($E66))),"⚠ CHECK DATE",IF(AND($D66="Not Ready",ISNUMBER($E66),$E66<$P$3),"⚠ PAST DUE - NOT READY",IF(AND($D66="Not Ready",ISNUMBER($E66),$E66>=$P$3,$E66<=$P$5),"⚠ EQUIP NOT READY",IF(AND($H66="Not Ready",ISNUMBER($E66),$E66>=$P$3,$E66<=$P$5),"⚠ CUSTOMER NOT READY","")))))) | O66: =IF($B66="",999999999,IF($D66="Installed",999999999,IF(NOT(ISNUMBER($E66)),999900000+62,$E66*10000+62))) -> 999999999 | Q66: =IF(LEFT($M66,1)="⚠",1,0) -> 0 | R66: =IF($Q66=1,SUM($Q$5:$Q66),"")
L67: =IF($D67="Installed","✔","") | M67: =IF($B67="","",IF($D67="Installed","",IF(AND($D67="Not Ready",$E67<>"",NOT(ISNUMBER($E67))),"⚠ CHECK DATE",IF(AND($D67="Not Ready",ISNUMBER($E67),$E67<$P$3),"⚠ PAST DUE - NOT READY",IF(AND($D67="Not Ready",ISNUMBER($E67),$E67>=$P$3,$E67<=$P$5),"⚠ EQUIP NOT READY",IF(AND($H67="Not Ready",ISNUMBER($E67),$E67>=$P$3,$E67<=$P$5),"⚠ CUSTOMER NOT READY","")))))) | O67: =IF($B67="",999999999,IF($D67="Installed",999999999,IF(NOT(ISNUMBER($E67)),999900000+63,$E67*10000+63))) -> 999999999 | Q67: =IF(LEFT($M67,1)="⚠",1,0) -> 0 | R67: =IF($Q67=1,SUM($Q$5:$Q67),"")
L68: =IF($D68="Installed","✔","") | M68: =IF($B68="","",IF($D68="Installed","",IF(AND($D68="Not Ready",$E68<>"",NOT(ISNUMBER($E68))),"⚠ CHECK DATE",IF(AND($D68="Not Ready",ISNUMBER($E68),$E68<$P$3),"⚠ PAST DUE - NOT READY",IF(AND($D68="Not Ready",ISNUMBER($E68),$E68>=$P$3,$E68<=$P$5),"⚠ EQUIP NOT READY",IF(AND($H68="Not Ready",ISNUMBER($E68),$E68>=$P$3,$E68<=$P$5),"⚠ CUSTOMER NOT READY","")))))) | O68: =IF($B68="",999999999,IF($D68="Installed",999999999,IF(NOT(ISNUMBER($E68)),999900000+64,$E68*10000+64))) -> 999999999 | Q68: =IF(LEFT($M68,1)="⚠",1,0) -> 0 | R68: =IF($Q68=1,SUM($Q$5:$Q68),"")
L69: =IF($D69="Installed","✔","") | M69: =IF($B69="","",IF($D69="Installed","",IF(AND($D69="Not Ready",$E69<>"",NOT(ISNUMBER($E69))),"⚠ CHECK DATE",IF(AND($D69="Not Ready",ISNUMBER($E69),$E69<$P$3),"⚠ PAST DUE - NOT READY",IF(AND($D69="Not Ready",ISNUMBER($E69),$E69>=$P$3,$E69<=$P$5),"⚠ EQUIP NOT READY",IF(AND($H69="Not Ready",ISNUMBER($E69),$E69>=$P$3,$E69<=$P$5),"⚠ CUSTOMER NOT READY","")))))) | O69: =IF($B69="",999999999,IF($D69="Installed",999999999,IF(NOT(ISNUMBER($E69)),999900000+65,$E69*10000+65))) -> 999999999 | Q69: =IF(LEFT($M69,1)="⚠",1,0) -> 0 | R69: =IF($Q69=1,SUM($Q$5:$Q69),"")
L70: =IF($D70="Installed","✔","") | M70: =IF($B70="","",IF($D70="Installed","",IF(AND($D70="Not Ready",$E70<>"",NOT(ISNUMBER($E70))),"⚠ CHECK DATE",IF(AND($D70="Not Ready",ISNUMBER($E70),$E70<$P$3),"⚠ PAST DUE - NOT READY",IF(AND($D70="Not Ready",ISNUMBER($E70),$E70>=$P$3,$E70<=$P$5),"⚠ EQUIP NOT READY",IF(AND($H70="Not Ready",ISNUMBER($E70),$E70>=$P$3,$E70<=$P$5),"⚠ CUSTOMER NOT READY","")))))) | O70: =IF($B70="",999999999,IF($D70="Installed",999999999,IF(NOT(ISNUMBER($E70)),999900000+66,$E70*10000+66))) -> 999999999 | Q70: =IF(LEFT($M70,1)="⚠",1,0) -> 0 | R70: =IF($Q70=1,SUM($Q$5:$Q70),"")
L71: =IF($D71="Installed","✔","") | M71: =IF($B71="","",IF($D71="Installed","",IF(AND($D71="Not Ready",$E71<>"",NOT(ISNUMBER($E71))),"⚠ CHECK DATE",IF(AND($D71="Not Ready",ISNUMBER($E71),$E71<$P$3),"⚠ PAST DUE - NOT READY",IF(AND($D71="Not Ready",ISNUMBER($E71),$E71>=$P$3,$E71<=$P$5),"⚠ EQUIP NOT READY",IF(AND($H71="Not Ready",ISNUMBER($E71),$E71>=$P$3,$E71<=$P$5),"⚠ CUSTOMER NOT READY","")))))) | O71: =IF($B71="",999999999,IF($D71="Installed",999999999,IF(NOT(ISNUMBER($E71)),999900000+67,$E71*10000+67))) -> 999999999 | Q71: =IF(LEFT($M71,1)="⚠",1,0) -> 0 | R71: =IF($Q71=1,SUM($Q$5:$Q71),"")
L72: =IF($D72="Installed","✔","") | M72: =IF($B72="","",IF($D72="Installed","",IF(AND($D72="Not Ready",$E72<>"",NOT(ISNUMBER($E72))),"⚠ CHECK DATE",IF(AND($D72="Not Ready",ISNUMBER($E72),$E72<$P$3),"⚠ PAST DUE - NOT READY",IF(AND($D72="Not Ready",ISNUMBER($E72),$E72>=$P$3,$E72<=$P$5),"⚠ EQUIP NOT READY",IF(AND($H72="Not Ready",ISNUMBER($E72),$E72>=$P$3,$E72<=$P$5),"⚠ CUSTOMER NOT READY","")))))) | O72: =IF($B72="",999999999,IF($D72="Installed",999999999,IF(NOT(ISNUMBER($E72)),999900000+68,$E72*10000+68))) -> 999999999 | Q72: =IF(LEFT($M72,1)="⚠",1,0) -> 0 | R72: =IF($Q72=1,SUM($Q$5:$Q72),"")
L73: =IF($D73="Installed","✔","") | M73: =IF($B73="","",IF($D73="Installed","",IF(AND($D73="Not Ready",$E73<>"",NOT(ISNUMBER($E73))),"⚠ CHECK DATE",IF(AND($D73="Not Ready",ISNUMBER($E73),$E73<$P$3),"⚠ PAST DUE - NOT READY",IF(AND($D73="Not Ready",ISNUMBER($E73),$E73>=$P$3,$E73<=$P$5),"⚠ EQUIP NOT READY",IF(AND($H73="Not Ready",ISNUMBER($E73),$E73>=$P$3,$E73<=$P$5),"⚠ CUSTOMER NOT READY","")))))) | O73: =IF($B73="",999999999,IF($D73="Installed",999999999,IF(NOT(ISNUMBER($E73)),999900000+69,$E73*10000+69))) -> 999999999 | Q73: =IF(LEFT($M73,1)="⚠",1,0) -> 0 | R73: =IF($Q73=1,SUM($Q$5:$Q73),"")
L74: =IF($D74="Installed","✔","") | M74: =IF($B74="","",IF($D74="Installed","",IF(AND($D74="Not Ready",$E74<>"",NOT(ISNUMBER($E74))),"⚠ CHECK DATE",IF(AND($D74="Not Ready",ISNUMBER($E74),$E74<$P$3),"⚠ PAST DUE - NOT READY",IF(AND($D74="Not Ready",ISNUMBER($E74),$E74>=$P$3,$E74<=$P$5),"⚠ EQUIP NOT READY",IF(AND($H74="Not Ready",ISNUMBER($E74),$E74>=$P$3,$E74<=$P$5),"⚠ CUSTOMER NOT READY","")))))) | O74: =IF($B74="",999999999,IF($D74="Installed",999999999,IF(NOT(ISNUMBER($E74)),999900000+70,$E74*10000+70))) -> 999999999 | Q74: =IF(LEFT($M74,1)="⚠",1,0) -> 0 | R74: =IF($Q74=1,SUM($Q$5:$Q74),"")
L75: =IF($D75="Installed","✔","") | M75: =IF($B75="","",IF($D75="Installed","",IF(AND($D75="Not Ready",$E75<>"",NOT(ISNUMBER($E75))),"⚠ CHECK DATE",IF(AND($D75="Not Ready",ISNUMBER($E75),$E75<$P$3),"⚠ PAST DUE - NOT READY",IF(AND($D75="Not Ready",ISNUMBER($E75),$E75>=$P$3,$E75<=$P$5),"⚠ EQUIP NOT READY",IF(AND($H75="Not Ready",ISNUMBER($E75),$E75>=$P$3,$E75<=$P$5),"⚠ CUSTOMER NOT READY","")))))) | O75: =IF($B75="",999999999,IF($D75="Installed",999999999,IF(NOT(ISNUMBER($E75)),999900000+71,$E75*10000+71))) -> 999999999 | Q75: =IF(LEFT($M75,1)="⚠",1,0) -> 0 | R75: =IF($Q75=1,SUM($Q$5:$Q75),"")
L76: =IF($D76="Installed","✔","") | M76: =IF($B76="","",IF($D76="Installed","",IF(AND($D76="Not Ready",$E76<>"",NOT(ISNUMBER($E76))),"⚠ CHECK DATE",IF(AND($D76="Not Ready",ISNUMBER($E76),$E76<$P$3),"⚠ PAST DUE - NOT READY",IF(AND($D76="Not Ready",ISNUMBER($E76),$E76>=$P$3,$E76<=$P$5),"⚠ EQUIP NOT READY",IF(AND($H76="Not Ready",ISNUMBER($E76),$E76>=$P$3,$E76<=$P$5),"⚠ CUSTOMER NOT READY","")))))) | O76: =IF($B76="",999999999,IF($D76="Installed",999999999,IF(NOT(ISNUMBER($E76)),999900000+72,$E76*10000+72))) -> 999999999 | Q76: =IF(LEFT($M76,1)="⚠",1,0) -> 0 | R76: =IF($Q76=1,SUM($Q$5:$Q76),"")
L77: =IF($D77="Installed","✔","") | M77: =IF($B77="","",IF($D77="Installed","",IF(AND($D77="Not Ready",$E77<>"",NOT(ISNUMBER($E77))),"⚠ CHECK DATE",IF(AND($D77="Not Ready",ISNUMBER($E77),$E77<$P$3),"⚠ PAST DUE - NOT READY",IF(AND($D77="Not Ready",ISNUMBER($E77),$E77>=$P$3,$E77<=$P$5),"⚠ EQUIP NOT READY",IF(AND($H77="Not Ready",ISNUMBER($E77),$E77>=$P$3,$E77<=$P$5),"⚠ CUSTOMER NOT READY","")))))) | O77: =IF($B77="",999999999,IF($D77="Installed",999999999,IF(NOT(ISNUMBER($E77)),999900000+73,$E77*10000+73))) -> 999999999 | Q77: =IF(LEFT($M77,1)="⚠",1,0) -> 0 | R77: =IF($Q77=1,SUM($Q$5:$Q77),"")
L78: =IF($D78="Installed","✔","") | M78: =IF($B78="","",IF($D78="Installed","",IF(AND($D78="Not Ready",$E78<>"",NOT(ISNUMBER($E78))),"⚠ CHECK DATE",IF(AND($D78="Not Ready",ISNUMBER($E78),$E78<$P$3),"⚠ PAST DUE - NOT READY",IF(AND($D78="Not Ready",ISNUMBER($E78),$E78>=$P$3,$E78<=$P$5),"⚠ EQUIP NOT READY",IF(AND($H78="Not Ready",ISNUMBER($E78),$E78>=$P$3,$E78<=$P$5),"⚠ CUSTOMER NOT READY","")))))) | O78: =IF($B78="",999999999,IF($D78="Installed",999999999,IF(NOT(ISNUMBER($E78)),999900000+74,$E78*10000+74))) -> 999999999 | Q78: =IF(LEFT($M78,1)="⚠",1,0) -> 0 | R78: =IF($Q78=1,SUM($Q$5:$Q78),"")
L79: =IF($D79="Installed","✔","") | M79: =IF($B79="","",IF($D79="Installed","",IF(AND($D79="Not Ready",$E79<>"",NOT(ISNUMBER($E79))),"⚠ CHECK DATE",IF(AND($D79="Not Ready",ISNUMBER($E79),$E79<$P$3),"⚠ PAST DUE - NOT READY",IF(AND($D79="Not Ready",ISNUMBER($E79),$E79>=$P$3,$E79<=$P$5),"⚠ EQUIP NOT READY",IF(AND($H79="Not Ready",ISNUMBER($E79),$E79>=$P$3,$E79<=$P$5),"⚠ CUSTOMER NOT READY","")))))) | O79: =IF($B79="",999999999,IF($D79="Installed",999999999,IF(NOT(ISNUMBER($E79)),999900000+75,$E79*10000+75))) -> 999999999 | Q79: =IF(LEFT($M79,1)="⚠",1,0) -> 0 | R79: =IF($Q79=1,SUM($Q$5:$Q79),"")
L80: =IF($D80="Installed","✔","") | M80: =IF($B80="","",IF($D80="Installed","",IF(AND($D80="Not Ready",$E80<>"",NOT(ISNUMBER($E80))),"⚠ CHECK DATE",IF(AND($D80="Not Ready",ISNUMBER($E80),$E80<$P$3),"⚠ PAST DUE - NOT READY",IF(AND($D80="Not Ready",ISNUMBER($E80),$E80>=$P$3,$E80<=$P$5),"⚠ EQUIP NOT READY",IF(AND($H80="Not Ready",ISNUMBER($E80),$E80>=$P$3,$E80<=$P$5),"⚠ CUSTOMER NOT READY","")))))) | O80: =IF($B80="",999999999,IF($D80="Installed",999999999,IF(NOT(ISNUMBER($E80)),999900000+76,$E80*10000+76))) -> 999999999 | Q80: =IF(LEFT($M80,1)="⚠",1,0) -> 0 | R80: =IF($Q80=1,SUM($Q$5:$Q80),"")
L81: =IF($D81="Installed","✔","") | M81: =IF($B81="","",IF($D81="Installed","",IF(AND($D81="Not Ready",$E81<>"",NOT(ISNUMBER($E81))),"⚠ CHECK DATE",IF(AND($D81="Not Ready",ISNUMBER($E81),$E81<$P$3),"⚠ PAST DUE - NOT READY",IF(AND($D81="Not Ready",ISNUMBER($E81),$E81>=$P$3,$E81<=$P$5),"⚠ EQUIP NOT READY",IF(AND($H81="Not Ready",ISNUMBER($E81),$E81>=$P$3,$E81<=$P$5),"⚠ CUSTOMER NOT READY","")))))) | O81: =IF($B81="",999999999,IF($D81="Installed",999999999,IF(NOT(ISNUMBER($E81)),999900000+77,$E81*10000+77))) -> 999999999 | Q81: =IF(LEFT($M81,1)="⚠",1,0) -> 0 | R81: =IF($Q81=1,SUM($Q$5:$Q81),"")
L82: =IF($D82="Installed","✔","") | M82: =IF($B82="","",IF($D82="Installed","",IF(AND($D82="Not Ready",$E82<>"",NOT(ISNUMBER($E82))),"⚠ CHECK DATE",IF(AND($D82="Not Ready",ISNUMBER($E82),$E82<$P$3),"⚠ PAST DUE - NOT READY",IF(AND($D82="Not Ready",ISNUMBER($E82),$E82>=$P$3,$E82<=$P$5),"⚠ EQUIP NOT READY",IF(AND($H82="Not Ready",ISNUMBER($E82),$E82>=$P$3,$E82<=$P$5),"⚠ CUSTOMER NOT READY","")))))) | O82: =IF($B82="",999999999,IF($D82="Installed",999999999,IF(NOT(ISNUMBER($E82)),999900000+78,$E82*10000+78))) -> 999999999 | Q82: =IF(LEFT($M82,1)="⚠",1,0) -> 0 | R82: =IF($Q82=1,SUM($Q$5:$Q82),"")
L83: =IF($D83="Installed","✔","") | M83: =IF($B83="","",IF($D83="Installed","",IF(AND($D83="Not Ready",$E83<>"",NOT(ISNUMBER($E83))),"⚠ CHECK DATE",IF(AND($D83="Not Ready",ISNUMBER($E83),$E83<$P$3),"⚠ PAST DUE - NOT READY",IF(AND($D83="Not Ready",ISNUMBER($E83),$E83>=$P$3,$E83<=$P$5),"⚠ EQUIP NOT READY",IF(AND($H83="Not Ready",ISNUMBER($E83),$E83>=$P$3,$E83<=$P$5),"⚠ CUSTOMER NOT READY","")))))) | O83: =IF($B83="",999999999,IF($D83="Installed",999999999,IF(NOT(ISNUMBER($E83)),999900000+79,$E83*10000+79))) -> 999999999 | Q83: =IF(LEFT($M83,1)="⚠",1,0) -> 0 | R83: =IF($Q83=1,SUM($Q$5:$Q83),"")
L84: =IF($D84="Installed","✔","") | M84: =IF($B84="","",IF($D84="Installed","",IF(AND($D84="Not Ready",$E84<>"",NOT(ISNUMBER($E84))),"⚠ CHECK DATE",IF(AND($D84="Not Ready",ISNUMBER($E84),$E84<$P$3),"⚠ PAST DUE - NOT READY",IF(AND($D84="Not Ready",ISNUMBER($E84),$E84>=$P$3,$E84<=$P$5),"⚠ EQUIP NOT READY",IF(AND($H84="Not Ready",ISNUMBER($E84),$E84>=$P$3,$E84<=$P$5),"⚠ CUSTOMER NOT READY","")))))) | O84: =IF($B84="",999999999,IF($D84="Installed",999999999,IF(NOT(ISNUMBER($E84)),999900000+80,$E84*10000+80))) -> 999999999 | Q84: =IF(LEFT($M84,1)="⚠",1,0) -> 0 | R84: =IF($Q84=1,SUM($Q$5:$Q84),"")
L85: =IF($D85="Installed","✔","") | M85: =IF($B85="","",IF($D85="Installed","",IF(AND($D85="Not Ready",$E85<>"",NOT(ISNUMBER($E85))),"⚠ CHECK DATE",IF(AND($D85="Not Ready",ISNUMBER($E85),$E85<$P$3),"⚠ PAST DUE - NOT READY",IF(AND($D85="Not Ready",ISNUMBER($E85),$E85>=$P$3,$E85<=$P$5),"⚠ EQUIP NOT READY",IF(AND($H85="Not Ready",ISNUMBER($E85),$E85>=$P$3,$E85<=$P$5),"⚠ CUSTOMER NOT READY","")))))) | O85: =IF($B85="",999999999,IF($D85="Installed",999999999,IF(NOT(ISNUMBER($E85)),999900000+81,$E85*10000+81))) -> 999999999 | Q85: =IF(LEFT($M85,1)="⚠",1,0) -> 0 | R85: =IF($Q85=1,SUM($Q$5:$Q85),"")
L86: =IF($D86="Installed","✔","") | M86: =IF($B86="","",IF($D86="Installed","",IF(AND($D86="Not Ready",$E86<>"",NOT(ISNUMBER($E86))),"⚠ CHECK DATE",IF(AND($D86="Not Ready",ISNUMBER($E86),$E86<$P$3),"⚠ PAST DUE - NOT READY",IF(AND($D86="Not Ready",ISNUMBER($E86),$E86>=$P$3,$E86<=$P$5),"⚠ EQUIP NOT READY",IF(AND($H86="Not Ready",ISNUMBER($E86),$E86>=$P$3,$E86<=$P$5),"⚠ CUSTOMER NOT READY","")))))) | O86: =IF($B86="",999999999,IF($D86="Installed",999999999,IF(NOT(ISNUMBER($E86)),999900000+82,$E86*10000+82))) -> 999999999 | Q86: =IF(LEFT($M86,1)="⚠",1,0) -> 0 | R86: =IF($Q86=1,SUM($Q$5:$Q86),"")
L87: =IF($D87="Installed","✔","") | M87: =IF($B87="","",IF($D87="Installed","",IF(AND($D87="Not Ready",$E87<>"",NOT(ISNUMBER($E87))),"⚠ CHECK DATE",IF(AND($D87="Not Ready",ISNUMBER($E87),$E87<$P$3),"⚠ PAST DUE - NOT READY",IF(AND($D87="Not Ready",ISNUMBER($E87),$E87>=$P$3,$E87<=$P$5),"⚠ EQUIP NOT READY",IF(AND($H87="Not Ready",ISNUMBER($E87),$E87>=$P$3,$E87<=$P$5),"⚠ CUSTOMER NOT READY","")))))) | O87: =IF($B87="",999999999,IF($D87="Installed",999999999,IF(NOT(ISNUMBER($E87)),999900000+83,$E87*10000+83))) -> 999999999 | Q87: =IF(LEFT($M87,1)="⚠",1,0) -> 0 | R87: =IF($Q87=1,SUM($Q$5:$Q87),"")
L88: =IF($D88="Installed","✔","") | M88: =IF($B88="","",IF($D88="Installed","",IF(AND($D88="Not Ready",$E88<>"",NOT(ISNUMBER($E88))),"⚠ CHECK DATE",IF(AND($D88="Not Ready",ISNUMBER($E88),$E88<$P$3),"⚠ PAST DUE - NOT READY",IF(AND($D88="Not Ready",ISNUMBER($E88),$E88>=$P$3,$E88<=$P$5),"⚠ EQUIP NOT READY",IF(AND($H88="Not Ready",ISNUMBER($E88),$E88>=$P$3,$E88<=$P$5),"⚠ CUSTOMER NOT READY","")))))) | O88: =IF($B88="",999999999,IF($D88="Installed",999999999,IF(NOT(ISNUMBER($E88)),999900000+84,$E88*10000+84))) -> 999999999 | Q88: =IF(LEFT($M88,1)="⚠",1,0) -> 0 | R88: =IF($Q88=1,SUM($Q$5:$Q88),"")
L89: =IF($D89="Installed","✔","") | M89: =IF($B89="","",IF($D89="Installed","",IF(AND($D89="Not Ready",$E89<>"",NOT(ISNUMBER($E89))),"⚠ CHECK DATE",IF(AND($D89="Not Ready",ISNUMBER($E89),$E89<$P$3),"⚠ PAST DUE - NOT READY",IF(AND($D89="Not Ready",ISNUMBER($E89),$E89>=$P$3,$E89<=$P$5),"⚠ EQUIP NOT READY",IF(AND($H89="Not Ready",ISNUMBER($E89),$E89>=$P$3,$E89<=$P$5),"⚠ CUSTOMER NOT READY","")))))) | O89: =IF($B89="",999999999,IF($D89="Installed",999999999,IF(NOT(ISNUMBER($E89)),999900000+85,$E89*10000+85))) -> 999999999 | Q89: =IF(LEFT($M89,1)="⚠",1,0) -> 0 | R89: =IF($Q89=1,SUM($Q$5:$Q89),"")
L90: =IF($D90="Installed","✔","") | M90: =IF($B90="","",IF($D90="Installed","",IF(AND($D90="Not Ready",$E90<>"",NOT(ISNUMBER($E90))),"⚠ CHECK DATE",IF(AND($D90="Not Ready",ISNUMBER($E90),$E90<$P$3),"⚠ PAST DUE - NOT READY",IF(AND($D90="Not Ready",ISNUMBER($E90),$E90>=$P$3,$E90<=$P$5),"⚠ EQUIP NOT READY",IF(AND($H90="Not Ready",ISNUMBER($E90),$E90>=$P$3,$E90<=$P$5),"⚠ CUSTOMER NOT READY","")))))) | O90: =IF($B90="",999999999,IF($D90="Installed",999999999,IF(NOT(ISNUMBER($E90)),999900000+86,$E90*10000+86))) -> 999999999 | Q90: =IF(LEFT($M90,1)="⚠",1,0) -> 0 | R90: =IF($Q90=1,SUM($Q$5:$Q90),"")
L91: =IF($D91="Installed","✔","") | M91: =IF($B91="","",IF($D91="Installed","",IF(AND($D91="Not Ready",$E91<>"",NOT(ISNUMBER($E91))),"⚠ CHECK DATE",IF(AND($D91="Not Ready",ISNUMBER($E91),$E91<$P$3),"⚠ PAST DUE - NOT READY",IF(AND($D91="Not Ready",ISNUMBER($E91),$E91>=$P$3,$E91<=$P$5),"⚠ EQUIP NOT READY",IF(AND($H91="Not Ready",ISNUMBER($E91),$E91>=$P$3,$E91<=$P$5),"⚠ CUSTOMER NOT READY","")))))) | O91: =IF($B91="",999999999,IF($D91="Installed",999999999,IF(NOT(ISNUMBER($E91)),999900000+87,$E91*10000+87))) -> 999999999 | Q91: =IF(LEFT($M91,1)="⚠",1,0) -> 0 | R91: =IF($Q91=1,SUM($Q$5:$Q91),"")
L92: =IF($D92="Installed","✔","") | M92: =IF($B92="","",IF($D92="Installed","",IF(AND($D92="Not Ready",$E92<>"",NOT(ISNUMBER($E92))),"⚠ CHECK DATE",IF(AND($D92="Not Ready",ISNUMBER($E92),$E92<$P$3),"⚠ PAST DUE - NOT READY",IF(AND($D92="Not Ready",ISNUMBER($E92),$E92>=$P$3,$E92<=$P$5),"⚠ EQUIP NOT READY",IF(AND($H92="Not Ready",ISNUMBER($E92),$E92>=$P$3,$E92<=$P$5),"⚠ CUSTOMER NOT READY","")))))) | O92: =IF($B92="",999999999,IF($D92="Installed",999999999,IF(NOT(ISNUMBER($E92)),999900000+88,$E92*10000+88))) -> 999999999 | Q92: =IF(LEFT($M92,1)="⚠",1,0) -> 0 | R92: =IF($Q92=1,SUM($Q$5:$Q92),"")
L93: =IF($D93="Installed","✔","") | M93: =IF($B93="","",IF($D93="Installed","",IF(AND($D93="Not Ready",$E93<>"",NOT(ISNUMBER($E93))),"⚠ CHECK DATE",IF(AND($D93="Not Ready",ISNUMBER($E93),$E93<$P$3),"⚠ PAST DUE - NOT READY",IF(AND($D93="Not Ready",ISNUMBER($E93),$E93>=$P$3,$E93<=$P$5),"⚠ EQUIP NOT READY",IF(AND($H93="Not Ready",ISNUMBER($E93),$E93>=$P$3,$E93<=$P$5),"⚠ CUSTOMER NOT READY","")))))) | O93: =IF($B93="",999999999,IF($D93="Installed",999999999,IF(NOT(ISNUMBER($E93)),999900000+89,$E93*10000+89))) -> 999999999 | Q93: =IF(LEFT($M93,1)="⚠",1,0) -> 0 | R93: =IF($Q93=1,SUM($Q$5:$Q93),"")
L94: =IF($D94="Installed","✔","") | M94: =IF($B94="","",IF($D94="Installed","",IF(AND($D94="Not Ready",$E94<>"",NOT(ISNUMBER($E94))),"⚠ CHECK DATE",IF(AND($D94="Not Ready",ISNUMBER($E94),$E94<$P$3),"⚠ PAST DUE - NOT READY",IF(AND($D94="Not Ready",ISNUMBER($E94),$E94>=$P$3,$E94<=$P$5),"⚠ EQUIP NOT READY",IF(AND($H94="Not Ready",ISNUMBER($E94),$E94>=$P$3,$E94<=$P$5),"⚠ CUSTOMER NOT READY","")))))) | O94: =IF($B94="",999999999,IF($D94="Installed",999999999,IF(NOT(ISNUMBER($E94)),999900000+90,$E94*10000+90))) -> 999999999 | Q94: =IF(LEFT($M94,1)="⚠",1,0) -> 0 | R94: =IF($Q94=1,SUM($Q$5:$Q94),"")
L95: =IF($D95="Installed","✔","") | M95: =IF($B95="","",IF($D95="Installed","",IF(AND($D95="Not Ready",$E95<>"",NOT(ISNUMBER($E95))),"⚠ CHECK DATE",IF(AND($D95="Not Ready",ISNUMBER($E95),$E95<$P$3),"⚠ PAST DUE - NOT READY",IF(AND($D95="Not Ready",ISNUMBER($E95),$E95>=$P$3,$E95<=$P$5),"⚠ EQUIP NOT READY",IF(AND($H95="Not Ready",ISNUMBER($E95),$E95>=$P$3,$E95<=$P$5),"⚠ CUSTOMER NOT READY","")))))) | O95: =IF($B95="",999999999,IF($D95="Installed",999999999,IF(NOT(ISNUMBER($E95)),999900000+91,$E95*10000+91))) -> 999999999 | Q95: =IF(LEFT($M95,1)="⚠",1,0) -> 0 | R95: =IF($Q95=1,SUM($Q$5:$Q95),"")
L96: =IF($D96="Installed","✔","") | M96: =IF($B96="","",IF($D96="Installed","",IF(AND($D96="Not Ready",$E96<>"",NOT(ISNUMBER($E96))),"⚠ CHECK DATE",IF(AND($D96="Not Ready",ISNUMBER($E96),$E96<$P$3),"⚠ PAST DUE - NOT READY",IF(AND($D96="Not Ready",ISNUMBER($E96),$E96>=$P$3,$E96<=$P$5),"⚠ EQUIP NOT READY",IF(AND($H96="Not Ready",ISNUMBER($E96),$E96>=$P$3,$E96<=$P$5),"⚠ CUSTOMER NOT READY","")))))) | O96: =IF($B96="",999999999,IF($D96="Installed",999999999,IF(NOT(ISNUMBER($E96)),999900000+92,$E96*10000+92))) -> 999999999 | Q96: =IF(LEFT($M96,1)="⚠",1,0) -> 0 | R96: =IF($Q96=1,SUM($Q$5:$Q96),"")
L97: =IF($D97="Installed","✔","") | M97: =IF($B97="","",IF($D97="Installed","",IF(AND($D97="Not Ready",$E97<>"",NOT(ISNUMBER($E97))),"⚠ CHECK DATE",IF(AND($D97="Not Ready",ISNUMBER($E97),$E97<$P$3),"⚠ PAST DUE - NOT READY",IF(AND($D97="Not Ready",ISNUMBER($E97),$E97>=$P$3,$E97<=$P$5),"⚠ EQUIP NOT READY",IF(AND($H97="Not Ready",ISNUMBER($E97),$E97>=$P$3,$E97<=$P$5),"⚠ CUSTOMER NOT READY","")))))) | O97: =IF($B97="",999999999,IF($D97="Installed",999999999,IF(NOT(ISNUMBER($E97)),999900000+93,$E97*10000+93))) -> 999999999 | Q97: =IF(LEFT($M97,1)="⚠",1,0) -> 0 | R97: =IF($Q97=1,SUM($Q$5:$Q97),"")
L98: =IF($D98="Installed","✔","") | M98: =IF($B98="","",IF($D98="Installed","",IF(AND($D98="Not Ready",$E98<>"",NOT(ISNUMBER($E98))),"⚠ CHECK DATE",IF(AND($D98="Not Ready",ISNUMBER($E98),$E98<$P$3),"⚠ PAST DUE - NOT READY",IF(AND($D98="Not Ready",ISNUMBER($E98),$E98>=$P$3,$E98<=$P$5),"⚠ EQUIP NOT READY",IF(AND($H98="Not Ready",ISNUMBER($E98),$E98>=$P$3,$E98<=$P$5),"⚠ CUSTOMER NOT READY","")))))) | O98: =IF($B98="",999999999,IF($D98="Installed",999999999,IF(NOT(ISNUMBER($E98)),999900000+94,$E98*10000+94))) -> 999999999 | Q98: =IF(LEFT($M98,1)="⚠",1,0) -> 0 | R98: =IF($Q98=1,SUM($Q$5:$Q98),"")
L99: =IF($D99="Installed","✔","") | M99: =IF($B99="","",IF($D99="Installed","",IF(AND($D99="Not Ready",$E99<>"",NOT(ISNUMBER($E99))),"⚠ CHECK DATE",IF(AND($D99="Not Ready",ISNUMBER($E99),$E99<$P$3),"⚠ PAST DUE - NOT READY",IF(AND($D99="Not Ready",ISNUMBER($E99),$E99>=$P$3,$E99<=$P$5),"⚠ EQUIP NOT READY",IF(AND($H99="Not Ready",ISNUMBER($E99),$E99>=$P$3,$E99<=$P$5),"⚠ CUSTOMER NOT READY","")))))) | O99: =IF($B99="",999999999,IF($D99="Installed",999999999,IF(NOT(ISNUMBER($E99)),999900000+95,$E99*10000+95))) -> 999999999 | Q99: =IF(LEFT($M99,1)="⚠",1,0) -> 0 | R99: =IF($Q99=1,SUM($Q$5:$Q99),"")
L100: =IF($D100="Installed","✔","") | M100: =IF($B100="","",IF($D100="Installed","",IF(AND($D100="Not Ready",$E100<>"",NOT(ISNUMBER($E100))),"⚠ CHECK DATE",IF(AND($D100="Not Ready",ISNUMBER($E100),$E100<$P$3),"⚠ PAST DUE - NOT READY",IF(AND($D100="Not Ready",ISNUMBER($E100),$E100>=$P$3,$E100<=$P$5),"⚠ EQUIP NOT READY",IF(AND($H100="Not Ready",ISNUMBER($E100),$E100>=$P$3,$E100<=$P$5),"⚠ CUSTOMER NOT READY","")))))) | O100: =IF($B100="",999999999,IF($D100="Installed",999999999,IF(NOT(ISNUMBER($E100)),999900000+96,$E100*10000+96))) -> 999999999 | Q100: =IF(LEFT($M100,1)="⚠",1,0) -> 0 | R100: =IF($Q100=1,SUM($Q$5:$Q100),"")
...

Sheet Lists
A1: Technicians | B1: Call Status | C1: Call Type | D1: Yes/No | E1: Equip Status | F1: PM Style | G1: Parts Status | H1: PM Status | I1: Account Reps | J1: Checkbox helper | K1: Add new technicians, statuses, or reps to these lists and the dropdowns on every tab update automatically. | L1: Module Platform | M1: Module Type | N1: Module Status | O1: Internal Techs | P1: Payment Status | Q1: Producers | R1: Payment Terms | S1: Completion | T1: Account Type | U1: Producer (map) | V1: Initials | W1: Requirements Ready?
A2: Josh | B2: Open | C2: Field Service | D2: Y | E2: Ready | F2: 6 month PM | G2: Yes - All Available | H2: Pending Scheduling | I2: AL | J2: ✔ | L2: Cameo | M2: Brew Module | N2: Not Started | O2: Ryan | P2: 50% Down / 50% at Install or Net 30 | Q2: Bill | R2: Payment Plan | S2: ✔ | T2: Avi Account | U2: Bill | V2: BM | W2: Ready
A3: Oliver | B3: Phone Resolved | C3: In-House Rebuild | D3: N | E3: Not Ready | F3: 12 month PM | G3: Partial | H3: Scheduled | I3: LO | L3: Enigma / e'Line | M3: Medium Brew Module | N3: In Progress | O3: Elias | P3: Paid in Full | Q3: Lance | R3: 50% Down + 50% upon install/30 days after | S3: X | T3: Richard Account | U3: Lance | V3: LO | W3: Not Ready
A4: Charles | B4: Dispatched | C4: Installation | E4: Installed | F4: 36 month PM | G4: No - Awaiting Parts | H4: Awaiting Parts | I4: LR | L4: Legacy | M4: Large Brew Module | N4: Waiting on Parts | O4: Oliver | P4: Lease | Q4: Sean | R4: Lease | U4: Sean | V4: SM
A5: Elias | B5: In Progress | F5: Grinder PM | G5: On Order | H5: Ready to Dispatch | I5: JG | M5: Steam S Module | N5: Ready | O5: Josh | P5: No Purchased Equipment | Q5: Shannon | R5: Paid in Full | U5: Shannon | V5: SC
A6: Ryan | B6: Completed | G6: TBD / Check Inventory | H6: In Progress | I6: SC | M6: Steam M Module | N6: Ship to Eversys (Core Swap) | O6: Charles | P6: Payment Plan | Q6: Lizbeth | U6: Lizbeth | V6: LR
A7: Bill | B7: Follow-up Needed | H7: Completed | I7: SM | M7: Hydraulic Module | N7: At Eversys - Awaiting Return | O7: Bill | Q7: Amanda | U7: Amanda | V7: AL
A8: Lance | B8: Cancelled | H8: Cancelled | I8: RK | M8: Grinder Module | N8: Installed at Account | O8: Lance | Q8: Jesus | U8: Jesus | V8: JG
A9: 3rd Party | I9: BM | M9: Milk Module | N9: Retired / Scrapped
M10: Pump Module
M11: Powder Module
