Workbook
Name ProviderList: OFFSET(Service_Providers!$A$2,0,0,MAX(1,COUNTA(Service_Providers!$A$2:$A$104)),1)

Sheet Dashboard
A1: SERVICE NETWORK MASTER DATABASE - Out-of-Network Accounts
A2: Updates automatically: add providers on Service_Providers (through row 101) and accounts on Accounts (through row 300) - dropdowns, dispatch info, and these tables refresh on their own.
A4: COVERAGE BY STATE | G4: ACCOUNTS BY PROVIDER
A5: State | B5: Total Accounts | C5: With Equipment | D5: Unassigned | E5: % Covered | G5: Provider | H5: Primary For | I5: Secondary For | J5: Dispatch Phone | K5: Dispatch Email
A6: AR | B6: =COUNTIF(Accounts!$G$2:$G$299,A6) -> 2 | C6: =COUNTIFS(Accounts!$G$2:$G$299,A6,Accounts!$I$2:$I$299,"<>") -> 2 | D6: =COUNTIFS(Accounts!$G$2:$G$299,A6,Accounts!$K$2:$K$299,"") -> 0 | E6: =IF(B6=0,0,(B6-D6)/B6) -> 1 | G6: =IF(Service_Providers!A2="","",Service_Providers!A2) -> A-1 Restuarant Service | H6: =IF(G6="","",COUNTIF(Accounts!$K$2:$K$299,G6)) -> 0 | I6: =IF(G6="","",COUNTIF(Accounts!$M$2:$M$299,G6)) -> 0 | J6: =IF(Service_Providers!C2="","",Service_Providers!C2) | K6: =IF(Service_Providers!D2="","",Service_Providers!D2)
A7: AZ | B7: =COUNTIF(Accounts!$G$2:$G$299,A7) -> 4 | C7: =COUNTIFS(Accounts!$G$2:$G$299,A7,Accounts!$I$2:$I$299,"<>") -> 4 | D7: =COUNTIFS(Accounts!$G$2:$G$299,A7,Accounts!$K$2:$K$299,"") -> 0 | E7: =IF(B7=0,0,(B7-D7)/B7) -> 1 | G7: =IF(Service_Providers!A3="","",Service_Providers!A3) -> A-Tech Espresso & Coffee Service Inc. | H7: =IF(G7="","",COUNTIF(Accounts!$K$2:$K$299,G7)) -> 0 | I7: =IF(G7="","",COUNTIF(Accounts!$M$2:$M$299,G7)) -> 0 | J7: =IF(Service_Providers!C3="","",Service_Providers!C3) -> 866.333.7350 | K7: =IF(Service_Providers!D3="","",Service_Providers!D3) -> servicerequest@Atech-service.com
A8: CA | B8: =COUNTIF(Accounts!$G$2:$G$299,A8) -> 8 | C8: =COUNTIFS(Accounts!$G$2:$G$299,A8,Accounts!$I$2:$I$299,"<>") -> 8 | D8: =COUNTIFS(Accounts!$G$2:$G$299,A8,Accounts!$K$2:$K$299,"") -> 0 | E8: =IF(B8=0,0,(B8-D8)/B8) -> 1 | G8: =IF(Service_Providers!A4="","",Service_Providers!A4) -> ABS Coffee Repair | H8: =IF(G8="","",COUNTIF(Accounts!$K$2:$K$299,G8)) -> 0 | I8: =IF(G8="","",COUNTIF(Accounts!$M$2:$M$299,G8)) -> 0 | J8: =IF(Service_Providers!C4="","",Service_Providers!C4) -> 314.389.2866 | K8: =IF(Service_Providers!D4="","",Service_Providers!D4)
A9: CO | B9: =COUNTIF(Accounts!$G$2:$G$299,A9) -> 6 | C9: =COUNTIFS(Accounts!$G$2:$G$299,A9,Accounts!$I$2:$I$299,"<>") -> 6 | D9: =COUNTIFS(Accounts!$G$2:$G$299,A9,Accounts!$K$2:$K$299,"") -> 0 | E9: =IF(B9=0,0,(B9-D9)/B9) -> 1 | G9: =IF(Service_Providers!A5="","",Service_Providers!A5) -> All Espresso Service | H9: =IF(G9="","",COUNTIF(Accounts!$K$2:$K$299,G9)) -> 4 | I9: =IF(G9="","",COUNTIF(Accounts!$M$2:$M$299,G9)) -> 0 | J9: =IF(Service_Providers!C5="","",Service_Providers!C5) -> 754.205.5076 | K9: =IF(Service_Providers!D5="","",Service_Providers!D5) -> service@allespressoservice.com
A10: DC | B10: =COUNTIF(Accounts!$G$2:$G$299,A10) -> 1 | C10: =COUNTIFS(Accounts!$G$2:$G$299,A10,Accounts!$I$2:$I$299,"<>") -> 1 | D10: =COUNTIFS(Accounts!$G$2:$G$299,A10,Accounts!$K$2:$K$299,"") -> 0 | E10: =IF(B10=0,0,(B10-D10)/B10) -> 1 | G10: =IF(Service_Providers!A6="","",Service_Providers!A6) -> All Star Coffee Service | H10: =IF(G10="","",COUNTIF(Accounts!$K$2:$K$299,G10)) -> 2 | I10: =IF(G10="","",COUNTIF(Accounts!$M$2:$M$299,G10)) -> 0 | J10: =IF(Service_Providers!C6="","",Service_Providers!C6) -> 626-315-8498 | K10: =IF(Service_Providers!D6="","",Service_Providers!D6) -> allstarcoffeeservice@gmail.com
A11: FL | B11: =COUNTIF(Accounts!$G$2:$G$299,A11) -> 9 | C11: =COUNTIFS(Accounts!$G$2:$G$299,A11,Accounts!$I$2:$I$299,"<>") -> 9 | D11: =COUNTIFS(Accounts!$G$2:$G$299,A11,Accounts!$K$2:$K$299,"") -> 0 | E11: =IF(B11=0,0,(B11-D11)/B11) -> 1 | G11: =IF(Service_Providers!A7="","",Service_Providers!A7) -> Anytime Beverage Service | H11: =IF(G11="","",COUNTIF(Accounts!$K$2:$K$299,G11)) -> 7 | I11: =IF(G11="","",COUNTIF(Accounts!$M$2:$M$299,G11)) -> 2 | J11: =IF(Service_Providers!C7="","",Service_Providers!C7) -> Contact: Cynthia Phone: 714-335-9964 Cell: 714-395-8108 | K11: =IF(Service_Providers!D7="","",Service_Providers!D7) -> anytimebeverageservice@gmail.com
A12: GA | B12: =COUNTIF(Accounts!$G$2:$G$299,A12) -> 3 | C12: =COUNTIFS(Accounts!$G$2:$G$299,A12,Accounts!$I$2:$I$299,"<>") -> 3 | D12: =COUNTIFS(Accounts!$G$2:$G$299,A12,Accounts!$K$2:$K$299,"") -> 0 | E12: =IF(B12=0,0,(B12-D12)/B12) -> 1 | G12: =IF(Service_Providers!A8="","",Service_Providers!A8) -> B & B Coffee Service | H12: =IF(G12="","",COUNTIF(Accounts!$K$2:$K$299,G12)) -> 2 | I12: =IF(G12="","",COUNTIF(Accounts!$M$2:$M$299,G12)) -> 0 | J12: =IF(Service_Providers!C8="","",Service_Providers!C8) -> 361.855.3066 | K12: =IF(Service_Providers!D8="","",Service_Providers!D8)
A13: IL | B13: =COUNTIF(Accounts!$G$2:$G$299,A13) -> 2 | C13: =COUNTIFS(Accounts!$G$2:$G$299,A13,Accounts!$I$2:$I$299,"<>") -> 2 | D13: =COUNTIFS(Accounts!$G$2:$G$299,A13,Accounts!$K$2:$K$299,"") -> 0 | E13: =IF(B13=0,0,(B13-D13)/B13) -> 1 | G13: =IF(Service_Providers!A9="","",Service_Providers!A9) -> Bar 9 Coffee Services LLC | H13: =IF(G13="","",COUNTIF(Accounts!$K$2:$K$299,G13)) -> 0 | I13: =IF(G13="","",COUNTIF(Accounts!$M$2:$M$299,G13)) -> 0 | J13: =IF(Service_Providers!C9="","",Service_Providers!C9) -> 443-460-4303 | K13: =IF(Service_Providers!D9="","",Service_Providers!D9) -> chuck@bar9coffee.com
A14: IN | B14: =COUNTIF(Accounts!$G$2:$G$299,A14) -> 5 | C14: =COUNTIFS(Accounts!$G$2:$G$299,A14,Accounts!$I$2:$I$299,"<>") -> 5 | D14: =COUNTIFS(Accounts!$G$2:$G$299,A14,Accounts!$K$2:$K$299,"") -> 0 | E14: =IF(B14=0,0,(B14-D14)/B14) -> 1 | G14: =IF(Service_Providers!A10="","",Service_Providers!A10) -> Best Beverage Equipment Service | H14: =IF(G14="","",COUNTIF(Accounts!$K$2:$K$299,G14)) -> 0 | I14: =IF(G14="","",COUNTIF(Accounts!$M$2:$M$299,G14)) -> 3 | J14: =IF(Service_Providers!C10="","",Service_Providers!C10) -> 866-966-5799 ext 1 | K14: =IF(Service_Providers!D10="","",Service_Providers!D10) -> service@bestbeverage.net
A15: KS | B15: =COUNTIF(Accounts!$G$2:$G$299,A15) -> 2 | C15: =COUNTIFS(Accounts!$G$2:$G$299,A15,Accounts!$I$2:$I$299,"<>") -> 2 | D15: =COUNTIFS(Accounts!$G$2:$G$299,A15,Accounts!$K$2:$K$299,"") -> 0 | E15: =IF(B15=0,0,(B15-D15)/B15) -> 1 | G15: =IF(Service_Providers!A11="","",Service_Providers!A11) -> Bev Pro Services | H15: =IF(G15="","",COUNTIF(Accounts!$K$2:$K$299,G15)) -> 0 | I15: =IF(G15="","",COUNTIF(Accounts!$M$2:$M$299,G15)) -> 0 | J15: =IF(Service_Providers!C11="","",Service_Providers!C11) -> 410-571-4902 ext. 501 (Office) | K15: =IF(Service_Providers!D11="","",Service_Providers!D11)
A16: LA | B16: =COUNTIF(Accounts!$G$2:$G$299,A16) -> 3 | C16: =COUNTIFS(Accounts!$G$2:$G$299,A16,Accounts!$I$2:$I$299,"<>") -> 3 | D16: =COUNTIFS(Accounts!$G$2:$G$299,A16,Accounts!$K$2:$K$299,"") -> 0 | E16: =IF(B16=0,0,(B16-D16)/B16) -> 1 | G16: =IF(Service_Providers!A12="","",Service_Providers!A12) -> Beverage Equipment Service Inc. | H16: =IF(G16="","",COUNTIF(Accounts!$K$2:$K$299,G16)) -> 0 | I16: =IF(G16="","",COUNTIF(Accounts!$M$2:$M$299,G16)) -> 0 | J16: =IF(Service_Providers!C12="","",Service_Providers!C12) -> (515) 494-0849 | K16: =IF(Service_Providers!D12="","",Service_Providers!D12) -> bevequip@outlook.com (best - copied on all comms)
A17: MD | B17: =COUNTIF(Accounts!$G$2:$G$299,A17) -> 1 | C17: =COUNTIFS(Accounts!$G$2:$G$299,A17,Accounts!$I$2:$I$299,"<>") -> 1 | D17: =COUNTIFS(Accounts!$G$2:$G$299,A17,Accounts!$K$2:$K$299,"") -> 1 | E17: =IF(B17=0,0,(B17-D17)/B17) -> 0 | G17: =IF(Service_Providers!A13="","",Service_Providers!A13) -> Carolina Beverage Solutions | H17: =IF(G17="","",COUNTIF(Accounts!$K$2:$K$299,G17)) -> 5 | I17: =IF(G17="","",COUNTIF(Accounts!$M$2:$M$299,G17)) -> 0 | J17: =IF(Service_Providers!C13="","",Service_Providers!C13) -> 803-280-5234 | K17: =IF(Service_Providers!D13="","",Service_Providers!D13) -> chris.powers@hotmail.com
... A22: NV | B22: =COUNTIF(Accounts!$G$2:$G$299,A22) -> 2 | C22: =COUNTIFS(Accounts!$G$2:$G$299,A22,Accounts!$I$2:$I$299,"<>") -> 2 | D22: =COUNTIFS(Accounts!$G$2:$G$299,A22,Accounts!$K$2:$K$299,"") -> 0 | E22: =IF(B22=0,0,(B22-D22)/B22) -> 1 | G22: =IF(Service_Providers!A18="","",Service_Providers!A18) -> ETSC (EspressoTech Service Company) | H22: =IF(G22="","",COUNTIF(Accounts!$K$2:$K$299,G22)) -> 7 | I22: =IF(G22="","",COUNTIF(Accounts!$M$2:$M$299,G22)) -> 1 | J22: =IF(Service_Providers!C18="","",Service_Providers!C18) -> (888) 523-1684 | K22: =IF(Service_Providers!D18="","",Service_Providers!D18) -> service@etsc.coffee
A23: OK | B23: =COUNTIF(Accounts!$G$2:$G$299,A23) -> 4 | C23: =COUNTIFS(Accounts!$G$2:$G$299,A23,Accounts!$I$2:$I$299,"<>") -> 4 | D23: =COUNTIFS(Accounts!$G$2:$G$299,A23,Accounts!$K$2:$K$299,"") -> 0 | E23: =IF(B23=0,0,(B23-D23)/B23) -> 1 | G23: =IF(Service_Providers!A20="","",Service_Providers!A20) -> First Coast Espresso | H23: =IF(G23="","",COUNTIF(Accounts!$K$2:$K$299,G23)) -> 1 | I23: =IF(G23="","",COUNTIF(Accounts!$M$2:$M$299,G23)) -> 0 | J23: =IF(Service_Providers!C20="","",Service_Providers!C20) -> 904-654-5662 | K23: =IF(Service_Providers!D20="","",Service_Providers!D20) -> jose@firstcoastespresso.com
A24: PA | B24: =COUNTIF(Accounts!$G$2:$G$299,A24) -> 1 | C24: =COUNTIFS(Accounts!$G$2:$G$299,A24,Accounts!$I$2:$I$299,"<>") -> 1 | D24: =COUNTIFS(Accounts!$G$2:$G$299,A24,Accounts!$K$2:$K$299,"") -> 0 | E24: =IF(B24=0,0,(B24-D24)/B24) -> 1 | G24: =IF(Service_Providers!A21="","",Service_Providers!A21) -> Iconik Coffee | H24: =IF(G24="","",COUNTIF(Accounts!$K$2:$K$299,G24)) -> 0 | I24: =IF(G24="","",COUNTIF(Accounts!$M$2:$M$299,G24)) -> 0 | J24: =IF(Service_Providers!C21="","",Service_Providers!C21) -> (505) 428-0669 | K24: =IF(Service_Providers!D21="","",Service_Providers!D21) -> sean@iconikcoffee.com
A25: SC | B25: =COUNTIF(Accounts!$G$2:$G$299,A25) -> 1 | C25: =COUNTIFS(Accounts!$G$2:$G$299,A25,Accounts!$I$2:$I$299,"<>") -> 1 | D25: =COUNTIFS(Accounts!$G$2:$G$299,A25,Accounts!$K$2:$K$299,"") -> 0 | E25: =IF(B25=0,0,(B25-D25)/B25) -> 1 | G25: =IF(Service_Providers!A23="","",Service_Providers!A23) -> Izzy's Espresso Services Inc. | H25: =IF(G25="","",COUNTIF(Accounts!$K$2:$K$299,G25)) -> 0 | I25: =IF(G25="","",COUNTIF(Accounts!$M$2:$M$299,G25)) -> 0 | J25: =IF(Service_Providers!C23="","",Service_Providers!C23) -> 816-373-7011 | K25: =IF(Service_Providers!D23="","",Service_Providers!D23) -> chris@izzysespresso.com
A26: TN | B26: =COUNTIF(Accounts!$G$2:$G$299,A26) -> 1 | C26: =COUNTIFS(Accounts!$G$2:$G$299,A26,Accounts!$I$2:$I$299,"<>") -> 1 | D26: =COUNTIFS(Accounts!$G$2:$G$299,A26,Accounts!$K$2:$K$299,"") -> 0 | E26: =IF(B26=0,0,(B26-D26)/B26) -> 1 | G26: =IF(Service_Providers!A24="","",Service_Providers!A24) -> Jaguar Coffee Co. | H26: =IF(G26="","",COUNTIF(Accounts!$K$2:$K$299,G26)) -> 5 | I26: =IF(G26="","",COUNTIF(Accounts!$M$2:$M$299,G26)) -> 1 | J26: =IF(Service_Providers!C24="","",Service_Providers!C24) -> 352 442 2506 | K26: =IF(Service_Providers!D24="","",Service_Providers!D24) -> sam.mendez@jaguarcoffee.com
A27: TX | B27: =COUNTIF(Accounts!$G$2:$G$299,A27) -> 10 | C27: =COUNTIFS(Accounts!$G$2:$G$299,A27,Accounts!$I$2:$I$299,"<>") -> 10 | D27: =COUNTIFS(Accounts!$G$2:$G$299,A27,Accounts!$K$2:$K$299,"") -> 0 | E27: =IF(B27=0,0,(B27-D27)/B27) -> 1 | G27: =IF(Service_Providers!A25="","",Service_Providers!A25) -> JVG Coffee Mechanics | H27: =IF(G27="","",COUNTIF(Accounts!$K$2:$K$299,G27)) -> 1 | I27: =IF(G27="","",COUNTIF(Accounts!$M$2:$M$299,G27)) -> 0 | J27: =IF(Service_Providers!C25="","",Service_Providers!C25) -> 919-240-8083 | K27: =IF(Service_Providers!D25="","",Service_Providers!D25) -> hayes@jvgcoffeemechanics.com
A28: VA | B28: =COUNTIF(Accounts!$G$2:$G$299,A28) -> 2 | C28: =COUNTIFS(Accounts!$G$2:$G$299,A28,Accounts!$I$2:$I$299,"<>") -> 2 | D28: =COUNTIFS(Accounts!$G$2:$G$299,A28,Accounts!$K$2:$K$299,"") -> 1 | E28: =IF(B28=0,0,(B28-D28)/B28) -> 0.5 | G28: =IF(Service_Providers!A27="","",Service_Providers!A27) -> Ken's Beverage | H28: =IF(G28="","",COUNTIF(Accounts!$K$2:$K$299,G28)) -> 0 | I28: =IF(G28="","",COUNTIF(Accounts!$M$2:$M$299,G28)) -> 0 | J28: =IF(Service_Providers!C27="","",Service_Providers!C27) -> 317.888.6400 | K28: =IF(Service_Providers!D27="","",Service_Providers!D27) -> awhitlock@kensbeverage.com
A29: TOTAL | B29: =SUM(B6:B28) -> 76 | C29: =SUM(C6:C28) -> 76 | D29: =SUM(D6:D28) -> 2 | E29: =IF(B29=0,0,(B29-D29)/B29) -> 0.97368421 | G29: =IF(Service_Providers!A28="","",Service_Providers!A28) -> LIQUISERVE LLC | H29: =IF(G29="","",COUNTIF(Accounts!$K$2:$K$299,G29)) -> 1 | I29: =IF(G29="","",COUNTIF(Accounts!$M$2:$M$299,G29)) -> 0 | J29: =IF(Service_Providers!C28="","",Service_Providers!C28) -> Toll Free: 800-528-6625 Main: 505-247-3707 | K29: =IF(Service_Providers!D28="","",Service_Providers!D28) -> Service@LiquiServe.com
G30: =IF(Service_Providers!A30="","",Service_Providers!A30) -> MB Coffee Services | H30: =IF(G30="","",COUNTIF(Accounts!$K$2:$K$299,G30)) -> 1 | I30: =IF(G30="","",COUNTIF(Accounts!$M$2:$M$299,G30)) -> 0 | J30: =IF(Service_Providers!C30="","",Service_Providers!C30) -> 509.302.7071 | K30: =IF(Service_Providers!D30="","",Service_Providers!D30)
G31: =IF(Service_Providers!A31="","",Service_Providers!A31) -> Midwest Equipment & Espresso Specialists, Inc. | H31: =IF(G31="","",COUNTIF(Accounts!$K$2:$K$299,G31)) -> 0 | I31: =IF(G31="","",COUNTIF(Accounts!$M$2:$M$299,G31)) -> 0 | J31: =IF(Service_Providers!C31="","",Service_Providers!C31) -> 402-293-7490 | K31: =IF(Service_Providers!D31="","",Service_Providers!D31) -> Paul@meesi.omhcoxmail.com
G32: =IF(Service_Providers!A32="","",Service_Providers!A32) -> Orleans Coffee / Perfect Shot Espresso Service | H32: =IF(G32="","",COUNTIF(Accounts!$K$2:$K$299,G32)) -> 1 | I32: =IF(G32="","",COUNTIF(Accounts!$M$2:$M$299,G32)) -> 0 | J32: =IF(Service_Providers!C32="","",Service_Providers!C32) -> 504-827-0878 (Office) | K32: =IF(Service_Providers!D32="","",Service_Providers!D32) -> robbie@orleanscoffee.com
G33: =IF(Service_Providers!A33="","",Service_Providers!A33) -> Prestige Technical Services | H33: =IF(G33="","",COUNTIF(Accounts!$K$2:$K$299,G33)) -> 4 | I33: =IF(G33="","",COUNTIF(Accounts!$M$2:$M$299,G33)) -> 0 | J33: =IF(Service_Providers!C33="","",Service_Providers!C33) -> 636-583-5788 | K33: =IF(Service_Providers!D33="","",Service_Providers!D33) -> prestigetech@prestigetech.us
G34: =IF(Service_Providers!A34="","",Service_Providers!A34) -> PriorityOne Group | H34: =IF(G34="","",COUNTIF(Accounts!$K$2:$K$299,G34)) -> 8 | I34: =IF(G34="","",COUNTIF(Accounts!$M$2:$M$299,G34)) -> 0 | J34: =IF(Service_Providers!C34="","",Service_Providers!C34) -> (800) 226-7146 | K34: =IF(Service_Providers!D34="","",Service_Providers!D34) -> service@priorityone247.com
G35: =IF(Service_Providers!A35="","",Service_Providers!A35) -> Remolinos Group | H35: =IF(G35="","",COUNTIF(Accounts!$K$2:$K$299,G35)) -> 2 | I35: =IF(G35="","",COUNTIF(Accounts!$M$2:$M$299,G35)) -> 0 | J35: =IF(Service_Providers!C35="","",Service_Providers!C35) -> 479.647.6800 | K35: =IF(Service_Providers!D35="","",Service_Providers!D35) -> tech@fidel.coffee
G36: =IF(Service_Providers!A36="","",Service_Providers!A36) -> Shepspresso Solutions | H36: =IF(G36="","",COUNTIF(Accounts!$K$2:$K$299,G36)) -> 0 | I36: =IF(G36="","",COUNTIF(Accounts!$M$2:$M$299,G36)) -> 0 | J36: =IF(Service_Providers!C36="","",Service_Providers!C36) -> 833.377.7370 | K36: =IF(Service_Providers!D36="","",Service_Providers!D36) -> info@shepspresso.com
G37: =IF(Service_Providers!A37="","",Service_Providers!A37) -> STCS | H37: =IF(G37="","",COUNTIF(Accounts!$K$2:$K$299,G37)) -> 7 | I37: =IF(G37="","",COUNTIF(Accounts!$M$2:$M$299,G37)) -> 0 | J37: =IF(Service_Providers!C37="","",Service_Providers!C37) -> 956-536-7846 | K37: =IF(Service_Providers!D37="","",Service_Providers!D37) -> alanmcgee@msn.com
G38: =IF(Service_Providers!A38="","",Service_Providers!A38) -> Stephen's Service Techician | H38: =IF(G38="","",COUNTIF(Accounts!$K$2:$K$299,G38)) -> 0 | I38: =IF(G38="","",COUNTIF(Accounts!$M$2:$M$299,G38)) -> 0 | J38: =IF(Service_Providers!C38="","",Service_Providers!C38) -> 806.789.0810 | K38: =IF(Service_Providers!D38="","",Service_Providers!D38)
G39: =IF(Service_Providers!A39="","",Service_Providers!A39) -> Swanson Service | H39: =IF(G39="","",COUNTIF(Accounts!$K$2:$K$299,G39)) -> 0 | I39: =IF(G39="","",COUNTIF(Accounts!$M$2:$M$299,G39)) -> 0 | J39: =IF(Service_Providers!C39="","",Service_Providers!C39) -> (515) 993-2272 | K39: =IF(Service_Providers!D39="","",Service_Providers!D39) -> swansonservice@msn.com
G40: =IF(Service_Providers!A40="","",Service_Providers!A40) -> Thunderbird Equipment Service | H40: =IF(G40="","",COUNTIF(Accounts!$K$2:$K$299,G40)) -> 4 | I40: =IF(G40="","",COUNTIF(Accounts!$M$2:$M$299,G40)) -> 0 | J40: =IF(Service_Providers!C40="","",Service_Providers!C40) -> 480-294-2434 | K40: =IF(Service_Providers!D40="","",Service_Providers!D40) -> service@thunderbirdequipment.com
G41: =IF(Service_Providers!A41="","",Service_Providers!A41) -> Ultimate Espresso Services | H41: =IF(G41="","",COUNTIF(Accounts!$K$2:$K$299,G41)) -> 1 | I41: =IF(G41="","",COUNTIF(Accounts!$M$2:$M$299,G41)) -> 1 | J41: =IF(Service_Providers!C41="","",Service_Providers!C41) -> 314.541.5256 | K41: =IF(Service_Providers!D41="","",Service_Providers!D41) -> ultimateespressoservices@gmail.com
G42: =IF(Service_Providers!A42="","",Service_Providers!A42) -> WHITEHEAD FOOD EQUIPMENT | H42: =IF(G42="","",COUNTIF(Accounts!$K$2:$K$299,G42)) -> 0 | I42: =IF(G42="","",COUNTIF(Accounts!$M$2:$M$299,G42)) -> 0 | J42: =IF(Service_Providers!C42="","",Service_Providers!C42) -> Office: 405-528-5117 | K42: =IF(Service_Providers!D42="","",Service_Providers!D42) -> Nate@wfeokc.com
G43: =IF(Service_Providers!A26="","",Service_Providers!A26) -> Katz Coffee | H43: =IF(G43="","",COUNTIF(Accounts!$K$2:$K$299,G43)) -> 2 | I43: =IF(G43="","",COUNTIF(Accounts!$M$2:$M$299,G43)) -> 0 | J43: =IF(Service_Providers!C26="","",Service_Providers!C26) -> 713.864.3338 | K43: =IF(Service_Providers!D26="","",Service_Providers!D26) -> service@katzcoffee.com
G44: =IF(Service_Providers!A43="","",Service_Providers!A43) | H44: =IF(G44="","",COUNTIF(Accounts!$K$2:$K$299,G44)) | I44: =IF(G44="","",COUNTIF(Accounts!$M$2:$M$299,G44)) | J44: =IF(Service_Providers!C43="","",Service_Providers!C43) | K44: =IF(Service_Providers!D43="","",Service_Providers!D43)
G45: =IF(Service_Providers!A44="","",Service_Providers!A44) | H45: =IF(G45="","",COUNTIF(Accounts!$K$2:$K$299,G45)) | I45: =IF(G45="","",COUNTIF(Accounts!$M$2:$M$299,G45)) | J45: =IF(Service_Providers!C44="","",Service_Providers!C44) | K45: =IF(Service_Providers!D44="","",Service_Providers!D44)
G46: =IF(Service_Providers!A45="","",Service_Providers!A45) | H46: =IF(G46="","",COUNTIF(Accounts!$K$2:$K$299,G46)) | I46: =IF(G46="","",COUNTIF(Accounts!$M$2:$M$299,G46)) | J46: =IF(Service_Providers!C45="","",Service_Providers!C45) | K46: =IF(Service_Providers!D45="","",Service_Providers!D45)
G47: =IF(Service_Providers!A46="","",Service_Providers!A46) | H47: =IF(G47="","",COUNTIF(Accounts!$K$2:$K$299,G47)) | I47: =IF(G47="","",COUNTIF(Accounts!$M$2:$M$299,G47)) | J47: =IF(Service_Providers!C46="","",Service_Providers!C46) | K47: =IF(Service_Providers!D46="","",Service_Providers!D46)
G48: =IF(Service_Providers!A47="","",Service_Providers!A47) | H48: =IF(G48="","",COUNTIF(Accounts!$K$2:$K$299,G48)) | I48: =IF(G48="","",COUNTIF(Accounts!$M$2:$M$299,G48)) | J48: =IF(Service_Providers!C47="","",Service_Providers!C47) | K48: =IF(Service_Providers!D47="","",Service_Providers!D47)
G49: =IF(Service_Providers!A48="","",Service_Providers!A48) | H49: =IF(G49="","",COUNTIF(Accounts!$K$2:$K$299,G49)) | I49: =IF(G49="","",COUNTIF(Accounts!$M$2:$M$299,G49)) | J49: =IF(Service_Providers!C48="","",Service_Providers!C48) | K49: =IF(Service_Providers!D48="","",Service_Providers!D48)
G50: =IF(Service_Providers!A49="","",Service_Providers!A49) | H50: =IF(G50="","",COUNTIF(Accounts!$K$2:$K$299,G50)) | I50: =IF(G50="","",COUNTIF(Accounts!$M$2:$M$299,G50)) | J50: =IF(Service_Providers!C49="","",Service_Providers!C49) | K50: =IF(Service_Providers!D49="","",Service_Providers!D49)
G51: =IF(Service_Providers!A50="","",Service_Providers!A50) | H51: =IF(G51="","",COUNTIF(Accounts!$K$2:$K$299,G51)) | I51: =IF(G51="","",COUNTIF(Accounts!$M$2:$M$299,G51)) | J51: =IF(Service_Providers!C50="","",Service_Providers!C50) | K51: =IF(Service_Providers!D50="","",Service_Providers!D50)
G52: =IF(Service_Providers!A51="","",Service_Providers!A51) | H52: =IF(G52="","",COUNTIF(Accounts!$K$2:$K$299,G52)) | I52: =IF(G52="","",COUNTIF(Accounts!$M$2:$M$299,G52)) | J52: =IF(Service_Providers!C51="","",Service_Providers!C51) | K52: =IF(Service_Providers!D51="","",Service_Providers!D51)
G53: =IF(Service_Providers!A52="","",Service_Providers!A52) | H53: =IF(G53="","",COUNTIF(Accounts!$K$2:$K$299,G53)) | I53: =IF(G53="","",COUNTIF(Accounts!$M$2:$M$299,G53)) | J53: =IF(Service_Providers!C52="","",Service_Providers!C52) | K53: =IF(Service_Providers!D52="","",Service_Providers!D52)
G54: =IF(Service_Providers!A53="","",Service_Providers!A53) | H54: =IF(G54="","",COUNTIF(Accounts!$K$2:$K$299,G54)) | I54: =IF(G54="","",COUNTIF(Accounts!$M$2:$M$299,G54)) | J54: =IF(Service_Providers!C53="","",Service_Providers!C53) | K54: =IF(Service_Providers!D53="","",Service_Providers!D53)
G55: =IF(Service_Providers!A54="","",Service_Providers!A54) | H55: =IF(G55="","",COUNTIF(Accounts!$K$2:$K$299,G55)) | I55: =IF(G55="","",COUNTIF(Accounts!$M$2:$M$299,G55)) | J55: =IF(Service_Providers!C54="","",Service_Providers!C54) | K55: =IF(Service_Providers!D54="","",Service_Providers!D54)
... G105: =IF(Service_Providers!A104="","",Service_Providers!A104) | H105: =IF(G105="","",COUNTIF(Accounts!$K$2:$K$299,G105)) | I105: =IF(G105="","",COUNTIF(Accounts!$M$2:$M$299,G105)) | J105: =IF(Service_Providers!C104="","",Service_Providers!C104) | K105: =IF(Service_Providers!D104="","",Service_Providers!D104)
G106: TOTAL ASSIGNED | H106: =SUM(H6:H105) -> 72 | I106: =SUM(I6:I105) -> 9

Sheet Service_Providers
A1: Provider_Name | B1: Status | C1: Primary Dispatch Phone | D1: Primary Dispatch Email | E1: Secondary Dispatch Phone | F1: Secondary Dispatch Email | G1: Response Time | H1: Standard Rate | I1: After Hours Rate | J1: Travel Rate Policy | K1: Equipment Serviced | L1: States / ZIP Coverage | M1: Contacts | N1: PM Pricing | O1: Parts Stocking | P1: Coverage Notes / Key Notes | Q1: Last_Updated
A2: A-1 Restuarant Service | L2: TX | M2: 1407 Tulip Ln. Odessa, TX 79761 | Q2: 2026-07-15
A3: A-Tech Espresso & Coffee Service Inc. | C3: 866.333.7350 | D3: servicerequest@Atech-service.com | L3: CA | M3: Contact: Paul Phone: 866.333.7350 servicerequest@Atech-service.com | Q3: 2026-07-15
A4: ABS Coffee Repair | C4: 314.389.2866 | L4: MO | M4: Contact: John Meese Phone: 314.389.2866 | Q4: 2026-07-15
A5: All Espresso Service | B5: Active | C5: 754.205.5076 | D5: service@allespressoservice.com | E5: 954.263.9530 | F5: miguel@allespressoservice.com | H5: Labor $100 Travel $100 hr | I5: Labor OT $150 Trip OT $150 | L5: FL | M5: Contact: Lillie Morton service@allespressoservice.com (866) 237-7782 | Q5: 2026-07-15
A6: All Star Coffee Service | B6: Active | C6: 626-315-8498 | D6: allstarcoffeeservice@gmail.com | E6: 626-627-9369 | H6: Labor $135 hr Travel $135 hr | L6: CA | M6: Contact: Fernando Phone: 626-315-8498 Cell: 626-627-9369 | Q6: 2026-07-15
A7: Anytime Beverage Service | B7: Active | C7: Contact: Cynthia Phone: 714-335-9964 Cell: 714-395-8108 | D7: anytimebeverageservice@gmail.com | E7: Emergency Service Calls 714-335-9964 | F7: absdispatch@gmail.com | L7: CA, CO | M7: Contact: Cynthia Phone: 714-335-9964 Cell: 714-395-8108 Servi23275 Lawson Rd Corona, CA 92883 US www.anytimebeverageservice.com Accounting, Installation and Preventative Maintenance 714-395-8108 anytimebeverageservice@gmail.com | Q7: 2026-07-15
A8: B & B Coffee Service | C8: 361.855.3066 | L8: TX | M8: Phone: 361.855.3066 4307 S Port Ave Ste 128 Corpus Christi, TX 78415 Note: 78 miles away. Closest Bunn Certified Company. | P8: Note: 78 miles away. Closest Bunn Certified Company. | Q8: 2026-07-15
A9: Bar 9 Coffee Services LLC | B9: Active | C9: 443-460-4303 | D9: chuck@bar9coffee.com | L9: DC | M9: Jeremy Lattimer Owner Phone: 443-460-4303 Chuck - Service Coordinator chuck@bar9coffee.com | Q9: 2026-07-15
A10: Best Beverage Equipment Service | B10: Active | C10: 866-966-5799 ext 1 | D10: service@bestbeverage.net | L10: AR, TN | M10: service@bestbeverage.net Phone: 866-966-5799 Contact: Dustin or Melissa. Contact: Dustin Smith Phone: 866-966-5799 ext 1 service@bestbeverage.net | Q10: 2026-07-15
A11: Bev Pro Services | C11: 410-571-4902 ext. 501 (Office) | E11: 410-693-7591 (Mobile) | L11: MD, VA | M11: Contact: Thomas Erber 410-571-4902 ext. 501 Office/ 410-693-7591 Mobile 2100 Concord Blvd. Suite K Crofton, MD 21114 Contact: Thomas Erber 410-571-4902 ext. 501 Office 410-693-7591 Mobile 2100 Concord Blvd. Suite K Crofton, MD 21114 | Q11: 2026-07-15
A12: Beverage Equipment Service Inc. | B12: Active | C12: (515) 494-0849 | D12: bevequip@outlook.com (best - copied on all comms) | F12: rdachenbach@beverageequipmentservice.net | G12: Same-day / Next-day | H12: $105/hr (labor + travel included) | I12: $157.50/hr (1.5x) | J12: $105/hr both directions; no separate truck/mileage charge; can batch/split calls to reduce cost | K12: Wilbur Curtis (full service); Schaerer espresso incl. super-automatic; Coffee Art Pro & bean-to-cup (extremely experienced); recently trained on WMF 5000 and Soul C | L12: IA IA ZIPs: 50158, 50248, 50401, 50421, 50447, 50468, 50525, 50590, 50595, 50703, 51446, 51454, 51531, 51537, 51546, 52501, 52544 | M12: Ryan Dachenbach (President) Phone: (515) 494-0849 Email: rdachenbach@beverageequipmentservice.net Fax: (641) 774-8749 | N12: $176 per machine + parts (SCA1 bean-to-cup example, incl. O-rings; negotiable on volume) | O12: Wide parts variety stocked on vehicles + warehouse for one-trip fixes; large stock of 3M HF-40S filters | P12: Covers all listed Iowa ZIPs. Cedar Rapids area: tech visits at least weekly. North Central / NE Iowa: some sites 2-3 hrs one-way; calls batched to control travel cost. Confirmed OK with paying travel both ways when needed. Ready to set up as client. High priority on minimizing downtime. | Q12: 2026-06-24
A13: Carolina Beverage Solutions | B13: Active | C13: 803-280-5234 | D13: chris.powers@hotmail.com | F13: billing@carolinabev.com | L13: NC, SC | M13: 117 Kanawha Street Fort Mill, SC 29715 Phone: 803-280-5234 Contact: Chris / Val chris.powers@hotmail.com billing@carolinabev.com service@carolinabev.com | Q13: 2026-07-15
A14: Commercial Kitchen | C14: 956.664.8267 | L14: TX | M14: Phone: 956.664.8267 | Q14: 2026-07-15
A15: Duke Services | C15: 714.525.2866 | L15: CA | M15: Phone: 714.525.2866 | Q15: 2026-07-15
A16: Espresso Enterprises | B16: Active | C16: 317-876-9031 | D16: carey@espressoenterprises.com | L16: IN | M16: Contact: Troy Smith/Carey Phone: 317-876-9031 carey@espressoenterprises.com | P16: 1-hour minimum. After first hour billed in 15-min increments. | Q16: 2026-07-15
A17: Espresso Southeast | B17: Active | C17: 770-867-3111 | D17: service@espressosoutheast.com | F17: priscila@espressosoutheast.com | G17: Same day when possible; most calls completed the next day | H17: Labor $100 / hour Travel $100 / hour | I17: Labor $150 / hour Travel $150 / hour Time-and-a-half on labor and travel. | J17: One-way billing (standard). 1-hour minimum. Extended travel may be billed round-trip case-by-case | K17: • Espresso: Most major brands — La Marzocco, Nuova Simonelli, Rancilio, Cimbali, Faema, and others • Coffee & Tea: Fetco, Curtis (Wilbur Curtis), Bunn | L17: – I-85N Greenville, SC – I-20E Augusta, GA – I-16E Swainsboro, GA – I-75S Cordele, GA – I-85S Auburn, AL – I-20W Oxford, AL – I-75N Chattanooga, TN | M17: Owner: Mario Scoccimaro Service Manager: Andrew Kane Mario Jr. Priscila (priscila@espressosoutheast.com) Phone: 770-867-3111 service@espressosoutheast.com | N17: N/A (no formal PM pricing program mentioned). | O17: Extensive inventory for many espresso machines. Fetco inventory is also extensive. Curtis and Bunn have many common parts (somewhat less depth). • If a part is not in stock they can order quickly, or they are happy to use parts you supply from your inventory. | P17: – I-85N Greenville, SC – I-20E Augusta, GA – I-16E Swainsboro, GA – I-75S Cordele, GA – I-85S Auburn, AL – I-20W Oxford, AL – I-75N Chattanooga, TN | Q17: 2026-07-15
A18: ETSC (EspressoTech Service Company) | B18: Active | C18: (888) 523-1684 | D18: service@etsc.coffee | F18: Jess@etsc.coffee | G18: Standard 24-48 hrs (priority & tech availability); same-day when possible | H18: $195 first hour | $125 each additional hour $70/hr travel | I18: 1.5x standard rates (after-hours / weekend) | J18: $70/hr travel for locations outside tech's local service area | K18: Wilbur Curtis - supported; Schaerer espresso - supported (carries Schaerer parts to maximize first-time fix) | L18: KS, IA, IL, MO, NE, CO, OK, MN, WI, TN + more KS ZIPs: 67456, 67460, 67501, 67502, 67554 MO ZIPs: 64804, 64850 | M18: Jessica Peacock Phone: (888) 523-1684 Email: Jess@etsc.coffee Regional contacts (merged from Espresso Tech / ETSC STL): [Illinois] service @ espressotechsc.com | 816-523-1684Technical Support Center | 11614 W 90th Street | Overland Park, KS 66214 [Kansas] Contact: Mark Robey | Phone: 816.523.1684 | service.espressotech@gmail.com [Missouri] Contact: Liz | Phone: 314-939-7159 | liz@etsc.coffee) | 1500 South 1st Capitol Drive Unit 344 | Saint Charles Missouri 63303 | 1500 South 1st Capitol Drive Unit 344 Saint Charles Missouri 63303 | N18: PM billed at standard service rates ($195 first hr / $125 add'l) | O18: Techs carry van stock of common Wilbur Curtis and Schaerer parts | P18: Tech hubs: Overland Park & Wichita KS | Des Moines & Quad Cities IA | Chicago | St. Louis | Elkhorn NE | Denver | Tulsa (OKC coming soon) | Bloomington MN | Milwaukee | Nashville (Knoxville coming soon). KS ZIPs covered: 67456, 67460, 67501, 67502, 67554. | Q18: 2026-07-15
A19: FASTCILITY CORP | B19: Active | C19: Office: (833) 203-2285 | D19: Service@FASTCILITYCORP.COM https://app.servicefusion.com/fastcility Username: Jesus@katzcoffee.com F!xmy5!t03 | E19: 714) 520-1486 | F19: ddavenport@fastcilitycorp.com | H19: Labor $115 / hour 1-hour minimum Travel $115 flat fee Flat fee (not hourly) Fuel Surcharge $25 flat fee Applied per call Parts 25% markup from cost For any parts used during repair | K19: • Bunn • Fetco • Wilbur Curtis • Schaerer • Eversys • La Marzocco • Mazzer • Everpure | L19: • Primary service region: Southwest U.S. (CA, AZ, NV, NM, TX) | M19: Dalton Davenport Business Development Manager Mobile: (714) 520-1486 Email: ddavenport@fastcilitycorp.com | P19: • Confirmed coverage: All ZIP codes provided in the Excel list for Arizona, California, New Mexico, Nevada, and Texas • Excluded: Illinois locations (Chicago / Rosemont) — not covered • Primary service region: Southwest U.S. (CA, AZ, NV, NM, TX) • Note: San Antonio / Austin area coverage requested for near-term expansion
A20: First Coast Espresso | B20: Pending Setup | C20: 904-654-5662 | D20: jose@firstcoastespresso.com | E20: 904-379-1455 | L20: GA | M20: Jose Parada jose@firstcoastespresso.com 3653 Regent Blvd Suite 203 Jacksonville, Fl 32224 904-654-5662 cell 904-379-1455 office $95 per hr labor and $95 per hr trip. 4 hr round trip. | Q20: 2026-07-15
A21: Iconik Coffee | B21: Inactive | C21: (505) 428-0669 | D21: sean@iconikcoffee.com | L21: NM | M21: Sean Ham sean@iconikcoffee.com Phone: (505) 428-0669 1366 Cerrillos Rd Santa Fe, NM 87505 | Q21: 2026-07-15
A22: Intergrated Coffee Solutions | B22: Active | C22: Phone / Text: (864) 606-4418 | D22: integratedcoffeesolutions@gmail.com | E22: Phone / Text: (864) 606-4418 | F22: integratedcoffeesolutions@gmail.com | G22: Within 72 hours (depends on dispatch schedule) | H22: Standard Labor $115 / hour Standard hourly rate Standard Travel $115 / hour 1-hour minimum after 15 minutes of travel. No return rate charged. | I22: Emergency Labor $175 / hour Emergency / after-hours rate Emergency Travel $175 / hour Same 1-hour minimum after 15 min. No return rate charged. | J22: Will travel up to 3 hours from Spartanburg, SC before return travel rates apply. Coverage area is variable beyond that. | K22: • Traditional Espresso: La Marzocco, Astoria, Rocket Espresso, Nuova Simonelli, Synesso, Victoria Arduino, Wega, and more major brands • Superautomatic: Most brands of superautomatic coffee machines • Tea Equipment: Most tea equipment supported | L22: SC | M22: Julia Richardson Director of Communications Same phone: (864) 606-4418 (text OK) Email: integratedcoffeesolutions@gmail.com Website: integratedcoffeesolutions.com | N22: • PM Programs: Yes — monthly installment plans available. Pricing generally ranges from $75–$150 per month depending on the machine. Happy to discuss specifics for your locations. | O22: • Parts: Stock common parts for major brands on trucks. Specialty parts or less-common brands are ordered as needed. | P22: • Emergency Response: Typically within 24 hours • Primary Coverage: Upstate South Carolina (including Powdersville) • Travel Radius: Will travel up to 3 hours from Spartanburg, SC before return travel rates apply. Coverage area is variable beyond that. | Q22: 2026-07-15
A23: Izzy's Espresso Services Inc. | C23: 816-373-7011 | D23: chris@izzysespresso.com | L23: KS | M23: Owner: Chris Isariotis Phone: 816-373-7011 chris@izzysespresso.com | Q23: 2026-07-15
A24: Jaguar Coffee Co. | C24: 352 442 2506 | D24: sam.mendez@jaguarcoffee.com | L24: FL | M24: Contact: Samantha Mendez Phone: 352 442 2506 sam.mendez@jaguarcoffee.com | Q24: 2026-07-15
A25: JVG Coffee Mechanics | B25: Active | C25: 919-240-8083 | D25: hayes@jvgcoffeemechanics.com | L25: VA | M25: 505 Meadowlands Dr Unit 101 Hillsborough, NC 27278 hayes@jvgcoffeemechanics.com 919-240-8083 | Q25: 2026-07-15
A26: Katz Coffee | B26: Active | C26: 713.864.3338 | D26: service@katzcoffee.com | E26: 832.517.9773 | Q26: 46219
A27: Ken's Beverage | C27: 317.888.6400 | D27: awhitlock@kensbeverage.com | L27: IN | M27: Contact: Alan Whitlock Phone: 317.888.6400 awhitlock@kensbeverage.com | Q27: 2026-07-15
A28: LIQUISERVE LLC | B28: Active | C28: Toll Free: 800-528-6625 Main: 505-247-3707 | D28: Service@LiquiServe.com | E28: Office: 505-247-3707 Ext. 1227 Mobile: 505-977-8066 505-308-8682 | F28: Matthew.Baca@LiquiServe.com | G28: Response Time: Next business day (standard). Same-day possible depending on priority/availability. | H28: Labor (Service/Repair/Install) $95/hr Travel $95/hr | I28: Labor (Service/Repair/Install) $142.50/hr Travel$142.50/hr Billed in 15-min increments after first hour. OT for calls outside normal business hours. Fuel surcharge $5 | J28: Round trip from nearest warehouse. Local zone = one-way 30-min charge. | K28: • Wilbur Curtis — Supported (stocked parts) • Schaerer — Supported (stocked parts) • Other: Bunn, Eversys also supported with stocked parts. Rancilio serviced but limited stock. | L28: SD ZIPs: 57501, 57532, 57543, 57551, 57701, 57703, 57717, 57719, 57730, 57735, 57747, 57783, 57785 | M28: Matthew Baca CFO / Primary Contact Dirk Brunson Field Service Supervisor Phone: Office: 505-247-3707 Ext. 1227 Mobile: 505-977-8066 505-308-8682 Email: Matthew.Baca@LiquiServe.com | N28: Preventive Maintenance (PM) $95/hr (or agreed flat) | O28: • Wilbur Curtis — Supported (stocked parts) • Schaerer — Supported (stocked parts) • Other: Bunn, Eversys also supported with stocked parts. Rancilio serviced but limited stock. | P28: Coverage: Broad multi-state territory. For the latest inquiry, most ZIPs in NM, TX, OK, NE are covered. Warehouses: Multiple regional warehouses (travel billed from nearest one). Strong presence in Southwest & Plains states. | Q28: 2026-07-09
A29: Masket Services | B29: Active | C29: 866-803-8088 | D29: service@masketservices.com | E29: 866-803-8088 | F29: shane@masketservices.com | K29: Eversys, Franke, Schaerer , Nuova, Cimbali , Rancilio , Unic , La Marzocco, Synesso, Wega, WMF, Gaggia Curtis, Fetco, Bunn after warranty work | L29: PA | M29: Shane Stroman Service / Sales shane@masketservices.com / 866-803-8088 | Q29: 46223
A30: MB Coffee Services | C30: 509.302.7071 | L30: CA | M30: Contact: Mathew Phone: 509.302.7071 | Q30: 2026-07-15
A31: Midwest Equipment & Espresso Specialists, Inc. | C31: 402-293-7490 | D31: Paul@meesi.omhcoxmail.com | E31: 402-293-7503 | L31: KS, NE | M31: Contact: Jen Phone: 402-293-7490 Fax: 402-293-7503 Paul@meesi.omhcoxmail.com | Q31: 2026-07-15
A32: Orleans Coffee / Perfect Shot Espresso Service | B32: Active | C32: 504-827-0878 (Office) | D32: robbie@orleanscoffee.com | E32: 504-258-6881 (Cell - Robbie Mahner) | L32: LA | M32: Orleans Coffee / Perfect Shot Espresso Service Robbie Mahner Service Manager Perfect Shot Espresso Service 504-258-6881 cell 504-827-0878 office robbie@orleanscoffee.com | Q32: 2026-07-15
A33: Prestige Technical Services | B33: Active | C33: 636-583-5788 | D33: prestigetech@prestigetech.us | L33: KS, OK | M33: Phone: 636-583-5788 prestigetech@prestigetech.us | Q33: 2026-07-15
A34: PriorityOne Group | B34: Active | C34: (800) 226-7146 | D34: service@priorityone247.com | E34: (800) 226-7146 | (303) 577-1285 CO | (505) 234-1831 NM/TX | G34: Zone 1: 24/7/365 | Zone 2: standard + on-call | Zone 3: clustered/scheduled | Zone 4: limited/out-of-area | H34: Beverage $90/hr | Espresso $105/hr | Cooking/Refrig $125-135/hr (valid 11/1/2025 - 12/31/2026) | I34: 1.5x (5pm-10pm) | 2x overnight (10pm-7:30am) | 2x holidays (24 hr) | J34: Travel billed in 15-min increments from last call location (GPS tracked); efficient routing by dispatch | K34: Full beverage equipment service: beverage, espresso, cooking, refrigeration/HVAC | L34: CO, NM, TX + surrounding NM ZIPs: 87002, 87004, 87013, 87020, 87021, 87031, 87104, 87105, 87114, 87121, 87124, 87301, 87401, 87501, 87505, 87507, 87508, 87532, 87571, 87701, 87732, 88007, 88012, 88081, 88201, 88301, 88310, 88317, 88336, 88345, 88353, 88401, 88435 | M34: Customer Service Team Phone: (800) 226-7146 | (303) 577-1285 CO | (505) 234-1831 NM/TX Email: service@priorityone247.com Fax: N/A (use main numbers) | N34: PM contracts available with discounted emergency rates | O34: Parts & equipment support via dedicated Parts team | P34: Strong coverage in CO Front Range, NM, and TX (see zone assignments on Stores tab). Labor & travel billed in quarter-hour increments via mobile/GPS. Fastest service: call Customer Service or email service@priorityone247.com. QR code available for quick requests. | Q34: 2026-06-24
A35: Remolinos Group | C35: 479.647.6800 | D35: tech@fidel.coffee | E35: 479.647.6800 | F35: fidel@remolinosgroup.com | L35: AR | M35: Fidel Samour 479.647.6800 | Q35: 2026-07-15
A36: Shepspresso Solutions | C36: 833.377.7370 | D36: info@shepspresso.com | E36: 970.432.4250 | L36: GA | M36: Shepspresso Solutions Jaime Palmer Business: 833.377.7370 Text for Service: 970.432.4250 info@shepspresso.com 730 Main St PMB358, North Myrtle Beach, SC 29582 | Q36: 2026-07-15
A37: STCS | B37: Active | C37: 956-536-7846 | D37: alanmcgee@msn.com | L37: TX | M37: Contact:Alan McGee Phone: 956-536-7846 Email: alanmcgee@msn.com 200 North Business 77 Combes, TX 78535 | Q37: 2026-07-15
A38: Stephen's Service Techician | C38: 806.789.0810 | L38: TX | M38: Contact: Don Phone: 806.789.0810 | Q38: 2026-07-15
A39: Swanson Service | B39: Active | C39: (515) 993-2272 | D39: swansonservice@msn.com | G39: Usually completes calls within 24 hrs | H39: Labor $90/hr Travel $115/hr | I39: OT: $135/hr labor + $172.50/hr travel (round trip) | J39: Travel $115/hr, round trip, billed hourly | K39: Wilbur Curtis (full service confirmed). Does NOT service Schaerer espresso machines. | L39: IA IA ZIPs: 50158, 50248, 50421, 50468, 50525, 50590, 50595, 50703, 51446, 51531, 51537, 51546, 52501, 52544 | M39: Scott Swanson / Lisa Phone: (515) 993-2272 Email: swansonservice@msn.com | N39: Not provided - follow up | O39: Carries parts on vehicle (details not provided) | P39: Main office in Adel, IA. Serves North Central / NE Iowa; confirmed they can service all listed locations. Same 15 IA ZIPs as Beverage Equipment Service. Response was brief - no details on PM pricing, parts stocking, dispatch process, or W-9. Follow-up recommended. | Q39: 2026-06-25
A40: Thunderbird Equipment Service | B40: Active | C40: 480-294-2434 | D40: service@thunderbirdequipment.com | E40: C| 480-294-2434 O| 602-675-2420 | F40: brian@thunderbirdequipment.com | G40: Same day or Next day | H40: Labor $120/hr Travel $85 hourly | K40: Eversys, Fetco | L40: AZ | M40: Thunderbird Equipment Brian Koren President and Founder Thunderbird Equipment Service 480-294-2434 C 602-675-2420 O Thunderbirdequipment.com 10439 N Cave Creek Rd Suite 10. Phoenix, AZ 85020 | Q40: 2026-07-15
A41: Ultimate Espresso Services | B41: Active | C41: 314.541.5256 | D41: ultimateespressoservices@gmail.com | L41: MO | M41: Ultimate Espresso Services Contact: Azmir Phone: 314.541.5256 ultimateespressoservices@gmail.com Shipping Address: 5608 Wickershire Ln St Louis, MO 63129 Liftgate is needed | Q41: 2026-07-15
A42: WHITEHEAD FOOD EQUIPMENT | B42: Active | C42: Office: 405-528-5117 | D42: Nate@wfeokc.com | E42: Mobile: 405-887-0047 | F42: Juan@wfeokc.com | G42: Generally same day or within 24 hours (varies with workload) | H42: Service Calls / Repairs $110 per hour | I42: Labor (Service/Repair/Install) $142.50/hr Travel$142.50/hr Billed in 15-min increments after first hour. OT for calls outside normal business hours. Fuel surcharge $5 | J42: Travel — OKC Metro (Local) $65 flat Within Oklahoma City Metro Travel — Outside OKC Metro $110 per hour Round trip | K42: • Wilbur Curtis — Supported (stocked parts) • Schaerer — Supported (stocked parts) | L42: Oklahoma ZIP codes confirmed covered (73010, 73030, 73036, 73401, 73446, 73459, 73521, 73542, 73644, 73942, 74432, 74467, 74525, 74553, 74554, 74820 OK ZIPs: 74728 | M42: Juan Herrera Director of Operationsr Phone: Mobile: 405-887-0047 Email: Juan@wfeokc.com | N42: Preventive Maintenance (PM) $110 per hour | O42: • Wilbur Curtis — Supported (stocked parts) • Schaerer — Supported (stocked parts) | P42: Entire state of Oklahoma + surrounding states (if travel costs approved) Warehouses: Multiple regional warehouses (travel billed from nearest one). Strong presence in Southwest & Plains states. | Q42: 2026-07-09

Sheet Accounts
A1: Account Name | B1: Main Email | C1: Primary Contact | D1: Main Phone | E1: Address | F1: City | G1: State | H1: Zip | I1: Equipment Details | J1: Ownership | K1: Primary Provider | L1: Dispatch Phone & Email | M1: Secondary Provider | N1: Secondary Phone & Email | O1: Service Region | P1: Last Updated
A2: MTA Engineers, INC | B2: lajean@mtaengineers.com | C2: Claudia Bremer | D2: 501.753.2526 | E2: 8001 National Drive | F2: Little Rock | G2: AR | H2: 72209 | I2: Virtu 9236A | J2: Lease | K2: Remolinos Group | L2: =IF($K2="","",IFERROR(IF(INDEX(Service_Providers!$C$2:$C$104,MATCH($K2,Service_Providers!$A$2:$A$104,0))="","",INDEX(Service_Providers!$C$2:$C$104,MATCH($K2,Service_Providers!$A$2:$A$104,0)))&IF(AND(INDEX(Service_Providers!$C$2:$C$104,MATCH($K2,Service_Providers!$A$2:$A$104,0))<>"",INDEX(Service_Providers!$D$2:$D$104,MATCH($K2,Service_Providers!$A$2:$A$104,0))<>""),CHAR(10),"")&IF(INDEX(Service_Providers!$D$2:$D$104,MATCH($K2,Service_Providers!$A$2:$A$104,0))="","",INDEX(Service_Providers!$D$2:$D$104,MATCH($K2,Service_Providers!$A$2:$A$104,0))),"Provider not found")) -> 479.647.6800 tech@fidel.coffee | M2: Best Beverage Equipment Service | N2: =IF($M2="","",IFERROR(IF(INDEX(Service_Providers!$C$2:$C$104,MATCH($M2,Service_Providers!$A$2:$A$104,0))="","",INDEX(Service_Providers!$C$2:$C$104,MATCH($M2,Service_Providers!$A$2:$A$104,0)))&IF(AND(INDEX(Service_Providers!$C$2:$C$104,MATCH($M2,Service_Providers!$A$2:$A$104,0))<>"",INDEX(Service_Providers!$D$2:$D$104,MATCH($M2,Service_Providers!$A$2:$A$104,0))<>""),CHAR(10),"")&IF(INDEX(Service_Providers!$D$2:$D$104,MATCH($M2,Service_Providers!$A$2:$A$104,0))="","",INDEX(Service_Providers!$D$2:$D$104,MATCH($M2,Service_Providers!$A$2:$A$104,0))),"Provider not found")) -> 866-966-5799 ext 1 service@bestbeverage.net | O2: Arkansas Area | P2: 2026-07-15
A3: Porsche Little Rock | B3: aravi@indigoautogroup.com | C3: Ashley Ravi | D3: 501.497.5656 | E3: 516 Colonel Glenn Plaza Loop | F3: Little Rock | G3: AR | H3: 72210 | I3: De Jong Duke Virtua93; La Marzocco Linea PB 2AV; La Marzocco Swift Grinder | J3: Lease; Owned - Purchased from Katz | K3: Remolinos Group | L3: =IF($K3="","",IFERROR(IF(INDEX(Service_Providers!$C$2:$C$104,MATCH($K3,Service_Providers!$A$2:$A$104,0))="","",INDEX(Service_Providers!$C$2:$C$104,MATCH($K3,Service_Providers!$A$2:$A$104,0)))&IF(AND(INDEX(Service_Providers!$C$2:$C$104,MATCH($K3,Service_Providers!$A$2:$A$104,0))<>"",INDEX(Service_Providers!$D$2:$D$104,MATCH($K3,Service_Providers!$A$2:$A$104,0))<>""),CHAR(10),"")&IF(INDEX(Service_Providers!$D$2:$D$104,MATCH($K3,Service_Providers!$A$2:$A$104,0))="","",INDEX(Service_Providers!$D$2:$D$104,MATCH($K3,Service_Providers!$A$2:$A$104,0))),"Provider not found")) -> 479.647.6800 tech@fidel.coffee | M3: Best Beverage Equipment Service | N3: =IF($M3="","",IFERROR(IF(INDEX(Service_Providers!$C$2:$C$104,MATCH($M3,Service_Providers!$A$2:$A$104,0))="","",INDEX(Service_Providers!$C$2:$C$104,MATCH($M3,Service_Providers!$A$2:$A$104,0)))&IF(AND(INDEX(Service_Providers!$C$2:$C$104,MATCH($M3,Service_Providers!$A$2:$A$104,0))<>"",INDEX(Service_Providers!$D$2:$D$104,MATCH($M3,Service_Providers!$A$2:$A$104,0))<>""),CHAR(10),"")&IF(INDEX(Service_Providers!$D$2:$D$104,MATCH($M3,Service_Providers!$A$2:$A$104,0))="","",INDEX(Service_Providers!$D$2:$D$104,MATCH($M3,Service_Providers!$A$2:$A$104,0))),"Provider not found")) -> 866-966-5799 ext 1 service@bestbeverage.net | O3: Arkansas Area | P3: 2026-07-15
A4: Dominick's Steakhouse | B4: joel@domsteak.com | D4: 480-272-7271 | E4: 15169 N Scottsdale Rd | F4: Scottsdale | G4: AZ | H4: 85254 | I4: Cameo c'2s (Downstairs); Cameo c'2s (Upstairs); Wilbur Curtis G4TP1S63A3100 Coffee Brewer; Wilbur Curtis ILGD-10 | J4: Owned - Purchased from 3rd Party | K4: Thunderbird Equipment Service | L4: =IF($K4="","",IFERROR(IF(INDEX(Service_Providers!$C$2:$C$104,MATCH($K4,Service_Providers!$A$2:$A$104,0))="","",INDEX(Service_Providers!$C$2:$C$104,MATCH($K4,Service_Providers!$A$2:$A$104,0)))&IF(AND(INDEX(Service_Providers!$C$2:$C$104,MATCH($K4,Service_Providers!$A$2:$A$104,0))<>"",INDEX(Service_Providers!$D$2:$D$104,MATCH($K4,Service_Providers!$A$2:$A$104,0))<>""),CHAR(10),"")&IF(INDEX(Service_Providers!$D$2:$D$104,MATCH($K4,Service_Providers!$A$2:$A$104,0))="","",INDEX(Service_Providers!$D$2:$D$104,MATCH($K4,Service_Providers!$A$2:$A$104,0))),"Provider not found")) -> 480-294-2434 service@thunderbirdequipment.com | M4: FASTCILITY CORP | N4: =IF($M4="","",IFERROR(IF(INDEX(Service_Providers!$C$2:$C$104,MATCH($M4,Service_Providers!$A$2:$A$104,0))="","",INDEX(Service_Providers!$C$2:$C$104,MATCH($M4,Service_Providers!$A$2:$A$104,0)))&IF(AND(INDEX(Service_Providers!$C$2:$C$104,MATCH($M4,Service_Providers!$A$2:$A$104,0))<>"",INDEX(Service_Providers!$D$2:$D$104,MATCH($M4,Service_Providers!$A$2:$A$104,0))<>""),CHAR(10),"")&IF(INDEX(Service_Providers!$D$2:$D$104,MATCH($M4,Service_Providers!$A$2:$A$104,0))="","",INDEX(Service_Providers!$D$2:$D$104,MATCH($M4,Service_Providers!$A$2:$A$104,0))),"Provider not found")) -> Office: (833) 203-2285 Service@FASTCILITYCORP.COM https://app.servicefusion.com/fastcility Username: Jesus@katzcoffee.com F!xmy5!t03 | O4: Arizona Area | P4: 2026-07-15
A5: Durant's Steakhouse | B5: andria@primesteakconcepts.com | C5: Paul Morris | D5: 6022645967 | E5: 2611 N Central Ave | F5: Phoenix | G5: AZ | H5: 85004 | I5: Fetco 1231 Plus; Eversys Cameo c'2s | J5: Loaned; Owned - Purchased from 3rd Party | K5: Thunderbird Equipment Service | L5: =IF($K5="","",IFERROR(IF(INDEX(Service_Providers!$C$2:$C$104,MATCH($K5,Service_Providers!$A$2:$A$104,0))="","",INDEX(Service_Providers!$C$2:$C$104,MATCH($K5,Service_Providers!$A$2:$A$104,0)))&IF(AND(INDEX(Service_Providers!$C$2:$C$104,MATCH($K5,Service_Providers!$A$2:$A$104,0))<>"",INDEX(Service_Providers!$D$2:$D$104,MATCH($K5,Service_Providers!$A$2:$A$104,0))<>""),CHAR(10),"")&IF(INDEX(Service_Providers!$D$2:$D$104,MATCH($K5,Service_Providers!$A$2:$A$104,0))="","",INDEX(Service_Providers!$D$2:$D$104,MATCH($K5,Service_Providers!$A$2:$A$104,0))),"Provider not found")) -> 480-294-2434 service@thunderbirdequipment.com | M5: FASTCILITY CORP | N5: =IF($M5="","",IFERROR(IF(INDEX(Service_Providers!$C$2:$C$104,MATCH($M5,Service_Providers!$A$2:$A$104,0))="","",INDEX(Service_Providers!$C$2:$C$104,MATCH($M5,Service_Providers!$A$2:$A$104,0)))&IF(AND(INDEX(Service_Providers!$C$2:$C$104,MATCH($M5,Service_Providers!$A$2:$A$104,0))<>"",INDEX(Service_Providers!$D$2:$D$104,MATCH($M5,Service_Providers!$A$2:$A$104,0))<>""),CHAR(10),"")&IF(INDEX(Service_Providers!$D$2:$D$104,MATCH($M5,Service_Providers!$A$2:$A$104,0))="","",INDEX(Service_Providers!$D$2:$D$104,MATCH($M5,Service_Providers!$A$2:$A$104,0))),"Provider not found")) -> Office: (833) 203-2285 Service@FASTCILITYCORP.COM https://app.servicefusion.com/fastcility Username: Jesus@katzcoffee.com F!xmy5!t03 | O5: Arizona Area | P5: 2026-07-15
A6: Ocean 44 Scottsdale | B6: craig@ocean44.com | D6: 480.867.0044 | E6: 4748 N Goldwater Blvd | F6: Scottsdale | G6: AZ | H6: 85251 | I6: Cameo c'2s; Wilbur Curtis G4TP1S63A3100 Coffee Brewer; Wilbur Curtis ILGD-10 Grinder | J6: Owned - Purchased from 3rd Party | K6: Thunderbird Equipment Service | L6: =IF($K6="","",IFERROR(IF(INDEX(Service_Providers!$C$2:$C$104,MATCH($K6,Service_Providers!$A$2:$A$104,0))="","",INDEX(Service_Providers!$C$2:$C$104,MATCH($K6,Service_Providers!$A$2:$A$104,0)))&IF(AND(INDEX(Service_Providers!$C$2:$C$104,MATCH($K6,Service_Providers!$A$2:$A$104,0))<>"",INDEX(Service_Providers!$D$2:$D$104,MATCH($K6,Service_Providers!$A$2:$A$104,0))<>""),CHAR(10),"")&IF(INDEX(Service_Providers!$D$2:$D$104,MATCH($K6,Service_Providers!$A$2:$A$104,0))="","",INDEX(Service_Providers!$D$2:$D$104,MATCH($K6,Service_Providers!$A$2:$A$104,0))),"Provider not found")) -> 480-294-2434 service@thunderbirdequipment.com | M6: FASTCILITY CORP | N6: =IF($M6="","",IFERROR(IF(INDEX(Service_Providers!$C$2:$C$104,MATCH($M6,Service_Providers!$A$2:$A$104,0))="","",INDEX(Service_Providers!$C$2:$C$104,MATCH($M6,Service_Providers!$A$2:$A$104,0)))&IF(AND(INDEX(Service_Providers!$C$2:$C$104,MATCH($M6,Service_Providers!$A$2:$A$104,0))<>"",INDEX(Service_Providers!$D$2:$D$104,MATCH($M6,Service_Providers!$A$2:$A$104,0))<>""),CHAR(10),"")&IF(INDEX(Service_Providers!$D$2:$D$104,MATCH($M6,Service_Providers!$A$2:$A$104,0))="","",INDEX(Service_Providers!$D$2:$D$104,MATCH($M6,Service_Providers!$A$2:$A$104,0))),"Provider not found")) -> Office: (833) 203-2285 Service@FASTCILITYCORP.COM https://app.servicefusion.com/fastcility Username: Jesus@katzcoffee.com F!xmy5!t03 | O6: Arizona Area | P6: 2026-07-15
A7: Steak 44 Phoenix | B7: jonathan@steak44.com | D7: 602.271.4400 | E7: 5101 N 44th St | F7: Phoenix | G7: AZ | H7: 85018 | I7: Wilbur Curtis G4TP1S63A100 Coffee Brewer; Bunn MHG Grinder; Cameo c'2s | J7: Owned - Purchased from 3rd Party | K7: Thunderbird Equipment Service | L7: =IF($K7="","",IFERROR(IF(INDEX(Service_Providers!$C$2:$C$104,MATCH($K7,Service_Providers!$A$2:$A$104,0))="","",INDEX(Service_Providers!$C$2:$C$104,MATCH($K7,Service_Providers!$A$2:$A$104,0)))&IF(AND(INDEX(Service_Providers!$C$2:$C$104,MATCH($K7,Service_Providers!$A$2:$A$104,0))<>"",INDEX(Service_Providers!$D$2:$D$104,MATCH($K7,Service_Providers!$A$2:$A$104,0))<>""),CHAR(10),"")&IF(INDEX(Service_Providers!$D$2:$D$104,MATCH($K7,Service_Providers!$A$2:$A$104,0))="","",INDEX(Service_Providers!$D$2:$D$104,MATCH($K7,Service_Providers!$A$2:$A$104,0))),"Provider not found")) -> 480-294-2434 service@thunderbirdequipment.com | M7: FASTCILITY CORP | N7: =IF($M7="","",IFERROR(IF(INDEX(Service_Providers!$C$2:$C$104,MATCH($M7,Service_Providers!$A$2:$A$104,0))="","",INDEX(Service_Providers!$C$2:$C$104,MATCH($M7,Service_Providers!$A$2:$A$104,0)))&IF(AND(INDEX(Service_Providers!$C$2:$C$104,MATCH($M7,Service_Providers!$A$2:$A$104,0))<>"",INDEX(Service_Providers!$D$2:$D$104,MATCH($M7,Service_Providers!$A$2:$A$104,0))<>""),CHAR(10),"")&IF(INDEX(Service_Providers!$D$2:$D$104,MATCH($M7,Service_Providers!$A$2:$A$104,0))="","",INDEX(Service_Providers!$D$2:$D$104,MATCH($M7,Service_Providers!$A$2:$A$104,0))),"Provider not found")) -> Office: (833) 203-2285 Service@FASTCILITYCORP.COM https://app.servicefusion.com/fastcility Username: Jesus@katzcoffee.com F!xmy5!t03 | O7: Arizona Area | P7: 2026-07-15
A8: iPEC | B8: mbaker@indigoautogroup.com | C8: Patrick Stam | D8: 760.393.4400 | E8: 6 Jasper Way | F8: Thermal | G8: CA | H8: 92274 | I8: Eversys Cameo c'2m; c'Fridge Beside | J8: Lease | K8: Anytime Beverage Service | L8: =IF($K8="","",IFERROR(IF(INDEX(Service_Providers!$C$2:$C$104,MATCH($K8,Service_Providers!$A$2:$A$104,0))="","",INDEX(Service_Providers!$C$2:$C$104,MATCH($K8,Service_Providers!$A$2:$A$104,0)))&IF(AND(INDEX(Service_Providers!$C$2:$C$104,MATCH($K8,Service_Providers!$A$2:$A$104,0))<>"",INDEX(Service_Providers!$D$2:$D$104,MATCH($K8,Service_Providers!$A$2:$A$104,0))<>""),CHAR(10),"")&IF(INDEX(Service_Providers!$D$2:$D$104,MATCH($K8,Service_Providers!$A$2:$A$104,0))="","",INDEX(Service_Providers!$D$2:$D$104,MATCH($K8,Service_Providers!$A$2:$A$104,0))),"Provider not found")) -> Contact: Cynthia Phone: 714-335-9964 Cell: 714-395-8108 anytimebeverageservice@gmail.com | M8: FASTCILITY CORP | N8: =IF($M8="","",IFERROR(IF(INDEX(Service_Providers!$C$2:$C$104,MATCH($M8,Service_Providers!$A$2:$A$104,0))="","",INDEX(Service_Providers!$C$2:$C$104,MATCH($M8,Service_Providers!$A$2:$A$104,0)))&IF(AND(INDEX(Service_Providers!$C$2:$C$104,MATCH($M8,Service_Providers!$A$2:$A$104,0))<>"",INDEX(Service_Providers!$D$2:$D$104,MATCH($M8,Service_Providers!$A$2:$A$104,0))<>""),CHAR(10),"")&IF(INDEX(Service_Providers!$D$2:$D$104,MATCH($M8,Service_Providers!$A$2:$A$104,0))="","",INDEX(Service_Providers!$D$2:$D$104,MATCH($M8,Service_Providers!$A$2:$A$104,0))),"Provider not found")) -> Office: (833) 203-2285 Service@FASTCILITYCORP.COM https://app.servicefusion.com/fastcility Username: Jesus@katzcoffee.com F!xmy5!t03 | O8: California Area | P8: 2026-07-15
A9: Kol Fac #070CF - Tustin, CA | B9: tkskaff@kolfac.com | C9: Kathy/Destiny | D9: 714.730.2253 | E9: 14091 Newport Avenue | F9: Tustin | G9: CA | H9: 92780 | I9: ITCB Combo Brewer; Cameo c'2s | J9: Loaned; Owned - Purchased from Katz | K9: All Star Coffee Service | L9: =IF($K9="","",IFERROR(IF(INDEX(Service_Providers!$C$2:$C$104,MATCH($K9,Service_Providers!$A$2:$A$104,0))="","",INDEX(Service_Providers!$C$2:$C$104,MATCH($K9,Service_Providers!$A$2:$A$104,0)))&IF(AND(INDEX(Service_Providers!$C$2:$C$104,MATCH($K9,Service_Providers!$A$2:$A$104,0))<>"",INDEX(Service_Providers!$D$2:$D$104,MATCH($K9,Service_Providers!$A$2:$A$104,0))<>""),CHAR(10),"")&IF(INDEX(Service_Providers!$D$2:$D$104,MATCH($K9,Service_Providers!$A$2:$A$104,0))="","",INDEX(Service_Providers!$D$2:$D$104,MATCH($K9,Service_Providers!$A$2:$A$104,0))),"Provider not found")) -> 626-315-8498 allstarcoffeeservice@gmail.com | M9: Anytime Beverage Service | N9: =IF($M9="","",IFERROR(IF(INDEX(Service_Providers!$C$2:$C$104,MATCH($M9,Service_Providers!$A$2:$A$104,0))="","",INDEX(Service_Providers!$C$2:$C$104,MATCH($M9,Service_Providers!$A$2:$A$104,0)))&IF(AND(INDEX(Service_Providers!$C$2:$C$104,MATCH($M9,Service_Providers!$A$2:$A$104,0))<>"",INDEX(Service_Providers!$D$2:$D$104,MATCH($M9,Service_Providers!$A$2:$A$104,0))<>""),CHAR(10),"")&IF(INDEX(Service_Providers!$D$2:$D$104,MATCH($M9,Service_Providers!$A$2:$A$104,0))="","",INDEX(Service_Providers!$D$2:$D$104,MATCH($M9,Service_Providers!$A$2:$A$104,0))),"Provider not found")) -> Contact: Cynthia Phone: 714-335-9964 Cell: 714-395-8108 anytimebeverageservice@gmail.com | O9: California Area | P9: 2026-07-15
A10: Kol Fac #071CF - Huntington Beach, CA | B10: skaffkathy@yahoo.com | C10: Kathy Skaff | D10: 949.235.6782 | E10: 6502 Bolsa Avenue, Unit 102 | F10: Huntington Beach | G10: CA | H10: 92647 | I10: Bunn ITCB Combo Brewer (NS) | J10: Loaned | K10: All Star Coffee Service | L10: =IF($K10="","",IFERROR(IF(INDEX(Service_Providers!$C$2:$C$104,MATCH($K10,Service_Providers!$A$2:$A$104,0))="","",INDEX(Service_Providers!$C$2:$C$104,MATCH($K10,Service_Providers!$A$2:$A$104,0)))&IF(AND(INDEX(Service_Providers!$C$2:$C$104,MATCH($K10,Service_Providers!$A$2:$A$104,0))<>"",INDEX(Service_Providers!$D$2:$D$104,MATCH($K10,Service_Providers!$A$2:$A$104,0))<>""),CHAR(10),"")&IF(INDEX(Service_Providers!$D$2:$D$104,MATCH($K10,Service_Providers!$A$2:$A$104,0))="","",INDEX(Service_Providers!$D$2:$D$104,MATCH($K10,Service_Providers!$A$2:$A$104,0))),"Provider not found")) -> 626-315-8498 allstarcoffeeservice@gmail.com | M10: Anytime Beverage Service | N10: =IF($M10="","",IFERROR(IF(INDEX(Service_Providers!$C$2:$C$104,MATCH($M10,Service_Providers!$A$2:$A$104,0))="","",INDEX(Service_Providers!$C$2:$C$104,MATCH($M10,Service_Providers!$A$2:$A$104,0)))&IF(AND(INDEX(Service_Providers!$C$2:$C$104,MATCH($M10,Service_Providers!$A$2:$A$104,0))<>"",INDEX(Service_Providers!$D$2:$D$104,MATCH($M10,Service_Providers!$A$2:$A$104,0))<>""),CHAR(10),"")&IF(INDEX(Service_Providers!$D$2:$D$104,MATCH($M10,Service_Providers!$A$2:$A$104,0))="","",INDEX(Service_Providers!$D$2:$D$104,MATCH($M10,Service_Providers!$A$2:$A$104,0))),"Provider not found")) -> Contact: Cynthia Phone: 714-335-9964 Cell: 714-395-8108 anytimebeverageservice@gmail.com | O10: California Area | P10: 2026-07-15
A11: Ocean 48 Newport Beach | B11: brent@ocean48.com | D11: 949.989.0048 | E11: 151 Newport Center Drive | F11: Newport Beach | G11: CA | H11: 92660 | I11: Cameo c'2s; Wilbur Curtis G4TP1S63A3100 Coffee Brewer; Wilbur Curtis ILGD-10 Grinder | J11: Owned - Purchased from 3rd Party | K11: Anytime Beverage Service | L11: =IF($K11="","",IFERROR(IF(INDEX(Service_Providers!$C$2:$C$104,MATCH($K11,Service_Providers!$A$2:$A$104,0))="","",INDEX(Service_Providers!$C$2:$C$104,MATCH($K11,Service_Providers!$A$2:$A$104,0)))&IF(AND(INDEX(Service_Providers!$C$2:$C$104,MATCH($K11,Service_Providers!$A$2:$A$104,0))<>"",INDEX(Service_Providers!$D$2:$D$104,MATCH($K11,Service_Providers!$A$2:$A$104,0))<>""),CHAR(10),"")&IF(INDEX(Service_Providers!$D$2:$D$104,MATCH($K11,Service_Providers!$A$2:$A$104,0))="","",INDEX(Service_Providers!$D$2:$D$104,MATCH($K11,Service_Providers!$A$2:$A$104,0))),"Provider not found")) -> Contact: Cynthia Phone: 714-335-9964 Cell: 714-395-8108 anytimebeverageservice@gmail.com | M11: FASTCILITY CORP | N11: =IF($M11="","",IFERROR(IF(INDEX(Service_Providers!$C$2:$C$104,MATCH($M11,Service_Providers!$A$2:$A$104,0))="","",INDEX(Service_Providers!$C$2:$C$104,MATCH($M11,Service_Providers!$A$2:$A$104,0)))&IF(AND(INDEX(Service_Providers!$C$2:$C$104,MATCH($M11,Service_Providers!$A$2:$A$104,0))<>"",INDEX(Service_Providers!$D$2:$D$104,MATCH($M11,Service_Providers!$A$2:$A$104,0))<>""),CHAR(10),"")&IF(INDEX(Service_Providers!$D$2:$D$104,MATCH($M11,Service_Providers!$A$2:$A$104,0))="","",INDEX(Service_Providers!$D$2:$D$104,MATCH($M11,Service_Providers!$A$2:$A$104,0))),"Provider not found")) -> Office: (833) 203-2285 Service@FASTCILITYCORP.COM https://app.servicefusion.com/fastcility Username: Jesus@katzcoffee.com F!xmy5!t03 | O11: California Area | P11: 2026-07-15
A12: Porsche Marin | B12: marinvendors@indigoautogroup.com | D12: (415) 944-1610 | E12: 900 Redwood Hwy | F12: Mill Valley | G12: CA | H12: 94941 | I12: La Marzocco Linea PB 2AV; La Marzocco Swift Grinder; BWS100/10 | J12: Owned - Purchased from Katz | K12: MB Coffee Services | L12: =IF($K12="","",IFERROR(IF(INDEX(Service_Providers!$C$2:$C$104,MATCH($K12,Service_Providers!$A$2:$A$104,0))="","",INDEX(Service_Providers!$C$2:$C$104,MATCH($K12,Service_Providers!$A$2:$A$104,0)))&IF(AND(INDEX(Service_Providers!$C$2:$C$104,MATCH($K12,Service_Providers!$A$2:$A$104,0))<>"",INDEX(Service_Providers!$D$2:$D$104,MATCH($K12,Service_Providers!$A$2:$A$104,0))<>""),CHAR(10),"")&IF(INDEX(Service_Providers!$D$2:$D$104,MATCH($K12,Service_Providers!$A$2:$A$104,0))="","",INDEX(Service_Providers!$D$2:$D$104,MATCH($K12,Service_Providers!$A$2:$A$104,0))),"Provider not found")) -> 509.302.7071 | M12: FASTCILITY CORP | N12: =IF($M12="","",IFERROR(IF(INDEX(Service_Providers!$C$2:$C$104,MATCH($M12,Service_Providers!$A$2:$A$104,0))="","",INDEX(Service_Providers!$C$2:$C$104,MATCH($M12,Service_Providers!$A$2:$A$104,0)))&IF(AND(INDEX(Service_Providers!$C$2:$C$104,MATCH($M12,Service_Providers!$A$2:$A$104,0))<>"",INDEX(Service_Providers!$D$2:$D$104,MATCH($M12,Service_Providers!$A$2:$A$104,0))<>""),CHAR(10),"")&IF(INDEX(Service_Providers!$D$2:$D$104,MATCH($M12,Service_Providers!$A$2:$A$104,0))="","",INDEX(Service_Providers!$D$2:$D$104,MATCH($M12,Service_Providers!$A$2:$A$104,0))),"Provider not found")) -> Office: (833) 203-2285 Service@FASTCILITYCORP.COM https://app.servicefusion.com/fastcility Username: Jesus@katzcoffee.com F!xmy5!t03 | O12: California Area | P12: 2026-07-15
A13: Rolls Royce - Rancho Mirage | B13: lmccurley@indigoautogroup.com | C13: Lesley McCurley | D13: 760.773.5000 | E13: 71-387 Highway 111 | F13: Rancho Mirage | G13: CA | H13: 92270 | I13: Eversys Cameo c'2m; c'Fridge Beside | J13: Lease | K13: Anytime Beverage Service | L13: =IF($K13="","",IFERROR(IF(INDEX(Service_Providers!$C$2:$C$104,MATCH($K13,Service_Providers!$A$2:$A$104,0))="","",INDEX(Service_Providers!$C$2:$C$104,MATCH($K13,Service_Providers!$A$2:$A$104,0)))&IF(AND(INDEX(Service_Providers!$C$2:$C$104,MATCH($K13,Service_Providers!$A$2:$A$104,0))<>"",INDEX(Service_Providers!$D$2:$D$104,MATCH($K13,Service_Providers!$A$2:$A$104,0))<>""),CHAR(10),"")&IF(INDEX(Service_Providers!$D$2:$D$104,MATCH($K13,Service_Providers!$A$2:$A$104,0))="","",INDEX(Service_Providers!$D$2:$D$104,MATCH($K13,Service_Providers!$A$2:$A$104,0))),"Provider not found")) -> Contact: Cynthia Phone: 714-335-9964 Cell: 714-395-8108 anytimebeverageservice@gmail.com | M13: FASTCILITY CORP | N13: =IF($M13="","",IFERROR(IF(INDEX(Service_Providers!$C$2:$C$104,MATCH($M13,Service_Providers!$A$2:$A$104,0))="","",INDEX(Service_Providers!$C$2:$C$104,MATCH($M13,Service_Providers!$A$2:$A$104,0)))&IF(AND(INDEX(Service_Providers!$C$2:$C$104,MATCH($M13,Service_Providers!$A$2:$A$104,0))<>"",INDEX(Service_Providers!$D$2:$D$104,MATCH($M13,Service_Providers!$A$2:$A$104,0))<>""),CHAR(10),"")&IF(INDEX(Service_Providers!$D$2:$D$104,MATCH($M13,Service_Providers!$A$2:$A$104,0))="","",INDEX(Service_Providers!$D$2:$D$104,MATCH($M13,Service_Providers!$A$2:$A$104,0))),"Provider not found")) -> Office: (833) 203-2285 Service@FASTCILITYCORP.COM https://app.servicefusion.com/fastcility Username: Jesus@katzcoffee.com F!xmy5!t03 | O13: California Area | P13: 2026-07-15
A14: Steak 48 Beverly Hills | B14: leila@steak48.com | D14: 310.388.0048 | E14: 9680 Wilshire Blvd. | F14: Beverly Hills | G14: CA | H14: 90212 | I14: Cameo c'2s; Wilbur Curtis G4TPX2S63A3100 Coffee Brewer; Wilbur Curtis ILGD-10 Grinder | J14: Owned - Purchased from 3rd Party | K14: Anytime Beverage Service | L14: =IF($K14="","",IFERROR(IF(INDEX(Service_Providers!$C$2:$C$104,MATCH($K14,Service_Providers!$A$2:$A$104,0))="","",INDEX(Service_Providers!$C$2:$C$104,MATCH($K14,Service_Providers!$A$2:$A$104,0)))&IF(AND(INDEX(Service_Providers!$C$2:$C$104,MATCH($K14,Service_Providers!$A$2:$A$104,0))<>"",INDEX(Service_Providers!$D$2:$D$104,MATCH($K14,Service_Providers!$A$2:$A$104,0))<>""),CHAR(10),"")&IF(INDEX(Service_Providers!$D$2:$D$104,MATCH($K14,Service_Providers!$A$2:$A$104,0))="","",INDEX(Service_Providers!$D$2:$D$104,MATCH($K14,Service_Providers!$A$2:$A$104,0))),"Provider not found")) -> Contact: Cynthia Phone: 714-335-9964 Cell: 714-395-8108 anytimebeverageservice@gmail.com | M14: FASTCILITY CORP | N14: =IF($M14="","",IFERROR(IF(INDEX(Service_Providers!$C$2:$C$104,MATCH($M14,Service_Providers!$A$2:$A$104,0))="","",INDEX(Service_Providers!$C$2:$C$104,MATCH($M14,Service_Providers!$A$2:$A$104,0)))&IF(AND(INDEX(Service_Providers!$C$2:$C$104,MATCH($M14,Service_Providers!$A$2:$A$104,0))<>"",INDEX(Service_Providers!$D$2:$D$104,MATCH($M14,Service_Providers!$A$2:$A$104,0))<>""),CHAR(10),"")&IF(INDEX(Service_Providers!$D$2:$D$104,MATCH($M14,Service_Providers!$A$2:$A$104,0))="","",INDEX(Service_Providers!$D$2:$D$104,MATCH($M14,Service_Providers!$A$2:$A$104,0))),"Provider not found")) -> Office: (833) 203-2285 Service@FASTCILITYCORP.COM https://app.servicefusion.com/fastcility Username: Jesus@katzcoffee.com F!xmy5!t03 | O14: California Area | P14: 2026-07-15
A15: Steak 48 Del Mar | B15: jacob@steak48.com | D15: 619.901.0048 | E15: 12995 El Camino Real | F15: Del Mar Heights | G15: CA | H15: 92130 | I15: Cameo c'2s; Wilbur Curtis G4TP1S63A3100 Coffee Brewer; Wilbur Curtis ILGD-10 Grinder | J15: Owned - Purchased from 3rd Party | K15: Anytime Beverage Service | L15: =IF($K15="","",IFERROR(IF(INDEX(Service_Providers!$C$2:$C$104,MATCH($K15,Service_Providers!$A$2:$A$104,0))="","",INDEX(Service_Providers!$C$2:$C$104,MATCH($K15,Service_Providers!$A$2:$A$104,0)))&IF(AND(INDEX(Service_Providers!$C$2:$C$104,MATCH($K15,Service_Providers!$A$2:$A$104,0))<>"",INDEX(Service_Providers!$D$2:$D$104,MATCH($K15,Service_Providers!$A$2:$A$104,0))<>""),CHAR(10),"")&IF(INDEX(Service_Providers!$D$2:$D$104,MATCH($K15,Service_Providers!$A$2:$A$104,0))="","",INDEX(Service_Providers!$D$2:$D$104,MATCH($K15,Service_Providers!$A$2:$A$104,0))),"Provider not found")) -> Contact: Cynthia Phone: 714-335-9964 Cell: 714-395-8108 anytimebeverageservice@gmail.com | M15: FASTCILITY CORP | N15: =IF($M15="","",IFERROR(IF(INDEX(Service_Providers!$C$2:$C$104,MATCH($M15,Service_Providers!$A$2:$A$104,0))="","",INDEX(Service_Providers!$C$2:$C$104,MATCH($M15,Service_Providers!$A$2:$A$104,0)))&IF(AND(INDEX(Service_Providers!$C$2:$C$104,MATCH($M15,Service_Providers!$A$2:$A$104,0))<>"",INDEX(Service_Providers!$D$2:$D$104,MATCH($M15,Service_Providers!$A$2:$A$104,0))<>""),CHAR(10),"")&IF(INDEX(Service_Providers!$D$2:$D$104,MATCH($M15,Service_Providers!$A$2:$A$104,0))="","",INDEX(Service_Providers!$D$2:$D$104,MATCH($M15,Service_Providers!$A$2:$A$104,0))),"Provider not found")) -> Office: (833) 203-2285 Service@FASTCILITYCORP.COM https://app.servicefusion.com/fastcility Username: Jesus@katzcoffee.com F!xmy5!t03 | O15: California Area | P15: 2026-07-15
A16: Rare Italian | B16: collinm@rareitalian.com | C16: Collin McDowell | D16: 970.294.4544 | E16: 101 South College Avenue | F16: Fort Collins | G16: CO | H16: 80524 | I16: Cameo c'2s | J16: Lease | K16: PriorityOne Group | L16: =IF($K16="","",IFERROR(IF(INDEX(Service_Providers!$C$2:$C$104,MATCH($K16,Service_Providers!$A$2:$A$104,0))="","",INDEX(Service_Providers!$C$2:$C$104,MATCH($K16,Service_Providers!$A$2:$A$104,0)))&IF(AND(INDEX(Service_Providers!$C$2:$C$104,MATCH($K16,Service_Providers!$A$2:$A$104,0))<>"",INDEX(Service_Providers!$D$2:$D$104,MATCH($K16,Service_Providers!$A$2:$A$104,0))<>""),CHAR(10),"")&IF(INDEX(Service_Providers!$D$2:$D$104,MATCH($K16,Service_Providers!$A$2:$A$104,0))="","",INDEX(Service_Providers!$D$2:$D$104,MATCH($K16,Service_Providers!$A$2:$A$104,0))),"Provider not found")) -> (800) 226-7146 service@priorityone247.com | N16: =IF($M16="","",IFERROR(IF(INDEX(Service_Providers!$C$2:$C$104,MATCH($M16,Service_Providers!$A$2:$A$104,0))="","",INDEX(Service_Providers!$C$2:$C$104,MATCH($M16,Service_Providers!$A$2:$A$104,0)))&IF(AND(INDEX(Service_Providers!$C$2:$C$104,MATCH($M16,Service_Providers!$A$2:$A$104,0))<>"",INDEX(Service_Providers!$D$2:$D$104,MATCH($M16,Service_Providers!$A$2:$A$104,0))<>""),CHAR(10),"")&IF(INDEX(Service_Providers!$D$2:$D$104,MATCH($M16,Service_Providers!$A$2:$A$104,0))="","",INDEX(Service_Providers!$D$2:$D$104,MATCH($M16,Service_Providers!$A$2:$A$104,0))),"Provider not found")) | O16: Colorado Area | P16: 2026-07-15
A17: Rio Grande Mexican Restaurant - Boulder | B17: boulder@riograndemexican.com | C17: Julio Vasquez | D17: 303.444.3690 | E17: 1101 Walnut St | F17: Boulder | G17: CO | H17: 80302 | I17: ITCB w/Shelf (New Style) | J17: Loaned | K17: PriorityOne Group | L17: =IF($K17="","",IFERROR(IF(INDEX(Service_Providers!$C$2:$C$104,MATCH($K17,Service_Providers!$A$2:$A$104,0))="","",INDEX(Service_Providers!$C$2:$C$104,MATCH($K17,Service_Providers!$A$2:$A$104,0)))&IF(AND(INDEX(Service_Providers!$C$2:$C$104,MATCH($K17,Service_Providers!$A$2:$A$104,0))<>"",INDEX(Service_Providers!$D$2:$D$104,MATCH($K17,Service_Providers!$A$2:$A$104,0))<>""),CHAR(10),"")&IF(INDEX(Service_Providers!$D$2:$D$104,MATCH($K17,Service_Providers!$A$2:$A$104,0))="","",INDEX(Service_Providers!$D$2:$D$104,MATCH($K17,Service_Providers!$A$2:$A$104,0))),"Provider not found")) -> (800) 226-7146 service@priorityone247.com | N17: =IF($M17="","",IFERROR(IF(INDEX(Service_Providers!$C$2:$C$104,MATCH($M17,Service_Providers!$A$2:$A$104,0))="","",INDEX(Service_Providers!$C$2:$C$104,MATCH($M17,Service_Providers!$A$2:$A$104,0)))&IF(AND(INDEX(Service_Providers!$C$2:$C$104,MATCH($M17,Service_Providers!$A$2:$A$104,0))<>"",INDEX(Service_Providers!$D$2:$D$104,MATCH($M17,Service_Providers!$A$2:$A$104,0))<>""),CHAR(10),"")&IF(INDEX(Service_Providers!$D$2:$D$104,MATCH($M17,Service_Providers!$A$2:$A$104,0))="","",INDEX(Service_Providers!$D$2:$D$104,MATCH($M17,Service_Providers!$A$2:$A$104,0))),"Provider not found")) | O17: Colorado Area | P17: 2026-07-15
A18: Rio Grande Mexican Restaurant - Denver | B18: denver@riograndemexican.com | C18: Matt Ciani | D18: 303.623.5432 | E18: 1745 Wazee St | F18: Denver | G18: CO | H18: 80202 | I18: ITCB w/Shelf (New Style) | J18: Loaned | K18: PriorityOne Group | L18: =IF($K18="","",IFERROR(IF(INDEX(Service_Providers!$C$2:$C$104,MATCH($K18,Service_Providers!$A$2:$A$104,0))="","",INDEX(Service_Providers!$C$2:$C$104,MATCH($K18,Service_Providers!$A$2:$A$104,0)))&IF(AND(INDEX(Service_Providers!$C$2:$C$104,MATCH($K18,Service_Providers!$A$2:$A$104,0))<>"",INDEX(Service_Providers!$D$2:$D$104,MATCH($K18,Service_Providers!$A$2:$A$104,0))<>""),CHAR(10),"")&IF(INDEX(Service_Providers!$D$2:$D$104,MATCH($K18,Service_Providers!$A$2:$A$104,0))="","",INDEX(Service_Providers!$D$2:$D$104,MATCH($K18,Service_Providers!$A$2:$A$104,0))),"Provider not found")) -> (800) 226-7146 service@priorityone247.com | N18: =IF($M18="","",IFERROR(IF(INDEX(Service_Providers!$C$2:$C$104,MATCH($M18,Service_Providers!$A$2:$A$104,0))="","",INDEX(Service_Providers!$C$2:$C$104,MATCH($M18,Service_Providers!$A$2:$A$104,0)))&IF(AND(INDEX(Service_Providers!$C$2:$C$104,MATCH($M18,Service_Providers!$A$2:$A$104,0))<>"",INDEX(Service_Providers!$D$2:$D$104,MATCH($M18,Service_Providers!$A$2:$A$104,0))<>""),CHAR(10),"")&IF(INDEX(Service_Providers!$D$2:$D$104,MATCH($M18,Service_Providers!$A$2:$A$104,0))="","",INDEX(Service_Providers!$D$2:$D$104,MATCH($M18,Service_Providers!$A$2:$A$104,0))),"Provider not found")) | O18: Colorado Area | P18: 2026-07-15
A19: Rio Grande Mexican Restaurant - Greeley | B19: apgreeley@riograndemexican.com | C19: Eric Lozano | D19: 970.304.9292 | E19: 825 9th Street | F19: Greeley | G19: CO | H19: 80631 | I19: ITCB w/Shelf (New Style) | J19: Loaned | K19: PriorityOne Group | L19: =IF($K19="","",IFERROR(IF(INDEX(Service_Providers!$C$2:$C$104,MATCH($K19,Service_Providers!$A$2:$A$104,0))="","",INDEX(Service_Providers!$C$2:$C$104,MATCH($K19,Service_Providers!$A$2:$A$104,0)))&IF(AND(INDEX(Service_Providers!$C$2:$C$104,MATCH($K19,Service_Providers!$A$2:$A$104,0))<>"",INDEX(Service_Providers!$D$2:$D$104,MATCH($K19,Service_Providers!$A$2:$A$104,0))<>""),CHAR(10),"")&IF(INDEX(Service_Providers!$D$2:$D$104,MATCH($K19,Service_Providers!$A$2:$A$104,0))="","",INDEX(Service_Providers!$D$2:$D$104,MATCH($K19,Service_Providers!$A$2:$A$104,0))),"Provider not found")) -> (800) 226-7146 service@priorityone247.com | N19: =IF($M19="","",IFERROR(IF(INDEX(Service_Providers!$C$2:$C$104,MATCH($M19,Service_Providers!$A$2:$A$104,0))="","",INDEX(Service_Providers!$C$2:$C$104,MATCH($M19,Service_Providers!$A$2:$A$104,0)))&IF(AND(INDEX(Service_Providers!$C$2:$C$104,MATCH($M19,Service_Providers!$A$2:$A$104,0))<>"",INDEX(Service_Providers!$D$2:$D$104,MATCH($M19,Service_Providers!$A$2:$A$104,0))<>""),CHAR(10),"")&IF(INDEX(Service_Providers!$D$2:$D$104,MATCH($M19,Service_Providers!$A$2:$A$104,0))="","",INDEX(Service_Providers!$D$2:$D$104,MATCH($M19,Service_Providers!$A$2:$A$104,0))),"Provider not found")) | O19: Colorado Area | P19: 2026-07-15
A20: Rio Grande Mexican Restaurant - Lone Tree | B20: lonetree@riograndemexican.com | C20: Matt Ciani | D20: 303.799.4999 | E20: 9535 Park Meadows Drive | F20: Lone Tree | G20: CO | H20: 80124 | I20: ITCB w/Shelf (New Style) | J20: Loaned | K20: PriorityOne Group | L20: =IF($K20="","",IFERROR(IF(INDEX(Service_Providers!$C$2:$C$104,MATCH($K20,Service_Providers!$A$2:$A$104,0))="","",INDEX(Service_Providers!$C$2:$C$104,MATCH($K20,Service_Providers!$A$2:$A$104,0)))&IF(AND(INDEX(Service_Providers!$C$2:$C$104,MATCH($K20,Service_Providers!$A$2:$A$104,0))<>"",INDEX(Service_Providers!$D$2:$D$104,MATCH($K20,Service_Providers!$A$2:$A$104,0))<>""),CHAR(10),"")&IF(INDEX(Service_Providers!$D$2:$D$104,MATCH($K20,Service_Providers!$A$2:$A$104,0))="","",INDEX(Service_Providers!$D$2:$D$104,MATCH($K20,Service_Providers!$A$2:$A$104,0))),"Provider not found")) -> (800) 226-7146 service@priorityone247.com | N20: =IF($M20="","",IFERROR(IF(INDEX(Service_Providers!$C$2:$C$104,MATCH($M20,Service_Providers!$A$2:$A$104,0))="","",INDEX(Service_Providers!$C$2:$C$104,MATCH($M20,Service_Providers!$A$2:$A$104,0)))&IF(AND(INDEX(Service_Providers!$C$2:$C$104,MATCH($M20,Service_Providers!$A$2:$A$104,0))<>"",INDEX(Service_Providers!$D$2:$D$104,MATCH($M20,Service_Providers!$A$2:$A$104,0))<>""),CHAR(10),"")&IF(INDEX(Service_Providers!$D$2:$D$104,MATCH($M20,Service_Providers!$A$2:$A$104,0))="","",INDEX(Service_Providers!$D$2:$D$104,MATCH($M20,Service_Providers!$A$2:$A$104,0))),"Provider not found")) | O20: Colorado Area | P20: 2026-07-15
A21: Rio Grande Mexican Restaurant- Ft Collins | B21: apfortcollins@riograndemexican.com | C21: Paul Sisson | D21: 970.224.3049 | E21: 143 W Mountain Ave | F21: Fort Collins | G21: CO | H21: 80524 | I21: ITCB w/ Shelf (New Style) | J21: Loaned | K21: PriorityOne Group | L21: =IF($K21="","",IFERROR(IF(INDEX(Service_Providers!$C$2:$C$104,MATCH($K21,Service_Providers!$A$2:$A$104,0))="","",INDEX(Service_Providers!$C$2:$C$104,MATCH($K21,Service_Providers!$A$2:$A$104,0)))&IF(AND(INDEX(Service_Providers!$C$2:$C$104,MATCH($K21,Service_Providers!$A$2:$A$104,0))<>"",INDEX(Service_Providers!$D$2:$D$104,MATCH($K21,Service_Providers!$A$2:$A$104,0))<>""),CHAR(10),"")&IF(INDEX(Service_Providers!$D$2:$D$104,MATCH($K21,Service_Providers!$A$2:$A$104,0))="","",INDEX(Service_Providers!$D$2:$D$104,MATCH($K21,Service_Providers!$A$2:$A$104,0))),"Provider not found")) -> (800) 226-7146 service@priorityone247.com | N21: =IF($M21="","",IFERROR(IF(INDEX(Service_Providers!$C$2:$C$104,MATCH($M21,Service_Providers!$A$2:$A$104,0))="","",INDEX(Service_Providers!$C$2:$C$104,MATCH($M21,Service_Providers!$A$2:$A$104,0)))&IF(AND(INDEX(Service_Providers!$C$2:$C$104,MATCH($M21,Service_Providers!$A$2:$A$104,0))<>"",INDEX(Service_Providers!$D$2:$D$104,MATCH($M21,Service_Providers!$A$2:$A$104,0))<>""),CHAR(10),"")&IF(INDEX(Service_Providers!$D$2:$D$104,MATCH($M21,Service_Providers!$A$2:$A$104,0))="","",INDEX(Service_Providers!$D$2:$D$104,MATCH($M21,Service_Providers!$A$2:$A$104,0))),"Provider not found")) | O21: Colorado Area | P21: 2026-07-15
A22: Truluck's - Washington DC | B22: trulucks-washingtondc@trulucks.com | D22: 202.898.0680 | E22: 700 K Street NW, Suite 70 | F22: Washington | G22: DC | H22: 20001 | I22: Eversys Cameo c'2s; ITCB w/Shelf (NS); H5X Hot Water Tower; FPG-2E | J22: Lease; Loaned | K22: PriorityOne Group | L22: =IF($K22="","",IFERROR(IF(INDEX(Service_Providers!$C$2:$C$104,MATCH($K22,Service_Providers!$A$2:$A$104,0))="","",INDEX(Service_Providers!$C$2:$C$104,MATCH($K22,Service_Providers!$A$2:$A$104,0)))&IF(AND(INDEX(Service_Providers!$C$2:$C$104,MATCH($K22,Service_Providers!$A$2:$A$104,0))<>"",INDEX(Service_Providers!$D$2:$D$104,MATCH($K22,Service_Providers!$A$2:$A$104,0))<>""),CHAR(10),"")&IF(INDEX(Service_Providers!$D$2:$D$104,MATCH($K22,Service_Providers!$A$2:$A$104,0))="","",INDEX(Service_Providers!$D$2:$D$104,MATCH($K22,Service_Providers!$A$2:$A$104,0))),"Provider not found")) -> (800) 226-7146 service@priorityone247.com | N22: =IF($M22="","",IFERROR(IF(INDEX(Service_Providers!$C$2:$C$104,MATCH($M22,Service_Providers!$A$2:$A$104,0))="","",INDEX(Service_Providers!$C$2:$C$104,MATCH($M22,Service_Providers!$A$2:$A$104,0)))&IF(AND(INDEX(Service_Providers!$C$2:$C$104,MATCH($M22,Service_Providers!$A$2:$A$104,0))<>"",INDEX(Service_Providers!$D$2:$D$104,MATCH($M22,Service_Providers!$A$2:$A$104,0))<>""),CHAR(10),"")&IF(INDEX(Service_Providers!$D$2:$D$104,MATCH($M22,Service_Providers!$A$2:$A$104,0))="","",INDEX(Service_Providers!$D$2:$D$104,MATCH($M22,Service_Providers!$A$2:$A$104,0))),"Provider not found")) | O22: Washington DC | P22: 2026-07-15
A23: Hawkers - Delray Beach, FL | B23: APdelray107@eathawkers.com | C23: James Gnehm | D23: 561.485.4111 | E23: 640 E. Atlantic Ave. | F23: Delray Beach | G23: FL | H23: 33483 | I23: Bunn ITCB Combo Brewer | J23: Loaned | K23: All Espresso Service | L23: =IF($K23="","",IFERROR(IF(INDEX(Service_Providers!$C$2:$C$104,MATCH($K23,Service_Providers!$A$2:$A$104,0))="","",INDEX(Service_Providers!$C$2:$C$104,MATCH($K23,Service_Providers!$A$2:$A$104,0)))&IF(AND(INDEX(Service_Providers!$C$2:$C$104,MATCH($K23,Service_Providers!$A$2:$A$104,0))<>"",INDEX(Service_Providers!$D$2:$D$104,MATCH($K23,Service_Providers!$A$2:$A$104,0))<>""),CHAR(10),"")&IF(INDEX(Service_Providers!$D$2:$D$104,MATCH($K23,Service_Providers!$A$2:$A$104,0))="","",INDEX(Service_Providers!$D$2:$D$104,MATCH($K23,Service_Providers!$A$2:$A$104,0))),"Provider not found")) -> 754.205.5076 service@allespressoservice.com | M23: Jaguar Coffee Co. | N23: =IF($M23="","",IFERROR(IF(INDEX(Service_Providers!$C$2:$C$104,MATCH($M23,Service_Providers!$A$2:$A$104,0))="","",INDEX(Service_Providers!$C$2:$C$104,MATCH($M23,Service_Providers!$A$2:$A$104,0)))&IF(AND(INDEX(Service_Providers!$C$2:$C$104,MATCH($M23,Service_Providers!$A$2:$A$104,0))<>"",INDEX(Service_Providers!$D$2:$D$104,MATCH($M23,Service_Providers!$A$2:$A$104,0))<>""),CHAR(10),"")&IF(INDEX(Service_Providers!$D$2:$D$104,MATCH($M23,Service_Providers!$A$2:$A$104,0))="","",INDEX(Service_Providers!$D$2:$D$104,MATCH($M23,Service_Providers!$A$2:$A$104,0))),"Provider not found")) -> 352 442 2506 sam.mendez@jaguarcoffee.com | O23: Florida Area | P23: 2026-07-15
A24: Hawkers - Jacksonville, FL (Five Points) | B24: bkamarat@eathawkers.com | C24: Randy McCauley | D24: 904.508.0342 | E24: 1001 Park St. | F24: Jacksonville | G24: FL | H24: 32204 | I24: ITCB Combo Brewer | J24: Loaned | K24: Jaguar Coffee Co. | L24: =IF($K24="","",IFERROR(IF(INDEX(Service_Providers!$C$2:$C$104,MATCH($K24,Service_Providers!$A$2:$A$104,0))="","",INDEX(Service_Providers!$C$2:$C$104,MATCH($K24,Service_Providers!$A$2:$A$104,0)))&IF(AND(INDEX(Service_Providers!$C$2:$C$104,MATCH($K24,Service_Providers!$A$2:$A$104,0))<>"",INDEX(Service_Providers!$D$2:$D$104,MATCH($K24,Service_Providers!$A$2:$A$104,0))<>""),CHAR(10),"")&IF(INDEX(Service_Providers!$D$2:$D$104,MATCH($K24,Service_Providers!$A$2:$A$104,0))="","",INDEX(Service_Providers!$D$2:$D$104,MATCH($K24,Service_Providers!$A$2:$A$104,0))),"Provider not found")) -> 352 442 2506 sam.mendez@jaguarcoffee.com | N24: =IF($M24="","",IFERROR(IF(INDEX(Service_Providers!$C$2:$C$104,MATCH($M24,Service_Providers!$A$2:$A$104,0))="","",INDEX(Service_Providers!$C$2:$C$104,MATCH($M24,Service_Providers!$A$2:$A$104,0)))&IF(AND(INDEX(Service_Providers!$C$2:$C$104,MATCH($M24,Service_Providers!$A$2:$A$104,0))<>"",INDEX(Service_Providers!$D$2:$D$104,MATCH($M24,Service_Providers!$A$2:$A$104,0))<>""),CHAR(10),"")&IF(INDEX(Service_Providers!$D$2:$D$104,MATCH($M24,Service_Providers!$A$2:$A$104,0))="","",INDEX(Service_Providers!$D$2:$D$104,MATCH($M24,Service_Providers!$A$2:$A$104,0))),"Provider not found")) | O24: Florida Area | P24: 2026-07-15
A25: Hawkers - Neptune Beach, FL | B25: mtumminia@eathawkers.com | C25: Marie Tumminia | D25: 904.425.1025 | E25: 241 N. Atlantic Blvd., Suite 101 | F25: Neptune Beach | G25: FL | H25: 32266 | I25: ITCB Combo Brewer | J25: Loaned | K25: Jaguar Coffee Co. | L25: =IF($K25="","",IFERROR(IF(INDEX(Service_Providers!$C$2:$C$104,MATCH($K25,Service_Providers!$A$2:$A$104,0))="","",INDEX(Service_Providers!$C$2:$C$104,MATCH($K25,Service_Providers!$A$2:$A$104,0)))&IF(AND(INDEX(Service_Providers!$C$2:$C$104,MATCH($K25,Service_Providers!$A$2:$A$104,0))<>"",INDEX(Service_Providers!$D$2:$D$104,MATCH($K25,Service_Providers!$A$2:$A$104,0))<>""),CHAR(10),"")&IF(INDEX(Service_Providers!$D$2:$D$104,MATCH($K25,Service_Providers!$A$2:$A$104,0))="","",INDEX(Service_Providers!$D$2:$D$104,MATCH($K25,Service_Providers!$A$2:$A$104,0))),"Provider not found")) -> 352 442 2506 sam.mendez@jaguarcoffee.com | N25: =IF($M25="","",IFERROR(IF(INDEX(Service_Providers!$C$2:$C$104,MATCH($M25,Service_Providers!$A$2:$A$104,0))="","",INDEX(Service_Providers!$C$2:$C$104,MATCH($M25,Service_Providers!$A$2:$A$104,0)))&IF(AND(INDEX(Service_Providers!$C$2:$C$104,MATCH($M25,Service_Providers!$A$2:$A$104,0))<>"",INDEX(Service_Providers!$D$2:$D$104,MATCH($M25,Service_Providers!$A$2:$A$104,0))<>""),CHAR(10),"")&IF(INDEX(Service_Providers!$D$2:$D$104,MATCH($M25,Service_Providers!$A$2:$A$104,0))="","",INDEX(Service_Providers!$D$2:$D$104,MATCH($M25,Service_Providers!$A$2:$A$104,0))),"Provider not found")) | O25: Florida Area | P25: 2026-07-15
A26: Hawkers - Orlando, FL (Mills) | B26: APmills101@eathawkers.com | C26: Robert Wolfe | D26: 407.237.0606 | E26: 1103 N. Mills Ave. | F26: Orlando | G26: FL | H26: 32803 | I26: ITCB Combo Brewer | J26: Loaned | K26: Jaguar Coffee Co. | L26: =IF($K26="","",IFERROR(IF(INDEX(Service_Providers!$C$2:$C$104,MATCH($K26,Service_Providers!$A$2:$A$104,0))="","",INDEX(Service_Providers!$C$2:$C$104,MATCH($K26,Service_Providers!$A$2:$A$104,0)))&IF(AND(INDEX(Service_Providers!$C$2:$C$104,MATCH($K26,Service_Providers!$A$2:$A$104,0))<>"",INDEX(Service_Providers!$D$2:$D$104,MATCH($K26,Service_Providers!$A$2:$A$104,0))<>""),CHAR(10),"")&IF(INDEX(Service_Providers!$D$2:$D$104,MATCH($K26,Service_Providers!$A$2:$A$104,0))="","",INDEX(Service_Providers!$D$2:$D$104,MATCH($K26,Service_Providers!$A$2:$A$104,0))),"Provider not found")) -> 352 442 2506 sam.mendez@jaguarcoffee.com | N26: =IF($M26="","",IFERROR(IF(INDEX(Service_Providers!$C$2:$C$104,MATCH($M26,Service_Providers!$A$2:$A$104,0))="","",INDEX(Service_Providers!$C$2:$C$104,MATCH($M26,Service_Providers!$A$2:$A$104,0)))&IF(AND(INDEX(Service_Providers!$C$2:$C$104,MATCH($M26,Service_Providers!$A$2:$A$104,0))<>"",INDEX(Service_Providers!$D$2:$D$104,MATCH($M26,Service_Providers!$A$2:$A$104,0))<>""),CHAR(10),"")&IF(INDEX(Service_Providers!$D$2:$D$104,MATCH($M26,Service_Providers!$A$2:$A$104,0))="","",INDEX(Service_Providers!$D$2:$D$104,MATCH($M26,Service_Providers!$A$2:$A$104,0))),"Provider not found")) | O26: Florida Area | P26: 2026-07-15
A27: Hawkers - St. Petersburg, FL | B27: sgolden@eathawkers.com | C27: Stephen Golden | D27: 727.521.7253 | E27: 1235 Central Ave. | F27: St. Petersburg | G27: FL | H27: 33705 | I27: Bunn ITCB Combo Brewer | J27: Loaned | K27: Jaguar Coffee Co. | L27: =IF($K27="","",IFERROR(IF(INDEX(Service_Providers!$C$2:$C$104,MATCH($K27,Service_Providers!$A$2:$A$104,0))="","",INDEX(Service_Providers!$C$2:$C$104,MATCH($K27,Service_Providers!$A$2:$A$104,0)))&IF(AND(INDEX(Service_Providers!$C$2:$C$104,MATCH($K27,Service_Providers!$A$2:$A$104,0))<>"",INDEX(Service_Providers!$D$2:$D$104,MATCH($K27,Service_Providers!$A$2:$A$104,0))<>""),CHAR(10),"")&IF(INDEX(Service_Providers!$D$2:$D$104,MATCH($K27,Service_Providers!$A$2:$A$104,0))="","",INDEX(Service_Providers!$D$2:$D$104,MATCH($K27,Service_Providers!$A$2:$A$104,0))),"Provider not found")) -> 352 442 2506 sam.mendez@jaguarcoffee.com | N27: =IF($M27="","",IFERROR(IF(INDEX(Service_Providers!$C$2:$C$104,MATCH($M27,Service_Providers!$A$2:$A$104,0))="","",INDEX(Service_Providers!$C$2:$C$104,MATCH($M27,Service_Providers!$A$2:$A$104,0)))&IF(AND(INDEX(Service_Providers!$C$2:$C$104,MATCH($M27,Service_Providers!$A$2:$A$104,0))<>"",INDEX(Service_Providers!$D$2:$D$104,MATCH($M27,Service_Providers!$A$2:$A$104,0))<>""),CHAR(10),"")&IF(INDEX(Service_Providers!$D$2:$D$104,MATCH($M27,Service_Providers!$A$2:$A$104,0))="","",INDEX(Service_Providers!$D$2:$D$104,MATCH($M27,Service_Providers!$A$2:$A$104,0))),"Provider not found")) | O27: Florida Area | P27: 2026-07-15
A28: Hawkers - Windermere, FL | B28: gvavalides@eathawkers.com | C28: George Vavalides | D28: 407.583.6334 | E28: 9100 Conroy Windermere Rd. | F28: Windermere | G28: FL | H28: 34786 | I28: ITCB Combo Brewer | J28: Loaned | K28: Jaguar Coffee Co. | L28: =IF($K28="","",IFERROR(IF(INDEX(Service_Providers!$C$2:$C$104,MATCH($K28,Service_Providers!$A$2:$A$104,0))="","",INDEX(Service_Providers!$C$2:$C$104,MATCH($K28,Service_Providers!$A$2:$A$104,0)))&IF(AND(INDEX(Service_Providers!$C$2:$C$104,MATCH($K28,Service_Providers!$A$2:$A$104,0))<>"",INDEX(Service_Providers!$D$2:$D$104,MATCH($K28,Service_Providers!$A$2:$A$104,0))<>""),CHAR(10),"")&IF(INDEX(Service_Providers!$D$2:$D$104,MATCH($K28,Service_Providers!$A$2:$A$104,0))="","",INDEX(Service_Providers!$D$2:$D$104,MATCH($K28,Service_Providers!$A$2:$A$104,0))),"Provider not found")) -> 352 442 2506 sam.mendez@jaguarcoffee.com | N28: =IF($M28="","",IFERROR(IF(INDEX(Service_Providers!$C$2:$C$104,MATCH($M28,Service_Providers!$A$2:$A$104,0))="","",INDEX(Service_Providers!$C$2:$C$104,MATCH($M28,Service_Providers!$A$2:$A$104,0)))&IF(AND(INDEX(Service_Providers!$C$2:$C$104,MATCH($M28,Service_Providers!$A$2:$A$104,0))<>"",INDEX(Service_Providers!$D$2:$D$104,MATCH($M28,Service_Providers!$A$2:$A$104,0))<>""),CHAR(10),"")&IF(INDEX(Service_Providers!$D$2:$D$104,MATCH($M28,Service_Providers!$A$2:$A$104,0))="","",INDEX(Service_Providers!$D$2:$D$104,MATCH($M28,Service_Providers!$A$2:$A$104,0))),"Provider not found")) | O28: Florida Area | P28: 2026-07-15
A29: Truluck's - Ft. Lauderdale | B29: trulucks-ftlauderdale@trulucks.com | D29: 954.395.8175 | E29: 701 N Ft. Lauderdale Beach Blvd. | F29: Ft. Lauderdale | G29: FL | H29: 33304 | I29: Eversys Cameo c'2s; Bunn ITCB Combo Brewer; Bunn H5X; Bunn FPG-2E; Everpure OPS175 | J29: Lease; Loaned; Owned - Purchased from Katz | K29: All Espresso Service | L29: =IF($K29="","",IFERROR(IF(INDEX(Service_Providers!$C$2:$C$104,MATCH($K29,Service_Providers!$A$2:$A$104,0))="","",INDEX(Service_Providers!$C$2:$C$104,MATCH($K29,Service_Providers!$A$2:$A$104,0)))&IF(AND(INDEX(Service_Providers!$C$2:$C$104,MATCH($K29,Service_Providers!$A$2:$A$104,0))<>"",INDEX(Service_Providers!$D$2:$D$104,MATCH($K29,Service_Providers!$A$2:$A$104,0))<>""),CHAR(10),"")&IF(INDEX(Service_Providers!$D$2:$D$104,MATCH($K29,Service_Providers!$A$2:$A$104,0))="","",INDEX(Service_Providers!$D$2:$D$104,MATCH($K29,Service_Providers!$A$2:$A$104,0))),"Provider not found")) -> 754.205.5076 service@allespressoservice.com | N29: =IF($M29="","",IFERROR(IF(INDEX(Service_Providers!$C$2:$C$104,MATCH($M29,Service_Providers!$A$2:$A$104,0))="","",INDEX(Service_Providers!$C$2:$C$104,MATCH($M29,Service_Providers!$A$2:$A$104,0)))&IF(AND(INDEX(Service_Providers!$C$2:$C$104,MATCH($M29,Service_Providers!$A$2:$A$104,0))<>"",INDEX(Service_Providers!$D$2:$D$104,MATCH($M29,Service_Providers!$A$2:$A$104,0))<>""),CHAR(10),"")&IF(INDEX(Service_Providers!$D$2:$D$104,MATCH($M29,Service_Providers!$A$2:$A$104,0))="","",INDEX(Service_Providers!$D$2:$D$104,MATCH($M29,Service_Providers!$A$2:$A$104,0))),"Provider not found")) | O29: Florida Area | P29: 2026-07-15
A30: Truluck's - Miami | B30: trulucks-miami@trulucks.com | D30: 305.579.0035 | E30: 777 Brickell Ave., Suite 100 | F30: Miami | G30: FL | H30: 33131 | I30: Eversys Cameo c'2s; Bunn ITCB Combo Brewer; Bunn H5X Hot Water Tower; Bunn FPG Grinder | J30: Lease; Loaned | K30: All Espresso Service | L30: =IF($K30="","",IFERROR(IF(INDEX(Service_Providers!$C$2:$C$104,MATCH($K30,Service_Providers!$A$2:$A$104,0))="","",INDEX(Service_Providers!$C$2:$C$104,MATCH($K30,Service_Providers!$A$2:$A$104,0)))&IF(AND(INDEX(Service_Providers!$C$2:$C$104,MATCH($K30,Service_Providers!$A$2:$A$104,0))<>"",INDEX(Service_Providers!$D$2:$D$104,MATCH($K30,Service_Providers!$A$2:$A$104,0))<>""),CHAR(10),"")&IF(INDEX(Service_Providers!$D$2:$D$104,MATCH($K30,Service_Providers!$A$2:$A$104,0))="","",INDEX(Service_Providers!$D$2:$D$104,MATCH($K30,Service_Providers!$A$2:$A$104,0))),"Provider not found")) -> 754.205.5076 service@allespressoservice.com | N30: =IF($M30="","",IFERROR(IF(INDEX(Service_Providers!$C$2:$C$104,MATCH($M30,Service_Providers!$A$2:$A$104,0))="","",INDEX(Service_Providers!$C$2:$C$104,MATCH($M30,Service_Providers!$A$2:$A$104,0)))&IF(AND(INDEX(Service_Providers!$C$2:$C$104,MATCH($M30,Service_Providers!$A$2:$A$104,0))<>"",INDEX(Service_Providers!$D$2:$D$104,MATCH($M30,Service_Providers!$A$2:$A$104,0))<>""),CHAR(10),"")&IF(INDEX(Service_Providers!$D$2:$D$104,MATCH($M30,Service_Providers!$A$2:$A$104,0))="","",INDEX(Service_Providers!$D$2:$D$104,MATCH($M30,Service_Providers!$A$2:$A$104,0))),"Provider not found")) | O30: Florida Area | P30: 2026-07-15
A31: Truluck's - Naples | B31: trulucks-naples@trulucks.com | D31: 239.530.3131 | E31: 698 4th Avenue South | F31: Naples | G31: FL | H31: 34102 | I31: Eversys Cameo c'2s; Bunn ITCB Combo Brewer; Bunn FPG-2E Grinder; Bunn H5X Hot Water Tower | J31: Lease; Loaned | K31: All Espresso Service | L31: =IF($K31="","",IFERROR(IF(INDEX(Service_Providers!$C$2:$C$104,MATCH($K31,Service_Providers!$A$2:$A$104,0))="","",INDEX(Service_Providers!$C$2:$C$104,MATCH($K31,Service_Providers!$A$2:$A$104,0)))&IF(AND(INDEX(Service_Providers!$C$2:$C$104,MATCH($K31,Service_Providers!$A$2:$A$104,0))<>"",INDEX(Service_Providers!$D$2:$D$104,MATCH($K31,Service_Providers!$A$2:$A$104,0))<>""),CHAR(10),"")&IF(INDEX(Service_Providers!$D$2:$D$104,MATCH($K31,Service_Providers!$A$2:$A$104,0))="","",INDEX(Service_Providers!$D$2:$D$104,MATCH($K31,Service_Providers!$A$2:$A$104,0))),"Provider not found")) -> 754.205.5076 service@allespressoservice.com | N31: =IF($M31="","",IFERROR(IF(INDEX(Service_Providers!$C$2:$C$104,MATCH($M31,Service_Providers!$A$2:$A$104,0))="","",INDEX(Service_Providers!$C$2:$C$104,MATCH($M31,Service_Providers!$A$2:$A$104,0)))&IF(AND(INDEX(Service_Providers!$C$2:$C$104,MATCH($M31,Service_Providers!$A$2:$A$104,0))<>"",INDEX(Service_Providers!$D$2:$D$104,MATCH($M31,Service_Providers!$A$2:$A$104,0))<>""),CHAR(10),"")&IF(INDEX(Service_Providers!$D$2:$D$104,MATCH($M31,Service_Providers!$A$2:$A$104,0))="","",INDEX(Service_Providers!$D$2:$D$104,MATCH($M31,Service_Providers!$A$2:$A$104,0))),"Provider not found")) | O31: Florida Area | P31: 2026-07-15
A32: Hawkers - Atlanta, GA (Ashford) | B32: sbenson@eathawkers.com | C32: Sam Benson | D32: 407.255.2200 | E32: 1230 Ashford Crossing, Suite 300B | F32: Atlanta | G32: GA | H32: 30346 | I32: Bunn ITCB Combo Brewer | J32: Loaned | K32: Espresso Southeast | L32: =IF($K32="","",IFERROR(IF(INDEX(Service_Providers!$C$2:$C$104,MATCH($K32,Service_Providers!$A$2:$A$104,0))="","",INDEX(Service_Providers!$C$2:$C$104,MATCH($K32,Service_Providers!$A$2:$A$104,0)))&IF(AND(INDEX(Service_Providers!$C$2:$C$104,MATCH($K32,Service_Providers!$A$2:$A$104,0))<>"",INDEX(Service_Providers!$D$2:$D$104,MATCH($K32,Service_Providers!$A$2:$A$104,0))<>""),CHAR(10),"")&IF(INDEX(Service_Providers!$D$2:$D$104,MATCH($K32,Service_Providers!$A$2:$A$104,0))="","",INDEX(Service_Providers!$D$2:$D$104,MATCH($K32,Service_Providers!$A$2:$A$104,0))),"Provider not found")) -> 770-867-3111 service@espressosoutheast.com | N32: =IF($M32="","",IFERROR(IF(INDEX(Service_Providers!$C$2:$C$104,MATCH($M32,Service_Providers!$A$2:$A$104,0))="","",INDEX(Service_Providers!$C$2:$C$104,MATCH($M32,Service_Providers!$A$2:$A$104,0)))&IF(AND(INDEX(Service_Providers!$C$2:$C$104,MATCH($M32,Service_Providers!$A$2:$A$104,0))<>"",INDEX(Service_Providers!$D$2:$D$104,MATCH($M32,Service_Providers!$A$2:$A$104,0))<>""),CHAR(10),"")&IF(INDEX(Service_Providers!$D$2:$D$104,MATCH($M32,Service_Providers!$A$2:$A$104,0))="","",INDEX(Service_Providers!$D$2:$D$104,MATCH($M32,Service_Providers!$A$2:$A$104,0))),"Provider not found")) | O32: Georgia Area | P32: 2026-07-15
A33: Hawkers - Atlanta, GA (Beltline) | B33: dwitherspoon@eathawkers.com | C33: Derrick Witherspoon | D33: 407.255.2200 | E33: 661 Auburn Ave., Suite 180 | F33: Atlanta | G33: GA | H33: 30312 | I33: Bunn ITCB Combo Brewer | J33: Loaned | K33: Espresso Southeast | L33: =IF($K33="","",IFERROR(IF(INDEX(Service_Providers!$C$2:$C$104,MATCH($K33,Service_Providers!$A$2:$A$104,0))="","",INDEX(Service_Providers!$C$2:$C$104,MATCH($K33,Service_Providers!$A$2:$A$104,0)))&IF(AND(INDEX(Service_Providers!$C$2:$C$104,MATCH($K33,Service_Providers!$A$2:$A$104,0))<>"",INDEX(Service_Providers!$D$2:$D$104,MATCH($K33,Service_Providers!$A$2:$A$104,0))<>""),CHAR(10),"")&IF(INDEX(Service_Providers!$D$2:$D$104,MATCH($K33,Service_Providers!$A$2:$A$104,0))="","",INDEX(Service_Providers!$D$2:$D$104,MATCH($K33,Service_Providers!$A$2:$A$104,0))),"Provider not found")) -> 770-867-3111 service@espressosoutheast.com | N33: =IF($M33="","",IFERROR(IF(INDEX(Service_Providers!$C$2:$C$104,MATCH($M33,Service_Providers!$A$2:$A$104,0))="","",INDEX(Service_Providers!$C$2:$C$104,MATCH($M33,Service_Providers!$A$2:$A$104,0)))&IF(AND(INDEX(Service_Providers!$C$2:$C$104,MATCH($M33,Service_Providers!$A$2:$A$104,0))<>"",INDEX(Service_Providers!$D$2:$D$104,MATCH($M33,Service_Providers!$A$2:$A$104,0))<>""),CHAR(10),"")&IF(INDEX(Service_Providers!$D$2:$D$104,MATCH($M33,Service_Providers!$A$2:$A$104,0))="","",INDEX(Service_Providers!$D$2:$D$104,MATCH($M33,Service_Providers!$A$2:$A$104,0))),"Provider not found")) | O33: Georgia Area | P33: 2026-07-15
A34: Two Chicks And A Cup of Joe | B34: angelalonestarstucco@gmail.com | C34: Angela Morgan | D34: 9366621218 | E34: 130 Haley Ave | F34: Savannah | G34: GA | H34: 31409 | I34: ITCB Combo Brewer; G3 Retail Grinder; Eversys Cameo c'2s | J34: Lease; Loaned | K34: First Coast Espresso | L34: =IF($K34="","",IFERROR(IF(INDEX(Service_Providers!$C$2:$C$104,MATCH($K34,Service_Providers!$A$2:$A$104,0))="","",INDEX(Service_Providers!$C$2:$C$104,MATCH($K34,Service_Providers!$A$2:$A$104,0)))&IF(AND(INDEX(Service_Providers!$C$2:$C$104,MATCH($K34,Service_Providers!$A$2:$A$104,0))<>"",INDEX(Service_Providers!$D$2:$D$104,MATCH($K34,Service_Providers!$A$2:$A$104,0))<>""),CHAR(10),"")&IF(INDEX(Service_Providers!$D$2:$D$104,MATCH($K34,Service_Providers!$A$2:$A$104,0))="","",INDEX(Service_Providers!$D$2:$D$104,MATCH($K34,Service_Providers!$A$2:$A$104,0))),"Provider not found")) -> 904-654-5662 jose@firstcoastespresso.com | N34: =IF($M34="","",IFERROR(IF(INDEX(Service_Providers!$C$2:$C$104,MATCH($M34,Service_Providers!$A$2:$A$104,0))="","",INDEX(Service_Providers!$C$2:$C$104,MATCH($M34,Service_Providers!$A$2:$A$104,0)))&IF(AND(INDEX(Service_Providers!$C$2:$C$104,MATCH($M34,Service_Providers!$A$2:$A$104,0))<>"",INDEX(Service_Providers!$D$2:$D$104,MATCH($M34,Service_Providers!$A$2:$A$104,0))<>""),CHAR(10),"")&IF(INDEX(Service_Providers!$D$2:$D$104,MATCH($M34,Service_Providers!$A$2:$A$104,0))="","",INDEX(Service_Providers!$D$2:$D$104,MATCH($M34,Service_Providers!$A$2:$A$104,0))),"Provider not found")) | O34: Georgia Area | P34: 2026-07-15
A35: Steak 48 Chicago | B35: david@steak48.com | D35: 312.266.4848 | E35: 615 N Wabash Ave | F35: Chicago | G35: IL | H35: 60611 | I35: Cameo c'2s #1; Cameo c'2s #2; Wilbur Curtis TP2T19A3100 Coffee Brewer; Wilbur Curtis ILGD-10 | J35: Owned - Purchased from 3rd Party | K35: ETSC (EspressoTech Service Company) | L35: =IF($K35="","",IFERROR(IF(INDEX(Service_Providers!$C$2:$C$104,MATCH($K35,Service_Providers!$A$2:$A$104,0))="","",INDEX(Service_Providers!$C$2:$C$104,MATCH($K35,Service_Providers!$A$2:$A$104,0)))&IF(AND(INDEX(Service_Providers!$C$2:$C$104,MATCH($K35,Service_Providers!$A$2:$A$104,0))<>"",INDEX(Service_Providers!$D$2:$D$104,MATCH($K35,Service_Providers!$A$2:$A$104,0))<>""),CHAR(10),"")&IF(INDEX(Service_Providers!$D$2:$D$104,MATCH($K35,Service_Providers!$A$2:$A$104,0))="","",INDEX(Service_Providers!$D$2:$D$104,MATCH($K35,Service_Providers!$A$2:$A$104,0))),"Provider not found")) -> (888) 523-1684 service@etsc.coffee | N35: =IF($M35="","",IFERROR(IF(INDEX(Service_Providers!$C$2:$C$104,MATCH($M35,Service_Providers!$A$2:$A$104,0))="","",INDEX(Service_Providers!$C$2:$C$104,MATCH($M35,Service_Providers!$A$2:$A$104,0)))&IF(AND(INDEX(Service_Providers!$C$2:$C$104,MATCH($M35,Service_Providers!$A$2:$A$104,0))<>"",INDEX(Service_Providers!$D$2:$D$104,MATCH($M35,Service_Providers!$A$2:$A$104,0))<>""),CHAR(10),"")&IF(INDEX(Service_Providers!$D$2:$D$104,MATCH($M35,Service_Providers!$A$2:$A$104,0))="","",INDEX(Service_Providers!$D$2:$D$104,MATCH($M35,Service_Providers!$A$2:$A$104,0))),"Provider not found")) | O35: Illinois Area | P35: 2026-07-15
A36: Truluck's - Rosemont | B36: trulucks-rosemont@trulucks.com | D36: 312.982.0050 | E36: 9860 Berwyn Ave. | F36: Rosemont | G36: IL | H36: 60018 | I36: Bunn ITCB Combo Brewer #1; Cameo c'2s (Downstairs); Bunn ITCB Combo Brewer #2; Bunn H5X Hot Water Tower 1; Bunn H5X Hot Water Tower 2 (+3 more) | J36: Lease; Loaned | K36: ETSC (EspressoTech Service Company) | L36: =IF($K36="","",IFERROR(IF(INDEX(Service_Providers!$C$2:$C$104,MATCH($K36,Service_Providers!$A$2:$A$104,0))="","",INDEX(Service_Providers!$C$2:$C$104,MATCH($K36,Service_Providers!$A$2:$A$104,0)))&IF(AND(INDEX(Service_Providers!$C$2:$C$104,MATCH($K36,Service_Providers!$A$2:$A$104,0))<>"",INDEX(Service_Providers!$D$2:$D$104,MATCH($K36,Service_Providers!$A$2:$A$104,0))<>""),CHAR(10),"")&IF(INDEX(Service_Providers!$D$2:$D$104,MATCH($K36,Service_Providers!$A$2:$A$104,0))="","",INDEX(Service_Providers!$D$2:$D$104,MATCH($K36,Service_Providers!$A$2:$A$104,0))),"Provider not found")) -> (888) 523-1684 service@etsc.coffee | N36: =IF($M36="","",IFERROR(IF(INDEX(Service_Providers!$C$2:$C$104,MATCH($M36,Service_Providers!$A$2:$A$104,0))="","",INDEX(Service_Providers!$C$2:$C$104,MATCH($M36,Service_Providers!$A$2:$A$104,0)))&IF(AND(INDEX(Service_Providers!$C$2:$C$104,MATCH($M36,Service_Providers!$A$2:$A$104,0))<>"",INDEX(Service_Providers!$D$2:$D$104,MATCH($M36,Service_Providers!$A$2:$A$104,0))<>""),CHAR(10),"")&IF(INDEX(Service_Providers!$D$2:$D$104,MATCH($M36,Service_Providers!$A$2:$A$104,0))="","",INDEX(Service_Providers!$D$2:$D$104,MATCH($M36,Service_Providers!$A$2:$A$104,0))),"Provider not found")) | O36: Illinois Area | P36: 2026-07-15
A37: Kol Fac #020 - Castleton, IN | B37: alicia@kolfac.com | C37: Jason Lineberry | D37: 317.842.7200 | E37: 9650 Allisonville Rd. | F37: Indianapolis | G37: IN | H37: 46250 | I37: Bunn ITCB Combo Brewer (NS) | J37: Loaned | K37: Espresso Enterprises | L37: =IF($K37="","",IFERROR(IF(INDEX(Service_Providers!$C$2:$C$104,MATCH($K37,Service_Providers!$A$2:$A$104,0))="","",INDEX(Service_Providers!$C$2:$C$104,MATCH($K37,Service_Providers!$A$2:$A$104,0)))&IF(AND(INDEX(Service_Providers!$C$2:$C$104,MATCH($K37,Service_Providers!$A$2:$A$104,0))<>"",INDEX(Service_Providers!$D$2:$D$104,MATCH($K37,Service_Providers!$A$2:$A$104,0))<>""),CHAR(10),"")&IF(INDEX(Service_Providers!$D$2:$D$104,MATCH($K37,Service_Providers!$A$2:$A$104,0))="","",INDEX(Service_Providers!$D$2:$D$104,MATCH($K37,Service_Providers!$A$2:$A$104,0))),"Provider not found")) -> 317-876-9031 carey@espressoenterprises.com | N37: =IF($M37="","",IFERROR(IF(INDEX(Service_Providers!$C$2:$C$104,MATCH($M37,Service_Providers!$A$2:$A$104,0))="","",INDEX(Service_Providers!$C$2:$C$104,MATCH($M37,Service_Providers!$A$2:$A$104,0)))&IF(AND(INDEX(Service_Providers!$C$2:$C$104,MATCH($M37,Service_Providers!$A$2:$A$104,0))<>"",INDEX(Service_Providers!$D$2:$D$104,MATCH($M37,Service_Providers!$A$2:$A$104,0))<>""),CHAR(10),"")&IF(INDEX(Service_Providers!$D$2:$D$104,MATCH($M37,Service_Providers!$A$2:$A$104,0))="","",INDEX(Service_Providers!$D$2:$D$104,MATCH($M37,Service_Providers!$A$2:$A$104,0))),"Provider not found")) | O37: Indiana Area | P37: 2026-07-15
A38: Kol Fac #074C - Carmel, IN | B38: alicia@kolfac.com | C38: Tyler Johnson | D38: 317.816.2253 | E38: DELIVER BEFORE 2 | F38: Carmel | G38: IN | H38: 46032 | I38: Cameo c'2s; Bunn ITCB Combo Brewer (NS) | J38: Loaned; Owned | K38: Espresso Enterprises | L38: =IF($K38="","",IFERROR(IF(INDEX(Service_Providers!$C$2:$C$104,MATCH($K38,Service_Providers!$A$2:$A$104,0))="","",INDEX(Service_Providers!$C$2:$C$104,MATCH($K38,Service_Providers!$A$2:$A$104,0)))&IF(AND(INDEX(Service_Providers!$C$2:$C$104,MATCH($K38,Service_Providers!$A$2:$A$104,0))<>"",INDEX(Service_Providers!$D$2:$D$104,MATCH($K38,Service_Providers!$A$2:$A$104,0))<>""),CHAR(10),"")&IF(INDEX(Service_Providers!$D$2:$D$104,MATCH($K38,Service_Providers!$A$2:$A$104,0))="","",INDEX(Service_Providers!$D$2:$D$104,MATCH($K38,Service_Providers!$A$2:$A$104,0))),"Provider not found")) -> 317-876-9031 carey@espressoenterprises.com | N38: =IF($M38="","",IFERROR(IF(INDEX(Service_Providers!$C$2:$C$104,MATCH($M38,Service_Providers!$A$2:$A$104,0))="","",INDEX(Service_Providers!$C$2:$C$104,MATCH($M38,Service_Providers!$A$2:$A$104,0)))&IF(AND(INDEX(Service_Providers!$C$2:$C$104,MATCH($M38,Service_Providers!$A$2:$A$104,0))<>"",INDEX(Service_Providers!$D$2:$D$104,MATCH($M38,Service_Providers!$A$2:$A$104,0))<>""),CHAR(10),"")&IF(INDEX(Service_Providers!$D$2:$D$104,MATCH($M38,Service_Providers!$A$2:$A$104,0))="","",INDEX(Service_Providers!$D$2:$D$104,MATCH($M38,Service_Providers!$A$2:$A$104,0))),"Provider not found")) | O38: Indiana Area | P38: 2026-07-15
A39: Kol Fac #107F - Carmel, IN | B39: Lanhaywood@kolfac.com | C39: Lan Haywood | D39: 317.983.3048 | E39: 10460 North Michigan Rd., Suite 110 | F39: Carmel | G39: IN | H39: 46032 | I39: Bunn Axiom-APS | J39: Loaned | K39: ETSC (EspressoTech Service Company) | L39: =IF($K39="","",IFERROR(IF(INDEX(Service_Providers!$C$2:$C$104,MATCH($K39,Service_Providers!$A$2:$A$104,0))="","",INDEX(Service_Providers!$C$2:$C$104,MATCH($K39,Service_Providers!$A$2:$A$104,0)))&IF(AND(INDEX(Service_Providers!$C$2:$C$104,MATCH($K39,Service_Providers!$A$2:$A$104,0))<>"",INDEX(Service_Providers!$D$2:$D$104,MATCH($K39,Service_Providers!$A$2:$A$104,0))<>""),CHAR(10),"")&IF(INDEX(Service_Providers!$D$2:$D$104,MATCH($K39,Service_Providers!$A$2:$A$104,0))="","",INDEX(Service_Providers!$D$2:$D$104,MATCH($K39,Service_Providers!$A$2:$A$104,0))),"Provider not found")) -> (888) 523-1684 service@etsc.coffee | M39: Espresso Enterprises | N39: =IF($M39="","",IFERROR(IF(INDEX(Service_Providers!$C$2:$C$104,MATCH($M39,Service_Providers!$A$2:$A$104,0))="","",INDEX(Service_Providers!$C$2:$C$104,MATCH($M39,Service_Providers!$A$2:$A$104,0)))&IF(AND(INDEX(Service_Providers!$C$2:$C$104,MATCH($M39,Service_Providers!$A$2:$A$104,0))<>"",INDEX(Service_Providers!$D$2:$D$104,MATCH($M39,Service_Providers!$A$2:$A$104,0))<>""),CHAR(10),"")&IF(INDEX(Service_Providers!$D$2:$D$104,MATCH($M39,Service_Providers!$A$2:$A$104,0))="","",INDEX(Service_Providers!$D$2:$D$104,MATCH($M39,Service_Providers!$A$2:$A$104,0))),"Provider not found")) -> 317-876-9031 carey@espressoenterprises.com | O39: Indiana Area | P39: 2026-07-15
A40: Twin Peaks- Greenwood, IN | B40: accounting@avalanchefoodgroup.com | C40: EMILIO GONZALES | D40: 317-743-0038 | E40: 600 Greenwood Park Dr N | F40: Greenwood | G40: IN | H40: 46142 | I40: ITCB Combo Brewer (Expo Line Kitchen); ITCB Combo Brewer | J40: Loaned | K40: Espresso Enterprises | L40: =IF($K40="","",IFERROR(IF(INDEX(Service_Providers!$C$2:$C$104,MATCH($K40,Service_Providers!$A$2:$A$104,0))="","",INDEX(Service_Providers!$C$2:$C$104,MATCH($K40,Service_Providers!$A$2:$A$104,0)))&IF(AND(INDEX(Service_Providers!$C$2:$C$104,MATCH($K40,Service_Providers!$A$2:$A$104,0))<>"",INDEX(Service_Providers!$D$2:$D$104,MATCH($K40,Service_Providers!$A$2:$A$104,0))<>""),CHAR(10),"")&IF(INDEX(Service_Providers!$D$2:$D$104,MATCH($K40,Service_Providers!$A$2:$A$104,0))="","",INDEX(Service_Providers!$D$2:$D$104,MATCH($K40,Service_Providers!$A$2:$A$104,0))),"Provider not found")) -> 317-876-9031 carey@espressoenterprises.com | N40: =IF($M40="","",IFERROR(IF(INDEX(Service_Providers!$C$2:$C$104,MATCH($M40,Service_Providers!$A$2:$A$104,0))="","",INDEX(Service_Providers!$C$2:$C$104,MATCH($M40,Service_Providers!$A$2:$A$104,0)))&IF(AND(INDEX(Service_Providers!$C$2:$C$104,MATCH($M40,Service_Providers!$A$2:$A$104,0))<>"",INDEX(Service_Providers!$D$2:$D$104,MATCH($M40,Service_Providers!$A$2:$A$104,0))<>""),CHAR(10),"")&IF(INDEX(Service_Providers!$D$2:$D$104,MATCH($M40,Service_Providers!$A$2:$A$104,0))="","",INDEX(Service_Providers!$D$2:$D$104,MATCH($M40,Service_Providers!$A$2:$A$104,0))),"Provider not found")) | O40: Indiana Area | P40: 2026-07-15
A41: Twin Peaks- Indianapolis, IN | B41: accounting@avalanchefoodgroup.com | C41: CHRIS DINGES | D41: 317-913-0992 | E41: 6880 East 82nd Street | F41: Indianapolis | G41: IN | H41: 46250 | I41: ITCB Combo Brewer #1; ITCB Combo Brewer #2 | J41: Loaned | K41: ETSC (EspressoTech Service Company) | L41: =IF($K41="","",IFERROR(IF(INDEX(Service_Providers!$C$2:$C$104,MATCH($K41,Service_Providers!$A$2:$A$104,0))="","",INDEX(Service_Providers!$C$2:$C$104,MATCH($K41,Service_Providers!$A$2:$A$104,0)))&IF(AND(INDEX(Service_Providers!$C$2:$C$104,MATCH($K41,Service_Providers!$A$2:$A$104,0))<>"",INDEX(Service_Providers!$D$2:$D$104,MATCH($K41,Service_Providers!$A$2:$A$104,0))<>""),CHAR(10),"")&IF(INDEX(Service_Providers!$D$2:$D$104,MATCH($K41,Service_Providers!$A$2:$A$104,0))="","",INDEX(Service_Providers!$D$2:$D$104,MATCH($K41,Service_Providers!$A$2:$A$104,0))),"Provider not found")) -> (888) 523-1684 service@etsc.coffee | N41: =IF($M41="","",IFERROR(IF(INDEX(Service_Providers!$C$2:$C$104,MATCH($M41,Service_Providers!$A$2:$A$104,0))="","",INDEX(Service_Providers!$C$2:$C$104,MATCH($M41,Service_Providers!$A$2:$A$104,0)))&IF(AND(INDEX(Service_Providers!$C$2:$C$104,MATCH($M41,Service_Providers!$A$2:$A$104,0))<>"",INDEX(Service_Providers!$D$2:$D$104,MATCH($M41,Service_Providers!$A$2:$A$104,0))<>""),CHAR(10),"")&IF(INDEX(Service_Providers!$D$2:$D$104,MATCH($M41,Service_Providers!$A$2:$A$104,0))="","",INDEX(Service_Providers!$D$2:$D$104,MATCH($M41,Service_Providers!$A$2:$A$104,0))),"Provider not found")) | O41: Indiana Area | P41: 2026-07-15
A42: Kol Fac #037F - Deer Creek, KS | B42: Alicia@kolfac.com | C42: Gary | D42: 620.340.0785 | E42: 7112 W. 135th St. | F42: Overland Park | G42: KS | H42: 66223 | I42: Bunn Axiom-APS; Bunn ITCB Combo Brewer (NS) | J42: Loaned | K42: Espresso Enterprises | L42: =IF($K42="","",IFERROR(IF(INDEX(Service_Providers!$C$2:$C$104,MATCH($K42,Service_Providers!$A$2:$A$104,0))="","",INDEX(Service_Providers!$C$2:$C$104,MATCH($K42,Service_Providers!$A$2:$A$104,0)))&IF(AND(INDEX(Service_Providers!$C$2:$C$104,MATCH($K42,Service_Providers!$A$2:$A$104,0))<>"",INDEX(Service_Providers!$D$2:$D$104,MATCH($K42,Service_Providers!$A$2:$A$104,0))<>""),CHAR(10),"")&IF(INDEX(Service_Providers!$D$2:$D$104,MATCH($K42,Service_Providers!$A$2:$A$104,0))="","",INDEX(Service_Providers!$D$2:$D$104,MATCH($K42,Service_Providers!$A$2:$A$104,0))),"Provider not found")) -> 317-876-9031 carey@espressoenterprises.com | N42: =IF($M42="","",IFERROR(IF(INDEX(Service_Providers!$C$2:$C$104,MATCH($M42,Service_Providers!$A$2:$A$104,0))="","",INDEX(Service_Providers!$C$2:$C$104,MATCH($M42,Service_Providers!$A$2:$A$104,0)))&IF(AND(INDEX(Service_Providers!$C$2:$C$104,MATCH($M42,Service_Providers!$A$2:$A$104,0))<>"",INDEX(Service_Providers!$D$2:$D$104,MATCH($M42,Service_Providers!$A$2:$A$104,0))<>""),CHAR(10),"")&IF(INDEX(Service_Providers!$D$2:$D$104,MATCH($M42,Service_Providers!$A$2:$A$104,0))="","",INDEX(Service_Providers!$D$2:$D$104,MATCH($M42,Service_Providers!$A$2:$A$104,0))),"Provider not found")) | O42: Kansas Area | P42: 2026-07-15
A43: Kol Fac #087C - Shawnee, KS | B43: alicia@kolfac.com | C43: Gary Goyer | D43: 913-631-6000 | E43: 13103 Shawnee Mission Pkwy | F43: Shawnee | G43: KS | H43: 66216 | I43: Eversys Cameo c'2s; Bunn ITCB Combo Brewer | J43: Loaned; Owned - Purchased from Katz | K43: Espresso Enterprises | L43: =IF($K43="","",IFERROR(IF(INDEX(Service_Providers!$C$2:$C$104,MATCH($K43,Service_Providers!$A$2:$A$104,0))="","",INDEX(Service_Providers!$C$2:$C$104,MATCH($K43,Service_Providers!$A$2:$A$104,0)))&IF(AND(INDEX(Service_Providers!$C$2:$C$104,MATCH($K43,Service_Providers!$A$2:$A$104,0))<>"",INDEX(Service_Providers!$D$2:$D$104,MATCH($K43,Service_Providers!$A$2:$A$104,0))<>""),CHAR(10),"")&IF(INDEX(Service_Providers!$D$2:$D$104,MATCH($K43,Service_Providers!$A$2:$A$104,0))="","",INDEX(Service_Providers!$D$2:$D$104,MATCH($K43,Service_Providers!$A$2:$A$104,0))),"Provider not found")) -> 317-876-9031 carey@espressoenterprises.com | N43: =IF($M43="","",IFERROR(IF(INDEX(Service_Providers!$C$2:$C$104,MATCH($M43,Service_Providers!$A$2:$A$104,0))="","",INDEX(Service_Providers!$C$2:$C$104,MATCH($M43,Service_Providers!$A$2:$A$104,0)))&IF(AND(INDEX(Service_Providers!$C$2:$C$104,MATCH($M43,Service_Providers!$A$2:$A$104,0))<>"",INDEX(Service_Providers!$D$2:$D$104,MATCH($M43,Service_Providers!$A$2:$A$104,0))<>""),CHAR(10),"")&IF(INDEX(Service_Providers!$D$2:$D$104,MATCH($M43,Service_Providers!$A$2:$A$104,0))="","",INDEX(Service_Providers!$D$2:$D$104,MATCH($M43,Service_Providers!$A$2:$A$104,0))),"Provider not found")) | O43: Kansas Area | P43: 2026-07-15
A44: Coffee 30 - Ryan St. | B44: purchasing@coffee30co.com | C44: Taylor Smith | D44: 337.309.0584 | E44: 3420 Ryan St. | F44: Lake Charles | G44: LA | H44: 70605 | I44: Enigma e'4s Super Traditional | J44: Lease | K44: Katz Coffee | L44: =IF($K44="","",IFERROR(IF(INDEX(Service_Providers!$C$2:$C$104,MATCH($K44,Service_Providers!$A$2:$A$104,0))="","",INDEX(Service_Providers!$C$2:$C$104,MATCH($K44,Service_Providers!$A$2:$A$104,0)))&IF(AND(INDEX(Service_Providers!$C$2:$C$104,MATCH($K44,Service_Providers!$A$2:$A$104,0))<>"",INDEX(Service_Providers!$D$2:$D$104,MATCH($K44,Service_Providers!$A$2:$A$104,0))<>""),CHAR(10),"")&IF(INDEX(Service_Providers!$D$2:$D$104,MATCH($K44,Service_Providers!$A$2:$A$104,0))="","",INDEX(Service_Providers!$D$2:$D$104,MATCH($K44,Service_Providers!$A$2:$A$104,0))),"Provider not found")) -> 713.864.3338 service@katzcoffee.com | N44: =IF($M44="","",IFERROR(IF(INDEX(Service_Providers!$C$2:$C$104,MATCH($M44,Service_Providers!$A$2:$A$104,0))="","",INDEX(Service_Providers!$C$2:$C$104,MATCH($M44,Service_Providers!$A$2:$A$104,0)))&IF(AND(INDEX(Service_Providers!$C$2:$C$104,MATCH($M44,Service_Providers!$A$2:$A$104,0))<>"",INDEX(Service_Providers!$D$2:$D$104,MATCH($M44,Service_Providers!$A$2:$A$104,0))<>""),CHAR(10),"")&IF(INDEX(Service_Providers!$D$2:$D$104,MATCH($M44,Service_Providers!$A$2:$A$104,0))="","",INDEX(Service_Providers!$D$2:$D$104,MATCH($M44,Service_Providers!$A$2:$A$104,0))),"Provider not found")) | O44: Lousiana Area | P44: 2026-07-15
A45: Doris Metropolitan - New Orleans | B45: admin@dorismet.com | C45: Chris Dulaney | D45: 504.267.3500 | E45: 620 Chartres St. | F45: New Orleans | G45: LA | H45: 70130 | I45: Faema X20 | J45: Loaned | K45: Orleans Coffee / Perfect Shot Espresso Service | L45: =IF($K45="","",IFERROR(IF(INDEX(Service_Providers!$C$2:$C$104,MATCH($K45,Service_Providers!$A$2:$A$104,0))="","",INDEX(Service_Providers!$C$2:$C$104,MATCH($K45,Service_Providers!$A$2:$A$104,0)))&IF(AND(INDEX(Service_Providers!$C$2:$C$104,MATCH($K45,Service_Providers!$A$2:$A$104,0))<>"",INDEX(Service_Providers!$D$2:$D$104,MATCH($K45,Service_Providers!$A$2:$A$104,0))<>""),CHAR(10),"")&IF(INDEX(Service_Providers!$D$2:$D$104,MATCH($K45,Service_Providers!$A$2:$A$104,0))="","",INDEX(Service_Providers!$D$2:$D$104,MATCH($K45,Service_Providers!$A$2:$A$104,0))),"Provider not found")) -> 504-827-0878 (Office) robbie@orleanscoffee.com | N45: =IF($M45="","",IFERROR(IF(INDEX(Service_Providers!$C$2:$C$104,MATCH($M45,Service_Providers!$A$2:$A$104,0))="","",INDEX(Service_Providers!$C$2:$C$104,MATCH($M45,Service_Providers!$A$2:$A$104,0)))&IF(AND(INDEX(Service_Providers!$C$2:$C$104,MATCH($M45,Service_Providers!$A$2:$A$104,0))<>"",INDEX(Service_Providers!$D$2:$D$104,MATCH($M45,Service_Providers!$A$2:$A$104,0))<>""),CHAR(10),"")&IF(INDEX(Service_Providers!$D$2:$D$104,MATCH($M45,Service_Providers!$A$2:$A$104,0))="","",INDEX(Service_Providers!$D$2:$D$104,MATCH($M45,Service_Providers!$A$2:$A$104,0))),"Provider not found")) | O45: Lousiana Area | P45: 2026-07-15
A46: Southlake Theater | B46: finance@porcheinc.com | C46: Jacob Ryan Porche | D46: 337-426-1794 | E46: 4720 Nelson Rd Suite #100 | F46: Lake Charles | G46: LA | H46: 70605 | I46: Eversys e'4s ST; 1152 V+ Coffee Brewer; BWS100/10; GR2.3 Dual Portion Grinder; G3 (Flavor) (+1 more) | J46: Lease; Owned - Purchased from Katz | K46: Katz Coffee | L46: =IF($K46="","",IFERROR(IF(INDEX(Service_Providers!$C$2:$C$104,MATCH($K46,Service_Providers!$A$2:$A$104,0))="","",INDEX(Service_Providers!$C$2:$C$104,MATCH($K46,Service_Providers!$A$2:$A$104,0)))&IF(AND(INDEX(Service_Providers!$C$2:$C$104,MATCH($K46,Service_Providers!$A$2:$A$104,0))<>"",INDEX(Service_Providers!$D$2:$D$104,MATCH($K46,Service_Providers!$A$2:$A$104,0))<>""),CHAR(10),"")&IF(INDEX(Service_Providers!$D$2:$D$104,MATCH($K46,Service_Providers!$A$2:$A$104,0))="","",INDEX(Service_Providers!$D$2:$D$104,MATCH($K46,Service_Providers!$A$2:$A$104,0))),"Provider not found")) -> 713.864.3338 service@katzcoffee.com | N46: =IF($M46="","",IFERROR(IF(INDEX(Service_Providers!$C$2:$C$104,MATCH($M46,Service_Providers!$A$2:$A$104,0))="","",INDEX(Service_Providers!$C$2:$C$104,MATCH($M46,Service_Providers!$A$2:$A$104,0)))&IF(AND(INDEX(Service_Providers!$C$2:$C$104,MATCH($M46,Service_Providers!$A$2:$A$104,0))<>"",INDEX(Service_Providers!$D$2:$D$104,MATCH($M46,Service_Providers!$A$2:$A$104,0))<>""),CHAR(10),"")&IF(INDEX(Service_Providers!$D$2:$D$104,MATCH($M46,Service_Providers!$A$2:$A$104,0))="","",INDEX(Service_Providers!$D$2:$D$104,MATCH($M46,Service_Providers!$A$2:$A$104,0))),"Provider not found")) | O46: Lousiana Area | P46: 2026-07-15
A47: Hawkers - Bethesda, MD | B47: DSELLERS@EATHAWKERS.COM | C47: Jeremy George | D47: 240.203.8135 | E47: 7117 Bethesda Lane | F47: Bethesda | G47: MD | H47: 20814 | I47: Bunn ITB Tea Brewer | J47: Loaned | L47: =IF($K47="","",IFERROR(IF(INDEX(Service_Providers!$C$2:$C$104,MATCH($K47,Service_Providers!$A$2:$A$104,0))="","",INDEX(Service_Providers!$C$2:$C$104,MATCH($K47,Service_Providers!$A$2:$A$104,0)))&IF(AND(INDEX(Service_Providers!$C$2:$C$104,MATCH($K47,Service_Providers!$A$2:$A$104,0))<>"",INDEX(Service_Providers!$D$2:$D$104,MATCH($K47,Service_Providers!$A$2:$A$104,0))<>""),CHAR(10),"")&IF(INDEX(Service_Providers!$D$2:$D$104,MATCH($K47,Service_Providers!$A$2:$A$104,0))="","",INDEX(Service_Providers!$D$2:$D$104,MATCH($K47,Service_Providers!$A$2:$A$104,0))),"Provider not found")) | N47: =IF($M47="","",IFERROR(IF(INDEX(Service_Providers!$C$2:$C$104,MATCH($M47,Service_Providers!$A$2:$A$104,0))="","",INDEX(Service_Providers!$C$2:$C$104,MATCH($M47,Service_Providers!$A$2:$A$104,0)))&IF(AND(INDEX(Service_Providers!$C$2:$C$104,MATCH($M47,Service_Providers!$A$2:$A$104,0))<>"",INDEX(Service_Providers!$D$2:$D$104,MATCH($M47,Service_Providers!$A$2:$A$104,0))<>""),CHAR(10),"")&IF(INDEX(Service_Providers!$D$2:$D$104,MATCH($M47,Service_Providers!$A$2:$A$104,0))="","",INDEX(Service_Providers!$D$2:$D$104,MATCH($M47,Service_Providers!$A$2:$A$104,0))),"Provider not found")) | O47: Maryland Area | P47: 2026-07-15
A48: Kol Fac #021F - Brentwood, MO | B48: jsmith@kolfac.com | D48: 314.968.2253 | E48: 2604 S. Brentwood | F48: Brentwood | G48: MO | H48: 63144 | I48: Bunn ITCB Combo Brewer (NS) | J48: Loaned | K48: ETSC (EspressoTech Service Company) | L48: =IF($K48="","",IFERROR(IF(INDEX(Service_Providers!$C$2:$C$104,MATCH($K48,Service_Providers!$A$2:$A$104,0))="","",INDEX(Service_Providers!$C$2:$C$104,MATCH($K48,Service_Providers!$A$2:$A$104,0)))&IF(AND(INDEX(Service_Providers!$C$2:$C$104,MATCH($K48,Service_Providers!$A$2:$A$104,0))<>"",INDEX(Service_Providers!$D$2:$D$104,MATCH($K48,Service_Providers!$A$2:$A$104,0))<>""),CHAR(10),"")&IF(INDEX(Service_Providers!$D$2:$D$104,MATCH($K48,Service_Providers!$A$2:$A$104,0))="","",INDEX(Service_Providers!$D$2:$D$104,MATCH($K48,Service_Providers!$A$2:$A$104,0))),"Provider not found")) -> (888) 523-1684 service@etsc.coffee | M48: Ultimate Espresso Services | N48: =IF($M48="","",IFERROR(IF(INDEX(Service_Providers!$C$2:$C$104,MATCH($M48,Service_Providers!$A$2:$A$104,0))="","",INDEX(Service_Providers!$C$2:$C$104,MATCH($M48,Service_Providers!$A$2:$A$104,0)))&IF(AND(INDEX(Service_Providers!$C$2:$C$104,MATCH($M48,Service_Providers!$A$2:$A$104,0))<>"",INDEX(Service_Providers!$D$2:$D$104,MATCH($M48,Service_Providers!$A$2:$A$104,0))<>""),CHAR(10),"")&IF(INDEX(Service_Providers!$D$2:$D$104,MATCH($M48,Service_Providers!$A$2:$A$104,0))="","",INDEX(Service_Providers!$D$2:$D$104,MATCH($M48,Service_Providers!$A$2:$A$104,0))),"Provider not found")) -> 314.541.5256 ultimateespressoservices@gmail.com | O48: Missouri Area | P48: 2026-07-15
A49: Porsche Chesterfield | B49: STLvendors@porschestlouis.com | E49: 17455 N OUTER 40 RD | F49: CHESTERFIELD | G49: MO | H49: 63005 | I49: La Marzocco Linea PB 2AV; La Marzocco Swift Grinder; Everpure BWS100/10 | J49: Owned - Purchased from Katz | K49: Ultimate Espresso Services | L49: =IF($K49="","",IFERROR(IF(INDEX(Service_Providers!$C$2:$C$104,MATCH($K49,Service_Providers!$A$2:$A$104,0))="","",INDEX(Service_Providers!$C$2:$C$104,MATCH($K49,Service_Providers!$A$2:$A$104,0)))&IF(AND(INDEX(Service_Providers!$C$2:$C$104,MATCH($K49,Service_Providers!$A$2:$A$104,0))<>"",INDEX(Service_Providers!$D$2:$D$104,MATCH($K49,Service_Providers!$A$2:$A$104,0))<>""),CHAR(10),"")&IF(INDEX(Service_Providers!$D$2:$D$104,MATCH($K49,Service_Providers!$A$2:$A$104,0))="","",INDEX(Service_Providers!$D$2:$D$104,MATCH($K49,Service_Providers!$A$2:$A$104,0))),"Provider not found")) -> 314.541.5256 ultimateespressoservices@gmail.com | M49: ETSC (EspressoTech Service Company) | N49: =IF($M49="","",IFERROR(IF(INDEX(Service_Providers!$C$2:$C$104,MATCH($M49,Service_Providers!$A$2:$A$104,0))="","",INDEX(Service_Providers!$C$2:$C$104,MATCH($M49,Service_Providers!$A$2:$A$104,0)))&IF(AND(INDEX(Service_Providers!$C$2:$C$104,MATCH($M49,Service_Providers!$A$2:$A$104,0))<>"",INDEX(Service_Providers!$D$2:$D$104,MATCH($M49,Service_Providers!$A$2:$A$104,0))<>""),CHAR(10),"")&IF(INDEX(Service_Providers!$D$2:$D$104,MATCH($M49,Service_Providers!$A$2:$A$104,0))="","",INDEX(Service_Providers!$D$2:$D$104,MATCH($M49,Service_Providers!$A$2:$A$104,0))),"Provider not found")) -> (888) 523-1684 service@etsc.coffee | O49: Missouri Area | P49: 2026-07-15
A50: GM Performance Power Units | B50: accountspayable@gmppu.com | D50: 845-206-2949 | E50: 4540 Fortune Ave NW | F50: Concord | G50: NC | H50: 28027 | I50: Bunn Sure Immersion 312; Bunn Axiom-APS Brewer | J50: Loaned | K50: Carolina Beverage Solutions | L50: =IF($K50="","",IFERROR(IF(INDEX(Service_Providers!$C$2:$C$104,MATCH($K50,Service_Providers!$A$2:$A$104,0))="","",INDEX(Service_Providers!$C$2:$C$104,MATCH($K50,Service_Providers!$A$2:$A$104,0)))&IF(AND(INDEX(Service_Providers!$C$2:$C$104,MATCH($K50,Service_Providers!$A$2:$A$104,0))<>"",INDEX(Service_Providers!$D$2:$D$104,MATCH($K50,Service_Providers!$A$2:$A$104,0))<>""),CHAR(10),"")&IF(INDEX(Service_Providers!$D$2:$D$104,MATCH($K50,Service_Providers!$A$2:$A$104,0))="","",INDEX(Service_Providers!$D$2:$D$104,MATCH($K50,Service_Providers!$A$2:$A$104,0))),"Provider not found")) -> 803-280-5234 chris.powers@hotmail.com | N50: =IF($M50="","",IFERROR(IF(INDEX(Service_Providers!$C$2:$C$104,MATCH($M50,Service_Providers!$A$2:$A$104,0))="","",INDEX(Service_Providers!$C$2:$C$104,MATCH($M50,Service_Providers!$A$2:$A$104,0)))&IF(AND(INDEX(Service_Providers!$C$2:$C$104,MATCH($M50,Service_Providers!$A$2:$A$104,0))<>"",INDEX(Service_Providers!$D$2:$D$104,MATCH($M50,Service_Providers!$A$2:$A$104,0))<>""),CHAR(10),"")&IF(INDEX(Service_Providers!$D$2:$D$104,MATCH($M50,Service_Providers!$A$2:$A$104,0))="","",INDEX(Service_Providers!$D$2:$D$104,MATCH($M50,Service_Providers!$A$2:$A$104,0))),"Provider not found")) | O50: North and South Carolina Area | P50: 2026-07-15
A51: Hawkers - Chapel Hill, NC | B51: eathawkers@documents.restaurant365.com | C51: Rob Walker | D51: 407.255.2200 | E51: 201 S. Estes Drive, Suite 400A | F51: Chapel Hill | G51: NC | H51: 27514 | I51: Bunn ITB Tea Brewer | J51: Loaned | K51: Carolina Beverage Solutions | L51: =IF($K51="","",IFERROR(IF(INDEX(Service_Providers!$C$2:$C$104,MATCH($K51,Service_Providers!$A$2:$A$104,0))="","",INDEX(Service_Providers!$C$2:$C$104,MATCH($K51,Service_Providers!$A$2:$A$104,0)))&IF(AND(INDEX(Service_Providers!$C$2:$C$104,MATCH($K51,Service_Providers!$A$2:$A$104,0))<>"",INDEX(Service_Providers!$D$2:$D$104,MATCH($K51,Service_Providers!$A$2:$A$104,0))<>""),CHAR(10),"")&IF(INDEX(Service_Providers!$D$2:$D$104,MATCH($K51,Service_Providers!$A$2:$A$104,0))="","",INDEX(Service_Providers!$D$2:$D$104,MATCH($K51,Service_Providers!$A$2:$A$104,0))),"Provider not found")) -> 803-280-5234 chris.powers@hotmail.com | N51: =IF($M51="","",IFERROR(IF(INDEX(Service_Providers!$C$2:$C$104,MATCH($M51,Service_Providers!$A$2:$A$104,0))="","",INDEX(Service_Providers!$C$2:$C$104,MATCH($M51,Service_Providers!$A$2:$A$104,0)))&IF(AND(INDEX(Service_Providers!$C$2:$C$104,MATCH($M51,Service_Providers!$A$2:$A$104,0))<>"",INDEX(Service_Providers!$D$2:$D$104,MATCH($M51,Service_Providers!$A$2:$A$104,0))<>""),CHAR(10),"")&IF(INDEX(Service_Providers!$D$2:$D$104,MATCH($M51,Service_Providers!$A$2:$A$104,0))="","",INDEX(Service_Providers!$D$2:$D$104,MATCH($M51,Service_Providers!$A$2:$A$104,0))),"Provider not found")) | O51: North and South Carolina Area | P51: 2026-07-15
A52: Hawkers - Charlotte, NC | B52: eathawkers@documents.restaurant365.com | C52: Robert Field | D52: (704) 464-0770 | E52: 1930 Camden Rd., Suite 260 | F52: Charlotte | G52: NC | H52: 28203 | I52: Bunn ITB Tea Brewer | J52: Loaned | K52: Carolina Beverage Solutions | L52: =IF($K52="","",IFERROR(IF(INDEX(Service_Providers!$C$2:$C$104,MATCH($K52,Service_Providers!$A$2:$A$104,0))="","",INDEX(Service_Providers!$C$2:$C$104,MATCH($K52,Service_Providers!$A$2:$A$104,0)))&IF(AND(INDEX(Service_Providers!$C$2:$C$104,MATCH($K52,Service_Providers!$A$2:$A$104,0))<>"",INDEX(Service_Providers!$D$2:$D$104,MATCH($K52,Service_Providers!$A$2:$A$104,0))<>""),CHAR(10),"")&IF(INDEX(Service_Providers!$D$2:$D$104,MATCH($K52,Service_Providers!$A$2:$A$104,0))="","",INDEX(Service_Providers!$D$2:$D$104,MATCH($K52,Service_Providers!$A$2:$A$104,0))),"Provider not found")) -> 803-280-5234 chris.powers@hotmail.com | N52: =IF($M52="","",IFERROR(IF(INDEX(Service_Providers!$C$2:$C$104,MATCH($M52,Service_Providers!$A$2:$A$104,0))="","",INDEX(Service_Providers!$C$2:$C$104,MATCH($M52,Service_Providers!$A$2:$A$104,0)))&IF(AND(INDEX(Service_Providers!$C$2:$C$104,MATCH($M52,Service_Providers!$A$2:$A$104,0))<>"",INDEX(Service_Providers!$D$2:$D$104,MATCH($M52,Service_Providers!$A$2:$A$104,0))<>""),CHAR(10),"")&IF(INDEX(Service_Providers!$D$2:$D$104,MATCH($M52,Service_Providers!$A$2:$A$104,0))="","",INDEX(Service_Providers!$D$2:$D$104,MATCH($M52,Service_Providers!$A$2:$A$104,0))),"Provider not found")) | O52: North and South Carolina Area | P52: 2026-07-15
A53: Spire Motorsports | B53: rachael@katzcoffee.com | C53: Paul Horner | D53: 704.662.0000 | E53: 351 Mazeppa Rd. | F53: Mooresville | G53: NC | H53: 28115 | I53: Bunn Axiom-APS (Break Room); Bunn Axiom-APS (Conference Room); Bunn Axiom-TC (War Room); Bunn LPG Grinder (Employee Break Room); Bunn LPG Grinder (Conference Room) (+4 more) | J53: Loaned | K53: Carolina Beverage Solutions | L53: =IF($K53="","",IFERROR(IF(INDEX(Service_Providers!$C$2:$C$104,MATCH($K53,Service_Providers!$A$2:$A$104,0))="","",INDEX(Service_Providers!$C$2:$C$104,MATCH($K53,Service_Providers!$A$2:$A$104,0)))&IF(AND(INDEX(Service_Providers!$C$2:$C$104,MATCH($K53,Service_Providers!$A$2:$A$104,0))<>"",INDEX(Service_Providers!$D$2:$D$104,MATCH($K53,Service_Providers!$A$2:$A$104,0))<>""),CHAR(10),"")&IF(INDEX(Service_Providers!$D$2:$D$104,MATCH($K53,Service_Providers!$A$2:$A$104,0))="","",INDEX(Service_Providers!$D$2:$D$104,MATCH($K53,Service_Providers!$A$2:$A$104,0))),"Provider not found")) -> 803-280-5234 chris.powers@hotmail.com | N53: =IF($M53="","",IFERROR(IF(INDEX(Service_Providers!$C$2:$C$104,MATCH($M53,Service_Providers!$A$2:$A$104,0))="","",INDEX(Service_Providers!$C$2:$C$104,MATCH($M53,Service_Providers!$A$2:$A$104,0)))&IF(AND(INDEX(Service_Providers!$C$2:$C$104,MATCH($M53,Service_Providers!$A$2:$A$104,0))<>"",INDEX(Service_Providers!$D$2:$D$104,MATCH($M53,Service_Providers!$A$2:$A$104,0))<>""),CHAR(10),"")&IF(INDEX(Service_Providers!$D$2:$D$104,MATCH($M53,Service_Providers!$A$2:$A$104,0))="","",INDEX(Service_Providers!$D$2:$D$104,MATCH($M53,Service_Providers!$A$2:$A$104,0))),"Provider not found")) | O53: North and South Carolina Area | P53: 2026-07-15
A54: Steak 48 Charlotte | B54: ed@steak48.com | D54: 980.580.4848 | E54: 4425 Sharon Rd | F54: Charlotte | G54: NC | H54: 28211 | I54: Cameo c'2s; Bunn Axiom-APS; Bunn MHG | J54: Owned - Purchased from 3rd Party | K54: Carolina Beverage Solutions | L54: =IF($K54="","",IFERROR(IF(INDEX(Service_Providers!$C$2:$C$104,MATCH($K54,Service_Providers!$A$2:$A$104,0))="","",INDEX(Service_Providers!$C$2:$C$104,MATCH($K54,Service_Providers!$A$2:$A$104,0)))&IF(AND(INDEX(Service_Providers!$C$2:$C$104,MATCH($K54,Service_Providers!$A$2:$A$104,0))<>"",INDEX(Service_Providers!$D$2:$D$104,MATCH($K54,Service_Providers!$A$2:$A$104,0))<>""),CHAR(10),"")&IF(INDEX(Service_Providers!$D$2:$D$104,MATCH($K54,Service_Providers!$A$2:$A$104,0))="","",INDEX(Service_Providers!$D$2:$D$104,MATCH($K54,Service_Providers!$A$2:$A$104,0))),"Provider not found")) -> 803-280-5234 chris.powers@hotmail.com | N54: =IF($M54="","",IFERROR(IF(INDEX(Service_Providers!$C$2:$C$104,MATCH($M54,Service_Providers!$A$2:$A$104,0))="","",INDEX(Service_Providers!$C$2:$C$104,MATCH($M54,Service_Providers!$A$2:$A$104,0)))&IF(AND(INDEX(Service_Providers!$C$2:$C$104,MATCH($M54,Service_Providers!$A$2:$A$104,0))<>"",INDEX(Service_Providers!$D$2:$D$104,MATCH($M54,Service_Providers!$A$2:$A$104,0))<>""),CHAR(10),"")&IF(INDEX(Service_Providers!$D$2:$D$104,MATCH($M54,Service_Providers!$A$2:$A$104,0))="","",INDEX(Service_Providers!$D$2:$D$104,MATCH($M54,Service_Providers!$A$2:$A$104,0))),"Provider not found")) | O54: North and South Carolina Area | P54: 2026-07-15
A55: Kol Fac #085F - Omaha, NE | B55: wilber.enterprises@gmail.com | C55: Andy Wilber | D55: 402.218.1698 | E55: 4105 S. 84th | F55: Omaha | G55: NE | H55: 68127 | I55: Bunn ITCB Combo Brewer | J55: Loaned | K55: ETSC (EspressoTech Service Company) | L55: =IF($K55="","",IFERROR(IF(INDEX(Service_Providers!$C$2:$C$104,MATCH($K55,Service_Providers!$A$2:$A$104,0))="","",INDEX(Service_Providers!$C$2:$C$104,MATCH($K55,Service_Providers!$A$2:$A$104,0)))&IF(AND(INDEX(Service_Providers!$C$2:$C$104,MATCH($K55,Service_Providers!$A$2:$A$104,0))<>"",INDEX(Service_Providers!$D$2:$D$104,MATCH($K55,Service_Providers!$A$2:$A$104,0))<>""),CHAR(10),"")&IF(INDEX(Service_Providers!$D$2:$D$104,MATCH($K55,Service_Providers!$A$2:$A$104,0))="","",INDEX(Service_Providers!$D$2:$D$104,MATCH($K55,Service_Providers!$A$2:$A$104,0))),"Provider not found")) -> (888) 523-1684 service@etsc.coffee | N55: =IF($M55="","",IFERROR(IF(INDEX(Service_Providers!$C$2:$C$104,MATCH($M55,Service_Providers!$A$2:$A$104,0))="","",INDEX(Service_Providers!$C$2:$C$104,MATCH($M55,Service_Providers!$A$2:$A$104,0)))&IF(AND(INDEX(Service_Providers!$C$2:$C$104,MATCH($M55,Service_Providers!$A$2:$A$104,0))<>"",INDEX(Service_Providers!$D$2:$D$104,MATCH($M55,Service_Providers!$A$2:$A$104,0))<>""),CHAR(10),"")&IF(INDEX(Service_Providers!$D$2:$D$104,MATCH($M55,Service_Providers!$A$2:$A$104,0))="","",INDEX(Service_Providers!$D$2:$D$104,MATCH($M55,Service_Providers!$A$2:$A$104,0))),"Provider not found")) | O55: Nebraska Area | P55: 2026-07-15
A56: The Mystic at Santa Fe, LLC | B56: rick@rickmgoldberg.com | C56: Rick Goldberg | E56: 2810 Cerrillos Rd | F56: Santa Fe | G56: NM | H56: 87507 | I56: Bunn Axiom-APS; Eversys Cameo c'2s | J56: Lease; Loaned | K56: PriorityOne Group | L56: =IF($K56="","",IFERROR(IF(INDEX(Service_Providers!$C$2:$C$104,MATCH($K56,Service_Providers!$A$2:$A$104,0))="","",INDEX(Service_Providers!$C$2:$C$104,MATCH($K56,Service_Providers!$A$2:$A$104,0)))&IF(AND(INDEX(Service_Providers!$C$2:$C$104,MATCH($K56,Service_Providers!$A$2:$A$104,0))<>"",INDEX(Service_Providers!$D$2:$D$104,MATCH($K56,Service_Providers!$A$2:$A$104,0))<>""),CHAR(10),"")&IF(INDEX(Service_Providers!$D$2:$D$104,MATCH($K56,Service_Providers!$A$2:$A$104,0))="","",INDEX(Service_Providers!$D$2:$D$104,MATCH($K56,Service_Providers!$A$2:$A$104,0))),"Provider not found")) -> (800) 226-7146 service@priorityone247.com | M56: FASTCILITY CORP | N56: =IF($M56="","",IFERROR(IF(INDEX(Service_Providers!$C$2:$C$104,MATCH($M56,Service_Providers!$A$2:$A$104,0))="","",INDEX(Service_Providers!$C$2:$C$104,MATCH($M56,Service_Providers!$A$2:$A$104,0)))&IF(AND(INDEX(Service_Providers!$C$2:$C$104,MATCH($M56,Service_Providers!$A$2:$A$104,0))<>"",INDEX(Service_Providers!$D$2:$D$104,MATCH($M56,Service_Providers!$A$2:$A$104,0))<>""),CHAR(10),"")&IF(INDEX(Service_Providers!$D$2:$D$104,MATCH($M56,Service_Providers!$A$2:$A$104,0))="","",INDEX(Service_Providers!$D$2:$D$104,MATCH($M56,Service_Providers!$A$2:$A$104,0))),"Provider not found")) -> Office: (833) 203-2285 Service@FASTCILITYCORP.COM https://app.servicefusion.com/fastcility Username: Jesus@katzcoffee.com F!xmy5!t03 | O56: New Mexico Area | P56: 2026-07-15
A57: Emilio's | B57: sorellina01@refinedhq.com | C57: Michael Santos | E57: 9742 West Maule Ave | F57: Las Vegas | G57: NV | H57: 89148 | I57: Enigma e'4s Classic | J57: Owned - Purchased from Katz | K57: Anytime Beverage Service | L57: =IF($K57="","",IFERROR(IF(INDEX(Service_Providers!$C$2:$C$104,MATCH($K57,Service_Providers!$A$2:$A$104,0))="","",INDEX(Service_Providers!$C$2:$C$104,MATCH($K57,Service_Providers!$A$2:$A$104,0)))&IF(AND(INDEX(Service_Providers!$C$2:$C$104,MATCH($K57,Service_Providers!$A$2:$A$104,0))<>"",INDEX(Service_Providers!$D$2:$D$104,MATCH($K57,Service_Providers!$A$2:$A$104,0))<>""),CHAR(10),"")&IF(INDEX(Service_Providers!$D$2:$D$104,MATCH($K57,Service_Providers!$A$2:$A$104,0))="","",INDEX(Service_Providers!$D$2:$D$104,MATCH($K57,Service_Providers!$A$2:$A$104,0))),"Provider not found")) -> Contact: Cynthia Phone: 714-335-9964 Cell: 714-395-8108 anytimebeverageservice@gmail.com | M57: FASTCILITY CORP | N57: =IF($M57="","",IFERROR(IF(INDEX(Service_Providers!$C$2:$C$104,MATCH($M57,Service_Providers!$A$2:$A$104,0))="","",INDEX(Service_Providers!$C$2:$C$104,MATCH($M57,Service_Providers!$A$2:$A$104,0)))&IF(AND(INDEX(Service_Providers!$C$2:$C$104,MATCH($M57,Service_Providers!$A$2:$A$104,0))<>"",INDEX(Service_Providers!$D$2:$D$104,MATCH($M57,Service_Providers!$A$2:$A$104,0))<>""),CHAR(10),"")&IF(INDEX(Service_Providers!$D$2:$D$104,MATCH($M57,Service_Providers!$A$2:$A$104,0))="","",INDEX(Service_Providers!$D$2:$D$104,MATCH($M57,Service_Providers!$A$2:$A$104,0))),"Provider not found")) -> Office: (833) 203-2285 Service@FASTCILITYCORP.COM https://app.servicefusion.com/fastcility Username: Jesus@katzcoffee.com F!xmy5!t03 | P57: 2026-07-15
A58: Sorellina's | B58: sorellina01@refinedhq.com | C58: courtney | E58: 9742 West Maule Ave | F58: Las Vegas | G58: NV | H58: 89148 | I58: Enigma e'4s Classic | J58: Owned - Purchased from Katz | K58: Anytime Beverage Service | L58: =IF($K58="","",IFERROR(IF(INDEX(Service_Providers!$C$2:$C$104,MATCH($K58,Service_Providers!$A$2:$A$104,0))="","",INDEX(Service_Providers!$C$2:$C$104,MATCH($K58,Service_Providers!$A$2:$A$104,0)))&IF(AND(INDEX(Service_Providers!$C$2:$C$104,MATCH($K58,Service_Providers!$A$2:$A$104,0))<>"",INDEX(Service_Providers!$D$2:$D$104,MATCH($K58,Service_Providers!$A$2:$A$104,0))<>""),CHAR(10),"")&IF(INDEX(Service_Providers!$D$2:$D$104,MATCH($K58,Service_Providers!$A$2:$A$104,0))="","",INDEX(Service_Providers!$D$2:$D$104,MATCH($K58,Service_Providers!$A$2:$A$104,0))),"Provider not found")) -> Contact: Cynthia Phone: 714-335-9964 Cell: 714-395-8108 anytimebeverageservice@gmail.com | M58: FASTCILITY CORP | N58: =IF($M58="","",IFERROR(IF(INDEX(Service_Providers!$C$2:$C$104,MATCH($M58,Service_Providers!$A$2:$A$104,0))="","",INDEX(Service_Providers!$C$2:$C$104,MATCH($M58,Service_Providers!$A$2:$A$104,0)))&IF(AND(INDEX(Service_Providers!$C$2:$C$104,MATCH($M58,Service_Providers!$A$2:$A$104,0))<>"",INDEX(Service_Providers!$D$2:$D$104,MATCH($M58,Service_Providers!$A$2:$A$104,0))<>""),CHAR(10),"")&IF(INDEX(Service_Providers!$D$2:$D$104,MATCH($M58,Service_Providers!$A$2:$A$104,0))="","",INDEX(Service_Providers!$D$2:$D$104,MATCH($M58,Service_Providers!$A$2:$A$104,0))),"Provider not found")) -> Office: (833) 203-2285 Service@FASTCILITYCORP.COM https://app.servicefusion.com/fastcility Username: Jesus@katzcoffee.com F!xmy5!t03 | P58: 2026-07-15
A59: La Michoacana #08 - Oklahoma City, OK | B59: invoices@lmmm.net | E59: 2701 Southwest 29th St. | F59: Oklahoma City | G59: OK | H59: 73119 | I59: Bunn ITCB no Shelf | J59: Loaned | K59: Prestige Technical Services | L59: =IF($K59="","",IFERROR(IF(INDEX(Service_Providers!$C$2:$C$104,MATCH($K59,Service_Providers!$A$2:$A$104,0))="","",INDEX(Service_Providers!$C$2:$C$104,MATCH($K59,Service_Providers!$A$2:$A$104,0)))&IF(AND(INDEX(Service_Providers!$C$2:$C$104,MATCH($K59,Service_Providers!$A$2:$A$104,0))<>"",INDEX(Service_Providers!$D$2:$D$104,MATCH($K59,Service_Providers!$A$2:$A$104,0))<>""),CHAR(10),"")&IF(INDEX(Service_Providers!$D$2:$D$104,MATCH($K59,Service_Providers!$A$2:$A$104,0))="","",INDEX(Service_Providers!$D$2:$D$104,MATCH($K59,Service_Providers!$A$2:$A$104,0))),"Provider not found")) -> 636-583-5788 prestigetech@prestigetech.us | N59: =IF($M59="","",IFERROR(IF(INDEX(Service_Providers!$C$2:$C$104,MATCH($M59,Service_Providers!$A$2:$A$104,0))="","",INDEX(Service_Providers!$C$2:$C$104,MATCH($M59,Service_Providers!$A$2:$A$104,0)))&IF(AND(INDEX(Service_Providers!$C$2:$C$104,MATCH($M59,Service_Providers!$A$2:$A$104,0))<>"",INDEX(Service_Providers!$D$2:$D$104,MATCH($M59,Service_Providers!$A$2:$A$104,0))<>""),CHAR(10),"")&IF(INDEX(Service_Providers!$D$2:$D$104,MATCH($M59,Service_Providers!$A$2:$A$104,0))="","",INDEX(Service_Providers!$D$2:$D$104,MATCH($M59,Service_Providers!$A$2:$A$104,0))),"Provider not found")) | O59: Oklahoma Area | P59: 2026-07-15
A60: La Michoacana #10 - Oklahoma City, OK | B60: invoices@lmmm.net | D60: 405.632.5552 | E60: 415 SW 59th St. | F60: Oklahoma City | G60: OK | H60: 73109 | I60: ITCB Combo Brewer | J60: Loaned | K60: Prestige Technical Services | L60: =IF($K60="","",IFERROR(IF(INDEX(Service_Providers!$C$2:$C$104,MATCH($K60,Service_Providers!$A$2:$A$104,0))="","",INDEX(Service_Providers!$C$2:$C$104,MATCH($K60,Service_Providers!$A$2:$A$104,0)))&IF(AND(INDEX(Service_Providers!$C$2:$C$104,MATCH($K60,Service_Providers!$A$2:$A$104,0))<>"",INDEX(Service_Providers!$D$2:$D$104,MATCH($K60,Service_Providers!$A$2:$A$104,0))<>""),CHAR(10),"")&IF(INDEX(Service_Providers!$D$2:$D$104,MATCH($K60,Service_Providers!$A$2:$A$104,0))="","",INDEX(Service_Providers!$D$2:$D$104,MATCH($K60,Service_Providers!$A$2:$A$104,0))),"Provider not found")) -> 636-583-5788 prestigetech@prestigetech.us | N60: =IF($M60="","",IFERROR(IF(INDEX(Service_Providers!$C$2:$C$104,MATCH($M60,Service_Providers!$A$2:$A$104,0))="","",INDEX(Service_Providers!$C$2:$C$104,MATCH($M60,Service_Providers!$A$2:$A$104,0)))&IF(AND(INDEX(Service_Providers!$C$2:$C$104,MATCH($M60,Service_Providers!$A$2:$A$104,0))<>"",INDEX(Service_Providers!$D$2:$D$104,MATCH($M60,Service_Providers!$A$2:$A$104,0))<>""),CHAR(10),"")&IF(INDEX(Service_Providers!$D$2:$D$104,MATCH($M60,Service_Providers!$A$2:$A$104,0))="","",INDEX(Service_Providers!$D$2:$D$104,MATCH($M60,Service_Providers!$A$2:$A$104,0))),"Provider not found")) | O60: Oklahoma Area | P60: 2026-07-15
A61: La Michoacana #11 - Oklahoma City, OK | B61: invoices@lmmm.net | E61: 1104 Southeast 44th St. | F61: Oklahoma City | G61: OK | H61: 73129 | I61: ITCB Combo Brewer | J61: Loaned | K61: Prestige Technical Services | L61: =IF($K61="","",IFERROR(IF(INDEX(Service_Providers!$C$2:$C$104,MATCH($K61,Service_Providers!$A$2:$A$104,0))="","",INDEX(Service_Providers!$C$2:$C$104,MATCH($K61,Service_Providers!$A$2:$A$104,0)))&IF(AND(INDEX(Service_Providers!$C$2:$C$104,MATCH($K61,Service_Providers!$A$2:$A$104,0))<>"",INDEX(Service_Providers!$D$2:$D$104,MATCH($K61,Service_Providers!$A$2:$A$104,0))<>""),CHAR(10),"")&IF(INDEX(Service_Providers!$D$2:$D$104,MATCH($K61,Service_Providers!$A$2:$A$104,0))="","",INDEX(Service_Providers!$D$2:$D$104,MATCH($K61,Service_Providers!$A$2:$A$104,0))),"Provider not found")) -> 636-583-5788 prestigetech@prestigetech.us | N61: =IF($M61="","",IFERROR(IF(INDEX(Service_Providers!$C$2:$C$104,MATCH($M61,Service_Providers!$A$2:$A$104,0))="","",INDEX(Service_Providers!$C$2:$C$104,MATCH($M61,Service_Providers!$A$2:$A$104,0)))&IF(AND(INDEX(Service_Providers!$C$2:$C$104,MATCH($M61,Service_Providers!$A$2:$A$104,0))<>"",INDEX(Service_Providers!$D$2:$D$104,MATCH($M61,Service_Providers!$A$2:$A$104,0))<>""),CHAR(10),"")&IF(INDEX(Service_Providers!$D$2:$D$104,MATCH($M61,Service_Providers!$A$2:$A$104,0))="","",INDEX(Service_Providers!$D$2:$D$104,MATCH($M61,Service_Providers!$A$2:$A$104,0))),"Provider not found")) | O61: Oklahoma Area | P61: 2026-07-15
A62: La Michoacana - Oklahoma City, OK | B62: maximocruz@lmmm.net | C62: Yesenia Gomez | D62: 405.635.1130 | E62: 1125 SW 29th St. | F62: Oklahoma City | G62: OK | H62: 73109 | I62: ITCB Combo Brewer | J62: Loaned | K62: Prestige Technical Services | L62: =IF($K62="","",IFERROR(IF(INDEX(Service_Providers!$C$2:$C$104,MATCH($K62,Service_Providers!$A$2:$A$104,0))="","",INDEX(Service_Providers!$C$2:$C$104,MATCH($K62,Service_Providers!$A$2:$A$104,0)))&IF(AND(INDEX(Service_Providers!$C$2:$C$104,MATCH($K62,Service_Providers!$A$2:$A$104,0))<>"",INDEX(Service_Providers!$D$2:$D$104,MATCH($K62,Service_Providers!$A$2:$A$104,0))<>""),CHAR(10),"")&IF(INDEX(Service_Providers!$D$2:$D$104,MATCH($K62,Service_Providers!$A$2:$A$104,0))="","",INDEX(Service_Providers!$D$2:$D$104,MATCH($K62,Service_Providers!$A$2:$A$104,0))),"Provider not found")) -> 636-583-5788 prestigetech@prestigetech.us | N62: =IF($M62="","",IFERROR(IF(INDEX(Service_Providers!$C$2:$C$104,MATCH($M62,Service_Providers!$A$2:$A$104,0))="","",INDEX(Service_Providers!$C$2:$C$104,MATCH($M62,Service_Providers!$A$2:$A$104,0)))&IF(AND(INDEX(Service_Providers!$C$2:$C$104,MATCH($M62,Service_Providers!$A$2:$A$104,0))<>"",INDEX(Service_Providers!$D$2:$D$104,MATCH($M62,Service_Providers!$A$2:$A$104,0))<>""),CHAR(10),"")&IF(INDEX(Service_Providers!$D$2:$D$104,MATCH($M62,Service_Providers!$A$2:$A$104,0))="","",INDEX(Service_Providers!$D$2:$D$104,MATCH($M62,Service_Providers!$A$2:$A$104,0))),"Provider not found")) | O62: Oklahoma Area | P62: 2026-07-15
A63: Steak 48 Philadelphia | B63: william@steak48.com | D63: 215.552.4848 | E63: 260 South Broad St | F63: Philadelphia | G63: PA | H63: 19102 | I63: Fetco GR2.2 Grinder; Cameo c'2s; Fetco 2131-XTS | J63: Owned - Purchased from 3rd Party | K63: Masket Services | L63: =IF($K63="","",IFERROR(IF(INDEX(Service_Providers!$C$2:$C$104,MATCH($K63,Service_Providers!$A$2:$A$104,0))="","",INDEX(Service_Providers!$C$2:$C$104,MATCH($K63,Service_Providers!$A$2:$A$104,0)))&IF(AND(INDEX(Service_Providers!$C$2:$C$104,MATCH($K63,Service_Providers!$A$2:$A$104,0))<>"",INDEX(Service_Providers!$D$2:$D$104,MATCH($K63,Service_Providers!$A$2:$A$104,0))<>""),CHAR(10),"")&IF(INDEX(Service_Providers!$D$2:$D$104,MATCH($K63,Service_Providers!$A$2:$A$104,0))="","",INDEX(Service_Providers!$D$2:$D$104,MATCH($K63,Service_Providers!$A$2:$A$104,0))),"Provider not found")) -> 866-803-8088 service@masketservices.com | N63: =IF($M63="","",IFERROR(IF(INDEX(Service_Providers!$C$2:$C$104,MATCH($M63,Service_Providers!$A$2:$A$104,0))="","",INDEX(Service_Providers!$C$2:$C$104,MATCH($M63,Service_Providers!$A$2:$A$104,0)))&IF(AND(INDEX(Service_Providers!$C$2:$C$104,MATCH($M63,Service_Providers!$A$2:$A$104,0))<>"",INDEX(Service_Providers!$D$2:$D$104,MATCH($M63,Service_Providers!$A$2:$A$104,0))<>""),CHAR(10),"")&IF(INDEX(Service_Providers!$D$2:$D$104,MATCH($M63,Service_Providers!$A$2:$A$104,0))="","",INDEX(Service_Providers!$D$2:$D$104,MATCH($M63,Service_Providers!$A$2:$A$104,0))),"Provider not found")) | O63: Philadelphia Area | P63: 2026-07-15
A64: Kol Fac #098 - Powdersville, SC | B64: alicia@kolfac.com | D64: 607.760.0216 | E64: 3609 Highway 153 | F64: Powdersville | G64: SC | H64: 29611 | I64: Bunn ITCB Combo Brewer | J64: Loaned | K64: Intergrated Coffee Solutions | L64: =IF($K64="","",IFERROR(IF(INDEX(Service_Providers!$C$2:$C$104,MATCH($K64,Service_Providers!$A$2:$A$104,0))="","",INDEX(Service_Providers!$C$2:$C$104,MATCH($K64,Service_Providers!$A$2:$A$104,0)))&IF(AND(INDEX(Service_Providers!$C$2:$C$104,MATCH($K64,Service_Providers!$A$2:$A$104,0))<>"",INDEX(Service_Providers!$D$2:$D$104,MATCH($K64,Service_Providers!$A$2:$A$104,0))<>""),CHAR(10),"")&IF(INDEX(Service_Providers!$D$2:$D$104,MATCH($K64,Service_Providers!$A$2:$A$104,0))="","",INDEX(Service_Providers!$D$2:$D$104,MATCH($K64,Service_Providers!$A$2:$A$104,0))),"Provider not found")) -> Phone / Text: (864) 606-4418 integratedcoffeesolutions@gmail.com | N64: =IF($M64="","",IFERROR(IF(INDEX(Service_Providers!$C$2:$C$104,MATCH($M64,Service_Providers!$A$2:$A$104,0))="","",INDEX(Service_Providers!$C$2:$C$104,MATCH($M64,Service_Providers!$A$2:$A$104,0)))&IF(AND(INDEX(Service_Providers!$C$2:$C$104,MATCH($M64,Service_Providers!$A$2:$A$104,0))<>"",INDEX(Service_Providers!$D$2:$D$104,MATCH($M64,Service_Providers!$A$2:$A$104,0))<>""),CHAR(10),"")&IF(INDEX(Service_Providers!$D$2:$D$104,MATCH($M64,Service_Providers!$A$2:$A$104,0))="","",INDEX(Service_Providers!$D$2:$D$104,MATCH($M64,Service_Providers!$A$2:$A$104,0))),"Provider not found")) | O64: North and South Carolina Area | P64: 2026-07-15
A65: Hawkers - Nashville, TN | B65: APnashville110@eathawkers.com | C65: Linda Hurd | D65: 615-600-4762 | E65: 626-A Main Street | F65: Nashville | G65: TN | H65: 37206 | I65: Bunn ITCB Combo Brewer (NS) | J65: Loaned | K65: ETSC (EspressoTech Service Company) | L65: =IF($K65="","",IFERROR(IF(INDEX(Service_Providers!$C$2:$C$104,MATCH($K65,Service_Providers!$A$2:$A$104,0))="","",INDEX(Service_Providers!$C$2:$C$104,MATCH($K65,Service_Providers!$A$2:$A$104,0)))&IF(AND(INDEX(Service_Providers!$C$2:$C$104,MATCH($K65,Service_Providers!$A$2:$A$104,0))<>"",INDEX(Service_Providers!$D$2:$D$104,MATCH($K65,Service_Providers!$A$2:$A$104,0))<>""),CHAR(10),"")&IF(INDEX(Service_Providers!$D$2:$D$104,MATCH($K65,Service_Providers!$A$2:$A$104,0))="","",INDEX(Service_Providers!$D$2:$D$104,MATCH($K65,Service_Providers!$A$2:$A$104,0))),"Provider not found")) -> (888) 523-1684 service@etsc.coffee | M65: Best Beverage Equipment Service | N65: =IF($M65="","",IFERROR(IF(INDEX(Service_Providers!$C$2:$C$104,MATCH($M65,Service_Providers!$A$2:$A$104,0))="","",INDEX(Service_Providers!$C$2:$C$104,MATCH($M65,Service_Providers!$A$2:$A$104,0)))&IF(AND(INDEX(Service_Providers!$C$2:$C$104,MATCH($M65,Service_Providers!$A$2:$A$104,0))<>"",INDEX(Service_Providers!$D$2:$D$104,MATCH($M65,Service_Providers!$A$2:$A$104,0))<>""),CHAR(10),"")&IF(INDEX(Service_Providers!$D$2:$D$104,MATCH($M65,Service_Providers!$A$2:$A$104,0))="","",INDEX(Service_Providers!$D$2:$D$104,MATCH($M65,Service_Providers!$A$2:$A$104,0))),"Provider not found")) -> 866-966-5799 ext 1 service@bestbeverage.net | O65: Tennessee Area | P65: 2026-07-15
A66: Cotton Court Hotel | B66: corpacct@valenciagroup.com | D66: 806.758.5800 | E66: 1610 Broadway | F66: Lubbock | G66: TX | H66: 79401 | I66: Eversys Cameo c'2s; ITCB no shelf 220V; ITCB no Shelf 120V #2 | J66: Owned - Purchased from Katz | K66: LIQUISERVE LLC | L66: =IF($K66="","",IFERROR(IF(INDEX(Service_Providers!$C$2:$C$104,MATCH($K66,Service_Providers!$A$2:$A$104,0))="","",INDEX(Service_Providers!$C$2:$C$104,MATCH($K66,Service_Providers!$A$2:$A$104,0)))&IF(AND(INDEX(Service_Providers!$C$2:$C$104,MATCH($K66,Service_Providers!$A$2:$A$104,0))<>"",INDEX(Service_Providers!$D$2:$D$104,MATCH($K66,Service_Providers!$A$2:$A$104,0))<>""),CHAR(10),"")&IF(INDEX(Service_Providers!$D$2:$D$104,MATCH($K66,Service_Providers!$A$2:$A$104,0))="","",INDEX(Service_Providers!$D$2:$D$104,MATCH($K66,Service_Providers!$A$2:$A$104,0))),"Provider not found")) -> Toll Free: 800-528-6625 Main: 505-247-3707 Service@LiquiServe.com | M66: FASTCILITY CORP | N66: =IF($M66="","",IFERROR(IF(INDEX(Service_Providers!$C$2:$C$104,MATCH($M66,Service_Providers!$A$2:$A$104,0))="","",INDEX(Service_Providers!$C$2:$C$104,MATCH($M66,Service_Providers!$A$2:$A$104,0)))&IF(AND(INDEX(Service_Providers!$C$2:$C$104,MATCH($M66,Service_Providers!$A$2:$A$104,0))<>"",INDEX(Service_Providers!$D$2:$D$104,MATCH($M66,Service_Providers!$A$2:$A$104,0))<>""),CHAR(10),"")&IF(INDEX(Service_Providers!$D$2:$D$104,MATCH($M66,Service_Providers!$A$2:$A$104,0))="","",INDEX(Service_Providers!$D$2:$D$104,MATCH($M66,Service_Providers!$A$2:$A$104,0))),"Provider not found")) -> Office: (833) 203-2285 Service@FASTCILITYCORP.COM https://app.servicefusion.com/fastcility Username: Jesus@katzcoffee.com F!xmy5!t03 | O66: Texas Area | P66: 2026-07-15
A67: Kol Fac #028 - Trentonview | B67: alicia@kolfac.com | C67: Jason Schneider | D67: 956.686.2578 | E67: 7017-U N 10th | F67: McAllen | G67: TX | H67: 78504 | I67: Bunn ITCB Combo Brewer (NS) | J67: Loaned | K67: STCS | L67: =IF($K67="","",IFERROR(IF(INDEX(Service_Providers!$C$2:$C$104,MATCH($K67,Service_Providers!$A$2:$A$104,0))="","",INDEX(Service_Providers!$C$2:$C$104,MATCH($K67,Service_Providers!$A$2:$A$104,0)))&IF(AND(INDEX(Service_Providers!$C$2:$C$104,MATCH($K67,Service_Providers!$A$2:$A$104,0))<>"",INDEX(Service_Providers!$D$2:$D$104,MATCH($K67,Service_Providers!$A$2:$A$104,0))<>""),CHAR(10),"")&IF(INDEX(Service_Providers!$D$2:$D$104,MATCH($K67,Service_Providers!$A$2:$A$104,0))="","",INDEX(Service_Providers!$D$2:$D$104,MATCH($K67,Service_Providers!$A$2:$A$104,0))),"Provider not found")) -> 956-536-7846 alanmcgee@msn.com | N67: =IF($M67="","",IFERROR(IF(INDEX(Service_Providers!$C$2:$C$104,MATCH($M67,Service_Providers!$A$2:$A$104,0))="","",INDEX(Service_Providers!$C$2:$C$104,MATCH($M67,Service_Providers!$A$2:$A$104,0)))&IF(AND(INDEX(Service_Providers!$C$2:$C$104,MATCH($M67,Service_Providers!$A$2:$A$104,0))<>"",INDEX(Service_Providers!$D$2:$D$104,MATCH($M67,Service_Providers!$A$2:$A$104,0))<>""),CHAR(10),"")&IF(INDEX(Service_Providers!$D$2:$D$104,MATCH($M67,Service_Providers!$A$2:$A$104,0))="","",INDEX(Service_Providers!$D$2:$D$104,MATCH($M67,Service_Providers!$A$2:$A$104,0))),"Provider not found")) | O67: Texas Area | P67: 2026-07-15
A68: La Michoacana #01 - McAllen, TX | B68: invoices@lmmm.net | C68: Ruben Aranda | D68: 956.630.2330 | E68: 2200 N. 10th St., Suite C | F68: McAllen | G68: TX | H68: 78505 | I68: ITCB Combo Brewer | J68: Loaned | K68: STCS | L68: =IF($K68="","",IFERROR(IF(INDEX(Service_Providers!$C$2:$C$104,MATCH($K68,Service_Providers!$A$2:$A$104,0))="","",INDEX(Service_Providers!$C$2:$C$104,MATCH($K68,Service_Providers!$A$2:$A$104,0)))&IF(AND(INDEX(Service_Providers!$C$2:$C$104,MATCH($K68,Service_Providers!$A$2:$A$104,0))<>"",INDEX(Service_Providers!$D$2:$D$104,MATCH($K68,Service_Providers!$A$2:$A$104,0))<>""),CHAR(10),"")&IF(INDEX(Service_Providers!$D$2:$D$104,MATCH($K68,Service_Providers!$A$2:$A$104,0))="","",INDEX(Service_Providers!$D$2:$D$104,MATCH($K68,Service_Providers!$A$2:$A$104,0))),"Provider not found")) -> 956-536-7846 alanmcgee@msn.com | N68: =IF($M68="","",IFERROR(IF(INDEX(Service_Providers!$C$2:$C$104,MATCH($M68,Service_Providers!$A$2:$A$104,0))="","",INDEX(Service_Providers!$C$2:$C$104,MATCH($M68,Service_Providers!$A$2:$A$104,0)))&IF(AND(INDEX(Service_Providers!$C$2:$C$104,MATCH($M68,Service_Providers!$A$2:$A$104,0))<>"",INDEX(Service_Providers!$D$2:$D$104,MATCH($M68,Service_Providers!$A$2:$A$104,0))<>""),CHAR(10),"")&IF(INDEX(Service_Providers!$D$2:$D$104,MATCH($M68,Service_Providers!$A$2:$A$104,0))="","",INDEX(Service_Providers!$D$2:$D$104,MATCH($M68,Service_Providers!$A$2:$A$104,0))),"Provider not found")) | O68: Texas Area | P68: 2026-07-15
A69: La Michoacana #02 - Pharr, TX | B69: invoices@lmmm.net | C69: Antonio Aranda | D69: 956.283.0995 | E69: 806 S. Cage Blvd. | F69: Pharr | G69: TX | H69: 78577 | I69: Bunn ITCB Combo Brewer | J69: Loaned | K69: STCS | L69: =IF($K69="","",IFERROR(IF(INDEX(Service_Providers!$C$2:$C$104,MATCH($K69,Service_Providers!$A$2:$A$104,0))="","",INDEX(Service_Providers!$C$2:$C$104,MATCH($K69,Service_Providers!$A$2:$A$104,0)))&IF(AND(INDEX(Service_Providers!$C$2:$C$104,MATCH($K69,Service_Providers!$A$2:$A$104,0))<>"",INDEX(Service_Providers!$D$2:$D$104,MATCH($K69,Service_Providers!$A$2:$A$104,0))<>""),CHAR(10),"")&IF(INDEX(Service_Providers!$D$2:$D$104,MATCH($K69,Service_Providers!$A$2:$A$104,0))="","",INDEX(Service_Providers!$D$2:$D$104,MATCH($K69,Service_Providers!$A$2:$A$104,0))),"Provider not found")) -> 956-536-7846 alanmcgee@msn.com | N69: =IF($M69="","",IFERROR(IF(INDEX(Service_Providers!$C$2:$C$104,MATCH($M69,Service_Providers!$A$2:$A$104,0))="","",INDEX(Service_Providers!$C$2:$C$104,MATCH($M69,Service_Providers!$A$2:$A$104,0)))&IF(AND(INDEX(Service_Providers!$C$2:$C$104,MATCH($M69,Service_Providers!$A$2:$A$104,0))<>"",INDEX(Service_Providers!$D$2:$D$104,MATCH($M69,Service_Providers!$A$2:$A$104,0))<>""),CHAR(10),"")&IF(INDEX(Service_Providers!$D$2:$D$104,MATCH($M69,Service_Providers!$A$2:$A$104,0))="","",INDEX(Service_Providers!$D$2:$D$104,MATCH($M69,Service_Providers!$A$2:$A$104,0))),"Provider not found")) | O69: Texas Area | P69: 2026-07-15
A70: La Michoacana #03 - Harlingen, TX | B70: invoices@lmmm.net | C70: Jose Melendez | D70: 956.425.7018 | E70: 902 W. Harrison Ave. | F70: Harlingen | G70: TX | H70: 78550 | I70: Bunn ITCB Combo Brewer | J70: Loaned | K70: STCS | L70: =IF($K70="","",IFERROR(IF(INDEX(Service_Providers!$C$2:$C$104,MATCH($K70,Service_Providers!$A$2:$A$104,0))="","",INDEX(Service_Providers!$C$2:$C$104,MATCH($K70,Service_Providers!$A$2:$A$104,0)))&IF(AND(INDEX(Service_Providers!$C$2:$C$104,MATCH($K70,Service_Providers!$A$2:$A$104,0))<>"",INDEX(Service_Providers!$D$2:$D$104,MATCH($K70,Service_Providers!$A$2:$A$104,0))<>""),CHAR(10),"")&IF(INDEX(Service_Providers!$D$2:$D$104,MATCH($K70,Service_Providers!$A$2:$A$104,0))="","",INDEX(Service_Providers!$D$2:$D$104,MATCH($K70,Service_Providers!$A$2:$A$104,0))),"Provider not found")) -> 956-536-7846 alanmcgee@msn.com | N70: =IF($M70="","",IFERROR(IF(INDEX(Service_Providers!$C$2:$C$104,MATCH($M70,Service_Providers!$A$2:$A$104,0))="","",INDEX(Service_Providers!$C$2:$C$104,MATCH($M70,Service_Providers!$A$2:$A$104,0)))&IF(AND(INDEX(Service_Providers!$C$2:$C$104,MATCH($M70,Service_Providers!$A$2:$A$104,0))<>"",INDEX(Service_Providers!$D$2:$D$104,MATCH($M70,Service_Providers!$A$2:$A$104,0))<>""),CHAR(10),"")&IF(INDEX(Service_Providers!$D$2:$D$104,MATCH($M70,Service_Providers!$A$2:$A$104,0))="","",INDEX(Service_Providers!$D$2:$D$104,MATCH($M70,Service_Providers!$A$2:$A$104,0))),"Provider not found")) | O70: Texas Area | P70: 2026-07-15
A71: La Michoacana #04 - Weslaco, TX | B71: lmval04@lmmm.net | C71: Esther Sanchez | D71: 956.968.8685 | E71: 3001 E. Expressway 83 | F71: Weslaco | G71: TX | H71: 78596 | I71: Bunn ITCB Combo Brewer | J71: Loaned | K71: STCS | L71: =IF($K71="","",IFERROR(IF(INDEX(Service_Providers!$C$2:$C$104,MATCH($K71,Service_Providers!$A$2:$A$104,0))="","",INDEX(Service_Providers!$C$2:$C$104,MATCH($K71,Service_Providers!$A$2:$A$104,0)))&IF(AND(INDEX(Service_Providers!$C$2:$C$104,MATCH($K71,Service_Providers!$A$2:$A$104,0))<>"",INDEX(Service_Providers!$D$2:$D$104,MATCH($K71,Service_Providers!$A$2:$A$104,0))<>""),CHAR(10),"")&IF(INDEX(Service_Providers!$D$2:$D$104,MATCH($K71,Service_Providers!$A$2:$A$104,0))="","",INDEX(Service_Providers!$D$2:$D$104,MATCH($K71,Service_Providers!$A$2:$A$104,0))),"Provider not found")) -> 956-536-7846 alanmcgee@msn.com | N71: =IF($M71="","",IFERROR(IF(INDEX(Service_Providers!$C$2:$C$104,MATCH($M71,Service_Providers!$A$2:$A$104,0))="","",INDEX(Service_Providers!$C$2:$C$104,MATCH($M71,Service_Providers!$A$2:$A$104,0)))&IF(AND(INDEX(Service_Providers!$C$2:$C$104,MATCH($M71,Service_Providers!$A$2:$A$104,0))<>"",INDEX(Service_Providers!$D$2:$D$104,MATCH($M71,Service_Providers!$A$2:$A$104,0))<>""),CHAR(10),"")&IF(INDEX(Service_Providers!$D$2:$D$104,MATCH($M71,Service_Providers!$A$2:$A$104,0))="","",INDEX(Service_Providers!$D$2:$D$104,MATCH($M71,Service_Providers!$A$2:$A$104,0))),"Provider not found")) | O71: Texas Area | P71: 2026-07-15
A72: La Michoacana #06 - Harlingen, TX | B72: invoices@lmmm.net | C72: Mario Vasquez | D72: 956.440.8702 | E72: 1221 N. 7th St. | F72: Harlingen | G72: TX | H72: 78550 | I72: ITCB Combo Brewer | J72: Loaned | K72: STCS | L72: =IF($K72="","",IFERROR(IF(INDEX(Service_Providers!$C$2:$C$104,MATCH($K72,Service_Providers!$A$2:$A$104,0))="","",INDEX(Service_Providers!$C$2:$C$104,MATCH($K72,Service_Providers!$A$2:$A$104,0)))&IF(AND(INDEX(Service_Providers!$C$2:$C$104,MATCH($K72,Service_Providers!$A$2:$A$104,0))<>"",INDEX(Service_Providers!$D$2:$D$104,MATCH($K72,Service_Providers!$A$2:$A$104,0))<>""),CHAR(10),"")&IF(INDEX(Service_Providers!$D$2:$D$104,MATCH($K72,Service_Providers!$A$2:$A$104,0))="","",INDEX(Service_Providers!$D$2:$D$104,MATCH($K72,Service_Providers!$A$2:$A$104,0))),"Provider not found")) -> 956-536-7846 alanmcgee@msn.com | N72: =IF($M72="","",IFERROR(IF(INDEX(Service_Providers!$C$2:$C$104,MATCH($M72,Service_Providers!$A$2:$A$104,0))="","",INDEX(Service_Providers!$C$2:$C$104,MATCH($M72,Service_Providers!$A$2:$A$104,0)))&IF(AND(INDEX(Service_Providers!$C$2:$C$104,MATCH($M72,Service_Providers!$A$2:$A$104,0))<>"",INDEX(Service_Providers!$D$2:$D$104,MATCH($M72,Service_Providers!$A$2:$A$104,0))<>""),CHAR(10),"")&IF(INDEX(Service_Providers!$D$2:$D$104,MATCH($M72,Service_Providers!$A$2:$A$104,0))="","",INDEX(Service_Providers!$D$2:$D$104,MATCH($M72,Service_Providers!$A$2:$A$104,0))),"Provider not found")) | O72: Texas Area | P72: 2026-07-15
A73: La Michoacana #08 - Brownsville, TX | B73: invoices@lmmm.net | C73: Alejandra Robertson | D73: 956.544.4806 | E73: 770 W. Elizabeth | F73: Brownsville | G73: TX | H73: 78520 | I73: Bunn ITCB Combo Brewer | J73: Loaned | K73: STCS | L73: =IF($K73="","",IFERROR(IF(INDEX(Service_Providers!$C$2:$C$104,MATCH($K73,Service_Providers!$A$2:$A$104,0))="","",INDEX(Service_Providers!$C$2:$C$104,MATCH($K73,Service_Providers!$A$2:$A$104,0)))&IF(AND(INDEX(Service_Providers!$C$2:$C$104,MATCH($K73,Service_Providers!$A$2:$A$104,0))<>"",INDEX(Service_Providers!$D$2:$D$104,MATCH($K73,Service_Providers!$A$2:$A$104,0))<>""),CHAR(10),"")&IF(INDEX(Service_Providers!$D$2:$D$104,MATCH($K73,Service_Providers!$A$2:$A$104,0))="","",INDEX(Service_Providers!$D$2:$D$104,MATCH($K73,Service_Providers!$A$2:$A$104,0))),"Provider not found")) -> 956-536-7846 alanmcgee@msn.com | N73: =IF($M73="","",IFERROR(IF(INDEX(Service_Providers!$C$2:$C$104,MATCH($M73,Service_Providers!$A$2:$A$104,0))="","",INDEX(Service_Providers!$C$2:$C$104,MATCH($M73,Service_Providers!$A$2:$A$104,0)))&IF(AND(INDEX(Service_Providers!$C$2:$C$104,MATCH($M73,Service_Providers!$A$2:$A$104,0))<>"",INDEX(Service_Providers!$D$2:$D$104,MATCH($M73,Service_Providers!$A$2:$A$104,0))<>""),CHAR(10),"")&IF(INDEX(Service_Providers!$D$2:$D$104,MATCH($M73,Service_Providers!$A$2:$A$104,0))="","",INDEX(Service_Providers!$D$2:$D$104,MATCH($M73,Service_Providers!$A$2:$A$104,0))),"Provider not found")) | O73: Texas Area | P73: 2026-07-15
A74: Twin Peaks- Corpus Christi, TX | B74: accounting@avalanchefoodgroup.com | C74: BRIAN CONNELLY | D74: 361-992-7325 | E74: 5425 South Padre Island Drive | F74: Corpus Christi | G74: TX | H74: 78411 | I74: ITCB Combo Brewer | J74: Loaned | K74: B & B Coffee Service | L74: =IF($K74="","",IFERROR(IF(INDEX(Service_Providers!$C$2:$C$104,MATCH($K74,Service_Providers!$A$2:$A$104,0))="","",INDEX(Service_Providers!$C$2:$C$104,MATCH($K74,Service_Providers!$A$2:$A$104,0)))&IF(AND(INDEX(Service_Providers!$C$2:$C$104,MATCH($K74,Service_Providers!$A$2:$A$104,0))<>"",INDEX(Service_Providers!$D$2:$D$104,MATCH($K74,Service_Providers!$A$2:$A$104,0))<>""),CHAR(10),"")&IF(INDEX(Service_Providers!$D$2:$D$104,MATCH($K74,Service_Providers!$A$2:$A$104,0))="","",INDEX(Service_Providers!$D$2:$D$104,MATCH($K74,Service_Providers!$A$2:$A$104,0))),"Provider not found")) -> 361.855.3066 | N74: =IF($M74="","",IFERROR(IF(INDEX(Service_Providers!$C$2:$C$104,MATCH($M74,Service_Providers!$A$2:$A$104,0))="","",INDEX(Service_Providers!$C$2:$C$104,MATCH($M74,Service_Providers!$A$2:$A$104,0)))&IF(AND(INDEX(Service_Providers!$C$2:$C$104,MATCH($M74,Service_Providers!$A$2:$A$104,0))<>"",INDEX(Service_Providers!$D$2:$D$104,MATCH($M74,Service_Providers!$A$2:$A$104,0))<>""),CHAR(10),"")&IF(INDEX(Service_Providers!$D$2:$D$104,MATCH($M74,Service_Providers!$A$2:$A$104,0))="","",INDEX(Service_Providers!$D$2:$D$104,MATCH($M74,Service_Providers!$A$2:$A$104,0))),"Provider not found")) | O74: Texas Area | P74: 2026-07-15
A75: Twin Peaks- McAllen, TX | B75: clint.hurry@avalanchefoodgroup.com | C75: CLINT HURRY | D75: 956-215-8002 | E75: 901 Interstate Hwy 2, W Expy 83 | F75: McAllen | G75: TX | H75: 78503 | I75: ITCB Combo Brewer (NS) | J75: Loaned | K75: B & B Coffee Service | L75: =IF($K75="","",IFERROR(IF(INDEX(Service_Providers!$C$2:$C$104,MATCH($K75,Service_Providers!$A$2:$A$104,0))="","",INDEX(Service_Providers!$C$2:$C$104,MATCH($K75,Service_Providers!$A$2:$A$104,0)))&IF(AND(INDEX(Service_Providers!$C$2:$C$104,MATCH($K75,Service_Providers!$A$2:$A$104,0))<>"",INDEX(Service_Providers!$D$2:$D$104,MATCH($K75,Service_Providers!$A$2:$A$104,0))<>""),CHAR(10),"")&IF(INDEX(Service_Providers!$D$2:$D$104,MATCH($K75,Service_Providers!$A$2:$A$104,0))="","",INDEX(Service_Providers!$D$2:$D$104,MATCH($K75,Service_Providers!$A$2:$A$104,0))),"Provider not found")) -> 361.855.3066 | N75: =IF($M75="","",IFERROR(IF(INDEX(Service_Providers!$C$2:$C$104,MATCH($M75,Service_Providers!$A$2:$A$104,0))="","",INDEX(Service_Providers!$C$2:$C$104,MATCH($M75,Service_Providers!$A$2:$A$104,0)))&IF(AND(INDEX(Service_Providers!$C$2:$C$104,MATCH($M75,Service_Providers!$A$2:$A$104,0))<>"",INDEX(Service_Providers!$D$2:$D$104,MATCH($M75,Service_Providers!$A$2:$A$104,0))<>""),CHAR(10),"")&IF(INDEX(Service_Providers!$D$2:$D$104,MATCH($M75,Service_Providers!$A$2:$A$104,0))="","",INDEX(Service_Providers!$D$2:$D$104,MATCH($M75,Service_Providers!$A$2:$A$104,0))),"Provider not found")) | O75: Texas Area | P75: 2026-07-15
A76: Hawkers - Arlington, VA (Ballston) | B76: eathawkers@documents.restaurant365.com | C76: Simon Brown | D76: (703) 828-8287 | E76: 4201 Wilson Blvd., Suite 0170 | F76: Arlington | G76: VA | H76: 22203 | I76: Bunn ITB Tea Brewer | J76: Loaned | L76: =IF($K76="","",IFERROR(IF(INDEX(Service_Providers!$C$2:$C$104,MATCH($K76,Service_Providers!$A$2:$A$104,0))="","",INDEX(Service_Providers!$C$2:$C$104,MATCH($K76,Service_Providers!$A$2:$A$104,0)))&IF(AND(INDEX(Service_Providers!$C$2:$C$104,MATCH($K76,Service_Providers!$A$2:$A$104,0))<>"",INDEX(Service_Providers!$D$2:$D$104,MATCH($K76,Service_Providers!$A$2:$A$104,0))<>""),CHAR(10),"")&IF(INDEX(Service_Providers!$D$2:$D$104,MATCH($K76,Service_Providers!$A$2:$A$104,0))="","",INDEX(Service_Providers!$D$2:$D$104,MATCH($K76,Service_Providers!$A$2:$A$104,0))),"Provider not found")) | N76: =IF($M76="","",IFERROR(IF(INDEX(Service_Providers!$C$2:$C$104,MATCH($M76,Service_Providers!$A$2:$A$104,0))="","",INDEX(Service_Providers!$C$2:$C$104,MATCH($M76,Service_Providers!$A$2:$A$104,0)))&IF(AND(INDEX(Service_Providers!$C$2:$C$104,MATCH($M76,Service_Providers!$A$2:$A$104,0))<>"",INDEX(Service_Providers!$D$2:$D$104,MATCH($M76,Service_Providers!$A$2:$A$104,0))<>""),CHAR(10),"")&IF(INDEX(Service_Providers!$D$2:$D$104,MATCH($M76,Service_Providers!$A$2:$A$104,0))="","",INDEX(Service_Providers!$D$2:$D$104,MATCH($M76,Service_Providers!$A$2:$A$104,0))),"Provider not found")) | O76: Virginia Area | P76: 2026-07-15
A77: Kol Fac #081C - Virginia Beach | B77: store81@kolfac.com | D77: 757.340.5732 | E77: 460 S Independence Blvd. | F77: Virginia Beach | G77: VA | H77: 23452 | I77: Cameo c'2s; Bunn ITCB Combo Brewer (NS) | J77: Loaned; Owned - Purchased from Katz | K77: JVG Coffee Mechanics | L77: =IF($K77="","",IFERROR(IF(INDEX(Service_Providers!$C$2:$C$104,MATCH($K77,Service_Providers!$A$2:$A$104,0))="","",INDEX(Service_Providers!$C$2:$C$104,MATCH($K77,Service_Providers!$A$2:$A$104,0)))&IF(AND(INDEX(Service_Providers!$C$2:$C$104,MATCH($K77,Service_Providers!$A$2:$A$104,0))<>"",INDEX(Service_Providers!$D$2:$D$104,MATCH($K77,Service_Providers!$A$2:$A$104,0))<>""),CHAR(10),"")&IF(INDEX(Service_Providers!$D$2:$D$104,MATCH($K77,Service_Providers!$A$2:$A$104,0))="","",INDEX(Service_Providers!$D$2:$D$104,MATCH($K77,Service_Providers!$A$2:$A$104,0))),"Provider not found")) -> 919-240-8083 hayes@jvgcoffeemechanics.com | N77: =IF($M77="","",IFERROR(IF(INDEX(Service_Providers!$C$2:$C$104,MATCH($M77,Service_Providers!$A$2:$A$104,0))="","",INDEX(Service_Providers!$C$2:$C$104,MATCH($M77,Service_Providers!$A$2:$A$104,0)))&IF(AND(INDEX(Service_Providers!$C$2:$C$104,MATCH($M77,Service_Providers!$A$2:$A$104,0))<>"",INDEX(Service_Providers!$D$2:$D$104,MATCH($M77,Service_Providers!$A$2:$A$104,0))<>""),CHAR(10),"")&IF(INDEX(Service_Providers!$D$2:$D$104,MATCH($M77,Service_Providers!$A$2:$A$104,0))="","",INDEX(Service_Providers!$D$2:$D$104,MATCH($M77,Service_Providers!$A$2:$A$104,0))),"Provider not found")) | O77: Virginia Area | P77: 2026-07-15
L78: =IF($K78="","",IFERROR(IF(INDEX(Service_Providers!$C$2:$C$104,MATCH($K78,Service_Providers!$A$2:$A$104,0))="","",INDEX(Service_Providers!$C$2:$C$104,MATCH($K78,Service_Providers!$A$2:$A$104,0)))&IF(AND(INDEX(Service_Providers!$C$2:$C$104,MATCH($K78,Service_Providers!$A$2:$A$104,0))<>"",INDEX(Service_Providers!$D$2:$D$104,MATCH($K78,Service_Providers!$A$2:$A$104,0))<>""),CHAR(10),"")&IF(INDEX(Service_Providers!$D$2:$D$104,MATCH($K78,Service_Providers!$A$2:$A$104,0))="","",INDEX(Service_Providers!$D$2:$D$104,MATCH($K78,Service_Providers!$A$2:$A$104,0))),"Provider not found")) | N78: =IF($M78="","",IFERROR(IF(INDEX(Service_Providers!$C$2:$C$104,MATCH($M78,Service_Providers!$A$2:$A$104,0))="","",INDEX(Service_Providers!$C$2:$C$104,MATCH($M78,Service_Providers!$A$2:$A$104,0)))&IF(AND(INDEX(Service_Providers!$C$2:$C$104,MATCH($M78,Service_Providers!$A$2:$A$104,0))<>"",INDEX(Service_Providers!$D$2:$D$104,MATCH($M78,Service_Providers!$A$2:$A$104,0))<>""),CHAR(10),"")&IF(INDEX(Service_Providers!$D$2:$D$104,MATCH($M78,Service_Providers!$A$2:$A$104,0))="","",INDEX(Service_Providers!$D$2:$D$104,MATCH($M78,Service_Providers!$A$2:$A$104,0))),"Provider not found"))
L79: =IF($K79="","",IFERROR(IF(INDEX(Service_Providers!$C$2:$C$104,MATCH($K79,Service_Providers!$A$2:$A$104,0))="","",INDEX(Service_Providers!$C$2:$C$104,MATCH($K79,Service_Providers!$A$2:$A$104,0)))&IF(AND(INDEX(Service_Providers!$C$2:$C$104,MATCH($K79,Service_Providers!$A$2:$A$104,0))<>"",INDEX(Service_Providers!$D$2:$D$104,MATCH($K79,Service_Providers!$A$2:$A$104,0))<>""),CHAR(10),"")&IF(INDEX(Service_Providers!$D$2:$D$104,MATCH($K79,Service_Providers!$A$2:$A$104,0))="","",INDEX(Service_Providers!$D$2:$D$104,MATCH($K79,Service_Providers!$A$2:$A$104,0))),"Provider not found")) | N79: =IF($M79="","",IFERROR(IF(INDEX(Service_Providers!$C$2:$C$104,MATCH($M79,Service_Providers!$A$2:$A$104,0))="","",INDEX(Service_Providers!$C$2:$C$104,MATCH($M79,Service_Providers!$A$2:$A$104,0)))&IF(AND(INDEX(Service_Providers!$C$2:$C$104,MATCH($M79,Service_Providers!$A$2:$A$104,0))<>"",INDEX(Service_Providers!$D$2:$D$104,MATCH($M79,Service_Providers!$A$2:$A$104,0))<>""),CHAR(10),"")&IF(INDEX(Service_Providers!$D$2:$D$104,MATCH($M79,Service_Providers!$A$2:$A$104,0))="","",INDEX(Service_Providers!$D$2:$D$104,MATCH($M79,Service_Providers!$A$2:$A$104,0))),"Provider not found"))
L80: =IF($K80="","",IFERROR(IF(INDEX(Service_Providers!$C$2:$C$104,MATCH($K80,Service_Providers!$A$2:$A$104,0))="","",INDEX(Service_Providers!$C$2:$C$104,MATCH($K80,Service_Providers!$A$2:$A$104,0)))&IF(AND(INDEX(Service_Providers!$C$2:$C$104,MATCH($K80,Service_Providers!$A$2:$A$104,0))<>"",INDEX(Service_Providers!$D$2:$D$104,MATCH($K80,Service_Providers!$A$2:$A$104,0))<>""),CHAR(10),"")&IF(INDEX(Service_Providers!$D$2:$D$104,MATCH($K80,Service_Providers!$A$2:$A$104,0))="","",INDEX(Service_Providers!$D$2:$D$104,MATCH($K80,Service_Providers!$A$2:$A$104,0))),"Provider not found")) | N80: =IF($M80="","",IFERROR(IF(INDEX(Service_Providers!$C$2:$C$104,MATCH($M80,Service_Providers!$A$2:$A$104,0))="","",INDEX(Service_Providers!$C$2:$C$104,MATCH($M80,Service_Providers!$A$2:$A$104,0)))&IF(AND(INDEX(Service_Providers!$C$2:$C$104,MATCH($M80,Service_Providers!$A$2:$A$104,0))<>"",INDEX(Service_Providers!$D$2:$D$104,MATCH($M80,Service_Providers!$A$2:$A$104,0))<>""),CHAR(10),"")&IF(INDEX(Service_Providers!$D$2:$D$104,MATCH($M80,Service_Providers!$A$2:$A$104,0))="","",INDEX(Service_Providers!$D$2:$D$104,MATCH($M80,Service_Providers!$A$2:$A$104,0))),"Provider not found"))
L81: =IF($K81="","",IFERROR(IF(INDEX(Service_Providers!$C$2:$C$104,MATCH($K81,Service_Providers!$A$2:$A$104,0))="","",INDEX(Service_Providers!$C$2:$C$104,MATCH($K81,Service_Providers!$A$2:$A$104,0)))&IF(AND(INDEX(Service_Providers!$C$2:$C$104,MATCH($K81,Service_Providers!$A$2:$A$104,0))<>"",INDEX(Service_Providers!$D$2:$D$104,MATCH($K81,Service_Providers!$A$2:$A$104,0))<>""),CHAR(10),"")&IF(INDEX(Service_Providers!$D$2:$D$104,MATCH($K81,Service_Providers!$A$2:$A$104,0))="","",INDEX(Service_Providers!$D$2:$D$104,MATCH($K81,Service_Providers!$A$2:$A$104,0))),"Provider not found")) | N81: =IF($M81="","",IFERROR(IF(INDEX(Service_Providers!$C$2:$C$104,MATCH($M81,Service_Providers!$A$2:$A$104,0))="","",INDEX(Service_Providers!$C$2:$C$104,MATCH($M81,Service_Providers!$A$2:$A$104,0)))&IF(AND(INDEX(Service_Providers!$C$2:$C$104,MATCH($M81,Service_Providers!$A$2:$A$104,0))<>"",INDEX(Service_Providers!$D$2:$D$104,MATCH($M81,Service_Providers!$A$2:$A$104,0))<>""),CHAR(10),"")&IF(INDEX(Service_Providers!$D$2:$D$104,MATCH($M81,Service_Providers!$A$2:$A$104,0))="","",INDEX(Service_Providers!$D$2:$D$104,MATCH($M81,Service_Providers!$A$2:$A$104,0))),"Provider not found"))
L82: =IF($K82="","",IFERROR(IF(INDEX(Service_Providers!$C$2:$C$104,MATCH($K82,Service_Providers!$A$2:$A$104,0))="","",INDEX(Service_Providers!$C$2:$C$104,MATCH($K82,Service_Providers!$A$2:$A$104,0)))&IF(AND(INDEX(Service_Providers!$C$2:$C$104,MATCH($K82,Service_Providers!$A$2:$A$104,0))<>"",INDEX(Service_Providers!$D$2:$D$104,MATCH($K82,Service_Providers!$A$2:$A$104,0))<>""),CHAR(10),"")&IF(INDEX(Service_Providers!$D$2:$D$104,MATCH($K82,Service_Providers!$A$2:$A$104,0))="","",INDEX(Service_Providers!$D$2:$D$104,MATCH($K82,Service_Providers!$A$2:$A$104,0))),"Provider not found")) | N82: =IF($M82="","",IFERROR(IF(INDEX(Service_Providers!$C$2:$C$104,MATCH($M82,Service_Providers!$A$2:$A$104,0))="","",INDEX(Service_Providers!$C$2:$C$104,MATCH($M82,Service_Providers!$A$2:$A$104,0)))&IF(AND(INDEX(Service_Providers!$C$2:$C$104,MATCH($M82,Service_Providers!$A$2:$A$104,0))<>"",INDEX(Service_Providers!$D$2:$D$104,MATCH($M82,Service_Providers!$A$2:$A$104,0))<>""),CHAR(10),"")&IF(INDEX(Service_Providers!$D$2:$D$104,MATCH($M82,Service_Providers!$A$2:$A$104,0))="","",INDEX(Service_Providers!$D$2:$D$104,MATCH($M82,Service_Providers!$A$2:$A$104,0))),"Provider not found"))
L83: =IF($K83="","",IFERROR(IF(INDEX(Service_Providers!$C$2:$C$104,MATCH($K83,Service_Providers!$A$2:$A$104,0))="","",INDEX(Service_Providers!$C$2:$C$104,MATCH($K83,Service_Providers!$A$2:$A$104,0)))&IF(AND(INDEX(Service_Providers!$C$2:$C$104,MATCH($K83,Service_Providers!$A$2:$A$104,0))<>"",INDEX(Service_Providers!$D$2:$D$104,MATCH($K83,Service_Providers!$A$2:$A$104,0))<>""),CHAR(10),"")&IF(INDEX(Service_Providers!$D$2:$D$104,MATCH($K83,Service_Providers!$A$2:$A$104,0))="","",INDEX(Service_Providers!$D$2:$D$104,MATCH($K83,Service_Providers!$A$2:$A$104,0))),"Provider not found")) | N83: =IF($M83="","",IFERROR(IF(INDEX(Service_Providers!$C$2:$C$104,MATCH($M83,Service_Providers!$A$2:$A$104,0))="","",INDEX(Service_Providers!$C$2:$C$104,MATCH($M83,Service_Providers!$A$2:$A$104,0)))&IF(AND(INDEX(Service_Providers!$C$2:$C$104,MATCH($M83,Service_Providers!$A$2:$A$104,0))<>"",INDEX(Service_Providers!$D$2:$D$104,MATCH($M83,Service_Providers!$A$2:$A$104,0))<>""),CHAR(10),"")&IF(INDEX(Service_Providers!$D$2:$D$104,MATCH($M83,Service_Providers!$A$2:$A$104,0))="","",INDEX(Service_Providers!$D$2:$D$104,MATCH($M83,Service_Providers!$A$2:$A$104,0))),"Provider not found"))
L84: =IF($K84="","",IFERROR(IF(INDEX(Service_Providers!$C$2:$C$104,MATCH($K84,Service_Providers!$A$2:$A$104,0))="","",INDEX(Service_Providers!$C$2:$C$104,MATCH($K84,Service_Providers!$A$2:$A$104,0)))&IF(AND(INDEX(Service_Providers!$C$2:$C$104,MATCH($K84,Service_Providers!$A$2:$A$104,0))<>"",INDEX(Service_Providers!$D$2:$D$104,MATCH($K84,Service_Providers!$A$2:$A$104,0))<>""),CHAR(10),"")&IF(INDEX(Service_Providers!$D$2:$D$104,MATCH($K84,Service_Providers!$A$2:$A$104,0))="","",INDEX(Service_Providers!$D$2:$D$104,MATCH($K84,Service_Providers!$A$2:$A$104,0))),"Provider not found")) | N84: =IF($M84="","",IFERROR(IF(INDEX(Service_Providers!$C$2:$C$104,MATCH($M84,Service_Providers!$A$2:$A$104,0))="","",INDEX(Service_Providers!$C$2:$C$104,MATCH($M84,Service_Providers!$A$2:$A$104,0)))&IF(AND(INDEX(Service_Providers!$C$2:$C$104,MATCH($M84,Service_Providers!$A$2:$A$104,0))<>"",INDEX(Service_Providers!$D$2:$D$104,MATCH($M84,Service_Providers!$A$2:$A$104,0))<>""),CHAR(10),"")&IF(INDEX(Service_Providers!$D$2:$D$104,MATCH($M84,Service_Providers!$A$2:$A$104,0))="","",INDEX(Service_Providers!$D$2:$D$104,MATCH($M84,Service_Providers!$A$2:$A$104,0))),"Provider not found"))
L85: =IF($K85="","",IFERROR(IF(INDEX(Service_Providers!$C$2:$C$104,MATCH($K85,Service_Providers!$A$2:$A$104,0))="","",INDEX(Service_Providers!$C$2:$C$104,MATCH($K85,Service_Providers!$A$2:$A$104,0)))&IF(AND(INDEX(Service_Providers!$C$2:$C$104,MATCH($K85,Service_Providers!$A$2:$A$104,0))<>"",INDEX(Service_Providers!$D$2:$D$104,MATCH($K85,Service_Providers!$A$2:$A$104,0))<>""),CHAR(10),"")&IF(INDEX(Service_Providers!$D$2:$D$104,MATCH($K85,Service_Providers!$A$2:$A$104,0))="","",INDEX(Service_Providers!$D$2:$D$104,MATCH($K85,Service_Providers!$A$2:$A$104,0))),"Provider not found")) | N85: =IF($M85="","",IFERROR(IF(INDEX(Service_Providers!$C$2:$C$104,MATCH($M85,Service_Providers!$A$2:$A$104,0))="","",INDEX(Service_Providers!$C$2:$C$104,MATCH($M85,Service_Providers!$A$2:$A$104,0)))&IF(AND(INDEX(Service_Providers!$C$2:$C$104,MATCH($M85,Service_Providers!$A$2:$A$104,0))<>"",INDEX(Service_Providers!$D$2:$D$104,MATCH($M85,Service_Providers!$A$2:$A$104,0))<>""),CHAR(10),"")&IF(INDEX(Service_Providers!$D$2:$D$104,MATCH($M85,Service_Providers!$A$2:$A$104,0))="","",INDEX(Service_Providers!$D$2:$D$104,MATCH($M85,Service_Providers!$A$2:$A$104,0))),"Provider not found"))
L86: =IF($K86="","",IFERROR(IF(INDEX(Service_Providers!$C$2:$C$104,MATCH($K86,Service_Providers!$A$2:$A$104,0))="","",INDEX(Service_Providers!$C$2:$C$104,MATCH($K86,Service_Providers!$A$2:$A$104,0)))&IF(AND(INDEX(Service_Providers!$C$2:$C$104,MATCH($K86,Service_Providers!$A$2:$A$104,0))<>"",INDEX(Service_Providers!$D$2:$D$104,MATCH($K86,Service_Providers!$A$2:$A$104,0))<>""),CHAR(10),"")&IF(INDEX(Service_Providers!$D$2:$D$104,MATCH($K86,Service_Providers!$A$2:$A$104,0))="","",INDEX(Service_Providers!$D$2:$D$104,MATCH($K86,Service_Providers!$A$2:$A$104,0))),"Provider not found")) | N86: =IF($M86="","",IFERROR(IF(INDEX(Service_Providers!$C$2:$C$104,MATCH($M86,Service_Providers!$A$2:$A$104,0))="","",INDEX(Service_Providers!$C$2:$C$104,MATCH($M86,Service_Providers!$A$2:$A$104,0)))&IF(AND(INDEX(Service_Providers!$C$2:$C$104,MATCH($M86,Service_Providers!$A$2:$A$104,0))<>"",INDEX(Service_Providers!$D$2:$D$104,MATCH($M86,Service_Providers!$A$2:$A$104,0))<>""),CHAR(10),"")&IF(INDEX(Service_Providers!$D$2:$D$104,MATCH($M86,Service_Providers!$A$2:$A$104,0))="","",INDEX(Service_Providers!$D$2:$D$104,MATCH($M86,Service_Providers!$A$2:$A$104,0))),"Provider not found"))
L87: =IF($K87="","",IFERROR(IF(INDEX(Service_Providers!$C$2:$C$104,MATCH($K87,Service_Providers!$A$2:$A$104,0))="","",INDEX(Service_Providers!$C$2:$C$104,MATCH($K87,Service_Providers!$A$2:$A$104,0)))&IF(AND(INDEX(Service_Providers!$C$2:$C$104,MATCH($K87,Service_Providers!$A$2:$A$104,0))<>"",INDEX(Service_Providers!$D$2:$D$104,MATCH($K87,Service_Providers!$A$2:$A$104,0))<>""),CHAR(10),"")&IF(INDEX(Service_Providers!$D$2:$D$104,MATCH($K87,Service_Providers!$A$2:$A$104,0))="","",INDEX(Service_Providers!$D$2:$D$104,MATCH($K87,Service_Providers!$A$2:$A$104,0))),"Provider not found")) | N87: =IF($M87="","",IFERROR(IF(INDEX(Service_Providers!$C$2:$C$104,MATCH($M87,Service_Providers!$A$2:$A$104,0))="","",INDEX(Service_Providers!$C$2:$C$104,MATCH($M87,Service_Providers!$A$2:$A$104,0)))&IF(AND(INDEX(Service_Providers!$C$2:$C$104,MATCH($M87,Service_Providers!$A$2:$A$104,0))<>"",INDEX(Service_Providers!$D$2:$D$104,MATCH($M87,Service_Providers!$A$2:$A$104,0))<>""),CHAR(10),"")&IF(INDEX(Service_Providers!$D$2:$D$104,MATCH($M87,Service_Providers!$A$2:$A$104,0))="","",INDEX(Service_Providers!$D$2:$D$104,MATCH($M87,Service_Providers!$A$2:$A$104,0))),"Provider not found"))
L88: =IF($K88="","",IFERROR(IF(INDEX(Service_Providers!$C$2:$C$104,MATCH($K88,Service_Providers!$A$2:$A$104,0))="","",INDEX(Service_Providers!$C$2:$C$104,MATCH($K88,Service_Providers!$A$2:$A$104,0)))&IF(AND(INDEX(Service_Providers!$C$2:$C$104,MATCH($K88,Service_Providers!$A$2:$A$104,0))<>"",INDEX(Service_Providers!$D$2:$D$104,MATCH($K88,Service_Providers!$A$2:$A$104,0))<>""),CHAR(10),"")&IF(INDEX(Service_Providers!$D$2:$D$104,MATCH($K88,Service_Providers!$A$2:$A$104,0))="","",INDEX(Service_Providers!$D$2:$D$104,MATCH($K88,Service_Providers!$A$2:$A$104,0))),"Provider not found")) | N88: =IF($M88="","",IFERROR(IF(INDEX(Service_Providers!$C$2:$C$104,MATCH($M88,Service_Providers!$A$2:$A$104,0))="","",INDEX(Service_Providers!$C$2:$C$104,MATCH($M88,Service_Providers!$A$2:$A$104,0)))&IF(AND(INDEX(Service_Providers!$C$2:$C$104,MATCH($M88,Service_Providers!$A$2:$A$104,0))<>"",INDEX(Service_Providers!$D$2:$D$104,MATCH($M88,Service_Providers!$A$2:$A$104,0))<>""),CHAR(10),"")&IF(INDEX(Service_Providers!$D$2:$D$104,MATCH($M88,Service_Providers!$A$2:$A$104,0))="","",INDEX(Service_Providers!$D$2:$D$104,MATCH($M88,Service_Providers!$A$2:$A$104,0))),"Provider not found"))
L89: =IF($K89="","",IFERROR(IF(INDEX(Service_Providers!$C$2:$C$104,MATCH($K89,Service_Providers!$A$2:$A$104,0))="","",INDEX(Service_Providers!$C$2:$C$104,MATCH($K89,Service_Providers!$A$2:$A$104,0)))&IF(AND(INDEX(Service_Providers!$C$2:$C$104,MATCH($K89,Service_Providers!$A$2:$A$104,0))<>"",INDEX(Service_Providers!$D$2:$D$104,MATCH($K89,Service_Providers!$A$2:$A$104,0))<>""),CHAR(10),"")&IF(INDEX(Service_Providers!$D$2:$D$104,MATCH($K89,Service_Providers!$A$2:$A$104,0))="","",INDEX(Service_Providers!$D$2:$D$104,MATCH($K89,Service_Providers!$A$2:$A$104,0))),"Provider not found")) | N89: =IF($M89="","",IFERROR(IF(INDEX(Service_Providers!$C$2:$C$104,MATCH($M89,Service_Providers!$A$2:$A$104,0))="","",INDEX(Service_Providers!$C$2:$C$104,MATCH($M89,Service_Providers!$A$2:$A$104,0)))&IF(AND(INDEX(Service_Providers!$C$2:$C$104,MATCH($M89,Service_Providers!$A$2:$A$104,0))<>"",INDEX(Service_Providers!$D$2:$D$104,MATCH($M89,Service_Providers!$A$2:$A$104,0))<>""),CHAR(10),"")&IF(INDEX(Service_Providers!$D$2:$D$104,MATCH($M89,Service_Providers!$A$2:$A$104,0))="","",INDEX(Service_Providers!$D$2:$D$104,MATCH($M89,Service_Providers!$A$2:$A$104,0))),"Provider not found"))
... L299: =IF($K299="","",IFERROR(IF(INDEX(Service_Providers!$C$2:$C$104,MATCH($K299,Service_Providers!$A$2:$A$104,0))="","",INDEX(Service_Providers!$C$2:$C$104,MATCH($K299,Service_Providers!$A$2:$A$104,0)))&IF(AND(INDEX(Service_Providers!$C$2:$C$104,MATCH($K299,Service_Providers!$A$2:$A$104,0))<>"",INDEX(Service_Providers!$D$2:$D$104,MATCH($K299,Service_Providers!$A$2:$A$104,0))<>""),CHAR(10),"")&IF(INDEX(Service_Providers!$D$2:$D$104,MATCH($K299,Service_Providers!$A$2:$A$104,0))="","",INDEX(Service_Providers!$D$2:$D$104,MATCH($K299,Service_Providers!$A$2:$A$104,0))),"Provider not found")) | N299: =IF($M299="","",IFERROR(IF(INDEX(Service_Providers!$C$2:$C$104,MATCH($M299,Service_Providers!$A$2:$A$104,0))="","",INDEX(Service_Providers!$C$2:$C$104,MATCH($M299,Service_Providers!$A$2:$A$104,0)))&IF(AND(INDEX(Service_Providers!$C$2:$C$104,MATCH($M299,Service_Providers!$A$2:$A$104,0))<>"",INDEX(Service_Providers!$D$2:$D$104,MATCH($M299,Service_Providers!$A$2:$A$104,0))<>""),CHAR(10),"")&IF(INDEX(Service_Providers!$D$2:$D$104,MATCH($M299,Service_Providers!$A$2:$A$104,0))="","",INDEX(Service_Providers!$D$2:$D$104,MATCH($M299,Service_Providers!$A$2:$A$104,0))),"Provider not found"))

Sheet How_To_Update
A1: HOW TO KEEP THIS DATABASE UPDATED
A3: EVERYTHING UPDATES AUTOMATICALLY
A4: - Add a provider anywhere in rows 2-101 of Service_Providers: it instantly appears in the Primary/Secondary Provider dropdowns on the Accounts tab and in the Accounts by Provider table on the Dashboard. No named ranges or formulas to extend.
A5: - Add an account anywhere in rows 2-300 of Accounts: the Dashboard state counts pick it up automatically, and the dispatch formulas and dropdowns are already in place on those rows.
A6: - Only exception: a brand-new STATE needs one new row added to the Coverage by State table on the Dashboard (copy an existing row's formulas).
A8: ACCOUNTS TAB - COLUMN LAYOUT
A9: Cols A-J: account + equipment info | K: Primary Provider (dropdown) | L: Dispatch Phone & Email (auto-fills from Service_Providers when K is chosen - green formula, do not type over) | M: Secondary Provider (dropdown) | N: Secondary Phone & Email (auto-fills from M) | O: Service Region | P: Last Updated
A10: - Yellow cells in column K = account with no primary provider assigned; clears when you pick one.
A11: - Update Last Updated (col P) whenever you change a row.
A13: SERVICE_PROVIDERS TAB - COLUMN LAYOUT
A14: Columns (in order): Provider_Name | Status | Primary Dispatch Phone | Primary Dispatch Email | Secondary Dispatch Phone | Secondary Dispatch Email | Response Time | Standard Rate | After Hours Rate | Travel Rate Policy | Equipment Serviced | States / ZIP Coverage | Contacts | PM Pricing | Parts Stocking | Coverage Notes / Key Notes | Last_Updated
A15: - Always fill in Primary Dispatch Phone (col C) and Primary Dispatch Email (col D) - the Accounts tab and Dashboard read these.
... A32: - Keep the Accounts tab sorted by State, then Account Name. Dates use YYYY-MM-DD.
